Workbook

Sheet Read Me
C2: DAMM v1.7 — Scoring Workbook
C3: Digital Agriculture Maturity Model · draft for review · August 2026
C5: This file is the Egypt worked example, compiled 22 August 2026.
C7: The four steps
C8: 1 · ASSEMBLE | D8: Fill the six yellow columns on the scoring sheet: Value, Source, Source URL, Tier, Year, Assessor level. Every indicator gets a value, a source and a year — or a recorded gap. No level may exist without a recorded value.
C9: 2 · DERIVE | D9: Automatic. Evidence class, level, staleness, pillar bands, the layer profile, prerequisite status and the use-case matrix all compute by formula. Nothing here is typed.
C10: 3 · REPORT | D10: The diagnostic report renders from this workbook. It is the deliverable; this file is the instrument behind it.
C11: 4 · USE | D11: The task team leader takes the report into roadmap preparation, closes the verify list on mission, and executes the refresh list.
C13: What to type, and where
C14: Yellow cells, blue text | D14: The only cells an assessor edits: Value, Source, Source URL, Tier, Year, Assessor level (columns M–R of the scoring sheet).
C15: Everything else | D15: Model reference or derived by formula. Do not overwrite: a typed level that contradicts its value is the defect this model exists to prevent.
C16: Value | D16: A number, a citation ("NDPA 2023 in force; NDPC enforcing"), or a recorded gap beginning DATA GAP — followed by the sources actually searched.
C17: Tier | D17: T1–T5 per the Tiers sheet. Reported, never weighted. Machine-fetched rows arrive with the tier already filled by the pipeline.
C18: Assessor level | D18: 1–5, for ladder indicators only. Threshold indicators score themselves from the value.
C20: Quality control — gate sign-off
D21: Automated checks run at render time and block the report on failure. The three human gates are recorded here (QC Protocol).
C22: Gate | D22: What it certifies | E22: Name | F22: Date | G22: Note
C23: G1 | D23: Assessor has confirmed every machine-filled row: value, source, year, tier; every recorded gap accepted or re-searched.
C24: G2 | D24: A second reviewer has re-checked 100% of prerequisite rows and 100% of judged rows, plus a 15% sample of the remainder.
C25: G3 | D25: Task team leader sign-off against the four prohibitions, before anything leaves the team.
C27: The four prohibitions
D28: · No cross-country ranking.
D29: · No band used as a project development objective, disbursement-linked indicator, or disbursement condition.
D30: · No automatic financing decisions.
D31: · No public claim before human review.

Sheet Config
B1: Config — every constant with its meaning
B2: Assessment year | C2: 2026 | D2: ENTRY (yellow). Staleness is measured against this year.
B3: Staleness limit (years) | C3: 3 | D3: A reading older than this is flagged STALE. One rule for all indicators.
B4: Readiness threshold | C4: 2.6 | D4: A use-case column whose bearing indicators average below this reads Partial.
B5: Leapfrog threshold | C5: 1.5 | D5: |mean(Foundation) − mean(Transformation)| above this raises a structural flag.
B6: Band: Nascent | C6: 1.0 – <1.8 | D6: Half-open bands; a pillar band in parentheses means judged, gap and held rows outnumber the levelled measured and documented ones.
B7: Band: Emerging | C7: 1.8 – <2.6
B8: Band: Established | C8: 2.6 – <3.4
B9: Band: Advanced | C9: 3.4 – <4.2
B10: Band: Transformative | C10: 4.2 – 5.0
B11: Universal prerequisites | C11: 2.1, 2.9, 4.1 | D11: Absence blocks every use-case column. A universal prerequisite at Present (narrow) caps every column at Partial.
B12: AI-enabled services | C12: 7.12 binds AGI | D12: Ruling pending ratification: the consent-and-rights prerequisite binds the agricultural-intelligence column.

Sheet Ladder
B1: The shared ladder — scoring an indicator that is not a measurement
B2: Ask in stages: presence first, then quality, then scale. Stop at the first rung the evidence does not support.
B4: Level | C4: Condition | D4: Evidence required
B5: 1 | C5: Absent | D5: The search that established absence: sources consulted, in order.
B6: 2 | C6: Announced | D6: The announcement, draft or commitment, cited.
B7: 3 | C7: Adopted, or operating narrowly | D7: The instrument or system itself, with its adoption date or its operating footprint.
B8: 4 | C8: Operating with quality | D8: Governance, funding and institutionalisation — the evidence that it is run, not just live.
B9: 5 | C9: Operating at scale, with evidence of use | D9: Coverage or reach in the indicator's own unit, from a source that is not the operator's own claim.
B11: A scale figure reported only by the operator of the service does not carry rung 5.

Sheet Tiers
B1: Source tiers — what may carry what
B2: Tiers are reported beside the evidence class and never weighted. Search in tier order and stop when found; a dead end is recorded as a gap with its trail.
B4: Tier | C4: What it is | D4: Typical sources | E4: Admissible for
B5: T1 | C5: Official statistics & international databases | D5: FAOSTAT · AQUASTAT · World Bank WDI/ID4D/Findex · ITU · UN DESA · national statistical offices | E5: Any claim. The default for every number.
B6: T2 | C6: Peer-reviewed literature & IO flagship reports | D6: Journals · systematic reviews · World Bank / FAO / IFPRI / CGIAR flagships · evaluated impact studies | E6: Any claim. Required for impact and effectiveness claims.
B7: T3 | C7: Government legal, policy & budget artefacts | D7: Gazetted laws · adopted strategies · budgets · regulator reports · official programme pages | E7: Presence facts, policy intent, programme design — not outcomes.
B8: T4 | C8: Reputable grey literature | D8: GSMA · GIZ · USAID · AGRA · AfDB · donor evaluations · established industry analyses | E8: Context and sector narrative, flagged as T4; presence facts where T3 is silent.
B9: T5 | C9: News, vendor & market material | D9: Press · company sites · market-research releases · blogs | E9: Initiative register only, existence facts only. A T5-only citation derives the class Judged, never Documented.
C11: · Every citation is a deep link to the document, with an access date. A link that resolves only to a domain root is not a citation.
C12: · A load-bearing number needs two independent T1–T2 confirmations, or it ships flagged single-source.
C13: · Vintage beats tier at the margin for narrative; the scored row still records the official figure and its staleness honestly.

Sheet Egypt
A1: Egypt — DAMM v1.7 assessment
A2: Edit only the yellow columns (M–R). Everything else is model reference or derived by formula.
A4: ID | B4: Indicator | C4: Pillar | D4: Layer | E4: Use cases | F4: Prereq | G4: Meth | H4: Dir | I4: L2 | J4: L3 | K4: L4 | L4: L5 | M4: Value | N4: Source | O4: Source URL | P4: Tier | Q4: Year | R4: Assessor level | S4: Class | T4: Level | U4: Stale | V4: b_ADV | W4: b_SMF | X4: b_MKT | Y4: b_SCM | Z4: b_FIN | AA4: b_AGI | AB4: Open definition question (for ratification) | AC4: Ratification hold
A5: 1.1 | B5: Agriculture value added per worker (USD) | C5: A1 | D5: Foundation | E5: NEED | G5: T | H5: H | I5: 1000 | J5: 2500 | K5: 5000 | L5: 10000 | M5: 8942.4183 | N5: World Bank WDI NV.AGR.EMPL.KD | O5: https://api.worldbank.org/v2/country/EGY/indicator/NV.AGR.EMPL.KD?format=json&mrnev=1&per_page=5 | P5: T1 | Q5: 2025 | S5: =IF($M5="","",IF(ISNUMBER($M5),"Measured",IF(ISNUMBER(SEARCH("DATA GAP",UPPER($M5))),"Gap",IF(AND($N5<>"",$P5<>"T5"),"Documented","Judged")))) -> Measured | T5: =IF($AC5<>"","",IF(OR($S5="",$S5="Gap"),"",IF($S5="Measured",1+IF($H5="H",IF($M5>=$I5,1,0)+IF($M5>=$J5,1,0)+IF($M5>=$K5,1,0)+IF($M5>=$L5,1,0),IF($M5<=$I5,1,0)+IF($M5<=$J5,1,0)+IF($M5<=$K5,1,0)+IF($M5<=$L5,1,0)),IF($R5<>"",$R5,"")))) -> 4 | U5: =IF(OR($S5="",$S5="Gap",$Q5=""),"",IF($Q5<Config!$C$2-Config!$C$3,"STALE","")) | V5: =IF(OR(ISNUMBER(SEARCH("ALL",$E5)),ISNUMBER(SEARCH("ADV",$E5))),1,0) -> 0 | W5: =IF(OR(ISNUMBER(SEARCH("ALL",$E5)),ISNUMBER(SEARCH("SMF",$E5))),1,0) -> 0 | X5: =IF(OR(ISNUMBER(SEARCH("ALL",$E5)),ISNUMBER(SEARCH("MKT",$E5))),1,0) -> 0 | Y5: =IF(OR(ISNUMBER(SEARCH("ALL",$E5)),ISNUMBER(SEARCH("SCM",$E5))),1,0) -> 0 | Z5: =IF(OR(ISNUMBER(SEARCH("ALL",$E5)),ISNUMBER(SEARCH("FIN",$E5))),1,0) -> 0 | AA5: =IF(OR(ISNUMBER(SEARCH("ALL",$E5)),ISNUMBER(SEARCH("AGI",$E5))),1,0) -> 0 | AB5: The name says "Agriculture... (USD)" but both countries record WDI NV.AGR.EMPL.KD, which covers agriculture, forestry AND fishing and is denominated in constant 2015 US$ — neither the sector scope nor the price basis is stated in the name or in the bare-USD thresholds, and neither row carries…
A6: 1.2 | B6: Cereal yield (kg/ha) | C6: A1 | D6: Foundation | E6: NEED | G6: T | H6: H | I6: 1500 | J6: 3000 | K6: 4500 | L6: 6000 | M6: 7402.2 | N6: World Bank WDI AG.YLD.CREL.KG | O6: https://api.worldbank.org/v2/country/EGY/indicator/AG.YLD.CREL.KG?format=json&mrnev=1&per_page=5 | P6: T1 | Q6: 2023 | S6: =IF($M6="","",IF(ISNUMBER($M6),"Measured",IF(ISNUMBER(SEARCH("DATA GAP",UPPER($M6))),"Gap",IF(AND($N6<>"",$P6<>"T5"),"Documented","Judged")))) -> Measured | T6: =IF($AC6<>"","",IF(OR($S6="",$S6="Gap"),"",IF($S6="Measured",1+IF($H6="H",IF($M6>=$I6,1,0)+IF($M6>=$J6,1,0)+IF($M6>=$K6,1,0)+IF($M6>=$L6,1,0),IF($M6<=$I6,1,0)+IF($M6<=$J6,1,0)+IF($M6<=$K6,1,0)+IF($M6<=$L6,1,0)),IF($R6<>"",$R6,"")))) -> 5 | U6: =IF(OR($S6="",$S6="Gap",$Q6=""),"",IF($Q6<Config!$C$2-Config!$C$3,"STALE","")) | V6: =IF(OR(ISNUMBER(SEARCH("ALL",$E6)),ISNUMBER(SEARCH("ADV",$E6))),1,0) -> 0 | W6: =IF(OR(ISNUMBER(SEARCH("ALL",$E6)),ISNUMBER(SEARCH("SMF",$E6))),1,0) -> 0 | X6: =IF(OR(ISNUMBER(SEARCH("ALL",$E6)),ISNUMBER(SEARCH("MKT",$E6))),1,0) -> 0 | Y6: =IF(OR(ISNUMBER(SEARCH("ALL",$E6)),ISNUMBER(SEARCH("SCM",$E6))),1,0) -> 0 | Z6: =IF(OR(ISNUMBER(SEARCH("ALL",$E6)),ISNUMBER(SEARCH("FIN",$E6))),1,0) -> 0 | AA6: =IF(OR(ISNUMBER(SEARCH("ALL",$E6)),ISNUMBER(SEARCH("AGI",$E6))),1,0) -> 0
A7: 1.3 | B7: Employment in agriculture (%) | C7: A1 | D7: Foundation | E7: NEED | G7: T | H7: L | I7: 45 | J7: 30 | K7: 15 | L7: 5 | M7: 17.524644 | N7: World Bank WDI SL.AGR.EMPL.ZS (ILO modeled estimate) | O7: https://api.worldbank.org/v2/country/EGY/indicator/SL.AGR.EMPL.ZS?format=json&mrnev=1&per_page=5 | P7: T1 | Q7: 2025 | S7: =IF($M7="","",IF(ISNUMBER($M7),"Measured",IF(ISNUMBER(SEARCH("DATA GAP",UPPER($M7))),"Gap",IF(AND($N7<>"",$P7<>"T5"),"Documented","Judged")))) -> Measured | T7: =IF($AC7<>"","",IF(OR($S7="",$S7="Gap"),"",IF($S7="Measured",1+IF($H7="H",IF($M7>=$I7,1,0)+IF($M7>=$J7,1,0)+IF($M7>=$K7,1,0)+IF($M7>=$L7,1,0),IF($M7<=$I7,1,0)+IF($M7<=$J7,1,0)+IF($M7<=$K7,1,0)+IF($M7<=$L7,1,0)),IF($R7<>"",$R7,"")))) -> 3 | U7: =IF(OR($S7="",$S7="Gap",$Q7=""),"",IF($Q7<Config!$C$2-Config!$C$3,"STALE","")) | V7: =IF(OR(ISNUMBER(SEARCH("ALL",$E7)),ISNUMBER(SEARCH("ADV",$E7))),1,0) -> 0 | W7: =IF(OR(ISNUMBER(SEARCH("ALL",$E7)),ISNUMBER(SEARCH("SMF",$E7))),1,0) -> 0 | X7: =IF(OR(ISNUMBER(SEARCH("ALL",$E7)),ISNUMBER(SEARCH("MKT",$E7))),1,0) -> 0 | Y7: =IF(OR(ISNUMBER(SEARCH("ALL",$E7)),ISNUMBER(SEARCH("SCM",$E7))),1,0) -> 0 | Z7: =IF(OR(ISNUMBER(SEARCH("ALL",$E7)),ISNUMBER(SEARCH("FIN",$E7))),1,0) -> 0 | AA7: =IF(OR(ISNUMBER(SEARCH("ALL",$E7)),ISNUMBER(SEARCH("AGI",$E7))),1,0) -> 0 | AB7: The name omits the denominator (% of total employment), the recorded series covers ISIC-A (agriculture, hunting, forestry and fishing) rather than agriculture alone, and both rows carry an ILO MODELLED 2025 nowcast under cls "Measured" — the register's highest evidence class — which the…
A8: 1.4 | B8: Food production index (2014-16=100) | C8: A1 | D8: Foundation | E8: NEED | G8: T | H8: H | I8: 95 | J8: 105 | K8: 115 | L8: 130 | M8: 109.07 | N8: World Bank WDI AG.PRD.FOOD.XD | O8: https://api.worldbank.org/v2/country/EGY/indicator/AG.PRD.FOOD.XD?format=json&mrnev=1&per_page=5 | P8: T1 | Q8: 2022 | S8: =IF($M8="","",IF(ISNUMBER($M8),"Measured",IF(ISNUMBER(SEARCH("DATA GAP",UPPER($M8))),"Gap",IF(AND($N8<>"",$P8<>"T5"),"Documented","Judged")))) -> Measured | T8: =IF($AC8<>"","",IF(OR($S8="",$S8="Gap"),"",IF($S8="Measured",1+IF($H8="H",IF($M8>=$I8,1,0)+IF($M8>=$J8,1,0)+IF($M8>=$K8,1,0)+IF($M8>=$L8,1,0),IF($M8<=$I8,1,0)+IF($M8<=$J8,1,0)+IF($M8<=$K8,1,0)+IF($M8<=$L8,1,0)),IF($R8<>"",$R8,"")))) -> 3 | U8: =IF(OR($S8="",$S8="Gap",$Q8=""),"",IF($Q8<Config!$C$2-Config!$C$3,"STALE","")) -> STALE | V8: =IF(OR(ISNUMBER(SEARCH("ALL",$E8)),ISNUMBER(SEARCH("ADV",$E8))),1,0) -> 0 | W8: =IF(OR(ISNUMBER(SEARCH("ALL",$E8)),ISNUMBER(SEARCH("SMF",$E8))),1,0) -> 0 | X8: =IF(OR(ISNUMBER(SEARCH("ALL",$E8)),ISNUMBER(SEARCH("MKT",$E8))),1,0) -> 0 | Y8: =IF(OR(ISNUMBER(SEARCH("ALL",$E8)),ISNUMBER(SEARCH("SCM",$E8))),1,0) -> 0 | Z8: =IF(OR(ISNUMBER(SEARCH("ALL",$E8)),ISNUMBER(SEARCH("FIN",$E8))),1,0) -> 0 | AA8: =IF(OR(ISNUMBER(SEARCH("ALL",$E8)),ISNUMBER(SEARCH("AGI",$E8))),1,0) -> 0
A9: 1.5 | B9: Post-harvest loss rate (%) | C9: A1 | D9: Foundation | E9: NEED | G9: T | H9: L | I9: 30 | J9: 20 | K9: 12 | L9: 5 | M9: No single national post-harvest loss rate exists. Cereals (labelled, admissible): ~10% pre- and post-harvest losses (SADS 2030, estimate c.2009); wheat losses in traditional shona storage 10-20% (FAO 2019). Horticulture: | N9: FAO (2019), Food loss and waste in Egypt, CA4310EN, FAO Representation in Egypt | O9: https://openknowledge.fao.org/server/api/core/bitstreams/3d94597d-cc5c-420a-8faa-0fe284d5c921/content | P9: T2 | Q9: 2019 | R9: 4 | S9: =IF($M9="","",IF(ISNUMBER($M9),"Measured",IF(ISNUMBER(SEARCH("DATA GAP",UPPER($M9))),"Gap",IF(AND($N9<>"",$P9<>"T5"),"Documented","Judged")))) -> Documented | T9: =IF($AC9<>"","",IF(OR($S9="",$S9="Gap"),"",IF($S9="Measured",1+IF($H9="H",IF($M9>=$I9,1,0)+IF($M9>=$J9,1,0)+IF($M9>=$K9,1,0)+IF($M9>=$L9,1,0),IF($M9<=$I9,1,0)+IF($M9<=$J9,1,0)+IF($M9<=$K9,1,0)+IF($M9<=$L9,1,0)),IF($R9<>"",$R9,"")))) -> 4 | U9: =IF(OR($S9="",$S9="Gap",$Q9=""),"",IF($Q9<Config!$C$2-Config!$C$3,"STALE","")) -> STALE | V9: =IF(OR(ISNUMBER(SEARCH("ALL",$E9)),ISNUMBER(SEARCH("ADV",$E9))),1,0) -> 0 | W9: =IF(OR(ISNUMBER(SEARCH("ALL",$E9)),ISNUMBER(SEARCH("SMF",$E9))),1,0) -> 0 | X9: =IF(OR(ISNUMBER(SEARCH("ALL",$E9)),ISNUMBER(SEARCH("MKT",$E9))),1,0) -> 0 | Y9: =IF(OR(ISNUMBER(SEARCH("ALL",$E9)),ISNUMBER(SEARCH("SCM",$E9))),1,0) -> 0 | Z9: =IF(OR(ISNUMBER(SEARCH("ALL",$E9)),ISNUMBER(SEARCH("FIN",$E9))),1,0) -> 0 | AA9: =IF(OR(ISNUMBER(SEARCH("ALL",$E9)),ISNUMBER(SEARCH("AGI",$E9))),1,0) -> 0 | AB9: The name asserts an all-crop national post-harvest loss rate; both countries record cereals-only figures, and Egypt's scored figure is described by its own source as covering pre- AND post-harvest losses.
A10: 1.6 | B10: Smallholder access to formal markets (%) | C10: A1 | D10: Foundation | E10: NEED,MKT | G10: T | H10: H | I10: 20 | J10: 40 | K10: 60 | L10: 80 | M10: No national figure. Upper Egypt (regional, labelled): 6% of surveyed smallholder households participate in contract farming (farm household survey Apr-May 2018, seven Upper Egypt governorates, n=2,237 households; IFPRI). | N10: Tabe-Ojong, M.P. Jr. & Abay, K.A. (2023), Smallholder farmers' participation in profitable value chains and contract farming: Evidence from irrigated agriculture in Egypt, IFPRI MENA Working Paper 42 | O10: https://cgspace.cgiar.org/items/b1bc85c0-7505-4fb7-9957-d7588eea9756 | P10: T2 | Q10: 2018 | R10: 1 | S10: =IF($M10="","",IF(ISNUMBER($M10),"Measured",IF(ISNUMBER(SEARCH("DATA GAP",UPPER($M10))),"Gap",IF(AND($N10<>"",$P10<>"T5"),"Documented","Judged")))) -> Documented | T10: =IF($AC10<>"","",IF(OR($S10="",$S10="Gap"),"",IF($S10="Measured",1+IF($H10="H",IF($M10>=$I10,1,0)+IF($M10>=$J10,1,0)+IF($M10>=$K10,1,0)+IF($M10>=$L10,1,0),IF($M10<=$I10,1,0)+IF($M10<=$J10,1,0)+IF($M10<=$K10,1,0)+IF($M10<=$L10,1,0)),IF($R10<>"",$R10,"")))) -> 1 | U10: =IF(OR($S10="",$S10="Gap",$Q10=""),"",IF($Q10<Config!$C$2-Config!$C$3,"STALE","")) -> STALE | V10: =IF(OR(ISNUMBER(SEARCH("ALL",$E10)),ISNUMBER(SEARCH("ADV",$E10))),1,0) -> 0 | W10: =IF(OR(ISNUMBER(SEARCH("ALL",$E10)),ISNUMBER(SEARCH("SMF",$E10))),1,0) -> 0 | X10: =IF(OR(ISNUMBER(SEARCH("ALL",$E10)),ISNUMBER(SEARCH("MKT",$E10))),1,0) -> 1 | Y10: =IF(OR(ISNUMBER(SEARCH("ALL",$E10)),ISNUMBER(SEARCH("SCM",$E10))),1,0) -> 0 | Z10: =IF(OR(ISNUMBER(SEARCH("ALL",$E10)),ISNUMBER(SEARCH("FIN",$E10))),1,0) -> 0 | AA10: =IF(OR(ISNUMBER(SEARCH("ALL",$E10)),ISNUMBER(SEARCH("AGI",$E10))),1,0) -> 0 | AB10: The name asserts national smallholder ACCESS to formal markets; Egypt records a regional contract-farming PARTICIPATION rate from seven governorates and Nigeria a 2012/13 channel-of-sale share — two different constructs, neither of which is access, and neither national in Egypt's case.
A11: 1.7 | B11: Agricultural credit access (% farmers) | C11: A1 | D11: Foundation | E11: NEED,FIN | G11: T | H11: H | I11: 10 | J11: 25 | K11: 40 | L11: 60 | M11: No direct '% of farmers with agricultural credit' figure exists for Egypt. Nearest labelled figures: only 2.3% of rural individuals aged 15+ had loans from formal financial institutions (ELMPS 2018, CAPMAS national panel | N11: Mansour, S., Samak, N. & Gad, N. (2024), Credit Choices in Rural Egypt: A Comparative Study of Formal and Informal Borrowing, Journal of Risk and Financial Management 17(11): 487 | O11: https://doi.org/10.3390/jrfm17110487 | P11: T2 | Q11: 2018 | R11: 1 | S11: =IF($M11="","",IF(ISNUMBER($M11),"Measured",IF(ISNUMBER(SEARCH("DATA GAP",UPPER($M11))),"Gap",IF(AND($N11<>"",$P11<>"T5"),"Documented","Judged")))) -> Documented | T11: =IF($AC11<>"","",IF(OR($S11="",$S11="Gap"),"",IF($S11="Measured",1+IF($H11="H",IF($M11>=$I11,1,0)+IF($M11>=$J11,1,0)+IF($M11>=$K11,1,0)+IF($M11>=$L11,1,0),IF($M11<=$I11,1,0)+IF($M11<=$J11,1,0)+IF($M11<=$K11,1,0)+IF($M11<=$L11,1,0)),IF($R11<>"",$R11,"")))) -> 1 | U11: =IF(OR($S11="",$S11="Gap",$Q11=""),"",IF($Q11<Config!$C$2-Config!$C$3,"STALE","")) -> STALE | V11: =IF(OR(ISNUMBER(SEARCH("ALL",$E11)),ISNUMBER(SEARCH("ADV",$E11))),1,0) -> 0 | W11: =IF(OR(ISNUMBER(SEARCH("ALL",$E11)),ISNUMBER(SEARCH("SMF",$E11))),1,0) -> 0 | X11: =IF(OR(ISNUMBER(SEARCH("ALL",$E11)),ISNUMBER(SEARCH("MKT",$E11))),1,0) -> 0 | Y11: =IF(OR(ISNUMBER(SEARCH("ALL",$E11)),ISNUMBER(SEARCH("SCM",$E11))),1,0) -> 0 | Z11: =IF(OR(ISNUMBER(SEARCH("ALL",$E11)),ISNUMBER(SEARCH("FIN",$E11))),1,0) -> 1 | AA11: =IF(OR(ISNUMBER(SEARCH("ALL",$E11)),ISNUMBER(SEARCH("AGI",$E11))),1,0) -> 0 | AB11: The name asserts a share of FARMERS with credit ACCESS; Egypt records rural adults aged 15+ (a population that includes non-farmers) and Nigeria records smallholder households, and both measure borrowing/use rather than access.
A12: 1.8 | B12: Farmers using climate-smart practices (%) | C12: A1 | D12: Foundation | E12: NEED,ADV | G12: T | H12: H | I12: 20 | J12: 40 | K12: 60 | L12: 80 | M12: No all-practice national CSA rate. Practice-specific (labelled): raised-bed wheat cultivation tripled 113,500 ha (2013/14) to 334,000 ha (2016/17) ~46% of wheat area; laser levelling and deficit-irrigation adoption documented | N12: USDA GAIN Egypt grain report (primary PDF); FAO/WB corroboration | O12: https://apps.fas.usda.gov/newgainapi/api/report/downloadreportbyfilename?filename=Grain%20and%20Feed%20Annual_Cairo_Egypt_3-15-2017.pdf | P12: T4 | Q12: 2017 | S12: =IF($M12="","",IF(ISNUMBER($M12),"Measured",IF(ISNUMBER(SEARCH("DATA GAP",UPPER($M12))),"Gap",IF(AND($N12<>"",$P12<>"T5"),"Documented","Judged")))) -> Documented | T12: =IF($AC12<>"","",IF(OR($S12="",$S12="Gap"),"",IF($S12="Measured",1+IF($H12="H",IF($M12>=$I12,1,0)+IF($M12>=$J12,1,0)+IF($M12>=$K12,1,0)+IF($M12>=$L12,1,0),IF($M12<=$I12,1,0)+IF($M12<=$J12,1,0)+IF($M12<=$K12,1,0)+IF($M12<=$L12,1,0)),IF($R12<>"",$R12,"")))) | U12: =IF(OR($S12="",$S12="Gap",$Q12=""),"",IF($Q12<Config!$C$2-Config!$C$3,"STALE","")) -> STALE | V12: =IF(OR(ISNUMBER(SEARCH("ALL",$E12)),ISNUMBER(SEARCH("ADV",$E12))),1,0) -> 1 | W12: =IF(OR(ISNUMBER(SEARCH("ALL",$E12)),ISNUMBER(SEARCH("SMF",$E12))),1,0) -> 0 | X12: =IF(OR(ISNUMBER(SEARCH("ALL",$E12)),ISNUMBER(SEARCH("MKT",$E12))),1,0) -> 0 | Y12: =IF(OR(ISNUMBER(SEARCH("ALL",$E12)),ISNUMBER(SEARCH("SCM",$E12))),1,0) -> 0 | Z12: =IF(OR(ISNUMBER(SEARCH("ALL",$E12)),ISNUMBER(SEARCH("FIN",$E12))),1,0) -> 0 | AA12: =IF(OR(ISNUMBER(SEARCH("ALL",$E12)),ISNUMBER(SEARCH("AGI",$E12))),1,0) -> 0 | AB12: The name counts FARMERS adopting climate-smart practices; Egypt records a share of WHEAT AREA under a single practice and Nigeria a share of farmers in two zones adopting at least one climate-resilient crop TRAIT — land, practice-basket and geographic scope all differ from the name. | AC12: HOLD
A13: 8.1 | B13: Prevalence of undernourishment (%) | C13: A1 | D13: Foundation | E13: NEED | G13: T | H13: L | I13: 25 | J13: 15 | K13: 7.5 | L13: 2.5 | M13: 9.4 | N13: World Bank WDI SN.ITK.DEFC.ZS | O13: https://api.worldbank.org/v2/country/EGY/indicator/SN.ITK.DEFC.ZS?format=json&mrnev=1&per_page=5 | P13: T1 | Q13: 2023 | S13: =IF($M13="","",IF(ISNUMBER($M13),"Measured",IF(ISNUMBER(SEARCH("DATA GAP",UPPER($M13))),"Gap",IF(AND($N13<>"",$P13<>"T5"),"Documented","Judged")))) -> Measured | T13: =IF($AC13<>"","",IF(OR($S13="",$S13="Gap"),"",IF($S13="Measured",1+IF($H13="H",IF($M13>=$I13,1,0)+IF($M13>=$J13,1,0)+IF($M13>=$K13,1,0)+IF($M13>=$L13,1,0),IF($M13<=$I13,1,0)+IF($M13<=$J13,1,0)+IF($M13<=$K13,1,0)+IF($M13<=$L13,1,0)),IF($R13<>"",$R13,"")))) -> 3 | U13: =IF(OR($S13="",$S13="Gap",$Q13=""),"",IF($Q13<Config!$C$2-Config!$C$3,"STALE","")) | V13: =IF(OR(ISNUMBER(SEARCH("ALL",$E13)),ISNUMBER(SEARCH("ADV",$E13))),1,0) -> 0 | W13: =IF(OR(ISNUMBER(SEARCH("ALL",$E13)),ISNUMBER(SEARCH("SMF",$E13))),1,0) -> 0 | X13: =IF(OR(ISNUMBER(SEARCH("ALL",$E13)),ISNUMBER(SEARCH("MKT",$E13))),1,0) -> 0 | Y13: =IF(OR(ISNUMBER(SEARCH("ALL",$E13)),ISNUMBER(SEARCH("SCM",$E13))),1,0) -> 0 | Z13: =IF(OR(ISNUMBER(SEARCH("ALL",$E13)),ISNUMBER(SEARCH("FIN",$E13))),1,0) -> 0 | AA13: =IF(OR(ISNUMBER(SEARCH("ALL",$E13)),ISNUMBER(SEARCH("AGI",$E13))),1,0) -> 0
A14: 8.5 | B14: Women who own land (% holders) | C14: A1 | D14: Foundation | E14: NEED,EQ | G14: T | H14: H | I14: 10 | J14: 25 | K14: 40 | L14: 50 | M14: 3.94 | N14: FAOSTAT, World Census of Agriculture domain — Egypt, item 'Civil holders, female', element 'Percent of total persons (holders)', Agricultural Census 2009/10 (CAPMAS) | O14: https://bulks-faostat.fao.org/production/World_Census_Agriculture_E_All_Data.zip | P14: T1 | Q14: 2010 | S14: =IF($M14="","",IF(ISNUMBER($M14),"Measured",IF(ISNUMBER(SEARCH("DATA GAP",UPPER($M14))),"Gap",IF(AND($N14<>"",$P14<>"T5"),"Documented","Judged")))) -> Measured | T14: =IF($AC14<>"","",IF(OR($S14="",$S14="Gap"),"",IF($S14="Measured",1+IF($H14="H",IF($M14>=$I14,1,0)+IF($M14>=$J14,1,0)+IF($M14>=$K14,1,0)+IF($M14>=$L14,1,0),IF($M14<=$I14,1,0)+IF($M14<=$J14,1,0)+IF($M14<=$K14,1,0)+IF($M14<=$L14,1,0)),IF($R14<>"",$R14,"")))) | U14: =IF(OR($S14="",$S14="Gap",$Q14=""),"",IF($Q14<Config!$C$2-Config!$C$3,"STALE","")) -> STALE | V14: =IF(OR(ISNUMBER(SEARCH("ALL",$E14)),ISNUMBER(SEARCH("ADV",$E14))),1,0) -> 0 | W14: =IF(OR(ISNUMBER(SEARCH("ALL",$E14)),ISNUMBER(SEARCH("SMF",$E14))),1,0) -> 0 | X14: =IF(OR(ISNUMBER(SEARCH("ALL",$E14)),ISNUMBER(SEARCH("MKT",$E14))),1,0) -> 0 | Y14: =IF(OR(ISNUMBER(SEARCH("ALL",$E14)),ISNUMBER(SEARCH("SCM",$E14))),1,0) -> 0 | Z14: =IF(OR(ISNUMBER(SEARCH("ALL",$E14)),ISNUMBER(SEARCH("FIN",$E14))),1,0) -> 0 | AA14: =IF(OR(ISNUMBER(SEARCH("ALL",$E14)),ISNUMBER(SEARCH("AGI",$E14))),1,0) -> 0 | AB14: ⚠ The indicator name says women who OWN land while the canonical statistic counts women agricultural holders (operators), who may rent rather than own. | AC14: HOLD
A15: 2.1 | B15: Rural mobile broadband coverage (3G/4G) | C15: C1 | D15: Foundation | E15: ALL | F15: UNIVERSAL | G15: T | H15: H | I15: 20 | J15: 40 | K15: 60 | L15: 80 | M15: DATA GAP — no rural-specific mobile broadband coverage is published for Egypt by ITU, NTRA or MCIT. Context (not scored): national population coverage at least 3G = 99.8% (ITU DataHub, 2025) | N15: Structured source search, 22 August 2026 | Q15: 2025 | S15: =IF($M15="","",IF(ISNUMBER($M15),"Measured",IF(ISNUMBER(SEARCH("DATA GAP",UPPER($M15))),"Gap",IF(AND($N15<>"",$P15<>"T5"),"Documented","Judged")))) -> Gap | T15: =IF($AC15<>"","",IF(OR($S15="",$S15="Gap"),"",IF($S15="Measured",1+IF($H15="H",IF($M15>=$I15,1,0)+IF($M15>=$J15,1,0)+IF($M15>=$K15,1,0)+IF($M15>=$L15,1,0),IF($M15<=$I15,1,0)+IF($M15<=$J15,1,0)+IF($M15<=$K15,1,0)+IF($M15<=$L15,1,0)),IF($R15<>"",$R15,"")))) | U15: =IF(OR($S15="",$S15="Gap",$Q15=""),"",IF($Q15<Config!$C$2-Config!$C$3,"STALE","")) | V15: =IF(OR(ISNUMBER(SEARCH("ALL",$E15)),ISNUMBER(SEARCH("ADV",$E15))),1,0) -> 1 | W15: =IF(OR(ISNUMBER(SEARCH("ALL",$E15)),ISNUMBER(SEARCH("SMF",$E15))),1,0) -> 1 | X15: =IF(OR(ISNUMBER(SEARCH("ALL",$E15)),ISNUMBER(SEARCH("MKT",$E15))),1,0) -> 1 | Y15: =IF(OR(ISNUMBER(SEARCH("ALL",$E15)),ISNUMBER(SEARCH("SCM",$E15))),1,0) -> 1 | Z15: =IF(OR(ISNUMBER(SEARCH("ALL",$E15)),ISNUMBER(SEARCH("FIN",$E15))),1,0) -> 1 | AA15: =IF(OR(ISNUMBER(SEARCH("ALL",$E15)),ISNUMBER(SEARCH("AGI",$E15))),1,0) -> 1 | AB15: ⚠ The name asserts RURAL coverage, but Egypt's row records the ITU national at-least-3G figure as a clean cls="Measured" number that scores level 5 mechanically, while Nigeria records a rural-but-4G-only modeled estimate — so the register's only universal connectivity prerequisite carries a…
A16: 2.4 | B16: Individuals using the Internet (%) | C16: C1 | D16: Foundation | E16: ALL | G16: T | H16: H | I16: 20 | J16: 40 | K16: 60 | L16: 80 | M16: 74.648399 | N16: World Bank WDI IT.NET.USER.ZS | O16: https://api.worldbank.org/v2/country/EGY/indicator/IT.NET.USER.ZS?format=json&mrnev=1&per_page=5 | P16: T1 | Q16: 2024 | S16: =IF($M16="","",IF(ISNUMBER($M16),"Measured",IF(ISNUMBER(SEARCH("DATA GAP",UPPER($M16))),"Gap",IF(AND($N16<>"",$P16<>"T5"),"Documented","Judged")))) -> Measured | T16: =IF($AC16<>"","",IF(OR($S16="",$S16="Gap"),"",IF($S16="Measured",1+IF($H16="H",IF($M16>=$I16,1,0)+IF($M16>=$J16,1,0)+IF($M16>=$K16,1,0)+IF($M16>=$L16,1,0),IF($M16<=$I16,1,0)+IF($M16<=$J16,1,0)+IF($M16<=$K16,1,0)+IF($M16<=$L16,1,0)),IF($R16<>"",$R16,"")))) -> 4 | U16: =IF(OR($S16="",$S16="Gap",$Q16=""),"",IF($Q16<Config!$C$2-Config!$C$3,"STALE","")) | V16: =IF(OR(ISNUMBER(SEARCH("ALL",$E16)),ISNUMBER(SEARCH("ADV",$E16))),1,0) -> 1 | W16: =IF(OR(ISNUMBER(SEARCH("ALL",$E16)),ISNUMBER(SEARCH("SMF",$E16))),1,0) -> 1 | X16: =IF(OR(ISNUMBER(SEARCH("ALL",$E16)),ISNUMBER(SEARCH("MKT",$E16))),1,0) -> 1 | Y16: =IF(OR(ISNUMBER(SEARCH("ALL",$E16)),ISNUMBER(SEARCH("SCM",$E16))),1,0) -> 1 | Z16: =IF(OR(ISNUMBER(SEARCH("ALL",$E16)),ISNUMBER(SEARCH("FIN",$E16))),1,0) -> 1 | AA16: =IF(OR(ISNUMBER(SEARCH("ALL",$E16)),ISNUMBER(SEARCH("AGI",$E16))),1,0) -> 1
A17: 2.5 | B17: Mobile broadband price (% GNI pc) | C17: C1 | D17: Foundation | E17: ALL | G17: T | H17: L | I17: 10 | J17: 5 | K17: 2 | L17: 1 | M17: 0.9 | N17: ITU DataHub — Other ICT price baskets: Data-only mobile-broadband basket (2GB) (2021-2024 definition), % of GNI p.c. — Egypt (accessed 2026-08-22) | O17: https://datahub.itu.int/data/?e=EGY&i=100123&s=34593 | P17: T1 | Q17: 2025 | S17: =IF($M17="","",IF(ISNUMBER($M17),"Measured",IF(ISNUMBER(SEARCH("DATA GAP",UPPER($M17))),"Gap",IF(AND($N17<>"",$P17<>"T5"),"Documented","Judged")))) -> Measured | T17: =IF($AC17<>"","",IF(OR($S17="",$S17="Gap"),"",IF($S17="Measured",1+IF($H17="H",IF($M17>=$I17,1,0)+IF($M17>=$J17,1,0)+IF($M17>=$K17,1,0)+IF($M17>=$L17,1,0),IF($M17<=$I17,1,0)+IF($M17<=$J17,1,0)+IF($M17<=$K17,1,0)+IF($M17<=$L17,1,0)),IF($R17<>"",$R17,"")))) -> 5 | U17: =IF(OR($S17="",$S17="Gap",$Q17=""),"",IF($Q17<Config!$C$2-Config!$C$3,"STALE","")) | V17: =IF(OR(ISNUMBER(SEARCH("ALL",$E17)),ISNUMBER(SEARCH("ADV",$E17))),1,0) -> 1 | W17: =IF(OR(ISNUMBER(SEARCH("ALL",$E17)),ISNUMBER(SEARCH("SMF",$E17))),1,0) -> 1 | X17: =IF(OR(ISNUMBER(SEARCH("ALL",$E17)),ISNUMBER(SEARCH("MKT",$E17))),1,0) -> 1 | Y17: =IF(OR(ISNUMBER(SEARCH("ALL",$E17)),ISNUMBER(SEARCH("SCM",$E17))),1,0) -> 1 | Z17: =IF(OR(ISNUMBER(SEARCH("ALL",$E17)),ISNUMBER(SEARCH("FIN",$E17))),1,0) -> 1 | AA17: =IF(OR(ISNUMBER(SEARCH("ALL",$E17)),ISNUMBER(SEARCH("AGI",$E17))),1,0) -> 1 | AB17: The name fixes neither the basket allowance (2GB vs ITU's 2025 headline 5GB), nor the basket type (data-only vs voice+data), nor whether "% GNI pc" is monthly or annual — and Egypt's value sits on a series ITU has retired to a legacy label while Nigeria's comes from the live headline series id,…
A18: 2.7 | B18: Rural smartphone ownership (%) | C18: C1 | D18: Foundation | E18: ALL | G18: T | H18: H | I18: 20 | J18: 40 | K18: 60 | L18: 80 | M18: 67.4 | N18: MCIT ICT Indicators Quarterly Bulletin, June 2022 (Q2 2022), p.6 — 'Households with Smartphone according to (Urban/Rural)', reporting the MCIT/CAPMAS 'ICT usage in household and individuals' survey 2021-2022 | O18: https://mcit.gov.eg/Upcont/Documents/Publications_2482022000_ICT_Indicators_Quarterly_Bulletin_Q2_2022_24082022.pdf | P18: T3 | Q18: 2022 | S18: =IF($M18="","",IF(ISNUMBER($M18),"Measured",IF(ISNUMBER(SEARCH("DATA GAP",UPPER($M18))),"Gap",IF(AND($N18<>"",$P18<>"T5"),"Documented","Judged")))) -> Measured | T18: =IF($AC18<>"","",IF(OR($S18="",$S18="Gap"),"",IF($S18="Measured",1+IF($H18="H",IF($M18>=$I18,1,0)+IF($M18>=$J18,1,0)+IF($M18>=$K18,1,0)+IF($M18>=$L18,1,0),IF($M18<=$I18,1,0)+IF($M18<=$J18,1,0)+IF($M18<=$K18,1,0)+IF($M18<=$L18,1,0)),IF($R18<>"",$R18,"")))) -> 4 | U18: =IF(OR($S18="",$S18="Gap",$Q18=""),"",IF($Q18<Config!$C$2-Config!$C$3,"STALE","")) -> STALE | V18: =IF(OR(ISNUMBER(SEARCH("ALL",$E18)),ISNUMBER(SEARCH("ADV",$E18))),1,0) -> 1 | W18: =IF(OR(ISNUMBER(SEARCH("ALL",$E18)),ISNUMBER(SEARCH("SMF",$E18))),1,0) -> 1 | X18: =IF(OR(ISNUMBER(SEARCH("ALL",$E18)),ISNUMBER(SEARCH("MKT",$E18))),1,0) -> 1 | Y18: =IF(OR(ISNUMBER(SEARCH("ALL",$E18)),ISNUMBER(SEARCH("SCM",$E18))),1,0) -> 1 | Z18: =IF(OR(ISNUMBER(SEARCH("ALL",$E18)),ISNUMBER(SEARCH("FIN",$E18))),1,0) -> 1 | AA18: =IF(OR(ISNUMBER(SEARCH("ALL",$E18)),ISNUMBER(SEARCH("AGI",$E18))),1,0) -> 1 | AB18: "Ownership" of a personal device implies individuals; both countries record the share of rural HOUSEHOLDS owning at least one smartphone, which reads systematically higher than the individual measure.
A19: 2.9 | B19: Rural electricity access (%) | C19: C1 | D19: Foundation | E19: ALL | F19: UNIVERSAL | G19: T | H19: H | I19: 20 | J19: 40 | K19: 60 | L19: 80 | M19: 100 | N19: World Bank WDI EG.ELC.ACCS.RU.ZS | O19: https://api.worldbank.org/v2/country/EGY/indicator/EG.ELC.ACCS.RU.ZS?format=json&mrnev=1&per_page=5 | P19: T1 | Q19: 2024 | S19: =IF($M19="","",IF(ISNUMBER($M19),"Measured",IF(ISNUMBER(SEARCH("DATA GAP",UPPER($M19))),"Gap",IF(AND($N19<>"",$P19<>"T5"),"Documented","Judged")))) -> Measured | T19: =IF($AC19<>"","",IF(OR($S19="",$S19="Gap"),"",IF($S19="Measured",1+IF($H19="H",IF($M19>=$I19,1,0)+IF($M19>=$J19,1,0)+IF($M19>=$K19,1,0)+IF($M19>=$L19,1,0),IF($M19<=$I19,1,0)+IF($M19<=$J19,1,0)+IF($M19<=$K19,1,0)+IF($M19<=$L19,1,0)),IF($R19<>"",$R19,"")))) -> 5 | U19: =IF(OR($S19="",$S19="Gap",$Q19=""),"",IF($Q19<Config!$C$2-Config!$C$3,"STALE","")) | V19: =IF(OR(ISNUMBER(SEARCH("ALL",$E19)),ISNUMBER(SEARCH("ADV",$E19))),1,0) -> 1 | W19: =IF(OR(ISNUMBER(SEARCH("ALL",$E19)),ISNUMBER(SEARCH("SMF",$E19))),1,0) -> 1 | X19: =IF(OR(ISNUMBER(SEARCH("ALL",$E19)),ISNUMBER(SEARCH("MKT",$E19))),1,0) -> 1 | Y19: =IF(OR(ISNUMBER(SEARCH("ALL",$E19)),ISNUMBER(SEARCH("SCM",$E19))),1,0) -> 1 | Z19: =IF(OR(ISNUMBER(SEARCH("ALL",$E19)),ISNUMBER(SEARCH("FIN",$E19))),1,0) -> 1 | AA19: =IF(OR(ISNUMBER(SEARCH("ALL",$E19)),ISNUMBER(SEARCH("AGI",$E19))),1,0) -> 1
A20: 2.11 | B20: Device financing/subsidy schemes | C20: C1 | D20: Foundation | E20: ALL | G20: L | M20: No government or telco device-financing/subsidy scheme targeting low-income or rural users found for Egypt (searched 2026-08-22). What exists instead: (1) commercial telco handset installments — Telecom Egypt 'WE Gold' p | N20: NTRA (tra.gov.eg) — 'Start of the installment service for fees due on mobile phones imported from abroad through consumer finance companies' (Arabic, 6 April 2026); NTRA — 'End of exceptional exemption on imported mobile phones' (21 Jan 2026) | O20: https://www.tra.gov.eg/ar/%D8%A8%D8%AF%D8%A1-%D8%AA%D8%B7%D8%A8%D9%8A%D9%82-%D8%AE%D8%AF%D9%85%D8%A9-%D8%AA%D9%82%D8%B3%D9%8A%D8%B7-%D8%A7%D9%84%D8%B1%D8%B3%D9%88%D9%85-%D8%A7%D9%84%D9%85%D8%B3%D8%AA%D8%AD%D9%82%D8%A9-%D8%B9/ | P20: T3 | Q20: 2026 | R20: 1 | S20: =IF($M20="","",IF(ISNUMBER($M20),"Measured",IF(ISNUMBER(SEARCH("DATA GAP",UPPER($M20))),"Gap",IF(AND($N20<>"",$P20<>"T5"),"Documented","Judged")))) -> Documented | T20: =IF($AC20<>"","",IF(OR($S20="",$S20="Gap"),"",IF($S20="Measured",1+IF($H20="H",IF($M20>=$I20,1,0)+IF($M20>=$J20,1,0)+IF($M20>=$K20,1,0)+IF($M20>=$L20,1,0),IF($M20<=$I20,1,0)+IF($M20<=$J20,1,0)+IF($M20<=$K20,1,0)+IF($M20<=$L20,1,0)),IF($R20<>"",$R20,"")))) -> 1 | U20: =IF(OR($S20="",$S20="Gap",$Q20=""),"",IF($Q20<Config!$C$2-Config!$C$3,"STALE","")) | V20: =IF(OR(ISNUMBER(SEARCH("ALL",$E20)),ISNUMBER(SEARCH("ADV",$E20))),1,0) -> 1 | W20: =IF(OR(ISNUMBER(SEARCH("ALL",$E20)),ISNUMBER(SEARCH("SMF",$E20))),1,0) -> 1 | X20: =IF(OR(ISNUMBER(SEARCH("ALL",$E20)),ISNUMBER(SEARCH("MKT",$E20))),1,0) -> 1 | Y20: =IF(OR(ISNUMBER(SEARCH("ALL",$E20)),ISNUMBER(SEARCH("SCM",$E20))),1,0) -> 1 | Z20: =IF(OR(ISNUMBER(SEARCH("ALL",$E20)),ISNUMBER(SEARCH("FIN",$E20))),1,0) -> 1 | AA20: =IF(OR(ISNUMBER(SEARCH("ALL",$E20)),ISNUMBER(SEARCH("AGI",$E20))),1,0) -> 1 | AB20: The ladder's name fixes neither a targeting test nor whether a subsidy is required, and the two countries applied opposite tests to the same class of evidence — commercial telco handset instalments — producing a two-rung divergence.
A21: 3.1 | B21: UN E-Government Development Index | C21: C2 | D21: Enablers | E21: AGI,ALL | G21: T | H21: H | I21: 0.2 | J21: 0.4 | K21: 0.6 | L21: 0.8 | M21: 0.6699 | N21: UN E-Government Knowledgebase — Egypt country profile (E-Government Survey 2024) | O21: https://publicadministration.un.org/egovkb/en-us/Data/Country-Information/id/53-Egypt | P21: T1 | Q21: 2024 | S21: =IF($M21="","",IF(ISNUMBER($M21),"Measured",IF(ISNUMBER(SEARCH("DATA GAP",UPPER($M21))),"Gap",IF(AND($N21<>"",$P21<>"T5"),"Documented","Judged")))) -> Measured | T21: =IF($AC21<>"","",IF(OR($S21="",$S21="Gap"),"",IF($S21="Measured",1+IF($H21="H",IF($M21>=$I21,1,0)+IF($M21>=$J21,1,0)+IF($M21>=$K21,1,0)+IF($M21>=$L21,1,0),IF($M21<=$I21,1,0)+IF($M21<=$J21,1,0)+IF($M21<=$K21,1,0)+IF($M21<=$L21,1,0)),IF($R21<>"",$R21,"")))) -> 4 | U21: =IF(OR($S21="",$S21="Gap",$Q21=""),"",IF($Q21<Config!$C$2-Config!$C$3,"STALE","")) | V21: =IF(OR(ISNUMBER(SEARCH("ALL",$E21)),ISNUMBER(SEARCH("ADV",$E21))),1,0) -> 1 | W21: =IF(OR(ISNUMBER(SEARCH("ALL",$E21)),ISNUMBER(SEARCH("SMF",$E21))),1,0) -> 1 | X21: =IF(OR(ISNUMBER(SEARCH("ALL",$E21)),ISNUMBER(SEARCH("MKT",$E21))),1,0) -> 1 | Y21: =IF(OR(ISNUMBER(SEARCH("ALL",$E21)),ISNUMBER(SEARCH("SCM",$E21))),1,0) -> 1 | Z21: =IF(OR(ISNUMBER(SEARCH("ALL",$E21)),ISNUMBER(SEARCH("FIN",$E21))),1,0) -> 1 | AA21: =IF(OR(ISNUMBER(SEARCH("ALL",$E21)),ISNUMBER(SEARCH("AGI",$E21))),1,0) -> 1
A22: 3.3 | B22: National farmer registry | C22: C2 | D22: Enablers | E22: FIN,AGI,ADV | F22: UC:FIN,AGI | G22: L | M22: National farmer registry EXISTS and is OPERATING: the MALR 'Farmer Card' (كارت الفلاح) smart-card system is the national electronic agricultural holding registry. MALR spokesperson (via SIS, 28 Mar 2026): ~5 million farm | N22: SIS (State Information Service): 'Agriculture spokesperson: continued efforts to ensure support reaches farmers through the Farmer Card' [Arabic], 28 March 2026 | O22: https://sis.gov.eg/ar/%D8%A7%D9%84%D9%85%D8%B1%D9%83%D8%B2-%D8%A7%D9%84%D8%A5%D8%B9%D9%84%D8%A7%D9%85%D9%8A/%D8%A7%D9%84%D8%A3%D8%AE%D8%A8%D8%A7%D8%B1/%D9%85%D8%AA%D8%AD%D8%AF%D8%AB-%D8%A7%D9%84%D8%B2%D8%B1%D8%A7%D8%B9%D8%A9-%D8%AC%D9%87%D9%88%D8%AF-%D9%85%D8%B3%D8%AA%D9%85%D8%B1%D8%A9-%D9%84%D8%B6%D9%85%D8%A7%D9%86-%D9%88%D8%B5%D9%88%D9%84-%D8%A7%D9%84%D8%AF%D8%B9%D9%85-%D9%84%D9%84%D9%85%D8%B2%D8%A7%D8%B1%D8%B9%D9%8A%D9%86-%D9%85%D9%86-%D8%AE%D9%84%D8%A7%D9%84-%D9%83%D8%A7%D8%B1%D8%AA-%D8%A7%D9%84%D9%81%D9%84%D8%A7%D8%AD/ | P22: T3 | Q22: 2026 | R22: 4 | S22: =IF($M22="","",IF(ISNUMBER($M22),"Measured",IF(ISNUMBER(SEARCH("DATA GAP",UPPER($M22))),"Gap",IF(AND($N22<>"",$P22<>"T5"),"Documented","Judged")))) -> Documented | T22: =IF($AC22<>"","",IF(OR($S22="",$S22="Gap"),"",IF($S22="Measured",1+IF($H22="H",IF($M22>=$I22,1,0)+IF($M22>=$J22,1,0)+IF($M22>=$K22,1,0)+IF($M22>=$L22,1,0),IF($M22<=$I22,1,0)+IF($M22<=$J22,1,0)+IF($M22<=$K22,1,0)+IF($M22<=$L22,1,0)),IF($R22<>"",$R22,"")))) -> 4 | U22: =IF(OR($S22="",$S22="Gap",$Q22=""),"",IF($Q22<Config!$C$2-Config!$C$3,"STALE","")) | V22: =IF(OR(ISNUMBER(SEARCH("ALL",$E22)),ISNUMBER(SEARCH("ADV",$E22))),1,0) -> 1 | W22: =IF(OR(ISNUMBER(SEARCH("ALL",$E22)),ISNUMBER(SEARCH("SMF",$E22))),1,0) -> 0 | X22: =IF(OR(ISNUMBER(SEARCH("ALL",$E22)),ISNUMBER(SEARCH("MKT",$E22))),1,0) -> 0 | Y22: =IF(OR(ISNUMBER(SEARCH("ALL",$E22)),ISNUMBER(SEARCH("SCM",$E22))),1,0) -> 0 | Z22: =IF(OR(ISNUMBER(SEARCH("ALL",$E22)),ISNUMBER(SEARCH("FIN",$E22))),1,0) -> 1 | AA22: =IF(OR(ISNUMBER(SEARCH("ALL",$E22)),ISNUMBER(SEARCH("AGI",$E22))),1,0) -> 1 | AB22: The name implies a register of farmers (individuals), but Egypt's record is an agricultural holding registry embedded in a subsidy smart-card scheme, whose scale figures mix four non-comparable units — cards printed, cards distributed, farmers benefiting, and holdings registered — with no…
A23: 3.4 | B23: Digital land/plot registration | C23: C2 | D23: Enablers | E23: FIN,AGI | G23: L | M23: Digital land registration is ADOPTED but not yet a comprehensive operating digital cadastre. New: Law No. 88 of 2025 (signed 18 June 2025; Official Gazette issue 24-bis, 17 June 2025) establishes a unified national elect | N23: SIS: 'President El-Sisi Signs Law Establishing National Real Estate Identification Number Database' (Law 88/2025), June 2025 | O23: https://sis.gov.eg/Story/209329/President-El--Sisi-Signs-Law-Establishing-National-Real-Estate-Identification-Number-Database?lang=en-us | P23: T3 | Q23: 2025 | R23: 3 | S23: =IF($M23="","",IF(ISNUMBER($M23),"Measured",IF(ISNUMBER(SEARCH("DATA GAP",UPPER($M23))),"Gap",IF(AND($N23<>"",$P23<>"T5"),"Documented","Judged")))) -> Documented | T23: =IF($AC23<>"","",IF(OR($S23="",$S23="Gap"),"",IF($S23="Measured",1+IF($H23="H",IF($M23>=$I23,1,0)+IF($M23>=$J23,1,0)+IF($M23>=$K23,1,0)+IF($M23>=$L23,1,0),IF($M23<=$I23,1,0)+IF($M23<=$J23,1,0)+IF($M23<=$K23,1,0)+IF($M23<=$L23,1,0)),IF($R23<>"",$R23,"")))) -> 3 | U23: =IF(OR($S23="",$S23="Gap",$Q23=""),"",IF($Q23<Config!$C$2-Config!$C$3,"STALE","")) | V23: =IF(OR(ISNUMBER(SEARCH("ALL",$E23)),ISNUMBER(SEARCH("ADV",$E23))),1,0) -> 0 | W23: =IF(OR(ISNUMBER(SEARCH("ALL",$E23)),ISNUMBER(SEARCH("SMF",$E23))),1,0) -> 0 | X23: =IF(OR(ISNUMBER(SEARCH("ALL",$E23)),ISNUMBER(SEARCH("MKT",$E23))),1,0) -> 0 | Y23: =IF(OR(ISNUMBER(SEARCH("ALL",$E23)),ISNUMBER(SEARCH("SCM",$E23))),1,0) -> 0 | Z23: =IF(OR(ISNUMBER(SEARCH("ALL",$E23)),ISNUMBER(SEARCH("FIN",$E23))),1,0) -> 1 | AA23: =IF(OR(ISNUMBER(SEARCH("ALL",$E23)),ISNUMBER(SEARCH("AGI",$E23))),1,0) -> 1 | AB23: The name reads as one object but three distinct registers are in play — legal title, a national all-property real-estate ID database, and agricultural usufruct/holding records — and Egypt's rung-3 anchor is an economy-wide real-estate identification law (urban property included) scored inside an…
A24: 3.5 | B24: Open agricultural data (machine-readable, AI-ready) | C24: C2 | D24: Enablers | E24: AGI,ADV,SMF | G24: L | M24: Open agricultural data is ADOPTED in policy but the national open-data portal is NOT yet live. Egypt's first Open Data Policy (issued by the National Council for Artificial Intelligence, 2025; prepared by MCIT; reported | N24: Open Data Policy, Arab Republic of Egypt — issued by the National Council for Artificial Intelligence, 2025 (official PDF on ai.gov.eg) | O24: https://ai.gov.eg/SynchedFiles/en/Resources/Open%20Data%20Policy.pdf | P24: T3 | Q24: 2025 | R24: 2 | S24: =IF($M24="","",IF(ISNUMBER($M24),"Measured",IF(ISNUMBER(SEARCH("DATA GAP",UPPER($M24))),"Gap",IF(AND($N24<>"",$P24<>"T5"),"Documented","Judged")))) -> Documented | T24: =IF($AC24<>"","",IF(OR($S24="",$S24="Gap"),"",IF($S24="Measured",1+IF($H24="H",IF($M24>=$I24,1,0)+IF($M24>=$J24,1,0)+IF($M24>=$K24,1,0)+IF($M24>=$L24,1,0),IF($M24<=$I24,1,0)+IF($M24<=$J24,1,0)+IF($M24<=$K24,1,0)+IF($M24<=$L24,1,0)),IF($R24<>"",$R24,"")))) -> 2 | U24: =IF(OR($S24="",$S24="Gap",$Q24=""),"",IF($Q24<Config!$C$2-Config!$C$3,"STALE","")) | V24: =IF(OR(ISNUMBER(SEARCH("ALL",$E24)),ISNUMBER(SEARCH("ADV",$E24))),1,0) -> 1 | W24: =IF(OR(ISNUMBER(SEARCH("ALL",$E24)),ISNUMBER(SEARCH("SMF",$E24))),1,0) -> 1 | X24: =IF(OR(ISNUMBER(SEARCH("ALL",$E24)),ISNUMBER(SEARCH("MKT",$E24))),1,0) -> 0 | Y24: =IF(OR(ISNUMBER(SEARCH("ALL",$E24)),ISNUMBER(SEARCH("SCM",$E24))),1,0) -> 0 | Z24: =IF(OR(ISNUMBER(SEARCH("ALL",$E24)),ISNUMBER(SEARCH("FIN",$E24))),1,0) -> 0 | AA24: =IF(OR(ISNUMBER(SEARCH("ALL",$E24)),ISNUMBER(SEARCH("AGI",$E24))),1,0) -> 1 | AB24: ⚠ The name asserts three conjoined qualifiers — open, machine-readable, AI-ready — and Nigeria scores rung 4 ('Operating with quality') on a registration-gated statistical microdata catalog that the cell's own text says is neither open nor AI-ready, while Nigeria's actual open-data portals are…
A25: 3.6 | B25: Weather/climate data infrastructure | C25: C2 | D25: Enablers | E25: ADV,SMF,AGI | G25: L | M25: Weather/climate data infrastructure is OPERATING with ag-tailored services. The Egyptian Meteorological Authority (EMA) is the operational national met service (official site www.ema.gov.eg resolves; agrometeorology is a | N25: SIS: 'Agriculture issues its recommendations to farmers on dealing with the unstable weather wave in the coming days' [Arabic] (CLAC/ARC advisory) | O25: https://sis.gov.eg/ar/%D8%A7%D9%84%D9%85%D8%B1%D9%83%D8%B2-%D8%A7%D9%84%D8%A5%D8%B9%D9%84%D8%A7%D9%85%D9%8A/%D8%A7%D9%84%D8%A3%D8%AE%D8%A8%D8%A7%D8%B1/%D8%A7%D9%84%D8%B2%D8%B1%D8%A7%D8%B9%D8%A9-%D8%AA%D8%B5%D8%AF%D8%B1-%D8%AA%D9%88%D8%B5%D9%8A%D8%A7%D8%AA%D9%87%D8%A7-%D9%84%D9%84%D9%85%D8%B2%D8%A7%D8%B1%D8%B9%D9%8A%D9%86-%D9%81%D9%8A-%D9%83%D9%8A%D9%81%D9%8A%D8%A9-%D8%A7%D9%84%D8%AA%D8%B9%D8%A7%D9%85%D9%84-%D9%85%D8%B9-%D9%85%D9%88%D8%AC%D8%A9-%D8%A7%D9%84%D8%B7%D9%82%D8%B3-%D8%BA%D9%8A%D8%B1-%D9%85%D8%B3%D8%AA%D9%82%D8%B1%D8%A9-%D8%AE%D9%84%D8%A7%D9%84-%D8%A7%D9%84%D8%A3%D9%8A%D8%A7%D9%85-%D8%A7%D9%84%D9%82%D8%A7%D8%AF%D9%85%D8%A9/ | P25: T3 | Q25: 2026 | R25: 4 | S25: =IF($M25="","",IF(ISNUMBER($M25),"Measured",IF(ISNUMBER(SEARCH("DATA GAP",UPPER($M25))),"Gap",IF(AND($N25<>"",$P25<>"T5"),"Documented","Judged")))) -> Documented | T25: =IF($AC25<>"","",IF(OR($S25="",$S25="Gap"),"",IF($S25="Measured",1+IF($H25="H",IF($M25>=$I25,1,0)+IF($M25>=$J25,1,0)+IF($M25>=$K25,1,0)+IF($M25>=$L25,1,0),IF($M25<=$I25,1,0)+IF($M25<=$J25,1,0)+IF($M25<=$K25,1,0)+IF($M25<=$L25,1,0)),IF($R25<>"",$R25,"")))) -> 4 | U25: =IF(OR($S25="",$S25="Gap",$Q25=""),"",IF($Q25<Config!$C$2-Config!$C$3,"STALE","")) | V25: =IF(OR(ISNUMBER(SEARCH("ALL",$E25)),ISNUMBER(SEARCH("ADV",$E25))),1,0) -> 1 | W25: =IF(OR(ISNUMBER(SEARCH("ALL",$E25)),ISNUMBER(SEARCH("SMF",$E25))),1,0) -> 1 | X25: =IF(OR(ISNUMBER(SEARCH("ALL",$E25)),ISNUMBER(SEARCH("MKT",$E25))),1,0) -> 0 | Y25: =IF(OR(ISNUMBER(SEARCH("ALL",$E25)),ISNUMBER(SEARCH("SCM",$E25))),1,0) -> 0 | Z25: =IF(OR(ISNUMBER(SEARCH("ALL",$E25)),ISNUMBER(SEARCH("FIN",$E25))),1,0) -> 0 | AA25: =IF(OR(ISNUMBER(SEARCH("ALL",$E25)),ISNUMBER(SEARCH("AGI",$E25))),1,0) -> 1 | AB25: The name is data infrastructure — observation networks, archives, data access — but both countries are scored at rung 4 on advisory products issued to farmers, with no station density, archive, API or data-access evidence recorded on either row, and the advisory content overlaps indicator 8.17…
A26: 3.7 | B26: Satellite/EO data integration | C26: C2 | D26: Enablers | E26: AGI,SMF | G26: L | M26: Satellite/EO integration in agriculture is OPERATING beyond pilots. T3 (MALR press conference, 6 Dec 2021): MALR and MCIT used AI to inventory the cropped area of each crop on the ground ('completed the summer-season cro | N26: MALR: 'Ministers of Agriculture and Communications announce pilot launch of digital transformation services in the agricultural sector' [Arabic], 6 December 2021 (includes completed AI crop-area inventory) | O26: https://moa.gov.eg/highlights/%D8%AE%D8%AF%D9%85%D8%A7%D8%AA-%D8%A7%D9%84%D8%AA%D8%AD%D9%88%D9%84-%D8%A7%D9%84%D8%B1%D9%82%D9%85%D9%89/ | P26: T3 | Q26: 2024 | R26: 4 | S26: =IF($M26="","",IF(ISNUMBER($M26),"Measured",IF(ISNUMBER(SEARCH("DATA GAP",UPPER($M26))),"Gap",IF(AND($N26<>"",$P26<>"T5"),"Documented","Judged")))) -> Documented | T26: =IF($AC26<>"","",IF(OR($S26="",$S26="Gap"),"",IF($S26="Measured",1+IF($H26="H",IF($M26>=$I26,1,0)+IF($M26>=$J26,1,0)+IF($M26>=$K26,1,0)+IF($M26>=$L26,1,0),IF($M26<=$I26,1,0)+IF($M26<=$J26,1,0)+IF($M26<=$K26,1,0)+IF($M26<=$L26,1,0)),IF($R26<>"",$R26,"")))) -> 4 | U26: =IF(OR($S26="",$S26="Gap",$Q26=""),"",IF($Q26<Config!$C$2-Config!$C$3,"STALE","")) | V26: =IF(OR(ISNUMBER(SEARCH("ALL",$E26)),ISNUMBER(SEARCH("ADV",$E26))),1,0) -> 0 | W26: =IF(OR(ISNUMBER(SEARCH("ALL",$E26)),ISNUMBER(SEARCH("SMF",$E26))),1,0) -> 1 | X26: =IF(OR(ISNUMBER(SEARCH("ALL",$E26)),ISNUMBER(SEARCH("MKT",$E26))),1,0) -> 0 | Y26: =IF(OR(ISNUMBER(SEARCH("ALL",$E26)),ISNUMBER(SEARCH("SCM",$E26))),1,0) -> 0 | Z26: =IF(OR(ISNUMBER(SEARCH("ALL",$E26)),ISNUMBER(SEARCH("FIN",$E26))),1,0) -> 0 | AA26: =IF(OR(ISNUMBER(SEARCH("ALL",$E26)),ISNUMBER(SEARCH("AGI",$E26))),1,0) -> 1 | AB26: The name fixes neither the object nor the bar for 'integration' — Egypt is scored rung 4 on producing national crop maps, Nigeria rung 3 on institutional arrangements — and Egypt's 'operating beyond pilots' assertion rests on a source whose own title announces a pilot launch, recorded under year…
A27: 3.8 | B27: National soil map/database | C27: C2 | D27: Enablers | E27: ADV,SMF | G27: L | M27: No operating national digital soil map/database service found — best-verified status is ABSENT for a public national digital soil information service, with legacy and research assets: FAO Soils Portal hosts legacy (digit | N27: FAO Soils Portal — Regional and National Soil Maps and Databases (Egypt legacy maps) | O27: https://www.fao.org/soils-portal/data-hub/soil-maps-and-databases/regional-and-national-soil-maps-and-databases/en/ | P27: T1 | Q27: 2026 | R27: 1 | S27: =IF($M27="","",IF(ISNUMBER($M27),"Measured",IF(ISNUMBER(SEARCH("DATA GAP",UPPER($M27))),"Gap",IF(AND($N27<>"",$P27<>"T5"),"Documented","Judged")))) -> Documented | T27: =IF($AC27<>"","",IF(OR($S27="",$S27="Gap"),"",IF($S27="Measured",1+IF($H27="H",IF($M27>=$I27,1,0)+IF($M27>=$J27,1,0)+IF($M27>=$K27,1,0)+IF($M27>=$L27,1,0),IF($M27<=$I27,1,0)+IF($M27<=$J27,1,0)+IF($M27<=$K27,1,0)+IF($M27<=$L27,1,0)),IF($R27<>"",$R27,"")))) -> 1 | U27: =IF(OR($S27="",$S27="Gap",$Q27=""),"",IF($Q27<Config!$C$2-Config!$C$3,"STALE","")) | V27: =IF(OR(ISNUMBER(SEARCH("ALL",$E27)),ISNUMBER(SEARCH("ADV",$E27))),1,0) -> 1 | W27: =IF(OR(ISNUMBER(SEARCH("ALL",$E27)),ISNUMBER(SEARCH("SMF",$E27))),1,0) -> 1 | X27: =IF(OR(ISNUMBER(SEARCH("ALL",$E27)),ISNUMBER(SEARCH("MKT",$E27))),1,0) -> 0 | Y27: =IF(OR(ISNUMBER(SEARCH("ALL",$E27)),ISNUMBER(SEARCH("SCM",$E27))),1,0) -> 0 | Z27: =IF(OR(ISNUMBER(SEARCH("ALL",$E27)),ISNUMBER(SEARCH("FIN",$E27))),1,0) -> 0 | AA27: =IF(OR(ISNUMBER(SEARCH("ALL",$E27)),ISNUMBER(SEARCH("AGI",$E27))),1,0) -> 0 | AB27: Does a digitized legacy paper soil map satisfy the indicator, or does the ladder measure an operating digital soil information service?
A28: 3.11 | B28: Agricultural data interoperability standards | C28: C2 | D28: Enablers | E28: AGI,ALL | F28: UC:AGI | G28: L | M28: No published agricultural data interoperability standards/schemas found for Egypt — ABSENT after active refutation attempt. Nearest instruments, none ag-specific: (1) Open Data Policy (NCAI, 2025, T3) mandates cross-gove | N28: Open Data Policy, Arab Republic of Egypt (NCAI, 2025) — closest instrument; no ag-specific standard exists | O28: https://ai.gov.eg/SynchedFiles/en/Resources/Open%20Data%20Policy.pdf | P28: T3 | Q28: 2026 | R28: 1 | S28: =IF($M28="","",IF(ISNUMBER($M28),"Measured",IF(ISNUMBER(SEARCH("DATA GAP",UPPER($M28))),"Gap",IF(AND($N28<>"",$P28<>"T5"),"Documented","Judged")))) -> Documented | T28: =IF($AC28<>"","",IF(OR($S28="",$S28="Gap"),"",IF($S28="Measured",1+IF($H28="H",IF($M28>=$I28,1,0)+IF($M28>=$J28,1,0)+IF($M28>=$K28,1,0)+IF($M28>=$L28,1,0),IF($M28<=$I28,1,0)+IF($M28<=$J28,1,0)+IF($M28<=$K28,1,0)+IF($M28<=$L28,1,0)),IF($R28<>"",$R28,"")))) -> 1 | U28: =IF(OR($S28="",$S28="Gap",$Q28=""),"",IF($Q28<Config!$C$2-Config!$C$3,"STALE","")) | V28: =IF(OR(ISNUMBER(SEARCH("ALL",$E28)),ISNUMBER(SEARCH("ADV",$E28))),1,0) -> 1 | W28: =IF(OR(ISNUMBER(SEARCH("ALL",$E28)),ISNUMBER(SEARCH("SMF",$E28))),1,0) -> 1 | X28: =IF(OR(ISNUMBER(SEARCH("ALL",$E28)),ISNUMBER(SEARCH("MKT",$E28))),1,0) -> 1 | Y28: =IF(OR(ISNUMBER(SEARCH("ALL",$E28)),ISNUMBER(SEARCH("SCM",$E28))),1,0) -> 1 | Z28: =IF(OR(ISNUMBER(SEARCH("ALL",$E28)),ISNUMBER(SEARCH("FIN",$E28))),1,0) -> 1 | AA28: =IF(OR(ISNUMBER(SEARCH("ALL",$E28)),ISNUMBER(SEARCH("AGI",$E28))),1,0) -> 1 | AB28: Must the standard be agriculture-specific, or do cross-government open-data/DPI instruments and draft harmonisation work count as Present/Announced for this prerequisite cell?
A29: 4.1 | B29: Data protection/privacy law | C29: C3 | D29: Enablers | E29: ALL | F29: UNIVERSAL | G29: L | M29: Personal Data Protection Law No. 151/2020 in force since October 2020; Executive Regulations issued by Decree No. 816/2025 of the Minister of Communications and Information Technology on 1 November 2025, published in the | N29: Shalakany Law Office, "New Executive Regulations for Egypt's Personal Data Protection Law" (Dec 2025) — full-text analysis of Decree 816/2025 | O29: https://shalakany.com/wp-content/uploads/2025/12/New-Executive-Regulations-for-Egypts-Personal-Data-Protection-Law-.pdf | P29: T4 | Q29: 2025 | R29: 3 | S29: =IF($M29="","",IF(ISNUMBER($M29),"Measured",IF(ISNUMBER(SEARCH("DATA GAP",UPPER($M29))),"Gap",IF(AND($N29<>"",$P29<>"T5"),"Documented","Judged")))) -> Documented | T29: =IF($AC29<>"","",IF(OR($S29="",$S29="Gap"),"",IF($S29="Measured",1+IF($H29="H",IF($M29>=$I29,1,0)+IF($M29>=$J29,1,0)+IF($M29>=$K29,1,0)+IF($M29>=$L29,1,0),IF($M29<=$I29,1,0)+IF($M29<=$J29,1,0)+IF($M29<=$K29,1,0)+IF($M29<=$L29,1,0)),IF($R29<>"",$R29,"")))) -> 3 | U29: =IF(OR($S29="",$S29="Gap",$Q29=""),"",IF($Q29<Config!$C$2-Config!$C$3,"STALE","")) | V29: =IF(OR(ISNUMBER(SEARCH("ALL",$E29)),ISNUMBER(SEARCH("ADV",$E29))),1,0) -> 1 | W29: =IF(OR(ISNUMBER(SEARCH("ALL",$E29)),ISNUMBER(SEARCH("SMF",$E29))),1,0) -> 1 | X29: =IF(OR(ISNUMBER(SEARCH("ALL",$E29)),ISNUMBER(SEARCH("MKT",$E29))),1,0) -> 1 | Y29: =IF(OR(ISNUMBER(SEARCH("ALL",$E29)),ISNUMBER(SEARCH("SCM",$E29))),1,0) -> 1 | Z29: =IF(OR(ISNUMBER(SEARCH("ALL",$E29)),ISNUMBER(SEARCH("FIN",$E29))),1,0) -> 1 | AA29: =IF(OR(ISNUMBER(SEARCH("ALL",$E29)),ISNUMBER(SEARCH("AGI",$E29))),1,0) -> 1
A30: 4.2 | B30: Cybersecurity framework (ITU GCI) | C30: C3 | D30: Enablers | E30: ALL | G30: T | H30: H | I30: 0.2 | J30: 0.4 | K30: 0.6 | L30: 0.8 | M30: 100 | N30: ITU Global Cybersecurity Index 2024 (5th edition) — Egypt in Tier 1 'Role-modelling' (score band 95-100); exact score 100/100 per NTRA announcement | O30: https://www.itu.int/dms_pub/itu-d/opb/hdb/D-HDB-GCI.01-2024-PDF-E.pdf | P30: T1 | Q30: 2024 | S30: =IF($M30="","",IF(ISNUMBER($M30),"Measured",IF(ISNUMBER(SEARCH("DATA GAP",UPPER($M30))),"Gap",IF(AND($N30<>"",$P30<>"T5"),"Documented","Judged")))) -> Measured | T30: =IF($AC30<>"","",IF(OR($S30="",$S30="Gap"),"",IF($S30="Measured",1+IF($H30="H",IF($M30>=$I30,1,0)+IF($M30>=$J30,1,0)+IF($M30>=$K30,1,0)+IF($M30>=$L30,1,0),IF($M30<=$I30,1,0)+IF($M30<=$J30,1,0)+IF($M30<=$K30,1,0)+IF($M30<=$L30,1,0)),IF($R30<>"",$R30,"")))) -> 5 | U30: =IF(OR($S30="",$S30="Gap",$Q30=""),"",IF($Q30<Config!$C$2-Config!$C$3,"STALE","")) | V30: =IF(OR(ISNUMBER(SEARCH("ALL",$E30)),ISNUMBER(SEARCH("ADV",$E30))),1,0) -> 1 | W30: =IF(OR(ISNUMBER(SEARCH("ALL",$E30)),ISNUMBER(SEARCH("SMF",$E30))),1,0) -> 1 | X30: =IF(OR(ISNUMBER(SEARCH("ALL",$E30)),ISNUMBER(SEARCH("MKT",$E30))),1,0) -> 1 | Y30: =IF(OR(ISNUMBER(SEARCH("ALL",$E30)),ISNUMBER(SEARCH("SCM",$E30))),1,0) -> 1 | Z30: =IF(OR(ISNUMBER(SEARCH("ALL",$E30)),ISNUMBER(SEARCH("FIN",$E30))),1,0) -> 1 | AA30: =IF(OR(ISNUMBER(SEARCH("ALL",$E30)),ISNUMBER(SEARCH("AGI",$E30))),1,0) -> 1 | AB30: Thresholds are defined on a 0–1 basis but Egypt is recorded as 100 and Nigeria as 0.824, so the same register column holds two incommensurable scales; separately, neither number is an overall score ITU actually publishes in the GCI 2024 report.
A31: 4.3 | B31: Government AI Readiness Index | C31: C3 | D31: Enablers | E31: AGI,ALL | G31: T | H31: H | I31: 20 | J31: 40 | K31: 60 | L31: 80 | M31: 55.63 | N31: Oxford Insights Government AI Readiness Index 2024 — Full rankings annex: Egypt total 55.63 (Government 68.98, Technology Sector 42.13, Data & Infrastructure 55.77) | O31: https://oxfordinsights.com/wp-content/uploads/2024/12/2024-Government-AI-Readiness-Index.pdf | P31: T4 | Q31: 2024 | S31: =IF($M31="","",IF(ISNUMBER($M31),"Measured",IF(ISNUMBER(SEARCH("DATA GAP",UPPER($M31))),"Gap",IF(AND($N31<>"",$P31<>"T5"),"Documented","Judged")))) -> Measured | T31: =IF($AC31<>"","",IF(OR($S31="",$S31="Gap"),"",IF($S31="Measured",1+IF($H31="H",IF($M31>=$I31,1,0)+IF($M31>=$J31,1,0)+IF($M31>=$K31,1,0)+IF($M31>=$L31,1,0),IF($M31<=$I31,1,0)+IF($M31<=$J31,1,0)+IF($M31<=$K31,1,0)+IF($M31<=$L31,1,0)),IF($R31<>"",$R31,"")))) -> 3 | U31: =IF(OR($S31="",$S31="Gap",$Q31=""),"",IF($Q31<Config!$C$2-Config!$C$3,"STALE","")) | V31: =IF(OR(ISNUMBER(SEARCH("ALL",$E31)),ISNUMBER(SEARCH("ADV",$E31))),1,0) -> 1 | W31: =IF(OR(ISNUMBER(SEARCH("ALL",$E31)),ISNUMBER(SEARCH("SMF",$E31))),1,0) -> 1 | X31: =IF(OR(ISNUMBER(SEARCH("ALL",$E31)),ISNUMBER(SEARCH("MKT",$E31))),1,0) -> 1 | Y31: =IF(OR(ISNUMBER(SEARCH("ALL",$E31)),ISNUMBER(SEARCH("SCM",$E31))),1,0) -> 1 | Z31: =IF(OR(ISNUMBER(SEARCH("ALL",$E31)),ISNUMBER(SEARCH("FIN",$E31))),1,0) -> 1 | AA31: =IF(OR(ISNUMBER(SEARCH("ALL",$E31)),ISNUMBER(SEARCH("AGI",$E31))),1,0) -> 1 | AB31: Now that the 2025 edition dropped the open overall score, does the cell score the stale 2024 overall score, substitute rank plus pillar scores, or gap?
A32: 4.4 | B32: National digital agriculture strategy | C32: C3 | D32: Enablers | E32: ALL | G32: L | M32: No dedicated national digital agriculture strategy identified as of August 2026. Digital agriculture exists as components inside broader frameworks: (a) the updated Sustainable Agricultural Development Strategy (SADS 203 | N32: MCIT press release, 'ICT Minister, Agriculture Minister follow up on joint digital transformation projects', 9 June 2021 | O32: https://mcit.gov.eg/en/Media_Center/Press_Room/Press_Releases/63422 | P32: T3 | Q32: 2021 | R32: 1 | S32: =IF($M32="","",IF(ISNUMBER($M32),"Measured",IF(ISNUMBER(SEARCH("DATA GAP",UPPER($M32))),"Gap",IF(AND($N32<>"",$P32<>"T5"),"Documented","Judged")))) -> Documented | T32: =IF($AC32<>"","",IF(OR($S32="",$S32="Gap"),"",IF($S32="Measured",1+IF($H32="H",IF($M32>=$I32,1,0)+IF($M32>=$J32,1,0)+IF($M32>=$K32,1,0)+IF($M32>=$L32,1,0),IF($M32<=$I32,1,0)+IF($M32<=$J32,1,0)+IF($M32<=$K32,1,0)+IF($M32<=$L32,1,0)),IF($R32<>"",$R32,"")))) -> 1 | U32: =IF(OR($S32="",$S32="Gap",$Q32=""),"",IF($Q32<Config!$C$2-Config!$C$3,"STALE","")) -> STALE | V32: =IF(OR(ISNUMBER(SEARCH("ALL",$E32)),ISNUMBER(SEARCH("ADV",$E32))),1,0) -> 1 | W32: =IF(OR(ISNUMBER(SEARCH("ALL",$E32)),ISNUMBER(SEARCH("SMF",$E32))),1,0) -> 1 | X32: =IF(OR(ISNUMBER(SEARCH("ALL",$E32)),ISNUMBER(SEARCH("MKT",$E32))),1,0) -> 1 | Y32: =IF(OR(ISNUMBER(SEARCH("ALL",$E32)),ISNUMBER(SEARCH("SCM",$E32))),1,0) -> 1 | Z32: =IF(OR(ISNUMBER(SEARCH("ALL",$E32)),ISNUMBER(SEARCH("FIN",$E32))),1,0) -> 1 | AA32: =IF(OR(ISNUMBER(SEARCH("ALL",$E32)),ISNUMBER(SEARCH("AGI",$E32))),1,0) -> 1 | AB32: Does the indicator score only a dedicated digital-agriculture strategy document, or does it credit digital-ag components embedded in broader national strategies and active programmes running without a strategy?
A33: 4.5 | B33: Agricultural data governance framework | C33: C3 | D33: Enablers | E33: AGI,FIN | F33: UC:AGI | G33: L | M33: No agricultural data governance framework (sector-specific rules on agricultural data sharing, ownership or use) identified — refutation attempt failed. The general PDPL 151/2020 and its Executive Regulations (Decree 816 | N33: OECD, Policies for the Future of Farming and Food in Egypt (agricultural policy review — no agricultural data governance instrument appears) | O33: https://www.oecd.org/en/publications/policies-for-the-future-of-farming-and-food-in-egypt_cab0cefd-en/full-report/trends-and-evaluation-of-agricultural-policy-in-egypt_416e1bd0.html | P33: T2 | Q33: 2026 | R33: 1 | S33: =IF($M33="","",IF(ISNUMBER($M33),"Measured",IF(ISNUMBER(SEARCH("DATA GAP",UPPER($M33))),"Gap",IF(AND($N33<>"",$P33<>"T5"),"Documented","Judged")))) -> Documented | T33: =IF($AC33<>"","",IF(OR($S33="",$S33="Gap"),"",IF($S33="Measured",1+IF($H33="H",IF($M33>=$I33,1,0)+IF($M33>=$J33,1,0)+IF($M33>=$K33,1,0)+IF($M33>=$L33,1,0),IF($M33<=$I33,1,0)+IF($M33<=$J33,1,0)+IF($M33<=$K33,1,0)+IF($M33<=$L33,1,0)),IF($R33<>"",$R33,"")))) -> 1 | U33: =IF(OR($S33="",$S33="Gap",$Q33=""),"",IF($Q33<Config!$C$2-Config!$C$3,"STALE","")) | V33: =IF(OR(ISNUMBER(SEARCH("ALL",$E33)),ISNUMBER(SEARCH("ADV",$E33))),1,0) -> 0 | W33: =IF(OR(ISNUMBER(SEARCH("ALL",$E33)),ISNUMBER(SEARCH("SMF",$E33))),1,0) -> 0 | X33: =IF(OR(ISNUMBER(SEARCH("ALL",$E33)),ISNUMBER(SEARCH("MKT",$E33))),1,0) -> 0 | Y33: =IF(OR(ISNUMBER(SEARCH("ALL",$E33)),ISNUMBER(SEARCH("SCM",$E33))),1,0) -> 0 | Z33: =IF(OR(ISNUMBER(SEARCH("ALL",$E33)),ISNUMBER(SEARCH("FIN",$E33))),1,0) -> 1 | AA33: =IF(OR(ISNUMBER(SEARCH("ALL",$E33)),ISNUMBER(SEARCH("AGI",$E33))),1,0) -> 1
A34: 4.6 | B34: National AI strategy with agriculture component | C34: C3 | D34: Enablers | E34: AGI,ALL | G34: L | M34: Egypt National AI Strategy, 2nd edition (2025-2030), unveiled January 2025 (1st edition 2021), explicitly includes agriculture: named among strategic sectors for AI integration ('agriculture, manufacturing, defense, educ | N34: Egypt National Artificial Intelligence Strategy, Second Edition 2025-2030 (official English text, ai.gov.eg, 16 Jan 2025) | O34: https://ai.gov.eg/SynchedFiles/en/Resources/AIstrategy%20English%2016-1-2025-1.pdf | P34: T3 | Q34: 2025 | R34: 4 | S34: =IF($M34="","",IF(ISNUMBER($M34),"Measured",IF(ISNUMBER(SEARCH("DATA GAP",UPPER($M34))),"Gap",IF(AND($N34<>"",$P34<>"T5"),"Documented","Judged")))) -> Documented | T34: =IF($AC34<>"","",IF(OR($S34="",$S34="Gap"),"",IF($S34="Measured",1+IF($H34="H",IF($M34>=$I34,1,0)+IF($M34>=$J34,1,0)+IF($M34>=$K34,1,0)+IF($M34>=$L34,1,0),IF($M34<=$I34,1,0)+IF($M34<=$J34,1,0)+IF($M34<=$K34,1,0)+IF($M34<=$L34,1,0)),IF($R34<>"",$R34,"")))) -> 4 | U34: =IF(OR($S34="",$S34="Gap",$Q34=""),"",IF($Q34<Config!$C$2-Config!$C$3,"STALE","")) | V34: =IF(OR(ISNUMBER(SEARCH("ALL",$E34)),ISNUMBER(SEARCH("ADV",$E34))),1,0) -> 1 | W34: =IF(OR(ISNUMBER(SEARCH("ALL",$E34)),ISNUMBER(SEARCH("SMF",$E34))),1,0) -> 1 | X34: =IF(OR(ISNUMBER(SEARCH("ALL",$E34)),ISNUMBER(SEARCH("MKT",$E34))),1,0) -> 1 | Y34: =IF(OR(ISNUMBER(SEARCH("ALL",$E34)),ISNUMBER(SEARCH("SCM",$E34))),1,0) -> 1 | Z34: =IF(OR(ISNUMBER(SEARCH("ALL",$E34)),ISNUMBER(SEARCH("FIN",$E34))),1,0) -> 1 | AA34: =IF(OR(ISNUMBER(SEARCH("ALL",$E34)),ISNUMBER(SEARCH("AGI",$E34))),1,0) -> 1 | AB34: What evidence makes a strategy 'Adopted' — official publication, or formal executive/cabinet approval?
A35: 4.7 | B35: Digital ID coverage (%) | C35: C3 | D35: Enablers | E35: FIN,ALL | F35: UC:FIN | G35: T | H35: H | I35: 20 | J35: 40 | K35: 60 | L35: 80 | M35: 98.8 | N35: World Bank Identification for Development (ID4D) Data — ID ownership, total (% of population ages 15+), Egypt, 2024 observation: 98.78 (API value 98.7781785562663; source 89, indicator ID.OWN.TOTL.ZS; 2025 dataset update based on the Global Findex 2024 survey round) | O35: https://api.worldbank.org/v2/country/EGY/indicator/ID.OWN.TOTL.ZS?format=json&source=89 | P35: T1 | Q35: 2024 | S35: =IF($M35="","",IF(ISNUMBER($M35),"Measured",IF(ISNUMBER(SEARCH("DATA GAP",UPPER($M35))),"Gap",IF(AND($N35<>"",$P35<>"T5"),"Documented","Judged")))) -> Measured | T35: =IF($AC35<>"","",IF(OR($S35="",$S35="Gap"),"",IF($S35="Measured",1+IF($H35="H",IF($M35>=$I35,1,0)+IF($M35>=$J35,1,0)+IF($M35>=$K35,1,0)+IF($M35>=$L35,1,0),IF($M35<=$I35,1,0)+IF($M35<=$J35,1,0)+IF($M35<=$K35,1,0)+IF($M35<=$L35,1,0)),IF($R35<>"",$R35,"")))) -> 5 | U35: =IF(OR($S35="",$S35="Gap",$Q35=""),"",IF($Q35<Config!$C$2-Config!$C$3,"STALE","")) | V35: =IF(OR(ISNUMBER(SEARCH("ALL",$E35)),ISNUMBER(SEARCH("ADV",$E35))),1,0) -> 1 | W35: =IF(OR(ISNUMBER(SEARCH("ALL",$E35)),ISNUMBER(SEARCH("SMF",$E35))),1,0) -> 1 | X35: =IF(OR(ISNUMBER(SEARCH("ALL",$E35)),ISNUMBER(SEARCH("MKT",$E35))),1,0) -> 1 | Y35: =IF(OR(ISNUMBER(SEARCH("ALL",$E35)),ISNUMBER(SEARCH("SCM",$E35))),1,0) -> 1 | Z35: =IF(OR(ISNUMBER(SEARCH("ALL",$E35)),ISNUMBER(SEARCH("FIN",$E35))),1,0) -> 1 | AA35: =IF(OR(ISNUMBER(SEARCH("ALL",$E35)),ISNUMBER(SEARCH("AGI",$E35))),1,0) -> 1 | AB35: ⚠ The name asserts a digital ID, but Egypt records the World Bank ID4D foundational national-ID-card ownership series while ID4D's actual digital-ID series exists and was not used — and on top of that the two countries are recorded on different denominators (Egypt % of adults 15+, Nigeria % of…
A36: 4.9 | B36: Inter-ministerial coordination mechanism | C36: C3 | D36: Enablers | E36: ALL | F36: DELIVERY | G36: L | M36: No gazetted standing inter-ministerial committee for digital agriculture identified; what exists and is documented is a continuous de facto coordination mechanism between MALR and MCIT: recurring joint ministerial review | N36: MCIT press release, 9 June 2021 — ICT and Agriculture Ministers follow up on joint digital transformation projects (portfolio listed; MALR digital transformation unit created) | O36: https://mcit.gov.eg/en/Media_Center/Press_Room/Press_Releases/63422 | P36: T3 | Q36: 2021 | R36: 4 | S36: =IF($M36="","",IF(ISNUMBER($M36),"Measured",IF(ISNUMBER(SEARCH("DATA GAP",UPPER($M36))),"Gap",IF(AND($N36<>"",$P36<>"T5"),"Documented","Judged")))) -> Documented | T36: =IF($AC36<>"","",IF(OR($S36="",$S36="Gap"),"",IF($S36="Measured",1+IF($H36="H",IF($M36>=$I36,1,0)+IF($M36>=$J36,1,0)+IF($M36>=$K36,1,0)+IF($M36>=$L36,1,0),IF($M36<=$I36,1,0)+IF($M36<=$J36,1,0)+IF($M36<=$K36,1,0)+IF($M36<=$L36,1,0)),IF($R36<>"",$R36,"")))) -> 4 | U36: =IF(OR($S36="",$S36="Gap",$Q36=""),"",IF($Q36<Config!$C$2-Config!$C$3,"STALE","")) -> STALE | V36: =IF(OR(ISNUMBER(SEARCH("ALL",$E36)),ISNUMBER(SEARCH("ADV",$E36))),1,0) -> 1 | W36: =IF(OR(ISNUMBER(SEARCH("ALL",$E36)),ISNUMBER(SEARCH("SMF",$E36))),1,0) -> 1 | X36: =IF(OR(ISNUMBER(SEARCH("ALL",$E36)),ISNUMBER(SEARCH("MKT",$E36))),1,0) -> 1 | Y36: =IF(OR(ISNUMBER(SEARCH("ALL",$E36)),ISNUMBER(SEARCH("SCM",$E36))),1,0) -> 1 | Z36: =IF(OR(ISNUMBER(SEARCH("ALL",$E36)),ISNUMBER(SEARCH("FIN",$E36))),1,0) -> 1 | AA36: =IF(OR(ISNUMBER(SEARCH("ALL",$E36)),ISNUMBER(SEARCH("AGI",$E36))),1,0) -> 1 | AB36: Does the indicator require a formally constituted standing body or committee, or does any documented recurring — including project-based — coordination mechanism satisfy it?
A37: 5.2 | B37: Adult literacy rate (%) | C37: C4 | D37: Enablers | E37: ALL | G37: T | H37: H | I37: 50 | J37: 65 | K37: 80 | L37: 90 | M37: 79.453162 | N37: World Bank WDI SE.ADT.LITR.ZS | O37: https://api.worldbank.org/v2/country/EGY/indicator/SE.ADT.LITR.ZS?format=json&mrnev=1&per_page=5 | P37: T1 | Q37: 2022 | S37: =IF($M37="","",IF(ISNUMBER($M37),"Measured",IF(ISNUMBER(SEARCH("DATA GAP",UPPER($M37))),"Gap",IF(AND($N37<>"",$P37<>"T5"),"Documented","Judged")))) -> Measured | T37: =IF($AC37<>"","",IF(OR($S37="",$S37="Gap"),"",IF($S37="Measured",1+IF($H37="H",IF($M37>=$I37,1,0)+IF($M37>=$J37,1,0)+IF($M37>=$K37,1,0)+IF($M37>=$L37,1,0),IF($M37<=$I37,1,0)+IF($M37<=$J37,1,0)+IF($M37<=$K37,1,0)+IF($M37<=$L37,1,0)),IF($R37<>"",$R37,"")))) -> 3 | U37: =IF(OR($S37="",$S37="Gap",$Q37=""),"",IF($Q37<Config!$C$2-Config!$C$3,"STALE","")) -> STALE | V37: =IF(OR(ISNUMBER(SEARCH("ALL",$E37)),ISNUMBER(SEARCH("ADV",$E37))),1,0) -> 1 | W37: =IF(OR(ISNUMBER(SEARCH("ALL",$E37)),ISNUMBER(SEARCH("SMF",$E37))),1,0) -> 1 | X37: =IF(OR(ISNUMBER(SEARCH("ALL",$E37)),ISNUMBER(SEARCH("MKT",$E37))),1,0) -> 1 | Y37: =IF(OR(ISNUMBER(SEARCH("ALL",$E37)),ISNUMBER(SEARCH("SCM",$E37))),1,0) -> 1 | Z37: =IF(OR(ISNUMBER(SEARCH("ALL",$E37)),ISNUMBER(SEARCH("FIN",$E37))),1,0) -> 1 | AA37: =IF(OR(ISNUMBER(SEARCH("ALL",$E37)),ISNUMBER(SEARCH("AGI",$E37))),1,0) -> 1
A38: 5.3 | B38: Tertiary STEM enrollment (% gross) | C38: C4 | D38: Enablers | E38: ALL | G38: T | H38: H | I38: 10 | J38: 20 | K38: 30 | L38: 40 | M38: 38.039835 | N38: World Bank WDI SE.TER.ENRR | O38: https://api.worldbank.org/v2/country/EGY/indicator/SE.TER.ENRR?format=json&mrnev=1&per_page=5 | P38: T1 | Q38: 2025 | S38: =IF($M38="","",IF(ISNUMBER($M38),"Measured",IF(ISNUMBER(SEARCH("DATA GAP",UPPER($M38))),"Gap",IF(AND($N38<>"",$P38<>"T5"),"Documented","Judged")))) -> Measured | T38: =IF($AC38<>"","",IF(OR($S38="",$S38="Gap"),"",IF($S38="Measured",1+IF($H38="H",IF($M38>=$I38,1,0)+IF($M38>=$J38,1,0)+IF($M38>=$K38,1,0)+IF($M38>=$L38,1,0),IF($M38<=$I38,1,0)+IF($M38<=$J38,1,0)+IF($M38<=$K38,1,0)+IF($M38<=$L38,1,0)),IF($R38<>"",$R38,"")))) | U38: =IF(OR($S38="",$S38="Gap",$Q38=""),"",IF($Q38<Config!$C$2-Config!$C$3,"STALE","")) | V38: =IF(OR(ISNUMBER(SEARCH("ALL",$E38)),ISNUMBER(SEARCH("ADV",$E38))),1,0) -> 1 | W38: =IF(OR(ISNUMBER(SEARCH("ALL",$E38)),ISNUMBER(SEARCH("SMF",$E38))),1,0) -> 1 | X38: =IF(OR(ISNUMBER(SEARCH("ALL",$E38)),ISNUMBER(SEARCH("MKT",$E38))),1,0) -> 1 | Y38: =IF(OR(ISNUMBER(SEARCH("ALL",$E38)),ISNUMBER(SEARCH("SCM",$E38))),1,0) -> 1 | Z38: =IF(OR(ISNUMBER(SEARCH("ALL",$E38)),ISNUMBER(SEARCH("FIN",$E38))),1,0) -> 1 | AA38: =IF(OR(ISNUMBER(SEARCH("ALL",$E38)),ISNUMBER(SEARCH("AGI",$E38))),1,0) -> 1 | AB38: ⚠ The name asserts the STEM subset of tertiary enrollment, but both countries record World Bank WDI SE.TER.ENRR, which is total tertiary gross enrollment across all fields, and the level is then scored against thresholds calibrated for a STEM share. | AC38: HOLD
A39: 5.4 | B39: Digital literacy among farmers (%) | C39: C4 | D39: Enablers | E39: ALL | G39: T | H39: H | I39: 10 | J39: 25 | K39: 50 | L39: 75 | M39: No national farmer-specific digital-literacy rate is published for Egypt. Best available evidence (regional, single-source): IFPRI RCT baseline phone survey, Minya & Beni Suef governorates, Jul-Sep 2023, n=3,332 farmers: | N39: Abdelaziz, F. & Abay, K.A. (2025). Digital literacy training to promote diffusion of digital agricultural tools to smallholder farmers: Evidence from a randomized intervention in Egypt. IFPRI Discussion Paper 2359 (baseline survey Jul-Sep 2023) | O39: https://cgspace.cgiar.org/items/18a9ca8e-af59-4f88-a5e1-4b7a2a9155cd | P39: T2 | Q39: 2023 | S39: =IF($M39="","",IF(ISNUMBER($M39),"Measured",IF(ISNUMBER(SEARCH("DATA GAP",UPPER($M39))),"Gap",IF(AND($N39<>"",$P39<>"T5"),"Documented","Judged")))) -> Documented | T39: =IF($AC39<>"","",IF(OR($S39="",$S39="Gap"),"",IF($S39="Measured",1+IF($H39="H",IF($M39>=$I39,1,0)+IF($M39>=$J39,1,0)+IF($M39>=$K39,1,0)+IF($M39>=$L39,1,0),IF($M39<=$I39,1,0)+IF($M39<=$J39,1,0)+IF($M39<=$K39,1,0)+IF($M39<=$L39,1,0)),IF($R39<>"",$R39,"")))) | U39: =IF(OR($S39="",$S39="Gap",$Q39=""),"",IF($Q39<Config!$C$2-Config!$C$3,"STALE","")) | V39: =IF(OR(ISNUMBER(SEARCH("ALL",$E39)),ISNUMBER(SEARCH("ADV",$E39))),1,0) -> 1 | W39: =IF(OR(ISNUMBER(SEARCH("ALL",$E39)),ISNUMBER(SEARCH("SMF",$E39))),1,0) -> 1 | X39: =IF(OR(ISNUMBER(SEARCH("ALL",$E39)),ISNUMBER(SEARCH("MKT",$E39))),1,0) -> 1 | Y39: =IF(OR(ISNUMBER(SEARCH("ALL",$E39)),ISNUMBER(SEARCH("SCM",$E39))),1,0) -> 1 | Z39: =IF(OR(ISNUMBER(SEARCH("ALL",$E39)),ISNUMBER(SEARCH("FIN",$E39))),1,0) -> 1 | AA39: =IF(OR(ISNUMBER(SEARCH("ALL",$E39)),ISNUMBER(SEARCH("AGI",$E39))),1,0) -> 1 | AB39: The name asserts a national digital-literacy rate among farmers, but Nigeria records rural-population digital skills and Egypt records a two-governorate RCT baseline whose headline figure is digital ILliteracy, the inverse of the indicator's H direction. | AC39: HOLD
A40: 5.5 | B40: Digital extension capability | C40: C4 | D40: Enablers | E40: ADV | F40: UC:ADV | G40: L | M40: Government digital-extension channels are operating: El-Mufeed (FAO/MALR digital advisory app, launched 2020, content produced with ARC, presented to extension agents from all governorates) and Hudhud AI farmer assistant | N40: IFPRI Policy Note Dec 2025 (Digital Services Portfolio/El-Mufeed operating); UN Egypt/FAO-MALR programme page | O40: https://cgspace.cgiar.org/server/api/core/bitstreams/d4a33acc-564a-4e4c-a413-81ba3ebd4d90/content | P40: T2 | Q40: 2025 | R40: 4 | S40: =IF($M40="","",IF(ISNUMBER($M40),"Measured",IF(ISNUMBER(SEARCH("DATA GAP",UPPER($M40))),"Gap",IF(AND($N40<>"",$P40<>"T5"),"Documented","Judged")))) -> Documented | T40: =IF($AC40<>"","",IF(OR($S40="",$S40="Gap"),"",IF($S40="Measured",1+IF($H40="H",IF($M40>=$I40,1,0)+IF($M40>=$J40,1,0)+IF($M40>=$K40,1,0)+IF($M40>=$L40,1,0),IF($M40<=$I40,1,0)+IF($M40<=$J40,1,0)+IF($M40<=$K40,1,0)+IF($M40<=$L40,1,0)),IF($R40<>"",$R40,"")))) -> 4 | U40: =IF(OR($S40="",$S40="Gap",$Q40=""),"",IF($Q40<Config!$C$2-Config!$C$3,"STALE","")) | V40: =IF(OR(ISNUMBER(SEARCH("ALL",$E40)),ISNUMBER(SEARCH("ADV",$E40))),1,0) -> 1 | W40: =IF(OR(ISNUMBER(SEARCH("ALL",$E40)),ISNUMBER(SEARCH("SMF",$E40))),1,0) -> 0 | X40: =IF(OR(ISNUMBER(SEARCH("ALL",$E40)),ISNUMBER(SEARCH("MKT",$E40))),1,0) -> 0 | Y40: =IF(OR(ISNUMBER(SEARCH("ALL",$E40)),ISNUMBER(SEARCH("SCM",$E40))),1,0) -> 0 | Z40: =IF(OR(ISNUMBER(SEARCH("ALL",$E40)),ISNUMBER(SEARCH("FIN",$E40))),1,0) -> 0 | AA40: =IF(OR(ISNUMBER(SEARCH("ALL",$E40)),ISNUMBER(SEARCH("AGI",$E40))),1,0) -> 0
A41: 5.7 | B41: MoAg digital/AI unit | C41: C4 | D41: Enablers | E41: ALL | F41: DELIVERY | G41: L | M41: A joint MALR-MCIT digital transformation program has been operating since 6 Dec 2021 (Hudhud AI assistant; agricultural e-portal with 20 services in trial operation; AI/satellite crop mapping; quarantine mechanisation; d | N41: MCIT-MALR joint press release, 'Digital Transformation Services in Agriculture Announced' (6 December 2021) | O41: https://mcit.gov.eg/en/Media_Center/Press_Room/Press_Releases/64824 | P41: T3 | Q41: 2021 | S41: =IF($M41="","",IF(ISNUMBER($M41),"Measured",IF(ISNUMBER(SEARCH("DATA GAP",UPPER($M41))),"Gap",IF(AND($N41<>"",$P41<>"T5"),"Documented","Judged")))) -> Documented | T41: =IF($AC41<>"","",IF(OR($S41="",$S41="Gap"),"",IF($S41="Measured",1+IF($H41="H",IF($M41>=$I41,1,0)+IF($M41>=$J41,1,0)+IF($M41>=$K41,1,0)+IF($M41>=$L41,1,0),IF($M41<=$I41,1,0)+IF($M41<=$J41,1,0)+IF($M41<=$K41,1,0)+IF($M41<=$L41,1,0)),IF($R41<>"",$R41,"")))) | U41: =IF(OR($S41="",$S41="Gap",$Q41=""),"",IF($Q41<Config!$C$2-Config!$C$3,"STALE","")) -> STALE | V41: =IF(OR(ISNUMBER(SEARCH("ALL",$E41)),ISNUMBER(SEARCH("ADV",$E41))),1,0) -> 1 | W41: =IF(OR(ISNUMBER(SEARCH("ALL",$E41)),ISNUMBER(SEARCH("SMF",$E41))),1,0) -> 1 | X41: =IF(OR(ISNUMBER(SEARCH("ALL",$E41)),ISNUMBER(SEARCH("MKT",$E41))),1,0) -> 1 | Y41: =IF(OR(ISNUMBER(SEARCH("ALL",$E41)),ISNUMBER(SEARCH("SCM",$E41))),1,0) -> 1 | Z41: =IF(OR(ISNUMBER(SEARCH("ALL",$E41)),ISNUMBER(SEARCH("FIN",$E41))),1,0) -> 1 | AA41: =IF(OR(ISNUMBER(SEARCH("ALL",$E41)),ISNUMBER(SEARCH("AGI",$E41))),1,0) -> 1 | AB41: ⚠ The name asserts a standing digital/AI unit inside the ministry of agriculture, but Egypt is scored level 3 on a joint MALR-MCIT programme while the row's own note records that the named unit could not be confirmed and that the prior evidence for it was ruled inadmissible — and because this row… | AC41: HOLD
A42: 5.8 | B42: Agtech/data-science training pipeline | C42: C4 | D42: Enablers | E42: ALL | G42: L | M42: No dedicated agtech/digital-agriculture university degree or certificate program was identified for Egypt. Citable pipeline elements: (1) Digital Egypt Builders Initiative (DEBI, MCIT, launched Sept 2020 in the President | N42: MCIT, Digital Egypt Builders Initiative (DEBI) program page | O42: https://mcit.gov.eg/en/Human_Capacity/MCIT/Digital_Egypt_Builders_Initiative | P42: T3 | Q42: 2024 | R42: 3 | S42: =IF($M42="","",IF(ISNUMBER($M42),"Measured",IF(ISNUMBER(SEARCH("DATA GAP",UPPER($M42))),"Gap",IF(AND($N42<>"",$P42<>"T5"),"Documented","Judged")))) -> Documented | T42: =IF($AC42<>"","",IF(OR($S42="",$S42="Gap"),"",IF($S42="Measured",1+IF($H42="H",IF($M42>=$I42,1,0)+IF($M42>=$J42,1,0)+IF($M42>=$K42,1,0)+IF($M42>=$L42,1,0),IF($M42<=$I42,1,0)+IF($M42<=$J42,1,0)+IF($M42<=$K42,1,0)+IF($M42<=$L42,1,0)),IF($R42<>"",$R42,"")))) -> 3 | U42: =IF(OR($S42="",$S42="Gap",$Q42=""),"",IF($Q42<Config!$C$2-Config!$C$3,"STALE","")) | V42: =IF(OR(ISNUMBER(SEARCH("ALL",$E42)),ISNUMBER(SEARCH("ADV",$E42))),1,0) -> 1 | W42: =IF(OR(ISNUMBER(SEARCH("ALL",$E42)),ISNUMBER(SEARCH("SMF",$E42))),1,0) -> 1 | X42: =IF(OR(ISNUMBER(SEARCH("ALL",$E42)),ISNUMBER(SEARCH("MKT",$E42))),1,0) -> 1 | Y42: =IF(OR(ISNUMBER(SEARCH("ALL",$E42)),ISNUMBER(SEARCH("SCM",$E42))),1,0) -> 1 | Z42: =IF(OR(ISNUMBER(SEARCH("ALL",$E42)),ISNUMBER(SEARCH("FIN",$E42))),1,0) -> 1 | AA42: =IF(OR(ISNUMBER(SEARCH("ALL",$E42)),ISNUMBER(SEARCH("AGI",$E42))),1,0) -> 1 | AB42: The name's "agtech" half is unevidenced in both countries — each level 3 is carried entirely by a generic national ICT/data-talent programme with the agriculture bridging explicitly absent — and the slash never says whether the two halves are conjunctive or disjunctive.
A43: 5.12 | B43: Gender balance in digital-ag workforce (%) | C43: C4 | D43: Enablers | E43: EQ,ADV | G43: T | H43: H | I43: 20 | J43: 35 | K43: 45 | L43: 50 | M43: DATA GAP — searched WDI/ILO female-agricultural-employment series and MCIT/CAPMAS ICT gender indicators (T1: population-level only, no digital-ag workforce breakdown); FAO Country Gender Assessment of the Agriculture and Rural Sector - Egypt (2022) and FAO Status of Women in Agrifood Systems (2023) (T2: no extension or digital-ag workforce gender share); moa.gov.eg / MALR publications (T3: nothing); GFRAS Worldwide Extension Study Egypt profile and JICA Egypt Country Gender Profile 2018 (T4: extension-staff proxies only, underlying data 2011). Searched 2026-08. | N43: Structured source search, 22 August 2026 | Q43: 2026 | S43: =IF($M43="","",IF(ISNUMBER($M43),"Measured",IF(ISNUMBER(SEARCH("DATA GAP",UPPER($M43))),"Gap",IF(AND($N43<>"",$P43<>"T5"),"Documented","Judged")))) -> Gap | T43: =IF($AC43<>"","",IF(OR($S43="",$S43="Gap"),"",IF($S43="Measured",1+IF($H43="H",IF($M43>=$I43,1,0)+IF($M43>=$J43,1,0)+IF($M43>=$K43,1,0)+IF($M43>=$L43,1,0),IF($M43<=$I43,1,0)+IF($M43<=$J43,1,0)+IF($M43<=$K43,1,0)+IF($M43<=$L43,1,0)),IF($R43<>"",$R43,"")))) | U43: =IF(OR($S43="",$S43="Gap",$Q43=""),"",IF($Q43<Config!$C$2-Config!$C$3,"STALE","")) | V43: =IF(OR(ISNUMBER(SEARCH("ALL",$E43)),ISNUMBER(SEARCH("ADV",$E43))),1,0) -> 1 | W43: =IF(OR(ISNUMBER(SEARCH("ALL",$E43)),ISNUMBER(SEARCH("SMF",$E43))),1,0) -> 0 | X43: =IF(OR(ISNUMBER(SEARCH("ALL",$E43)),ISNUMBER(SEARCH("MKT",$E43))),1,0) -> 0 | Y43: =IF(OR(ISNUMBER(SEARCH("ALL",$E43)),ISNUMBER(SEARCH("SCM",$E43))),1,0) -> 0 | Z43: =IF(OR(ISNUMBER(SEARCH("ALL",$E43)),ISNUMBER(SEARCH("FIN",$E43))),1,0) -> 0 | AA43: =IF(OR(ISNUMBER(SEARCH("ALL",$E43)),ISNUMBER(SEARCH("AGI",$E43))),1,0) -> 0 | AB43: Who counts as the 'digital-ag workforce' — extension staff, agtech-company employees, or ICT-in-agriculture roles generally — given the H 20/35/45/50 thresholds presuppose a share no source publishes?
A44: 6.1 | B44: Global Innovation Index | C44: E1 | D44: Enablers | E44: ALL | G44: T | H44: H | I44: 25 | J44: 35 | K44: 45 | L44: 55 | M44: 24.7 | N44: WIPO Global Innovation Index 2025 (full report), GII 2025 rankings table p.18: "86 Egypt 24.7" | O44: https://www.wipo.int/web-publications/global-innovation-index-2025/assets/89507/global-innovation-index-2025-en.pdf | P44: T2 | Q44: 2025 | S44: =IF($M44="","",IF(ISNUMBER($M44),"Measured",IF(ISNUMBER(SEARCH("DATA GAP",UPPER($M44))),"Gap",IF(AND($N44<>"",$P44<>"T5"),"Documented","Judged")))) -> Measured | T44: =IF($AC44<>"","",IF(OR($S44="",$S44="Gap"),"",IF($S44="Measured",1+IF($H44="H",IF($M44>=$I44,1,0)+IF($M44>=$J44,1,0)+IF($M44>=$K44,1,0)+IF($M44>=$L44,1,0),IF($M44<=$I44,1,0)+IF($M44<=$J44,1,0)+IF($M44<=$K44,1,0)+IF($M44<=$L44,1,0)),IF($R44<>"",$R44,"")))) -> 1 | U44: =IF(OR($S44="",$S44="Gap",$Q44=""),"",IF($Q44<Config!$C$2-Config!$C$3,"STALE","")) | V44: =IF(OR(ISNUMBER(SEARCH("ALL",$E44)),ISNUMBER(SEARCH("ADV",$E44))),1,0) -> 1 | W44: =IF(OR(ISNUMBER(SEARCH("ALL",$E44)),ISNUMBER(SEARCH("SMF",$E44))),1,0) -> 1 | X44: =IF(OR(ISNUMBER(SEARCH("ALL",$E44)),ISNUMBER(SEARCH("MKT",$E44))),1,0) -> 1 | Y44: =IF(OR(ISNUMBER(SEARCH("ALL",$E44)),ISNUMBER(SEARCH("SCM",$E44))),1,0) -> 1 | Z44: =IF(OR(ISNUMBER(SEARCH("ALL",$E44)),ISNUMBER(SEARCH("FIN",$E44))),1,0) -> 1 | AA44: =IF(OR(ISNUMBER(SEARCH("ALL",$E44)),ISNUMBER(SEARCH("AGI",$E44))),1,0) -> 1
A45: 6.3 | B45: Business Ready (B-READY) | C45: E1 | D45: Enablers | E45: ALL | G45: T | H45: H | I45: 30 | J45: 45 | K45: 60 | L45: 75 | M45: DATA GAP — Egypt is not covered in B-READY 2024 (51 economies) nor in B-READY 2025 (interim edition, 101 economies). Egypt is listed as economy #16 of 71 in the Third B-READY Report cohort (2026 full edition), which is not yet published as of 2026-08-22. Searched: World Bank B-READY publications page; official 'List of Economies Proposed for Inclusion in the First Three Editions of the B-READY Report' (thedocs.worldbank.org); B-READY 2025 report record (documents.worldbank.org); B-READY Methodology Handbook Third Edition (Jan 2026) confirming the 2026 rollout is in progress. | N45: Structured source search, 22 August 2026 | Q45: 2026 | S45: =IF($M45="","",IF(ISNUMBER($M45),"Measured",IF(ISNUMBER(SEARCH("DATA GAP",UPPER($M45))),"Gap",IF(AND($N45<>"",$P45<>"T5"),"Documented","Judged")))) -> Gap | T45: =IF($AC45<>"","",IF(OR($S45="",$S45="Gap"),"",IF($S45="Measured",1+IF($H45="H",IF($M45>=$I45,1,0)+IF($M45>=$J45,1,0)+IF($M45>=$K45,1,0)+IF($M45>=$L45,1,0),IF($M45<=$I45,1,0)+IF($M45<=$J45,1,0)+IF($M45<=$K45,1,0)+IF($M45<=$L45,1,0)),IF($R45<>"",$R45,"")))) | U45: =IF(OR($S45="",$S45="Gap",$Q45=""),"",IF($Q45<Config!$C$2-Config!$C$3,"STALE","")) | V45: =IF(OR(ISNUMBER(SEARCH("ALL",$E45)),ISNUMBER(SEARCH("ADV",$E45))),1,0) -> 1 | W45: =IF(OR(ISNUMBER(SEARCH("ALL",$E45)),ISNUMBER(SEARCH("SMF",$E45))),1,0) -> 1 | X45: =IF(OR(ISNUMBER(SEARCH("ALL",$E45)),ISNUMBER(SEARCH("MKT",$E45))),1,0) -> 1 | Y45: =IF(OR(ISNUMBER(SEARCH("ALL",$E45)),ISNUMBER(SEARCH("SCM",$E45))),1,0) -> 1 | Z45: =IF(OR(ISNUMBER(SEARCH("ALL",$E45)),ISNUMBER(SEARCH("FIN",$E45))),1,0) -> 1 | AA45: =IF(OR(ISNUMBER(SEARCH("ALL",$E45)),ISNUMBER(SEARCH("AGI",$E45))),1,0) -> 1
A46: 6.4 | B46: Agtech venture ecosystem | C46: E1 | D46: Transformation | E46: ALL | G46: L | M46: Operating agtech venture ecosystem: Egypt is one of Africa's 'big three' agrifoodtech markets (with Kenya and Nigeria); 22 agrifoodtech deals totalling USD 26M in 2024 (+2,775% YoY after a depressed 2023), vs USD 112M ac | N46: AgFunder, Developing Markets AgriFoodTech Investment Report 2025 (Africa: investment by country p.49; top-funded companies pp.53-54; investor list p.80) | O46: https://omnivore.vc/uploads/developing_markets_agrifoodtech_investment_report_2025_4_61f213a206.pdf | P46: T4 | Q46: 2024 | R46: 3 | S46: =IF($M46="","",IF(ISNUMBER($M46),"Measured",IF(ISNUMBER(SEARCH("DATA GAP",UPPER($M46))),"Gap",IF(AND($N46<>"",$P46<>"T5"),"Documented","Judged")))) -> Documented | T46: =IF($AC46<>"","",IF(OR($S46="",$S46="Gap"),"",IF($S46="Measured",1+IF($H46="H",IF($M46>=$I46,1,0)+IF($M46>=$J46,1,0)+IF($M46>=$K46,1,0)+IF($M46>=$L46,1,0),IF($M46<=$I46,1,0)+IF($M46<=$J46,1,0)+IF($M46<=$K46,1,0)+IF($M46<=$L46,1,0)),IF($R46<>"",$R46,"")))) -> 3 | U46: =IF(OR($S46="",$S46="Gap",$Q46=""),"",IF($Q46<Config!$C$2-Config!$C$3,"STALE","")) | V46: =IF(OR(ISNUMBER(SEARCH("ALL",$E46)),ISNUMBER(SEARCH("ADV",$E46))),1,0) -> 1 | W46: =IF(OR(ISNUMBER(SEARCH("ALL",$E46)),ISNUMBER(SEARCH("SMF",$E46))),1,0) -> 1 | X46: =IF(OR(ISNUMBER(SEARCH("ALL",$E46)),ISNUMBER(SEARCH("MKT",$E46))),1,0) -> 1 | Y46: =IF(OR(ISNUMBER(SEARCH("ALL",$E46)),ISNUMBER(SEARCH("SCM",$E46))),1,0) -> 1 | Z46: =IF(OR(ISNUMBER(SEARCH("ALL",$E46)),ISNUMBER(SEARCH("FIN",$E46))),1,0) -> 1 | AA46: =IF(OR(ISNUMBER(SEARCH("ALL",$E46)),ISNUMBER(SEARCH("AGI",$E46))),1,0) -> 1 | AB46: The scale evidence is AgFunder "agrifoodtech" deal flow, a category that includes downstream food-tech and non-farmer-facing ventures, standing in for an agtech venture ecosystem — a measurably broader denominator that inflates deal and funding counts.
A47: 6.9 | B47: Public-private partnerships in digital ag | C47: E1 | D47: Transformation | E47: ADV,AGI,SCM | G47: L | M47: Multiple operating digital-agriculture partnerships with named partners: 'Agri Misr' e-platform (launched 13 Jul 2021: MALR + Ministry of Planning + Agricultural Bank of Egypt + eFinance Investment Group/eAswaaq); FAO x | N47: IFPRI Policy Note (Dec 2025): Digital Agricultural Technology in Egypt — Insights from App Developers (Abdallah, Abdelhadi & Karachiwalla) | O47: https://cgspace.cgiar.org/server/api/core/bitstreams/d4a33acc-564a-4e4c-a413-81ba3ebd4d90/content | P47: T2 | Q47: 2025 | R47: 4 | S47: =IF($M47="","",IF(ISNUMBER($M47),"Measured",IF(ISNUMBER(SEARCH("DATA GAP",UPPER($M47))),"Gap",IF(AND($N47<>"",$P47<>"T5"),"Documented","Judged")))) -> Documented | T47: =IF($AC47<>"","",IF(OR($S47="",$S47="Gap"),"",IF($S47="Measured",1+IF($H47="H",IF($M47>=$I47,1,0)+IF($M47>=$J47,1,0)+IF($M47>=$K47,1,0)+IF($M47>=$L47,1,0),IF($M47<=$I47,1,0)+IF($M47<=$J47,1,0)+IF($M47<=$K47,1,0)+IF($M47<=$L47,1,0)),IF($R47<>"",$R47,"")))) -> 4 | U47: =IF(OR($S47="",$S47="Gap",$Q47=""),"",IF($Q47<Config!$C$2-Config!$C$3,"STALE","")) | V47: =IF(OR(ISNUMBER(SEARCH("ALL",$E47)),ISNUMBER(SEARCH("ADV",$E47))),1,0) -> 1 | W47: =IF(OR(ISNUMBER(SEARCH("ALL",$E47)),ISNUMBER(SEARCH("SMF",$E47))),1,0) -> 0 | X47: =IF(OR(ISNUMBER(SEARCH("ALL",$E47)),ISNUMBER(SEARCH("MKT",$E47))),1,0) -> 0 | Y47: =IF(OR(ISNUMBER(SEARCH("ALL",$E47)),ISNUMBER(SEARCH("SCM",$E47))),1,0) -> 1 | Z47: =IF(OR(ISNUMBER(SEARCH("ALL",$E47)),ISNUMBER(SEARCH("FIN",$E47))),1,0) -> 0 | AA47: =IF(OR(ISNUMBER(SEARCH("ALL",$E47)),ISNUMBER(SEARCH("AGI",$E47))),1,0) -> 1 | AB47: The name asserts operating public-private partnerships, but Nigeria's level 3 rests substantially on MOUs signed days before capture (intent, not operation) and Egypt's flagship partnership pairs ministries with state-owned financial entities, leaving the "private" half of the construct thin.
A48: 6.12 | B48: Digital public goods adopted | C48: E1 | D48: Transformation | E48: ALL | G48: L | M48: One registered digital public good is operating in Egyptian agriculture: El-Mufeed, the Egypt deployment of the FAO Digital Services Portfolio (a DPG listed on the Digital Public Goods Alliance registry), run with MALR s | N48: FAO e-Agriculture: Proud Contributor Since 2022 — FAO in the 2025 State of the Digital Public Goods Ecosystem Report (DPGA registry includes the FAO Digital Services Portfolio) | O48: https://www.fao.org/e-agriculture/news/proud-contributor-2022-fao-leading-innovation-2025-state-digital-public-goods-ecosystem-report | P48: T1 | Q48: 2025 | R48: 4 | S48: =IF($M48="","",IF(ISNUMBER($M48),"Measured",IF(ISNUMBER(SEARCH("DATA GAP",UPPER($M48))),"Gap",IF(AND($N48<>"",$P48<>"T5"),"Documented","Judged")))) -> Documented | T48: =IF($AC48<>"","",IF(OR($S48="",$S48="Gap"),"",IF($S48="Measured",1+IF($H48="H",IF($M48>=$I48,1,0)+IF($M48>=$J48,1,0)+IF($M48>=$K48,1,0)+IF($M48>=$L48,1,0),IF($M48<=$I48,1,0)+IF($M48<=$J48,1,0)+IF($M48<=$K48,1,0)+IF($M48<=$L48,1,0)),IF($R48<>"",$R48,"")))) -> 4 | U48: =IF(OR($S48="",$S48="Gap",$Q48=""),"",IF($Q48<Config!$C$2-Config!$C$3,"STALE","")) | V48: =IF(OR(ISNUMBER(SEARCH("ALL",$E48)),ISNUMBER(SEARCH("ADV",$E48))),1,0) -> 1 | W48: =IF(OR(ISNUMBER(SEARCH("ALL",$E48)),ISNUMBER(SEARCH("SMF",$E48))),1,0) -> 1 | X48: =IF(OR(ISNUMBER(SEARCH("ALL",$E48)),ISNUMBER(SEARCH("MKT",$E48))),1,0) -> 1 | Y48: =IF(OR(ISNUMBER(SEARCH("ALL",$E48)),ISNUMBER(SEARCH("SCM",$E48))),1,0) -> 1 | Z48: =IF(OR(ISNUMBER(SEARCH("ALL",$E48)),ISNUMBER(SEARCH("FIN",$E48))),1,0) -> 1 | AA48: =IF(OR(ISNUMBER(SEARCH("ALL",$E48)),ISNUMBER(SEARCH("AGI",$E48))),1,0) -> 1 | AB48: Does 'DPG adopted' mean the country deploying a globally registered DPG, or the country itself adopting a DPG policy or registering a national product?
A49: 6.13 | B49: SME/agribusiness adoption of digital tools (%) | C49: E1 | D49: Transformation | E49: SMF,SCM,MKT | G49: T | H49: H | I49: 10 | J49: 25 | K49: 50 | L49: 75 | M49: DATA GAP — no SME/agribusiness-specific digital-tool adoption percentage exists for Egypt. Searched in order: (1) CAPMAS/MCIT ICT-usage-in-enterprises survey (2019/20, economy-wide only: >70% of surveyed enterprises use computers/internet — no agribusiness breakout), as summarized in OECD 'SME and Entrepreneurship Policy in Egypt' (SME Digitalisation chapter); (2) World Bank Enterprise Surveys Egypt — no agricultural digital-tool adoption indicator; (3) UNDP Digital Agribusiness Map Egypt (2025) — publishes regional agri-tech adoption estimates (Delta 15%, Northern Coastal 10%, Upper Egypt 5%, Desert 3%) but these are farm-level regional estimates, not SME/agribusiness firm-level adoption; (4) IFPRI Dec 2025 policy note and A2K4D/AUC Mar 2025 report — qualitative only; (5) ITU DataHub — no enterprise agribusiness series. | N49: Structured source search, 22 August 2026 | Q49: 2026 | S49: =IF($M49="","",IF(ISNUMBER($M49),"Measured",IF(ISNUMBER(SEARCH("DATA GAP",UPPER($M49))),"Gap",IF(AND($N49<>"",$P49<>"T5"),"Documented","Judged")))) -> Gap | T49: =IF($AC49<>"","",IF(OR($S49="",$S49="Gap"),"",IF($S49="Measured",1+IF($H49="H",IF($M49>=$I49,1,0)+IF($M49>=$J49,1,0)+IF($M49>=$K49,1,0)+IF($M49>=$L49,1,0),IF($M49<=$I49,1,0)+IF($M49<=$J49,1,0)+IF($M49<=$K49,1,0)+IF($M49<=$L49,1,0)),IF($R49<>"",$R49,"")))) | U49: =IF(OR($S49="",$S49="Gap",$Q49=""),"",IF($Q49<Config!$C$2-Config!$C$3,"STALE","")) | V49: =IF(OR(ISNUMBER(SEARCH("ALL",$E49)),ISNUMBER(SEARCH("ADV",$E49))),1,0) -> 0 | W49: =IF(OR(ISNUMBER(SEARCH("ALL",$E49)),ISNUMBER(SEARCH("SMF",$E49))),1,0) -> 1 | X49: =IF(OR(ISNUMBER(SEARCH("ALL",$E49)),ISNUMBER(SEARCH("MKT",$E49))),1,0) -> 1 | Y49: =IF(OR(ISNUMBER(SEARCH("ALL",$E49)),ISNUMBER(SEARCH("SCM",$E49))),1,0) -> 1 | Z49: =IF(OR(ISNUMBER(SEARCH("ALL",$E49)),ISNUMBER(SEARCH("FIN",$E49))),1,0) -> 0 | AA49: =IF(OR(ISNUMBER(SEARCH("ALL",$E49)),ISNUMBER(SEARCH("AGI",$E49))),1,0) -> 0 | AB49: The name fixes neither the population (SMEs economy-wide or agribusiness firms specifically — the slash is undefined) nor what counts as a "digital tool", and the register itself records that the available evidence cannot be mapped onto it.
A50: 6.14 | B50: Agri-fintech rails for smallholders | C50: E1 | D50: Transformation | E50: FIN | F50: UC:FIN | G50: L | M50: Operating agri-fintech rails with documented smallholder reach: national Farmer Card converted to a Meeza payment card on ABE/e-finance rails — 4.2 million smart farmer cards issued (Minister of Agriculture statement, 7 | N50: IFPRI Policy Note (Dec 2025): Digital Agricultural Technology in Egypt — Insights from App Developers (harvest-linked finance platform, 5,000-6,000 active farmers/month) | O50: https://cgspace.cgiar.org/server/api/core/bitstreams/d4a33acc-564a-4e4c-a413-81ba3ebd4d90/content | P50: T2 | Q50: 2025 | R50: 4 | S50: =IF($M50="","",IF(ISNUMBER($M50),"Measured",IF(ISNUMBER(SEARCH("DATA GAP",UPPER($M50))),"Gap",IF(AND($N50<>"",$P50<>"T5"),"Documented","Judged")))) -> Documented | T50: =IF($AC50<>"","",IF(OR($S50="",$S50="Gap"),"",IF($S50="Measured",1+IF($H50="H",IF($M50>=$I50,1,0)+IF($M50>=$J50,1,0)+IF($M50>=$K50,1,0)+IF($M50>=$L50,1,0),IF($M50<=$I50,1,0)+IF($M50<=$J50,1,0)+IF($M50<=$K50,1,0)+IF($M50<=$L50,1,0)),IF($R50<>"",$R50,"")))) -> 4 | U50: =IF(OR($S50="",$S50="Gap",$Q50=""),"",IF($Q50<Config!$C$2-Config!$C$3,"STALE","")) | V50: =IF(OR(ISNUMBER(SEARCH("ALL",$E50)),ISNUMBER(SEARCH("ADV",$E50))),1,0) -> 0 | W50: =IF(OR(ISNUMBER(SEARCH("ALL",$E50)),ISNUMBER(SEARCH("SMF",$E50))),1,0) -> 0 | X50: =IF(OR(ISNUMBER(SEARCH("ALL",$E50)),ISNUMBER(SEARCH("MKT",$E50))),1,0) -> 0 | Y50: =IF(OR(ISNUMBER(SEARCH("ALL",$E50)),ISNUMBER(SEARCH("SCM",$E50))),1,0) -> 0 | Z50: =IF(OR(ISNUMBER(SEARCH("ALL",$E50)),ISNUMBER(SEARCH("FIN",$E50))),1,0) -> 1 | AA50: =IF(OR(ISNUMBER(SEARCH("ALL",$E50)),ISNUMBER(SEARCH("AGI",$E50))),1,0) -> 0 | AB50: The name asserts rails serving smallholders, but the scale evidence is instruments issued and vendor-reported farmers "reached" rather than active use, and Egypt's Farmer Card is a state-issued instrument for registered landholders generally rather than for smallholders specifically.
A51: 3.9 | B51: Digital advisory platforms at scale | C51: E1 | D51: Transformation | E51: ADV | G51: L | M51: Multiple digital advisory platforms operating, several above 10k users (platform-reported, compiled by IFPRI): Mahsoly and AlMorshed Poultry 100K+ users each; several other advisory platforms 10K+; farm-management platfo | N51: IFPRI Policy Note (Dec 2025): Digital Agricultural Technology in Egypt — Insights from App Developers | O51: https://cgspace.cgiar.org/server/api/core/bitstreams/d4a33acc-564a-4e4c-a413-81ba3ebd4d90/content | P51: T2 | Q51: 2025 | R51: 4 | S51: =IF($M51="","",IF(ISNUMBER($M51),"Measured",IF(ISNUMBER(SEARCH("DATA GAP",UPPER($M51))),"Gap",IF(AND($N51<>"",$P51<>"T5"),"Documented","Judged")))) -> Documented | T51: =IF($AC51<>"","",IF(OR($S51="",$S51="Gap"),"",IF($S51="Measured",1+IF($H51="H",IF($M51>=$I51,1,0)+IF($M51>=$J51,1,0)+IF($M51>=$K51,1,0)+IF($M51>=$L51,1,0),IF($M51<=$I51,1,0)+IF($M51<=$J51,1,0)+IF($M51<=$K51,1,0)+IF($M51<=$L51,1,0)),IF($R51<>"",$R51,"")))) -> 4 | U51: =IF(OR($S51="",$S51="Gap",$Q51=""),"",IF($Q51<Config!$C$2-Config!$C$3,"STALE","")) | V51: =IF(OR(ISNUMBER(SEARCH("ALL",$E51)),ISNUMBER(SEARCH("ADV",$E51))),1,0) -> 1 | W51: =IF(OR(ISNUMBER(SEARCH("ALL",$E51)),ISNUMBER(SEARCH("SMF",$E51))),1,0) -> 0 | X51: =IF(OR(ISNUMBER(SEARCH("ALL",$E51)),ISNUMBER(SEARCH("MKT",$E51))),1,0) -> 0 | Y51: =IF(OR(ISNUMBER(SEARCH("ALL",$E51)),ISNUMBER(SEARCH("SCM",$E51))),1,0) -> 0 | Z51: =IF(OR(ISNUMBER(SEARCH("ALL",$E51)),ISNUMBER(SEARCH("FIN",$E51))),1,0) -> 0 | AA51: =IF(OR(ISNUMBER(SEARCH("ALL",$E51)),ISNUMBER(SEARCH("AGI",$E51))),1,0) -> 0 | AB51: "At scale" fixes no threshold anywhere in the model (th=[] for all ladder rows), so a >10k-user bar imported from outside the audited files carries both level 4s, and the counts behind it are self-reported registered users rather than active or reached farmers.
A52: 3.10 | B52: Agricultural e-commerce platforms | C52: E1 | D52: Transformation | E52: MKT | G52: L | M52: Multiple agricultural e-commerce/marketplace platforms operating: Mahsoly (crops and land marketplace with El-Obour wholesale price feed; >100K reported users), Mahaseel, Khodarcom, Khodar Supply, Cropsa (aggregation/mar | N52: IFPRI Policy Note (Dec 2025): Digital Agricultural Technology in Egypt — Insights from App Developers | O52: https://cgspace.cgiar.org/server/api/core/bitstreams/d4a33acc-564a-4e4c-a413-81ba3ebd4d90/content | P52: T2 | Q52: 2025 | R52: 4 | S52: =IF($M52="","",IF(ISNUMBER($M52),"Measured",IF(ISNUMBER(SEARCH("DATA GAP",UPPER($M52))),"Gap",IF(AND($N52<>"",$P52<>"T5"),"Documented","Judged")))) -> Documented | T52: =IF($AC52<>"","",IF(OR($S52="",$S52="Gap"),"",IF($S52="Measured",1+IF($H52="H",IF($M52>=$I52,1,0)+IF($M52>=$J52,1,0)+IF($M52>=$K52,1,0)+IF($M52>=$L52,1,0),IF($M52<=$I52,1,0)+IF($M52<=$J52,1,0)+IF($M52<=$K52,1,0)+IF($M52<=$L52,1,0)),IF($R52<>"",$R52,"")))) -> 4 | U52: =IF(OR($S52="",$S52="Gap",$Q52=""),"",IF($Q52<Config!$C$2-Config!$C$3,"STALE","")) | V52: =IF(OR(ISNUMBER(SEARCH("ALL",$E52)),ISNUMBER(SEARCH("ADV",$E52))),1,0) -> 0 | W52: =IF(OR(ISNUMBER(SEARCH("ALL",$E52)),ISNUMBER(SEARCH("SMF",$E52))),1,0) -> 0 | X52: =IF(OR(ISNUMBER(SEARCH("ALL",$E52)),ISNUMBER(SEARCH("MKT",$E52))),1,0) -> 1 | Y52: =IF(OR(ISNUMBER(SEARCH("ALL",$E52)),ISNUMBER(SEARCH("SCM",$E52))),1,0) -> 0 | Z52: =IF(OR(ISNUMBER(SEARCH("ALL",$E52)),ISNUMBER(SEARCH("FIN",$E52))),1,0) -> 0 | AA52: =IF(OR(ISNUMBER(SEARCH("ALL",$E52)),ISNUMBER(SEARCH("AGI",$E52))),1,0) -> 0 | AB52: Does the indicator count only farmer-facing platforms, or any agri-food value-chain commerce platform (OneOrder, Cartona, AFEX)?
A53: 7.2 | B53: AI-enabled agricultural solutions deployed | C53: E1 | D53: Transformation | E53: ADV,FIN,SCM,SMF,AGI | G53: L | M53: AI-enabled agricultural solutions deployed but with limited verified reach: Hudhud (MALR x MCIT Arabic AI assistant: chatbot + photo-based pest/disease identification), pilot-launched Dec 2021, live on Google Play (publi | N53: A2K4D/American University in Cairo (MENA AI Observatory), AI Applications for Food Security in Egypt: Practices, Opportunities, and Challenges (Nagla Rizk, March 2025) | O53: https://menaobservatory.ai/storage/CHOmuyRvzMEC5LmRtmNQMZHpjlZbEM-metaQTJLNEQgLSBNRU5BIEFJIC0gRm9vZCBTZWN1cml0eSAtIEVneXB0IC0gVjIucGRm-.pdf | P53: T4 | Q53: 2025 | R53: 3 | S53: =IF($M53="","",IF(ISNUMBER($M53),"Measured",IF(ISNUMBER(SEARCH("DATA GAP",UPPER($M53))),"Gap",IF(AND($N53<>"",$P53<>"T5"),"Documented","Judged")))) -> Documented | T53: =IF($AC53<>"","",IF(OR($S53="",$S53="Gap"),"",IF($S53="Measured",1+IF($H53="H",IF($M53>=$I53,1,0)+IF($M53>=$J53,1,0)+IF($M53>=$K53,1,0)+IF($M53>=$L53,1,0),IF($M53<=$I53,1,0)+IF($M53<=$J53,1,0)+IF($M53<=$K53,1,0)+IF($M53<=$L53,1,0)),IF($R53<>"",$R53,"")))) -> 3 | U53: =IF(OR($S53="",$S53="Gap",$Q53=""),"",IF($Q53<Config!$C$2-Config!$C$3,"STALE","")) | V53: =IF(OR(ISNUMBER(SEARCH("ALL",$E53)),ISNUMBER(SEARCH("ADV",$E53))),1,0) -> 1 | W53: =IF(OR(ISNUMBER(SEARCH("ALL",$E53)),ISNUMBER(SEARCH("SMF",$E53))),1,0) -> 1 | X53: =IF(OR(ISNUMBER(SEARCH("ALL",$E53)),ISNUMBER(SEARCH("MKT",$E53))),1,0) -> 0 | Y53: =IF(OR(ISNUMBER(SEARCH("ALL",$E53)),ISNUMBER(SEARCH("SCM",$E53))),1,0) -> 1 | Z53: =IF(OR(ISNUMBER(SEARCH("ALL",$E53)),ISNUMBER(SEARCH("FIN",$E53))),1,0) -> 1 | AA53: =IF(OR(ISNUMBER(SEARCH("ALL",$E53)),ISNUMBER(SEARCH("AGI",$E53))),1,0) -> 1 | AB53: The name asserts deployment, but Egypt's level 3 rests on a solution restricted to a pilot cohort with no verified reach and Nigeria's row is anchored on a future-tense announcement of an intent to deploy.
A54: 7.12 | B54: Responsible-AI safeguards (consent, rights) | C54: E1 | D54: Enablers | E54: AI | F54: UC:AI | G54: L | M54: No agriculture/AI-specific consent or farmer-data-rights safeguards exist beyond the general regime. General regime now operational: PDPL 151/2020 became enforceable in practice with Executive Regulations issued by Minis | N54: Egyptian Charter for Responsible AI v1.0 (NCAI, 2023) — official PDF, ai.gov.eg (full-text searched: no agriculture/farmer provisions) | O54: https://ai.gov.eg/SynchedFiles/en/Resources/Egyptian%20Charter%20For%20Responsible%20AI.pdf | P54: T3 | Q54: 2025 | R54: 1 | S54: =IF($M54="","",IF(ISNUMBER($M54),"Measured",IF(ISNUMBER(SEARCH("DATA GAP",UPPER($M54))),"Gap",IF(AND($N54<>"",$P54<>"T5"),"Documented","Judged")))) -> Documented | T54: =IF($AC54<>"","",IF(OR($S54="",$S54="Gap"),"",IF($S54="Measured",1+IF($H54="H",IF($M54>=$I54,1,0)+IF($M54>=$J54,1,0)+IF($M54>=$K54,1,0)+IF($M54>=$L54,1,0),IF($M54<=$I54,1,0)+IF($M54<=$J54,1,0)+IF($M54<=$K54,1,0)+IF($M54<=$L54,1,0)),IF($R54<>"",$R54,"")))) -> 1 | U54: =IF(OR($S54="",$S54="Gap",$Q54=""),"",IF($Q54<Config!$C$2-Config!$C$3,"STALE","")) | V54: =IF(OR(ISNUMBER(SEARCH("ALL",$E54)),ISNUMBER(SEARCH("ADV",$E54))),1,0) -> 0 | W54: =IF(OR(ISNUMBER(SEARCH("ALL",$E54)),ISNUMBER(SEARCH("SMF",$E54))),1,0) -> 0 | X54: =IF(OR(ISNUMBER(SEARCH("ALL",$E54)),ISNUMBER(SEARCH("MKT",$E54))),1,0) -> 0 | Y54: =IF(OR(ISNUMBER(SEARCH("ALL",$E54)),ISNUMBER(SEARCH("SCM",$E54))),1,0) -> 0 | Z54: =IF(OR(ISNUMBER(SEARCH("ALL",$E54)),ISNUMBER(SEARCH("FIN",$E54))),1,0) -> 0 | AA54: =IF(OR(ISNUMBER(SEARCH("ALL",$E54)),ISNUMBER(SEARCH("AGI",$E54))),1,0) -> 0 | AB54: The name does not fix whether the safeguards must be agriculture- or farmer-specific or whether a cross-sector regime suffices, and the two countries resolve it in opposite directions on the same recorded fact pattern — each row states that nothing agriculture-specific exists, yet one is scored…
A55: 8.2 | B55: Account ownership, female (%) | C55: O1 | D55: Outcomes | E55: FIN,EQ | G55: T | H55: H | I55: 20 | J55: 40 | K55: 60 | L55: 80 | M55: 40.214218 | N55: World Bank WDI FX.OWN.TOTL.FE.ZS (Global Findex wave) | O55: https://api.worldbank.org/v2/country/EGY/indicator/FX.OWN.TOTL.FE.ZS?format=json&mrnev=1&per_page=5 | P55: T1 | Q55: 2024 | S55: =IF($M55="","",IF(ISNUMBER($M55),"Measured",IF(ISNUMBER(SEARCH("DATA GAP",UPPER($M55))),"Gap",IF(AND($N55<>"",$P55<>"T5"),"Documented","Judged")))) -> Measured | T55: =IF($AC55<>"","",IF(OR($S55="",$S55="Gap"),"",IF($S55="Measured",1+IF($H55="H",IF($M55>=$I55,1,0)+IF($M55>=$J55,1,0)+IF($M55>=$K55,1,0)+IF($M55>=$L55,1,0),IF($M55<=$I55,1,0)+IF($M55<=$J55,1,0)+IF($M55<=$K55,1,0)+IF($M55<=$L55,1,0)),IF($R55<>"",$R55,"")))) -> 3 | U55: =IF(OR($S55="",$S55="Gap",$Q55=""),"",IF($Q55<Config!$C$2-Config!$C$3,"STALE","")) | V55: =IF(OR(ISNUMBER(SEARCH("ALL",$E55)),ISNUMBER(SEARCH("ADV",$E55))),1,0) -> 0 | W55: =IF(OR(ISNUMBER(SEARCH("ALL",$E55)),ISNUMBER(SEARCH("SMF",$E55))),1,0) -> 0 | X55: =IF(OR(ISNUMBER(SEARCH("ALL",$E55)),ISNUMBER(SEARCH("MKT",$E55))),1,0) -> 0 | Y55: =IF(OR(ISNUMBER(SEARCH("ALL",$E55)),ISNUMBER(SEARCH("SCM",$E55))),1,0) -> 0 | Z55: =IF(OR(ISNUMBER(SEARCH("ALL",$E55)),ISNUMBER(SEARCH("FIN",$E55))),1,0) -> 1 | AA55: =IF(OR(ISNUMBER(SEARCH("ALL",$E55)),ISNUMBER(SEARCH("AGI",$E55))),1,0) -> 0 | AB55: "Account" is not defined in the name, and the chosen WDI series counts mobile-money accounts inside the total — the same construct scored separately at 8.4 — so mobile money is effectively double-weighted in the FIN use-case column and in the O1 mean.
A56: 8.4 | B56: Mobile money account (%) | C56: O1 | D56: Outcomes | E56: FIN | G56: T | H56: H | I56: 10 | J56: 25 | K56: 50 | L56: 75 | M56: 15.6 | N56: World Bank, The Little Data Book on Financial Inclusion 2025 (Global Findex Database 2025), Egypt, Arab Rep. country page (p. 56): Mobile money account (% age 15+) = 15.6 | O56: https://thedocs.worldbank.org/en/doc/be6615202d1f08a25855c8ac2d615122-0050012025/related/Little-Data-Book-2025-Web.pdf | P56: T1 | Q56: 2024 | S56: =IF($M56="","",IF(ISNUMBER($M56),"Measured",IF(ISNUMBER(SEARCH("DATA GAP",UPPER($M56))),"Gap",IF(AND($N56<>"",$P56<>"T5"),"Documented","Judged")))) -> Measured | T56: =IF($AC56<>"","",IF(OR($S56="",$S56="Gap"),"",IF($S56="Measured",1+IF($H56="H",IF($M56>=$I56,1,0)+IF($M56>=$J56,1,0)+IF($M56>=$K56,1,0)+IF($M56>=$L56,1,0),IF($M56<=$I56,1,0)+IF($M56<=$J56,1,0)+IF($M56<=$K56,1,0)+IF($M56<=$L56,1,0)),IF($R56<>"",$R56,"")))) -> 2 | U56: =IF(OR($S56="",$S56="Gap",$Q56=""),"",IF($Q56<Config!$C$2-Config!$C$3,"STALE","")) | V56: =IF(OR(ISNUMBER(SEARCH("ALL",$E56)),ISNUMBER(SEARCH("ADV",$E56))),1,0) -> 0 | W56: =IF(OR(ISNUMBER(SEARCH("ALL",$E56)),ISNUMBER(SEARCH("SMF",$E56))),1,0) -> 0 | X56: =IF(OR(ISNUMBER(SEARCH("ALL",$E56)),ISNUMBER(SEARCH("MKT",$E56))),1,0) -> 0 | Y56: =IF(OR(ISNUMBER(SEARCH("ALL",$E56)),ISNUMBER(SEARCH("SCM",$E56))),1,0) -> 0 | Z56: =IF(OR(ISNUMBER(SEARCH("ALL",$E56)),ISNUMBER(SEARCH("FIN",$E56))),1,0) -> 1 | AA56: =IF(OR(ISNUMBER(SEARCH("ALL",$E56)),ISNUMBER(SEARCH("AGI",$E56))),1,0) -> 0
A57: 8.6 | B57: Gender gap in phone ownership (pp) | C57: O1 | D57: Outcomes | E57: EQ | G57: T | H57: L | I57: 20 | J57: 10 | K57: 5 | L57: 2 | M57: 14.4 | N57: World Bank Global Findex Database 2025, Egypt: Own a mobile phone, men (con1.2) = 91.7% vs women (con1.1) = 77.3%, age 15+, 2024 — gap 14.4 percentage points (derived by subtraction of the two published series) | O57: https://api.worldbank.org/v2/country/EGY/indicator/con1.2?source=28&format=json | P57: T1 | Q57: 2024 | S57: =IF($M57="","",IF(ISNUMBER($M57),"Measured",IF(ISNUMBER(SEARCH("DATA GAP",UPPER($M57))),"Gap",IF(AND($N57<>"",$P57<>"T5"),"Documented","Judged")))) -> Measured | T57: =IF($AC57<>"","",IF(OR($S57="",$S57="Gap"),"",IF($S57="Measured",1+IF($H57="H",IF($M57>=$I57,1,0)+IF($M57>=$J57,1,0)+IF($M57>=$K57,1,0)+IF($M57>=$L57,1,0),IF($M57<=$I57,1,0)+IF($M57<=$J57,1,0)+IF($M57<=$K57,1,0)+IF($M57<=$L57,1,0)),IF($R57<>"",$R57,"")))) -> 2 | U57: =IF(OR($S57="",$S57="Gap",$Q57=""),"",IF($Q57<Config!$C$2-Config!$C$3,"STALE","")) | V57: =IF(OR(ISNUMBER(SEARCH("ALL",$E57)),ISNUMBER(SEARCH("ADV",$E57))),1,0) -> 0 | W57: =IF(OR(ISNUMBER(SEARCH("ALL",$E57)),ISNUMBER(SEARCH("SMF",$E57))),1,0) -> 0 | X57: =IF(OR(ISNUMBER(SEARCH("ALL",$E57)),ISNUMBER(SEARCH("MKT",$E57))),1,0) -> 0 | Y57: =IF(OR(ISNUMBER(SEARCH("ALL",$E57)),ISNUMBER(SEARCH("SCM",$E57))),1,0) -> 0 | Z57: =IF(OR(ISNUMBER(SEARCH("ALL",$E57)),ISNUMBER(SEARCH("FIN",$E57))),1,0) -> 0 | AA57: =IF(OR(ISNUMBER(SEARCH("ALL",$E57)),ISNUMBER(SEARCH("AGI",$E57))),1,0) -> 0 | AB57: The name fixes the unit as percentage points but not the sign convention or the basis, so a reversed gap (women ahead) scores as best-in-class under direction L, and the widely quoted GSMA figure for the same construct is a relative gap on a male-ownership base, a different number entirely.
A58: 8.9 | B58: Smallholders reached by digital services (%) | C58: O1 | D58: Outcomes | E58: ALL,EQ | G58: T | H58: H | I58: 10 | J58: 25 | K58: 50 | L58: 75 | M58: No national share with provenance. Regional (labelled, single-source): IFPRI RCT baseline, Minya & Beni Suef - digital ag service use among surveyed smallholders far below 10% | N58: IFPRI DP 2359 / RCT baseline (CGSpace) | O58: https://cgspace.cgiar.org/server/api/core/bitstreams/a95d7429-19f8-4a76-8152-06c | P58: T2 | Q58: 2023 | R58: 1 | S58: =IF($M58="","",IF(ISNUMBER($M58),"Measured",IF(ISNUMBER(SEARCH("DATA GAP",UPPER($M58))),"Gap",IF(AND($N58<>"",$P58<>"T5"),"Documented","Judged")))) -> Documented | T58: =IF($AC58<>"","",IF(OR($S58="",$S58="Gap"),"",IF($S58="Measured",1+IF($H58="H",IF($M58>=$I58,1,0)+IF($M58>=$J58,1,0)+IF($M58>=$K58,1,0)+IF($M58>=$L58,1,0),IF($M58<=$I58,1,0)+IF($M58<=$J58,1,0)+IF($M58<=$K58,1,0)+IF($M58<=$L58,1,0)),IF($R58<>"",$R58,"")))) -> 1 | U58: =IF(OR($S58="",$S58="Gap",$Q58=""),"",IF($Q58<Config!$C$2-Config!$C$3,"STALE","")) | V58: =IF(OR(ISNUMBER(SEARCH("ALL",$E58)),ISNUMBER(SEARCH("ADV",$E58))),1,0) -> 1 | W58: =IF(OR(ISNUMBER(SEARCH("ALL",$E58)),ISNUMBER(SEARCH("SMF",$E58))),1,0) -> 1 | X58: =IF(OR(ISNUMBER(SEARCH("ALL",$E58)),ISNUMBER(SEARCH("MKT",$E58))),1,0) -> 1 | Y58: =IF(OR(ISNUMBER(SEARCH("ALL",$E58)),ISNUMBER(SEARCH("SCM",$E58))),1,0) -> 1 | Z58: =IF(OR(ISNUMBER(SEARCH("ALL",$E58)),ISNUMBER(SEARCH("FIN",$E58))),1,0) -> 1 | AA58: =IF(OR(ISNUMBER(SEARCH("ALL",$E58)),ISNUMBER(SEARCH("AGI",$E58))),1,0) -> 1 | AB58: The name asserts a national share of smallholders reached, but Egypt's scored level 1 is derived from a two-governorate RCT baseline explicitly labelled as having no national provenance, and "reached" is nowhere defined against registered, active, or benefiting users.
A59: 8.11 | B59: Services in local languages (%) | C59: O1 | D59: Outcomes | E59: ADV,EQ | G59: T | H59: H | I59: 25 | J59: 50 | K59: 75 | L59: 90 | M59: No quantified share published; qualitative evidence indicates local-language delivery of flagship services is effectively universal. All major identified digital-agriculture services in Egypt are delivered in Arabic: Hud | N59: UN Egypt / FAO-MALR: 'FAO & MALR invite extension agents to use El Mufeed app and disseminate among targeted groups' (official programme page; El Mufeed is Arabic-language); corroborated by IFPRI Egypt CSA policy note (Dec 2025) naming Bashaer and Nabta | O59: https://egypt.un.org/en/106025-fao-malr-invite-extension-agents-use-%E2%80%9Cel-mufeed%E2%80%9D-app-and-disseminate-among-targeted-groups | P59: T3 | Q59: 2025 | R59: 5 | S59: =IF($M59="","",IF(ISNUMBER($M59),"Measured",IF(ISNUMBER(SEARCH("DATA GAP",UPPER($M59))),"Gap",IF(AND($N59<>"",$P59<>"T5"),"Documented","Judged")))) -> Documented | T59: =IF($AC59<>"","",IF(OR($S59="",$S59="Gap"),"",IF($S59="Measured",1+IF($H59="H",IF($M59>=$I59,1,0)+IF($M59>=$J59,1,0)+IF($M59>=$K59,1,0)+IF($M59>=$L59,1,0),IF($M59<=$I59,1,0)+IF($M59<=$J59,1,0)+IF($M59<=$K59,1,0)+IF($M59<=$L59,1,0)),IF($R59<>"",$R59,"")))) -> 5 | U59: =IF(OR($S59="",$S59="Gap",$Q59=""),"",IF($Q59<Config!$C$2-Config!$C$3,"STALE","")) | V59: =IF(OR(ISNUMBER(SEARCH("ALL",$E59)),ISNUMBER(SEARCH("ADV",$E59))),1,0) -> 1 | W59: =IF(OR(ISNUMBER(SEARCH("ALL",$E59)),ISNUMBER(SEARCH("SMF",$E59))),1,0) -> 0 | X59: =IF(OR(ISNUMBER(SEARCH("ALL",$E59)),ISNUMBER(SEARCH("MKT",$E59))),1,0) -> 0 | Y59: =IF(OR(ISNUMBER(SEARCH("ALL",$E59)),ISNUMBER(SEARCH("SCM",$E59))),1,0) -> 0 | Z59: =IF(OR(ISNUMBER(SEARCH("ALL",$E59)),ISNUMBER(SEARCH("FIN",$E59))),1,0) -> 0 | AA59: =IF(OR(ISNUMBER(SEARCH("ALL",$E59)),ISNUMBER(SEARCH("AGI",$E59))),1,0) -> 0 | AB59: Should 8.11 remain a %-share indicator when no country publishes a denominator for local-language service delivery — and the Nigeria bundle's guidance text is contaminated with Egypt-specific content that must be removed regardless of the ruling?
A60: 8.12 | B60: Documented impact evidence (yield/income) | C60: O1 | D60: Outcomes | E60: ALL | G60: L | M60: Rung facts. PRESENCE: one completed, published, independent impact evaluation of a digital-agriculture intervention in Egypt — Abdelaziz, F. & Abay, K.A., 'Digital literacy training to promote diffusion of digital agricu | N60: Abdelaziz & Abay (2025/2026), IFPRI DP 2359 / Food Policy — RCT of digital literacy training for smallholder digital-tool adoption, Egypt | O60: https://cgspace.cgiar.org/items/18a9ca8e-af59-4f88-a5e1-4b7a2a9155cd | P60: T2 | Q60: 2025 | R60: 3 | S60: =IF($M60="","",IF(ISNUMBER($M60),"Measured",IF(ISNUMBER(SEARCH("DATA GAP",UPPER($M60))),"Gap",IF(AND($N60<>"",$P60<>"T5"),"Documented","Judged")))) -> Documented | T60: =IF($AC60<>"","",IF(OR($S60="",$S60="Gap"),"",IF($S60="Measured",1+IF($H60="H",IF($M60>=$I60,1,0)+IF($M60>=$J60,1,0)+IF($M60>=$K60,1,0)+IF($M60>=$L60,1,0),IF($M60<=$I60,1,0)+IF($M60<=$J60,1,0)+IF($M60<=$K60,1,0)+IF($M60<=$L60,1,0)),IF($R60<>"",$R60,"")))) -> 3 | U60: =IF(OR($S60="",$S60="Gap",$Q60=""),"",IF($Q60<Config!$C$2-Config!$C$3,"STALE","")) | V60: =IF(OR(ISNUMBER(SEARCH("ALL",$E60)),ISNUMBER(SEARCH("ADV",$E60))),1,0) -> 1 | W60: =IF(OR(ISNUMBER(SEARCH("ALL",$E60)),ISNUMBER(SEARCH("SMF",$E60))),1,0) -> 1 | X60: =IF(OR(ISNUMBER(SEARCH("ALL",$E60)),ISNUMBER(SEARCH("MKT",$E60))),1,0) -> 1 | Y60: =IF(OR(ISNUMBER(SEARCH("ALL",$E60)),ISNUMBER(SEARCH("SCM",$E60))),1,0) -> 1 | Z60: =IF(OR(ISNUMBER(SEARCH("ALL",$E60)),ISNUMBER(SEARCH("FIN",$E60))),1,0) -> 1 | AA60: =IF(OR(ISNUMBER(SEARCH("ALL",$E60)),ISNUMBER(SEARCH("AGI",$E60))),1,0) -> 1 | AB60: The name's parenthetical fixes the outcome as yield or income, but Egypt's level 3 rests on an evaluation whose measured outcome is diffusion and adoption of digital tools, not yield or income.
A61: 8.17 | B61: Climate advisory reach (%) | C61: O1 | D61: Outcomes | E61: ADV | G61: T | H61: H | I61: 20 | J61: 40 | K61: 60 | L61: 80 | M61: DATA GAP — searched (2026-08-22, in order): web search for EMA / CCIC / DAIRS advisory-reach statistics (none published); IFPRI Egypt CSA policy note Dec 2025 (CCIC issues daily climate warnings; CCIC-EMA 'Bashaer' platform delivers tailored climate-smart recommendations to farmers — no reach figures; FAO RNE panelist states 'communication gaps mean that many smallholders never receive' warnings); targeted search for Bashaer user/reach numbers (none); ICARDA digital-ag review abstract (DAIRS 'under development', no reach); FAO/WFP Egypt climate publications (project-level reach only, no national %). No percentage of Egyptian farmers receiving actionable climate advisories exists with provenance. | N61: Structured source search, 22 August 2026 | Q61: 2026 | S61: =IF($M61="","",IF(ISNUMBER($M61),"Measured",IF(ISNUMBER(SEARCH("DATA GAP",UPPER($M61))),"Gap",IF(AND($N61<>"",$P61<>"T5"),"Documented","Judged")))) -> Gap | T61: =IF($AC61<>"","",IF(OR($S61="",$S61="Gap"),"",IF($S61="Measured",1+IF($H61="H",IF($M61>=$I61,1,0)+IF($M61>=$J61,1,0)+IF($M61>=$K61,1,0)+IF($M61>=$L61,1,0),IF($M61<=$I61,1,0)+IF($M61<=$J61,1,0)+IF($M61<=$K61,1,0)+IF($M61<=$L61,1,0)),IF($R61<>"",$R61,"")))) | U61: =IF(OR($S61="",$S61="Gap",$Q61=""),"",IF($Q61<Config!$C$2-Config!$C$3,"STALE","")) | V61: =IF(OR(ISNUMBER(SEARCH("ALL",$E61)),ISNUMBER(SEARCH("ADV",$E61))),1,0) -> 1 | W61: =IF(OR(ISNUMBER(SEARCH("ALL",$E61)),ISNUMBER(SEARCH("SMF",$E61))),1,0) -> 0 | X61: =IF(OR(ISNUMBER(SEARCH("ALL",$E61)),ISNUMBER(SEARCH("MKT",$E61))),1,0) -> 0 | Y61: =IF(OR(ISNUMBER(SEARCH("ALL",$E61)),ISNUMBER(SEARCH("SCM",$E61))),1,0) -> 0 | Z61: =IF(OR(ISNUMBER(SEARCH("ALL",$E61)),ISNUMBER(SEARCH("FIN",$E61))),1,0) -> 0 | AA61: =IF(OR(ISNUMBER(SEARCH("ALL",$E61)),ISNUMBER(SEARCH("AGI",$E61))),1,0) -> 0 | AB61: Does the indicator measure farmer receipt of advisories, or supply-side issuance (warnings issued, platforms live), which is all either country publishes?
A64: Pillar profile · n = indicators in the pillar; Rated = those that produced a level, which is what the mean averages; Held = level withheld pending ratification. A band in parentheses = judged rows, recorded gaps and held rows outnumber the levelled measured and documented ones
A65: Pillar | B65: n | C65: Rated | D65: Mean | E65: Band | F65: Measured | G65: Documented | H65: Judged | I65: Gap | J65: Held | K65: Stale
A66: A1 | B66: =COUNTIF($C$5:$C$61,$A66) -> 10 | C66: =COUNTIFS($C$5:$C$61,$A66,$T$5:$T$61,">0") -> 8 | D66: =IFERROR(ROUND(AVERAGEIF($C$5:$C$61,$A66,$T$5:$T$61),2),"") -> 3 | E66: =IF($D66="","Not rated",IF((COUNTIFS($C$5:$C$61,$A66,$S$5:$S$61,"Judged",$T$5:$T$61,">0")+$I66+$J66)>($C66-COUNTIFS($C$5:$C$61,$A66,$S$5:$S$61,"Judged",$T$5:$T$61,">0")),"("&IF($D66<1.8,"Nascent",IF($D66<2.6,"Emerging",IF($D66<3.4,"Established",IF($D66<4.2,"Advanced","Transformative"))))&")",IF($D66<1.8,"Nascent",IF($D66<2.6,"Emerging",IF($D66<3.4,"Established",IF($D66<4.2,"Advanced","Transformative")))))) -> Established | F66: =COUNTIFS($C$5:$C$61,$A66,$S$5:$S$61,"Measured") -> 6 | G66: =COUNTIFS($C$5:$C$61,$A66,$S$5:$S$61,"Documented") -> 4 | H66: =COUNTIFS($C$5:$C$61,$A66,$S$5:$S$61,"Judged") -> 0 | I66: =COUNTIFS($C$5:$C$61,$A66,$S$5:$S$61,"Gap") -> 0 | J66: =COUNTIFS($C$5:$C$61,$A66,$AC$5:$AC$61,"<>") -> 2 | K66: =COUNTIFS($C$5:$C$61,$A66,$U$5:$U$61,"STALE") -> 6
A67: C1 | B67: =COUNTIF($C$5:$C$61,$A67) -> 6 | C67: =COUNTIFS($C$5:$C$61,$A67,$T$5:$T$61,">0") -> 5 | D67: =IFERROR(ROUND(AVERAGEIF($C$5:$C$61,$A67,$T$5:$T$61),2),"") -> 3.8 | E67: =IF($D67="","Not rated",IF((COUNTIFS($C$5:$C$61,$A67,$S$5:$S$61,"Judged",$T$5:$T$61,">0")+$I67+$J67)>($C67-COUNTIFS($C$5:$C$61,$A67,$S$5:$S$61,"Judged",$T$5:$T$61,">0")),"("&IF($D67<1.8,"Nascent",IF($D67<2.6,"Emerging",IF($D67<3.4,"Established",IF($D67<4.2,"Advanced","Transformative"))))&")",IF($D67<1.8,"Nascent",IF($D67<2.6,"Emerging",IF($D67<3.4,"Established",IF($D67<4.2,"Advanced","Transformative")))))) -> Advanced | F67: =COUNTIFS($C$5:$C$61,$A67,$S$5:$S$61,"Measured") -> 4 | G67: =COUNTIFS($C$5:$C$61,$A67,$S$5:$S$61,"Documented") -> 1 | H67: =COUNTIFS($C$5:$C$61,$A67,$S$5:$S$61,"Judged") -> 0 | I67: =COUNTIFS($C$5:$C$61,$A67,$S$5:$S$61,"Gap") -> 1 | J67: =COUNTIFS($C$5:$C$61,$A67,$AC$5:$AC$61,"<>") -> 0 | K67: =COUNTIFS($C$5:$C$61,$A67,$U$5:$U$61,"STALE") -> 1
A68: C2 | B68: =COUNTIF($C$5:$C$61,$A68) -> 8 | C68: =COUNTIFS($C$5:$C$61,$A68,$T$5:$T$61,">0") -> 8 | D68: =IFERROR(ROUND(AVERAGEIF($C$5:$C$61,$A68,$T$5:$T$61),2),"") -> 2.88 | E68: =IF($D68="","Not rated",IF((COUNTIFS($C$5:$C$61,$A68,$S$5:$S$61,"Judged",$T$5:$T$61,">0")+$I68+$J68)>($C68-COUNTIFS($C$5:$C$61,$A68,$S$5:$S$61,"Judged",$T$5:$T$61,">0")),"("&IF($D68<1.8,"Nascent",IF($D68<2.6,"Emerging",IF($D68<3.4,"Established",IF($D68<4.2,"Advanced","Transformative"))))&")",IF($D68<1.8,"Nascent",IF($D68<2.6,"Emerging",IF($D68<3.4,"Established",IF($D68<4.2,"Advanced","Transformative")))))) -> Established | F68: =COUNTIFS($C$5:$C$61,$A68,$S$5:$S$61,"Measured") -> 1 | G68: =COUNTIFS($C$5:$C$61,$A68,$S$5:$S$61,"Documented") -> 7 | H68: =COUNTIFS($C$5:$C$61,$A68,$S$5:$S$61,"Judged") -> 0 | I68: =COUNTIFS($C$5:$C$61,$A68,$S$5:$S$61,"Gap") -> 0 | J68: =COUNTIFS($C$5:$C$61,$A68,$AC$5:$AC$61,"<>") -> 0 | K68: =COUNTIFS($C$5:$C$61,$A68,$U$5:$U$61,"STALE") -> 0
A69: C3 | B69: =COUNTIF($C$5:$C$61,$A69) -> 8 | C69: =COUNTIFS($C$5:$C$61,$A69,$T$5:$T$61,">0") -> 8 | D69: =IFERROR(ROUND(AVERAGEIF($C$5:$C$61,$A69,$T$5:$T$61),2),"") -> 3.25 | E69: =IF($D69="","Not rated",IF((COUNTIFS($C$5:$C$61,$A69,$S$5:$S$61,"Judged",$T$5:$T$61,">0")+$I69+$J69)>($C69-COUNTIFS($C$5:$C$61,$A69,$S$5:$S$61,"Judged",$T$5:$T$61,">0")),"("&IF($D69<1.8,"Nascent",IF($D69<2.6,"Emerging",IF($D69<3.4,"Established",IF($D69<4.2,"Advanced","Transformative"))))&")",IF($D69<1.8,"Nascent",IF($D69<2.6,"Emerging",IF($D69<3.4,"Established",IF($D69<4.2,"Advanced","Transformative")))))) -> Established | F69: =COUNTIFS($C$5:$C$61,$A69,$S$5:$S$61,"Measured") -> 3 | G69: =COUNTIFS($C$5:$C$61,$A69,$S$5:$S$61,"Documented") -> 5 | H69: =COUNTIFS($C$5:$C$61,$A69,$S$5:$S$61,"Judged") -> 0 | I69: =COUNTIFS($C$5:$C$61,$A69,$S$5:$S$61,"Gap") -> 0 | J69: =COUNTIFS($C$5:$C$61,$A69,$AC$5:$AC$61,"<>") -> 0 | K69: =COUNTIFS($C$5:$C$61,$A69,$U$5:$U$61,"STALE") -> 2
A70: C4 | B70: =COUNTIF($C$5:$C$61,$A70) -> 7 | C70: =COUNTIFS($C$5:$C$61,$A70,$T$5:$T$61,">0") -> 3 | D70: =IFERROR(ROUND(AVERAGEIF($C$5:$C$61,$A70,$T$5:$T$61),2),"") -> 3.33 | E70: =IF($D70="","Not rated",IF((COUNTIFS($C$5:$C$61,$A70,$S$5:$S$61,"Judged",$T$5:$T$61,">0")+$I70+$J70)>($C70-COUNTIFS($C$5:$C$61,$A70,$S$5:$S$61,"Judged",$T$5:$T$61,">0")),"("&IF($D70<1.8,"Nascent",IF($D70<2.6,"Emerging",IF($D70<3.4,"Established",IF($D70<4.2,"Advanced","Transformative"))))&")",IF($D70<1.8,"Nascent",IF($D70<2.6,"Emerging",IF($D70<3.4,"Established",IF($D70<4.2,"Advanced","Transformative")))))) -> (Established) | F70: =COUNTIFS($C$5:$C$61,$A70,$S$5:$S$61,"Measured") -> 2 | G70: =COUNTIFS($C$5:$C$61,$A70,$S$5:$S$61,"Documented") -> 4 | H70: =COUNTIFS($C$5:$C$61,$A70,$S$5:$S$61,"Judged") -> 0 | I70: =COUNTIFS($C$5:$C$61,$A70,$S$5:$S$61,"Gap") -> 1 | J70: =COUNTIFS($C$5:$C$61,$A70,$AC$5:$AC$61,"<>") -> 3 | K70: =COUNTIFS($C$5:$C$61,$A70,$U$5:$U$61,"STALE") -> 2
A71: E1 | B71: =COUNTIF($C$5:$C$61,$A71) -> 11 | C71: =COUNTIFS($C$5:$C$61,$A71,$T$5:$T$61,">0") -> 9 | D71: =IFERROR(ROUND(AVERAGEIF($C$5:$C$61,$A71,$T$5:$T$61),2),"") -> 3.11 | E71: =IF($D71="","Not rated",IF((COUNTIFS($C$5:$C$61,$A71,$S$5:$S$61,"Judged",$T$5:$T$61,">0")+$I71+$J71)>($C71-COUNTIFS($C$5:$C$61,$A71,$S$5:$S$61,"Judged",$T$5:$T$61,">0")),"("&IF($D71<1.8,"Nascent",IF($D71<2.6,"Emerging",IF($D71<3.4,"Established",IF($D71<4.2,"Advanced","Transformative"))))&")",IF($D71<1.8,"Nascent",IF($D71<2.6,"Emerging",IF($D71<3.4,"Established",IF($D71<4.2,"Advanced","Transformative")))))) -> Established | F71: =COUNTIFS($C$5:$C$61,$A71,$S$5:$S$61,"Measured") -> 1 | G71: =COUNTIFS($C$5:$C$61,$A71,$S$5:$S$61,"Documented") -> 8 | H71: =COUNTIFS($C$5:$C$61,$A71,$S$5:$S$61,"Judged") -> 0 | I71: =COUNTIFS($C$5:$C$61,$A71,$S$5:$S$61,"Gap") -> 2 | J71: =COUNTIFS($C$5:$C$61,$A71,$AC$5:$AC$61,"<>") -> 0 | K71: =COUNTIFS($C$5:$C$61,$A71,$U$5:$U$61,"STALE") -> 0
A72: O1 | B72: =COUNTIF($C$5:$C$61,$A72) -> 7 | C72: =COUNTIFS($C$5:$C$61,$A72,$T$5:$T$61,">0") -> 6 | D72: =IFERROR(ROUND(AVERAGEIF($C$5:$C$61,$A72,$T$5:$T$61),2),"") -> 2.67 | E72: =IF($D72="","Not rated",IF((COUNTIFS($C$5:$C$61,$A72,$S$5:$S$61,"Judged",$T$5:$T$61,">0")+$I72+$J72)>($C72-COUNTIFS($C$5:$C$61,$A72,$S$5:$S$61,"Judged",$T$5:$T$61,">0")),"("&IF($D72<1.8,"Nascent",IF($D72<2.6,"Emerging",IF($D72<3.4,"Established",IF($D72<4.2,"Advanced","Transformative"))))&")",IF($D72<1.8,"Nascent",IF($D72<2.6,"Emerging",IF($D72<3.4,"Established",IF($D72<4.2,"Advanced","Transformative")))))) -> Established | F72: =COUNTIFS($C$5:$C$61,$A72,$S$5:$S$61,"Measured") -> 3 | G72: =COUNTIFS($C$5:$C$61,$A72,$S$5:$S$61,"Documented") -> 3 | H72: =COUNTIFS($C$5:$C$61,$A72,$S$5:$S$61,"Judged") -> 0 | I72: =COUNTIFS($C$5:$C$61,$A72,$S$5:$S$61,"Gap") -> 1 | J72: =COUNTIFS($C$5:$C$61,$A72,$AC$5:$AC$61,"<>") -> 0 | K72: =COUNTIFS($C$5:$C$61,$A72,$U$5:$U$61,"STALE") -> 0
A75: Layer profile and structural gap
A76: Foundation | B76: =IFERROR(ROUND(AVERAGEIF($D$5:$D$61,$A76,$T$5:$T$61),2),"") -> 3.31
A77: Enablers | B77: =IFERROR(ROUND(AVERAGEIF($D$5:$D$61,$A77,$T$5:$T$61),2),"") -> 2.9
A78: Transformation | B78: =IFERROR(ROUND(AVERAGEIF($D$5:$D$61,$A78,$T$5:$T$61),2),"") -> 3.71
A79: Outcomes | B79: =IFERROR(ROUND(AVERAGEIF($D$5:$D$61,$A79,$T$5:$T$61),2),"") -> 2.67
A81: Gap (Foundation − Transformation) | B81: =IF(OR($B$76="",$B$78=""),"",ROUND($B$76-$B$78,2)) -> -0.4 | C81: =IF($B$81="","",IF(ABS($B$81)>Config!$C$5,IF($B$81>0,"FLAG — unrealized foundations","FLAG — services ahead of their rails"),"No structural flag")) -> No structural flag
A84: Prerequisites (presence only; Unverified = the presence could not be evidenced)
A85: ID | B85: Prerequisite | C85: Scope | D85: Status
A86: 2.1 | B86: =INDEX($B$5:$B$61,MATCH($A86,$A$5:$A$61,0)) -> Rural mobile broadband coverage (3G/4G) | C86: Universal | D86: =IF(OR(INDEX($S$5:$S$61,MATCH($A86,$A$5:$A$61,0))="Gap",INDEX($S$5:$S$61,MATCH($A86,$A$5:$A$61,0))="",INDEX($T$5:$T$61,MATCH($A86,$A$5:$A$61,0))=""),"Unverified",IF(INDEX($T$5:$T$61,MATCH($A86,$A$5:$A$61,0))>=3,"Present",IF(INDEX($T$5:$T$61,MATCH($A86,$A$5:$A$61,0))=2,"Present (narrow)","Absent"))) -> Unverified
A87: 2.9 | B87: =INDEX($B$5:$B$61,MATCH($A87,$A$5:$A$61,0)) -> Rural electricity access (%) | C87: Universal | D87: =IF(OR(INDEX($S$5:$S$61,MATCH($A87,$A$5:$A$61,0))="Gap",INDEX($S$5:$S$61,MATCH($A87,$A$5:$A$61,0))="",INDEX($T$5:$T$61,MATCH($A87,$A$5:$A$61,0))=""),"Unverified",IF(INDEX($T$5:$T$61,MATCH($A87,$A$5:$A$61,0))>=3,"Present",IF(INDEX($T$5:$T$61,MATCH($A87,$A$5:$A$61,0))=2,"Present (narrow)","Absent"))) -> Present
A88: 4.1 | B88: =INDEX($B$5:$B$61,MATCH($A88,$A$5:$A$61,0)) -> Data protection/privacy law | C88: Universal | D88: =IF(OR(INDEX($S$5:$S$61,MATCH($A88,$A$5:$A$61,0))="Gap",INDEX($S$5:$S$61,MATCH($A88,$A$5:$A$61,0))="",INDEX($T$5:$T$61,MATCH($A88,$A$5:$A$61,0))=""),"Unverified",IF(INDEX($T$5:$T$61,MATCH($A88,$A$5:$A$61,0))>=3,"Present",IF(INDEX($T$5:$T$61,MATCH($A88,$A$5:$A$61,0))=2,"Present (narrow)","Absent"))) -> Present
A89: 3.3 | B89: =INDEX($B$5:$B$61,MATCH($A89,$A$5:$A$61,0)) -> National farmer registry | C89: Use case: FIN, AGI | D89: =IF(OR(INDEX($S$5:$S$61,MATCH($A89,$A$5:$A$61,0))="Gap",INDEX($S$5:$S$61,MATCH($A89,$A$5:$A$61,0))="",INDEX($T$5:$T$61,MATCH($A89,$A$5:$A$61,0))=""),"Unverified",IF(INDEX($T$5:$T$61,MATCH($A89,$A$5:$A$61,0))>=3,"Present",IF(INDEX($T$5:$T$61,MATCH($A89,$A$5:$A$61,0))=2,"Present (narrow)","Absent"))) -> Present
A90: 3.11 | B90: =INDEX($B$5:$B$61,MATCH($A90,$A$5:$A$61,0)) -> Agricultural data interoperability standards | C90: Use case: AGI | D90: =IF(OR(INDEX($S$5:$S$61,MATCH($A90,$A$5:$A$61,0))="Gap",INDEX($S$5:$S$61,MATCH($A90,$A$5:$A$61,0))="",INDEX($T$5:$T$61,MATCH($A90,$A$5:$A$61,0))=""),"Unverified",IF(INDEX($T$5:$T$61,MATCH($A90,$A$5:$A$61,0))>=3,"Present",IF(INDEX($T$5:$T$61,MATCH($A90,$A$5:$A$61,0))=2,"Present (narrow)","Absent"))) -> Absent
A91: 4.5 | B91: =INDEX($B$5:$B$61,MATCH($A91,$A$5:$A$61,0)) -> Agricultural data governance framework | C91: Use case: AGI | D91: =IF(OR(INDEX($S$5:$S$61,MATCH($A91,$A$5:$A$61,0))="Gap",INDEX($S$5:$S$61,MATCH($A91,$A$5:$A$61,0))="",INDEX($T$5:$T$61,MATCH($A91,$A$5:$A$61,0))=""),"Unverified",IF(INDEX($T$5:$T$61,MATCH($A91,$A$5:$A$61,0))>=3,"Present",IF(INDEX($T$5:$T$61,MATCH($A91,$A$5:$A$61,0))=2,"Present (narrow)","Absent"))) -> Absent
A92: 4.7 | B92: =INDEX($B$5:$B$61,MATCH($A92,$A$5:$A$61,0)) -> Digital ID coverage (%) | C92: Use case: FIN | D92: =IF(OR(INDEX($S$5:$S$61,MATCH($A92,$A$5:$A$61,0))="Gap",INDEX($S$5:$S$61,MATCH($A92,$A$5:$A$61,0))="",INDEX($T$5:$T$61,MATCH($A92,$A$5:$A$61,0))=""),"Unverified",IF(INDEX($T$5:$T$61,MATCH($A92,$A$5:$A$61,0))>=3,"Present",IF(INDEX($T$5:$T$61,MATCH($A92,$A$5:$A$61,0))=2,"Present (narrow)","Absent"))) -> Present
A93: 4.9 | B93: =INDEX($B$5:$B$61,MATCH($A93,$A$5:$A$61,0)) -> Inter-ministerial coordination mechanism | C93: Delivery flag | D93: =IF(OR(INDEX($S$5:$S$61,MATCH($A93,$A$5:$A$61,0))="Gap",INDEX($S$5:$S$61,MATCH($A93,$A$5:$A$61,0))="",INDEX($T$5:$T$61,MATCH($A93,$A$5:$A$61,0))=""),"Unverified",IF(INDEX($T$5:$T$61,MATCH($A93,$A$5:$A$61,0))>=3,"Present",IF(INDEX($T$5:$T$61,MATCH($A93,$A$5:$A$61,0))=2,"Present (narrow)","Absent"))) -> Present
A94: 5.5 | B94: =INDEX($B$5:$B$61,MATCH($A94,$A$5:$A$61,0)) -> Digital extension capability | C94: Use case: ADV | D94: =IF(OR(INDEX($S$5:$S$61,MATCH($A94,$A$5:$A$61,0))="Gap",INDEX($S$5:$S$61,MATCH($A94,$A$5:$A$61,0))="",INDEX($T$5:$T$61,MATCH($A94,$A$5:$A$61,0))=""),"Unverified",IF(INDEX($T$5:$T$61,MATCH($A94,$A$5:$A$61,0))>=3,"Present",IF(INDEX($T$5:$T$61,MATCH($A94,$A$5:$A$61,0))=2,"Present (narrow)","Absent"))) -> Present
A95: 5.7 | B95: =INDEX($B$5:$B$61,MATCH($A95,$A$5:$A$61,0)) -> MoAg digital/AI unit | C95: Delivery flag | D95: =IF(OR(INDEX($S$5:$S$61,MATCH($A95,$A$5:$A$61,0))="Gap",INDEX($S$5:$S$61,MATCH($A95,$A$5:$A$61,0))="",INDEX($T$5:$T$61,MATCH($A95,$A$5:$A$61,0))=""),"Unverified",IF(INDEX($T$5:$T$61,MATCH($A95,$A$5:$A$61,0))>=3,"Present",IF(INDEX($T$5:$T$61,MATCH($A95,$A$5:$A$61,0))=2,"Present (narrow)","Absent"))) -> Unverified
A96: 6.14 | B96: =INDEX($B$5:$B$61,MATCH($A96,$A$5:$A$61,0)) -> Agri-fintech rails for smallholders | C96: Use case: FIN | D96: =IF(OR(INDEX($S$5:$S$61,MATCH($A96,$A$5:$A$61,0))="Gap",INDEX($S$5:$S$61,MATCH($A96,$A$5:$A$61,0))="",INDEX($T$5:$T$61,MATCH($A96,$A$5:$A$61,0))=""),"Unverified",IF(INDEX($T$5:$T$61,MATCH($A96,$A$5:$A$61,0))>=3,"Present",IF(INDEX($T$5:$T$61,MATCH($A96,$A$5:$A$61,0))=2,"Present (narrow)","Absent"))) -> Present
A97: 7.12 | B97: =INDEX($B$5:$B$61,MATCH($A97,$A$5:$A$61,0)) -> Responsible-AI safeguards (consent, rights) | C97: Use case: AI-enabled (binds AGI) | D97: =IF(OR(INDEX($S$5:$S$61,MATCH($A97,$A$5:$A$61,0))="Gap",INDEX($S$5:$S$61,MATCH($A97,$A$5:$A$61,0))="",INDEX($T$5:$T$61,MATCH($A97,$A$5:$A$61,0))=""),"Unverified",IF(INDEX($T$5:$T$61,MATCH($A97,$A$5:$A$61,0))>=3,"Present",IF(INDEX($T$5:$T$61,MATCH($A97,$A$5:$A$61,0))=2,"Present (narrow)","Absent"))) -> Absent
A100: Use-case readiness (feeds Playbook Step 2B — Digital Readiness)
A101: Use case area | B101: Mean of bearing indicators | C101: Status | D101: Blocking / limiting factor
A102: Advisory & extension | B102: =IFERROR(ROUND(AVERAGEIF(V$5:V$61,1,$T$5:$T$61),2),"") -> 3.27 | C102: =IF(OR($D$86="Absent",$D$87="Absent",$D$88="Absent",$D$94="Absent"),"Blocked",IF(OR($D$86="Unverified",$D$87="Unverified",$D$88="Unverified",$D$94="Unverified"),"Unverified",IF(OR(OR($D$94="Present (narrow)"),$B102<Config!$C$4,OR($D$86="Present (narrow)",$D$87="Present (narrow)",$D$88="Present (narrow)")),"Partial","Ready"))) -> Unverified | D102: =IF($C102="Ready","",IF(TRIM(IF($D$86<>"Present",$A$86&" ","")&IF($D$87<>"Present",$A$87&" ","")&IF($D$88<>"Present",$A$88&" ","")&IF($D$94<>"Present",$A$94&" ",""))<>"",TRIM(IF($D$86<>"Present",$A$86&" ","")&IF($D$87<>"Present",$A$87&" ","")&IF($D$88<>"Present",$A$88&" ","")&IF($D$94<>"Present",$A$94&" ","")),IF($B102<Config!$C$4,"thin enablers (mean below "&TEXT(Config!$C$4,"0.0")&")",""))) -> 2.1
A103: Smart farming | B103: =IFERROR(ROUND(AVERAGEIF(W$5:W$61,1,$T$5:$T$61),2),"") -> 3.12 | C103: =IF(OR($D$86="Absent",$D$87="Absent",$D$88="Absent"),"Blocked",IF(OR($D$86="Unverified",$D$87="Unverified",$D$88="Unverified"),"Unverified",IF(OR($B103<Config!$C$4,OR($D$86="Present (narrow)",$D$87="Present (narrow)",$D$88="Present (narrow)")),"Partial","Ready"))) -> Unverified | D103: =IF($C103="Ready","",IF(TRIM(IF($D$86<>"Present",$A$86&" ","")&IF($D$87<>"Present",$A$87&" ","")&IF($D$88<>"Present",$A$88&" ",""))<>"",TRIM(IF($D$86<>"Present",$A$86&" ","")&IF($D$87<>"Present",$A$87&" ","")&IF($D$88<>"Present",$A$88&" ","")),IF($B103<Config!$C$4,"thin enablers (mean below "&TEXT(Config!$C$4,"0.0")&")",""))) -> 2.1
A104: Market linkage | B104: =IFERROR(ROUND(AVERAGEIF(X$5:X$61,1,$T$5:$T$61),2),"") -> 3.13 | C104: =IF(OR($D$86="Absent",$D$87="Absent",$D$88="Absent"),"Blocked",IF(OR($D$86="Unverified",$D$87="Unverified",$D$88="Unverified"),"Unverified",IF(OR($B104<Config!$C$4,OR($D$86="Present (narrow)",$D$87="Present (narrow)",$D$88="Present (narrow)")),"Partial","Ready"))) -> Unverified | D104: =IF($C104="Ready","",IF(TRIM(IF($D$86<>"Present",$A$86&" ","")&IF($D$87<>"Present",$A$87&" ","")&IF($D$88<>"Present",$A$88&" ",""))<>"",TRIM(IF($D$86<>"Present",$A$86&" ","")&IF($D$87<>"Present",$A$87&" ","")&IF($D$88<>"Present",$A$88&" ","")),IF($B104<Config!$C$4,"thin enablers (mean below "&TEXT(Config!$C$4,"0.0")&")",""))) -> 2.1
A105: Supply chain | B105: =IFERROR(ROUND(AVERAGEIF(Y$5:Y$61,1,$T$5:$T$61),2),"") -> 3.22 | C105: =IF(OR($D$86="Absent",$D$87="Absent",$D$88="Absent"),"Blocked",IF(OR($D$86="Unverified",$D$87="Unverified",$D$88="Unverified"),"Unverified",IF(OR($B105<Config!$C$4,OR($D$86="Present (narrow)",$D$87="Present (narrow)",$D$88="Present (narrow)")),"Partial","Ready"))) -> Unverified | D105: =IF($C105="Ready","",IF(TRIM(IF($D$86<>"Present",$A$86&" ","")&IF($D$87<>"Present",$A$87&" ","")&IF($D$88<>"Present",$A$88&" ",""))<>"",TRIM(IF($D$86<>"Present",$A$86&" ","")&IF($D$87<>"Present",$A$87&" ","")&IF($D$88<>"Present",$A$88&" ","")),IF($B105<Config!$C$4,"thin enablers (mean below "&TEXT(Config!$C$4,"0.0")&")",""))) -> 2.1
A106: Financial services | B106: =IFERROR(ROUND(AVERAGEIF(Z$5:Z$61,1,$T$5:$T$61),2),"") -> 3.03 | C106: =IF(OR($D$86="Absent",$D$87="Absent",$D$88="Absent",$D$89="Absent",$D$92="Absent",$D$96="Absent"),"Blocked",IF(OR($D$86="Unverified",$D$87="Unverified",$D$88="Unverified",$D$89="Unverified",$D$92="Unverified",$D$96="Unverified"),"Unverified",IF(OR(OR($D$89="Present (narrow)",$D$92="Present (narrow)",$D$96="Present (narrow)"),$B106<Config!$C$4,OR($D$86="Present (narrow)",$D$87="Present (narrow)",$D$88="Present (narrow)")),"Partial","Ready"))) -> Unverified | D106: =IF($C106="Ready","",IF(TRIM(IF($D$86<>"Present",$A$86&" ","")&IF($D$87<>"Present",$A$87&" ","")&IF($D$88<>"Present",$A$88&" ","")&IF($D$89<>"Present",$A$89&" ","")&IF($D$92<>"Present",$A$92&" ","")&IF($D$96<>"Present",$A$96&" ",""))<>"",TRIM(IF($D$86<>"Present",$A$86&" ","")&IF($D$87<>"Present",$A$87&" ","")&IF($D$88<>"Present",$A$88&" ","")&IF($D$89<>"Present",$A$89&" ","")&IF($D$92<>"Present",$A$92&" ","")&IF($D$96<>"Present",$A$96&" ","")),IF($B106<Config!$C$4,"thin enablers (mean below "&TEXT(Config!$C$4,"0.0")&")",""))) -> 2.1
A107: Ag intelligence | B107: =IFERROR(ROUND(AVERAGEIF(AA$5:AA$61,1,$T$5:$T$61),2),"") -> 3.17 | C107: =IF(OR($D$86="Absent",$D$87="Absent",$D$88="Absent",$D$89="Absent",$D$90="Absent",$D$91="Absent",$D$97="Absent"),"Blocked",IF(OR($D$86="Unverified",$D$87="Unverified",$D$88="Unverified",$D$89="Unverified",$D$90="Unverified",$D$91="Unverified",$D$97="Unverified"),"Unverified",IF(OR(OR($D$89="Present (narrow)",$D$90="Present (narrow)",$D$91="Present (narrow)",$D$97="Present (narrow)"),$B107<Config!$C$4,OR($D$86="Present (narrow)",$D$87="Present (narrow)",$D$88="Present (narrow)")),"Partial","Ready"))) -> Blocked | D107: =IF($C107="Ready","",IF(TRIM(IF($D$86<>"Present",$A$86&" ","")&IF($D$87<>"Present",$A$87&" ","")&IF($D$88<>"Present",$A$88&" ","")&IF($D$89<>"Present",$A$89&" ","")&IF($D$90<>"Present",$A$90&" ","")&IF($D$91<>"Present",$A$91&" ","")&IF($D$97<>"Present",$A$97&" ",""))<>"",TRIM(IF($D$86<>"Present",$A$86&" ","")&IF($D$87<>"Present",$A$87&" ","")&IF($D$88<>"Present",$A$88&" ","")&IF($D$89<>"Present",$A$89&" ","")&IF($D$90<>"Present",$A$90&" ","")&IF($D$91<>"Present",$A$91&" ","")&IF($D$97<>"Present",$A$97&" ","")),IF($B107<Config!$C$4,"thin enablers (mean below "&TEXT(Config!$C$4,"0.0")&")",""))) -> 2.1 3.11 4.5 7.12
A110: Proposed additions — recorded for context, outside every aggregate (ratification item)
A111: A1-CAND-IMP | B111: Cereal import dependency ratio (%) | C111: A1? | M111: 42.8 | N111: FAOSTAT, Suite of Food Security Indicators (FS domain), item 21035 'Cereal import dependency ratio (percent) (3-year average)', Egypt, period 2021-2023 | O111: https://bulks-faostat.fao.org/production/Food_Security_Data_E_Africa.zip | P111: T1 | Q111: 2023 | S111: not scored
A112: A1-CAND-IRR | B112: Irrigation coverage (% of cultivated/agricultural land equipped) | C112: A1? | M112: 94.21 | N112: FAO AQUASTAT Dissemination System — Egypt, variable 4331 '% of the cultivated area equipped for irrigation', 2023 (flag E = estimate); companion variable 4313 'Area equipped for irrigation: total' = 3,823,000 ha (2023, flag I = imputed) | O112: https://api.data.apps.fao.org/api/v2/bigquery?sql_url=https://data.apps.fao.org/catalog/dataset/945666e6-7803-4621-b8ef-cfd885a84596/resource/4a000a1b-24f0-4328-aab6-b9b525892090/download/query_en.sql&area=Egypt&variable=4331,4313&year=2023&type=country | P112: T1 | Q112: 2023 | S112: not scored | AB112: Which denominator defines 'land equipped' — cultivated land, arable land, or total agricultural land — since Egypt reads 94.2-94.9% on the first and 100% on the second?

Sheet Issues
B1: Issues log — quality control findings
B2: Every automated failure, peer-review disagreement and sign-off exception is recorded here. Fixes change entries on the scoring sheet; derived fields are never edited.
B4: # | C4: Date | D4: Class | E4: Finding | F4: Row / ID | G4: Action | H4: Resolver | I4: Status

Sheet Visuals
A1: Visuals — charts read live from the scoring sheet
A2: Read a level chart together with the evidence-mix chart: a strong bar standing on a mostly grey evidence bar is a hypothesis, not a finding.
A3: Pillar | B3: Mean | C3: Measured | D3: Documented | E3: Judged | F3: Gap
A4: A1 Agriculture & need | B4: =Egypt!$D$66 -> 3 | C4: =Egypt!$F$66 -> 6 | D4: =Egypt!$G$66 -> 4 | E4: =Egypt!$H$66 -> 0 | F4: =Egypt!$I$66 -> 0
A5: C1 Connectivity & access | B5: =Egypt!$D$67 -> 3.8 | C5: =Egypt!$F$67 -> 4 | D5: =Egypt!$G$67 -> 1 | E5: =Egypt!$H$67 -> 0 | F5: =Egypt!$I$67 -> 1
A6: C2 Data & DPI | B6: =Egypt!$D$68 -> 2.88 | C6: =Egypt!$F$68 -> 1 | D6: =Egypt!$G$68 -> 7 | E6: =Egypt!$H$68 -> 0 | F6: =Egypt!$I$68 -> 0
A7: C3 Policy & safeguards | B7: =Egypt!$D$69 -> 3.25 | C7: =Egypt!$F$69 -> 3 | D7: =Egypt!$G$69 -> 5 | E7: =Egypt!$H$69 -> 0 | F7: =Egypt!$I$69 -> 0
A8: C4 People & institutions | B8: =Egypt!$D$70 -> 3.33 | C8: =Egypt!$F$70 -> 2 | D8: =Egypt!$G$70 -> 4 | E8: =Egypt!$H$70 -> 0 | F8: =Egypt!$I$70 -> 1
A9: E1 Innovation & emerging tech | B9: =Egypt!$D$71 -> 3.11 | C9: =Egypt!$F$71 -> 1 | D9: =Egypt!$G$71 -> 8 | E9: =Egypt!$H$71 -> 0 | F9: =Egypt!$I$71 -> 2
A10: O1 Outcomes & inclusion | B10: =Egypt!$D$72 -> 2.67 | C10: =Egypt!$F$72 -> 3 | D10: =Egypt!$G$72 -> 3 | E10: =Egypt!$H$72 -> 0 | F10: =Egypt!$I$72 -> 1
A12: Layer | B12: Mean
A13: Foundation | B13: =Egypt!$B$76 -> 3.31
A14: Enablers | B14: =Egypt!$B$77 -> 2.9
A15: Transformation | B15: =Egypt!$B$78 -> 3.71
A16: Outcomes | B16: =Egypt!$B$79 -> 2.67
A18: Level | B18: Indicators
A19: Level 1 | B19: =COUNTIF(Egypt!$T$5:$T$61,1) -> 10
A20: Level 2 | B20: =COUNTIF(Egypt!$T$5:$T$61,2) -> 3
A21: Level 3 | B21: =COUNTIF(Egypt!$T$5:$T$61,3) -> 12
A22: Level 4 | B22: =COUNTIF(Egypt!$T$5:$T$61,4) -> 16
A23: Level 5 | B23: =COUNTIF(Egypt!$T$5:$T$61,5) -> 6
A25: Year | B25: Readings
A26: 2010 | B26: =SUMPRODUCT((Egypt!$Q$5:$Q$61=2010)*(Egypt!$S$5:$S$61<>"Gap")) -> 1
A27: 2017 | B27: =SUMPRODUCT((Egypt!$Q$5:$Q$61=2017)*(Egypt!$S$5:$S$61<>"Gap")) -> 1
A28: 2018 | B28: =SUMPRODUCT((Egypt!$Q$5:$Q$61=2018)*(Egypt!$S$5:$S$61<>"Gap")) -> 2
A29: 2019 | B29: =SUMPRODUCT((Egypt!$Q$5:$Q$61=2019)*(Egypt!$S$5:$S$61<>"Gap")) -> 1
A30: 2021 | B30: =SUMPRODUCT((Egypt!$Q$5:$Q$61=2021)*(Egypt!$S$5:$S$61<>"Gap")) -> 3
A31: 2022 | B31: =SUMPRODUCT((Egypt!$Q$5:$Q$61=2022)*(Egypt!$S$5:$S$61<>"Gap")) -> 3
A32: 2023 | B32: =SUMPRODUCT((Egypt!$Q$5:$Q$61=2023)*(Egypt!$S$5:$S$61<>"Gap")) -> 4
A33: 2024 | B33: =SUMPRODUCT((Egypt!$Q$5:$Q$61=2024)*(Egypt!$S$5:$S$61<>"Gap")) -> 12
A34: 2025 | B34: =SUMPRODUCT((Egypt!$Q$5:$Q$61=2025)*(Egypt!$S$5:$S$61<>"Gap")) -> 19
A35: 2026 | B35: =SUMPRODUCT((Egypt!$Q$5:$Q$61=2026)*(Egypt!$S$5:$S$61<>"Gap")) -> 6
A37: Note: readings more than three years old are flagged STALE on the scoring sheet.
