Workbook
Name BandL1_from: Config!$D$7
Name BandL2_from: Config!$D$8
Name BandL3_from: Config!$D$9
Name BandL4_from: Config!$D$10
Name BandL5_from: Config!$D$11
Name BandL5_to: Config!$E$11
Name Conf_High: Config!$C$47
Name Conf_Low: Config!$C$49
Name Conf_Medium: Config!$C$48
Name Cov_CMS: Config!$C$18
Name Cov_EMS: Config!$C$19
Name Cov_Pillar: Config!$C$17
Name Ev_Min: Config!$C$20
Name Leapfrog_Gap: Config!$C$30
Name Pillars: Config!$B$34:$B$41
Name Roles: Config!$C$34:$C$41
Name Stage2_CMS: Config!$C$21
Name Stage3_CMS: Config!$C$22
Name Stage3_EMS: Config!$C$23
Name Stage4_CMS: Config!$C$24
Name Stage4_EMS: Config!$C$25
Name Stage4_OES: Config!$C$26
Name Stage5_CMS: Config!$C$27
Name Stage5_EMS: Config!$C$28
Name Stage5_OES: Config!$C$29
Name Weights: Config!$D$34:$D$41

Sheet Read Me
B2: DAMM v1.4 — Live Scoring Workbook
B3: Digital Agriculture Maturity Model · 102 indicators · 8 pillars · CMS / EMS / OES
B5: What this workbook is
B7: Purpose | C7: A structured diagnostic for scoring a country's digital-agriculture readiness. Feeds a Digital Agriculture Roadmap (DAR); does NOT replace professional judgement.
B8: What v1.4 adds vs v1.3 | C8: v1.3 was a config file for an external app. v1.4 restores live scoring in Excel: every pillar score, read-out, stage, coverage figure and gate flag is a formula, recomputed as you edit.
B9: Three read-outs, never one number | C9: Capability (CMS), Ecosystem (EMS) and Outcomes (OES) are reported separately and never averaged. A country can build strong systems before outcomes move; a composite would hide that.
B10: Foundations are not tradeable | C10: 14 core-gate indicators are prerequisites. A core gate at Level 1 caps the overall stage at Stage 1. An unmeasured core gate suppresses the stage entirely.
B11: Silence beats a confident guess | C11: Below its coverage gate (60% pillar / 70% CMS / 60% EMS) a pillar reads Not rated. An unmeasured core gate suppresses the stage.
B12: Confidence & staleness | C12: Every reading carries a High/Medium/Low confidence and an observation year. Readings past their max-age limit are flagged Stale.
B13: Nothing before the mandate is an assessment | C13: Everything assembled before a government mandate is an ENGAGEMENT PACKAGE, not an assessment. No stage is claimable until human validation.
B14: Prohibitions wired in | C14: No cross-country ranking. No stage as PDO/DLI/disbursement condition. No automatic financing or vendor decisions. No stage without human validation.
B16: How to use this workbook
B18: 1. Study Egypt worked example | C18: Open 'Egypt (worked)' to see how a country is populated. Note the Level column (D), Confidence (F), Year (G), Source (H).
B19: 2. Duplicate the Blank Template | C19: Right-click the 'Blank Template' tab → Move or Copy → tick Create a Copy. Rename to your country.
B20: 3. Populate columns C–H | C20: For each row: enter the observed Value, the assessor Level 1–5 (which always wins over the machine suggestion), Confidence H/M/L, Observation Year, Source name and URL. Leave Level blank to mark a Data Gap.
B21: 4. Read the 'Scores' tab | C21: The dashboard reads live from your populated sheet. Change the country reference in Config!D6 to point at your new sheet.
B22: 5. Check gate flags | C22: The Scores sheet flags any core gate at L1, any unmeasured core gate, any pillar below coverage, and any stale readings. Address these before claiming a stage.
B23: 6. Export for the panel | C23: Filter Indicators sheet for panel scoring. Record dissent on anchored rubrics in the Notes column.
B25: Sheet index
B27: Scores | C27: Live dashboard: pillar / CMS / EMS / OES / stage / coverage / core-gate status / staleness
B28: Egypt (worked) | C28: Full worked example populated with Egypt data — 102 rows, live formulas
B29: Blank Template | C29: Empty scoring workbook — duplicate and rename for a new country
B30: Indicators | C30: 102-indicator census: pillar, role, method, direction, core gate, max age, thresholds
B31: Level Anchors | C31: Written L1–L5 anchor text for anchored rubric indicators
B32: Core Gates | C32: The 14 prerequisite indicators and why they gate
B33: Config | C33: Single source of truth: bands, coverage gates, weights, confidence weights, staleness limits
B34: Decision Ladder | C34: 8 steps from automated diagnostic (T0) to adoption (D6), with named decider
B35: Glossary | C35: CMS, EMS, OES, core gates, coverage, provisional, stale, engagement package
B36: Methodology | C36: Rules, cascade, provenance, prohibitions
B37: Changelog | C37: v1.0 → v1.1 → v1.3 → v1.4

Sheet Scores
B2: Scores — live dashboard
B3: Reads 'Egypt (worked)'. To point at a different country, copy this sheet and Find/Replace the tab name.
B5: Pillar scores
B6: Pillar | C6: Name | D6: Role | E6: # indicators | F6: # levelled | G6: Coverage | H6: Mean level | I6: Band | J6: Status
B7: C0 | C7: Agricultural context & need | D7: Context | E7: =COUNTIF('Egypt (worked)'!$D$8:$D$109,"C0") -> 8 | F7: =SUMPRODUCT(('Egypt (worked)'!$D$8:$D$109="C0")*ISNUMBER('Egypt (worked)'!$L$8:$L$109)) -> 0 | G7: =IF(E7=0,0,F7/E7) -> 0 | H7: ="—" -> — | I7: ="Context (never scored)" -> Context (never scored) | J7: =""
B8: C1 | C8: Connectivity & affordable access | D8: Capability | E8: =COUNTIF('Egypt (worked)'!$D$8:$D$109,"C1") -> 11 | F8: =SUMPRODUCT(('Egypt (worked)'!$D$8:$D$109="C1")*ISNUMBER('Egypt (worked)'!$L$8:$L$109)) -> 11 | G8: =IF(E8=0,0,F8/E8) -> 1 | H8: =IF(G8<Cov_Pillar,"Not rated",IF(F8=0,"Not rated",AVERAGEIFS('Egypt (worked)'!$L$8:$L$109,'Egypt (worked)'!$D$8:$D$109,"C1"))) -> 3.8181818 | I8: =IF(NOT(ISNUMBER(H8)),H8,IF(H8<BandL2_from,"Nascent",IF(H8<BandL3_from,"Emerging",IF(H8<BandL4_from,"Established",IF(H8<BandL5_from,"Advanced","Transformative"))))) -> Advanced | J8: =IF(G8<Cov_Pillar,"⚑ COVERAGE",IF(SUMPRODUCT(('Egypt (worked)'!$D$8:$D$109="C1")*('Egypt (worked)'!$O$8:$O$109="STALE"))>0,"⚑ Stale evidence","")) -> ⚑ Stale evidence
B9: C2 | C9: Data infrastructure & DPI | D9: Capability | E9: =COUNTIF('Egypt (worked)'!$D$8:$D$109,"C2") -> 13 | F9: =SUMPRODUCT(('Egypt (worked)'!$D$8:$D$109="C2")*ISNUMBER('Egypt (worked)'!$L$8:$L$109)) -> 13 | G9: =IF(E9=0,0,F9/E9) -> 1 | H9: =IF(G9<Cov_Pillar,"Not rated",IF(F9=0,"Not rated",AVERAGEIFS('Egypt (worked)'!$L$8:$L$109,'Egypt (worked)'!$D$8:$D$109,"C2"))) -> 2.7692308 | I9: =IF(NOT(ISNUMBER(H9)),H9,IF(H9<BandL2_from,"Nascent",IF(H9<BandL3_from,"Emerging",IF(H9<BandL4_from,"Established",IF(H9<BandL5_from,"Advanced","Transformative"))))) -> Established | J9: =IF(G9<Cov_Pillar,"⚑ COVERAGE",IF(SUMPRODUCT(('Egypt (worked)'!$D$8:$D$109="C2")*('Egypt (worked)'!$O$8:$O$109="STALE"))>0,"⚑ Stale evidence",""))
B10: C3 | C10: Policy, governance & safeguards | D10: Capability | E10: =COUNTIF('Egypt (worked)'!$D$8:$D$109,"C3") -> 13 | F10: =SUMPRODUCT(('Egypt (worked)'!$D$8:$D$109="C3")*ISNUMBER('Egypt (worked)'!$L$8:$L$109)) -> 13 | G10: =IF(E10=0,0,F10/E10) -> 1 | H10: =IF(G10<Cov_Pillar,"Not rated",IF(F10=0,"Not rated",AVERAGEIFS('Egypt (worked)'!$L$8:$L$109,'Egypt (worked)'!$D$8:$D$109,"C3"))) -> 3.1538462 | I10: =IF(NOT(ISNUMBER(H10)),H10,IF(H10<BandL2_from,"Nascent",IF(H10<BandL3_from,"Emerging",IF(H10<BandL4_from,"Established",IF(H10<BandL5_from,"Advanced","Transformative"))))) -> Established | J10: =IF(G10<Cov_Pillar,"⚑ COVERAGE",IF(SUMPRODUCT(('Egypt (worked)'!$D$8:$D$109="C3")*('Egypt (worked)'!$O$8:$O$109="STALE"))>0,"⚑ Stale evidence","")) -> ⚑ Stale evidence
B11: C4 | C11: Human & institutional capacity | D11: Capability | E11: =COUNTIF('Egypt (worked)'!$D$8:$D$109,"C4") -> 14 | F11: =SUMPRODUCT(('Egypt (worked)'!$D$8:$D$109="C4")*ISNUMBER('Egypt (worked)'!$L$8:$L$109)) -> 13 | G11: =IF(E11=0,0,F11/E11) -> 0.92857143 | H11: =IF(G11<Cov_Pillar,"Not rated",IF(F11=0,"Not rated",AVERAGEIFS('Egypt (worked)'!$L$8:$L$109,'Egypt (worked)'!$D$8:$D$109,"C4"))) -> 2.4615385 | I11: =IF(NOT(ISNUMBER(H11)),H11,IF(H11<BandL2_from,"Nascent",IF(H11<BandL3_from,"Emerging",IF(H11<BandL4_from,"Established",IF(H11<BandL5_from,"Advanced","Transformative"))))) -> Emerging | J11: =IF(G11<Cov_Pillar,"⚑ COVERAGE",IF(SUMPRODUCT(('Egypt (worked)'!$D$8:$D$109="C4")*('Egypt (worked)'!$O$8:$O$109="STALE"))>0,"⚑ Stale evidence","")) -> ⚑ Stale evidence
B12: E1 | C12: Innovation & private sector | D12: Ecosystem | E12: =COUNTIF('Egypt (worked)'!$D$8:$D$109,"E1") -> 14 | F12: =SUMPRODUCT(('Egypt (worked)'!$D$8:$D$109="E1")*ISNUMBER('Egypt (worked)'!$L$8:$L$109)) -> 13 | G12: =IF(E12=0,0,F12/E12) -> 0.92857143 | H12: =IF(G12<Cov_Pillar,"Not rated",IF(F12=0,"Not rated",AVERAGEIFS('Egypt (worked)'!$L$8:$L$109,'Egypt (worked)'!$D$8:$D$109,"E1"))) -> 3 | I12: =IF(NOT(ISNUMBER(H12)),H12,IF(H12<BandL2_from,"Nascent",IF(H12<BandL3_from,"Emerging",IF(H12<BandL4_from,"Established",IF(H12<BandL5_from,"Advanced","Transformative"))))) -> Established | J12: =IF(G12<Cov_Pillar,"⚑ COVERAGE",IF(SUMPRODUCT(('Egypt (worked)'!$D$8:$D$109="E1")*('Egypt (worked)'!$O$8:$O$109="STALE"))>0,"⚑ Stale evidence","")) -> ⚑ Stale evidence
B13: E2 | C13: Responsible AI & emerging tech | D13: Ecosystem | E13: =COUNTIF('Egypt (worked)'!$D$8:$D$109,"E2") -> 12 | F13: =SUMPRODUCT(('Egypt (worked)'!$D$8:$D$109="E2")*ISNUMBER('Egypt (worked)'!$L$8:$L$109)) -> 12 | G13: =IF(E13=0,0,F13/E13) -> 1 | H13: =IF(G13<Cov_Pillar,"Not rated",IF(F13=0,"Not rated",AVERAGEIFS('Egypt (worked)'!$L$8:$L$109,'Egypt (worked)'!$D$8:$D$109,"E2"))) -> 2.6666667 | I13: =IF(NOT(ISNUMBER(H13)),H13,IF(H13<BandL2_from,"Nascent",IF(H13<BandL3_from,"Emerging",IF(H13<BandL4_from,"Established",IF(H13<BandL5_from,"Advanced","Transformative"))))) -> Established | J13: =IF(G13<Cov_Pillar,"⚑ COVERAGE",IF(SUMPRODUCT(('Egypt (worked)'!$D$8:$D$109="E2")*('Egypt (worked)'!$O$8:$O$109="STALE"))>0,"⚑ Stale evidence","")) -> ⚑ Stale evidence
B14: O1 | C14: Inclusion, sustainability & outcomes | D14: Outcome | E14: =COUNTIF('Egypt (worked)'!$D$8:$D$109,"O1") -> 17 | F14: =SUMPRODUCT(('Egypt (worked)'!$D$8:$D$109="O1")*ISNUMBER('Egypt (worked)'!$L$8:$L$109)) -> 17 | G14: =IF(E14=0,0,F14/E14) -> 1 | H14: =IF(G14<Cov_Pillar,"Not rated",IF(F14=0,"Not rated",AVERAGEIFS('Egypt (worked)'!$L$8:$L$109,'Egypt (worked)'!$D$8:$D$109,"O1"))) -> 2.4117647 | I14: =IF(NOT(ISNUMBER(H14)),H14,IF(H14<BandL2_from,"Nascent",IF(H14<BandL3_from,"Emerging",IF(H14<BandL4_from,"Established",IF(H14<BandL5_from,"Advanced","Transformative"))))) -> Emerging | J14: =IF(G14<Cov_Pillar,"⚑ COVERAGE",IF(SUMPRODUCT(('Egypt (worked)'!$D$8:$D$109="O1")*('Egypt (worked)'!$O$8:$O$109="STALE"))>0,"⚑ Stale evidence","")) -> ⚑ Stale evidence
B16: Composite read-outs
B17: Read-out | C17: Formula | D17: Coverage | E17: Score | F17: Band | G17: Stage-eligible?
B18: CMS | C18: Capability (C1×w + C2×w + C3×w + C4×w) — suppress if any pillar unrated | D18: =IF(SUM(E8:E11)=0,0,SUM(F8:F11)/SUM(E8:E11)) -> 0.98039216 | E18: =IF(OR(NOT(ISNUMBER(H8)),NOT(ISNUMBER(H9)),NOT(ISNUMBER(H10)),NOT(ISNUMBER(H11))),"Not rated",IF(D18<Cov_CMS,"Not rated",SUMPRODUCT(H8:H11,Config!$D$35:$D$38))) -> 3.0660839 | F18: =IF(NOT(ISNUMBER(E18)),E18,IF(E18<BandL2_from,"Nascent",IF(E18<BandL3_from,"Emerging",IF(E18<BandL4_from,"Established",IF(E18<BandL5_from,"Advanced","Transformative"))))) -> Established | G18: =IF(NOT(ISNUMBER(E18)),"No","Yes") -> Yes
B19: EMS | C19: Ecosystem (E1×w + E2×w) — suppress if any pillar unrated | D19: =IF(SUM(E12:E13)=0,0,SUM(F12:F13)/SUM(E12:E13)) -> 0.96153846 | E19: =IF(OR(NOT(ISNUMBER(H12)),NOT(ISNUMBER(H13))),"Not rated",IF(D19<Cov_EMS,"Not rated",SUMPRODUCT(H12:H13,Config!$D$39:$D$40))) -> 2.9 | F19: =IF(NOT(ISNUMBER(E19)),E19,IF(E19<BandL2_from,"Nascent",IF(E19<BandL3_from,"Emerging",IF(E19<BandL4_from,"Established",IF(E19<BandL5_from,"Advanced","Transformative"))))) -> Established | G19: =IF(NOT(ISNUMBER(E19)),"No","Yes") -> Yes
B20: OES | C20: Outcome (O1 mean) | D20: =IF(E14=0,0,F14/E14) -> 1 | E20: =IF(NOT(ISNUMBER(H14)),"Not rated",H14) -> 2.4117647 | F20: =IF(NOT(ISNUMBER(E20)),E20,IF(E20<BandL2_from,"Nascent",IF(E20<BandL3_from,"Emerging",IF(E20<BandL4_from,"Established",IF(E20<BandL5_from,"Advanced","Transformative"))))) -> Emerging | G20: =IF(NOT(ISNUMBER(E20)),"No","Yes") -> Yes
B22: Core-gate audit (14 prerequisites)
B23: Metric | C23: Count | D23: Meaning
B24: Core gates at L1 | C24: =SUMPRODUCT(('Egypt (worked)'!$G$8:$G$109="YES")*('Egypt (worked)'!$L$8:$L$109=1)) -> 0 | D24: Caps overall stage at Stage 1 if > 0
B25: Core gates unmeasured | C25: =SUMPRODUCT(('Egypt (worked)'!$G$8:$G$109="YES")*(NOT(ISNUMBER('Egypt (worked)'!$L$8:$L$109)))) -> 0 | D25: Suppresses overall stage if > 0
B26: Core gates ≥ L3 | C26: =SUMPRODUCT(('Egypt (worked)'!$G$8:$G$109="YES")*('Egypt (worked)'!$L$8:$L$109>=3)) -> 12 | D26: How many gates are already Established or better
B27: Overall stage (non-compensatory cascade)
B28: OVERALL STAGE | C28: =IF(C25>0,"Suppressed (unmeasured core gate)",IF(C24>0,"Stage 1 — Foundation constrained (core gate at L1)",IF(NOT(ISNUMBER(E18)),"Not rated (CMS coverage/pillar)",IF(AND(ISNUMBER(E18),E18>=Stage5_CMS,ISNUMBER(E19),E19>=Stage5_EMS,ISNUMBER(E20),E20>=Stage5_OES),"Stage 5 — Transformative",IF(AND(ISNUMBER(E18),E18>=Stage4_CMS,ISNUMBER(E19),E19>=Stage4_EMS,ISNUMBER(E20),E20>=Stage4_OES),"Stage 4 — Integrated scale",IF(AND(ISNUMBER(E18),E18>=Stage3_CMS,ISNUMBER(E19),E19>=Stage3_EMS),"Stage 3 — Ecosystem scaling",IF(ISNUMBER(E18),IF(E18>=Stage2_CMS,"Stage 2 — Capability building","Stage 1 — Foundation constrained"),"Not rated"))))))) -> Stage 2 — Capability building
B29: Claim status | C29: =IF("'Egypt (worked)'"="'Egypt (worked)'","ENGAGEMENT PACKAGE — pre-mandate. No stage is claimable until human validation.","Assessed — validated by government / evidence panel.") -> ENGAGEMENT PACKAGE — pre-mandate. No stage is claimable until human validation.
B30: Evidence adequacy & staleness
B31: Metric | C31: Value | D31: Meaning
B32: Weighted evidence adequacy | C32: =IFERROR((SUMPRODUCT(ISNUMBER('Egypt (worked)'!$L$8:$L$109)*('Egypt (worked)'!$M$8:$M$109="High"))*Conf_High+SUMPRODUCT(ISNUMBER('Egypt (worked)'!$L$8:$L$109)*('Egypt (worked)'!$M$8:$M$109="Medium"))*Conf_Medium+SUMPRODUCT(ISNUMBER('Egypt (worked)'!$L$8:$L$109)*('Egypt (worked)'!$M$8:$M$109="Low"))*Conf_Low)/SUMPRODUCT(ISNUMBER('Egypt (worked)'!$L$8:$L$109)*1),0) -> 0.57173913 | D32: 0.5+ required for the read-outs to stand (Ev_Min)
B33: Stale readings | C33: =COUNTIF('Egypt (worked)'!$O$8:$O$109,"STALE") -> 16 | D33: Observation year older than the indicator's max age
B34: Data gaps | C34: =SUMPRODUCT((NOT(ISNUMBER('Egypt (worked)'!$L$8:$L$109)))*('Egypt (worked)'!$D$8:$D$109<>"C0")) -> 2 | D34: Scored indicators with no assessor level AND no machine level
B35: Coverage — overall (scored pillars only) | C35: =SUMPRODUCT(ISNUMBER('Egypt (worked)'!$L$8:$L$109)*('Egypt (worked)'!$D$8:$D$109<>"C0"))/SUMPRODUCT(1*('Egypt (worked)'!$D$8:$D$109<>"C0")) -> 0.9787234 | D35: Share of scored indicators (excludes C0 context) that carry a level
B36: Fragile-progress (leapfrog) check
B37: Foundation vs Ecosystem gap | C37: =IF(AND(ISNUMBER(H8),ISNUMBER(E19)),H8-E19,"—") -> 0.91818182 | D37: =IF(NOT(ISNUMBER(C37)),"",IF(ABS(C37)>=Leapfrog_Gap,"⚑ FRAGILE PROGRESS — check sequencing","OK")) -> OK

Sheet Egypt (worked)
B2: Egypt — DAMM v1.4 assessment
B3: Live scoring. Edit columns I–R. Columns J, L, O are formulas.
B5: Assessment mode | C5: Comprehensive (draft, engagement package) | E5: Assessor | F5: World Bank task team (draft) | H5: Mandate date | I5: PRE-MANDATE — engagement package | K5: Reference year | L5: 2025
B7: ID | C7: Indicator | D7: Pillar | E7: Method | F7: Dir. | G7: Core gate | H7: Max age | I7: Value | J7: Machine L (auto) | K7: Assessor L | L7: Effective L | M7: Confidence | N7: Year | O7: Stale? | P7: Source | Q7: URL | R7: Notes / dissent
B8: 1.1 | C8: Agriculture value added per worker (constant 2015 USD) | D8: C0 | E8: Context profile (not aggregated) | F8: N/A | H8: 3 | I8: 8390.6 | J8: =IF(I8="","",IF(Indicators!$H$6<>"Quantitative threshold","",IF(Indicators!$I$6="Higher",IF(N(I8)>=Indicators!$O$6,5,IF(N(I8)>=Indicators!$N$6,4,IF(N(I8)>=Indicators!$M$6,3,IF(N(I8)>=Indicators!$L$6,2,1)))),IF(N(I8)<=Indicators!$O$6,5,IF(N(I8)<=Indicators!$N$6,4,IF(N(I8)<=Indicators!$M$6,3,IF(N(I8)<=Indicators!$L$6,2,1))))))) | L8: =IF(Indicators!$D$6="C0","",IF(K8<>"",K8,IF(J8<>"",J8,""))) | M8: High | N8: 2023 | O8: =IF(N8="","",IF(N8<($L$5-H8),"STALE","")) | P8: World Bank WDI (NV.AGR.EMPL.KD) | Q8: https://api.worldbank.org/v2/country/EGY/indicator/NV.AGR.EMPL.KD?format=json | R8: Latest confirmed annual WDI observation for Egypt is 2023 ($8,390.60); later WDI 2024/2025 figures are nowcasted/modeled.
B9: 1.2 | C9: Cereal yield (kg per hectare) | D9: C0 | E9: Context profile (not aggregated) | F9: N/A | H9: 3 | I9: 7402.2 | J9: =IF(I9="","",IF(Indicators!$H$7<>"Quantitative threshold","",IF(Indicators!$I$7="Higher",IF(N(I9)>=Indicators!$O$7,5,IF(N(I9)>=Indicators!$N$7,4,IF(N(I9)>=Indicators!$M$7,3,IF(N(I9)>=Indicators!$L$7,2,1)))),IF(N(I9)<=Indicators!$O$7,5,IF(N(I9)<=Indicators!$N$7,4,IF(N(I9)<=Indicators!$M$7,3,IF(N(I9)<=Indicators!$L$7,2,1))))))) | L9: =IF(Indicators!$D$7="C0","",IF(K9<>"",K9,IF(J9<>"",J9,""))) | M9: High | N9: 2023 | O9: =IF(N9="","",IF(N9<($L$5-H9),"STALE","")) | P9: World Bank WDI (AG.YLD.CREL.KG) | Q9: https://api.worldbank.org/v2/country/EGY/indicator/AG.YLD.CREL.KG?format=json | R9: Egypt has among the highest cereal yields globally due to intensive irrigated agriculture.
B10: 1.3 | C10: Employment in agriculture (% of total employment) | D10: C0 | E10: Context profile (not aggregated) | F10: N/A | H10: 3 | I10: 17.52 | J10: =IF(I10="","",IF(Indicators!$H$8<>"Quantitative threshold","",IF(Indicators!$I$8="Higher",IF(N(I10)>=Indicators!$O$8,5,IF(N(I10)>=Indicators!$N$8,4,IF(N(I10)>=Indicators!$M$8,3,IF(N(I10)>=Indicators!$L$8,2,1)))),IF(N(I10)<=Indicators!$O$8,5,IF(N(I10)<=Indicators!$N$8,4,IF(N(I10)<=Indicators!$M$8,3,IF(N(I10)<=Indicators!$L$8,2,1))))))) | L10: =IF(Indicators!$D$8="C0","",IF(K10<>"",K10,IF(J10<>"",J10,""))) | M10: Medium | N10: 2023 | O10: =IF(N10="","",IF(N10<($L$5-H10),"STALE","")) | P10: World Bank WDI (SL.AGR.EMPL.ZS) | Q10: https://api.worldbank.org/v2/country/EGY/indicator/SL.AGR.EMPL.ZS?format=json | R10: WDI series continues to publish nowcasted 2024/2025 values (~17.5%); using confirmed recent-year band as best estimate.
B11: 1.4 | C11: Food production index (2014-2016 = 100) | D11: C0 | E11: Context profile (not aggregated) | F11: N/A | H11: 3 | I11: 109.07 | J11: =IF(I11="","",IF(Indicators!$H$9<>"Quantitative threshold","",IF(Indicators!$I$9="Higher",IF(N(I11)>=Indicators!$O$9,5,IF(N(I11)>=Indicators!$N$9,4,IF(N(I11)>=Indicators!$M$9,3,IF(N(I11)>=Indicators!$L$9,2,1)))),IF(N(I11)<=Indicators!$O$9,5,IF(N(I11)<=Indicators!$N$9,4,IF(N(I11)<=Indicators!$M$9,3,IF(N(I11)<=Indicators!$L$9,2,1))))))) | L11: =IF(Indicators!$D$9="C0","",IF(K11<>"",K11,IF(J11<>"",J11,""))) | M11: High | N11: 2022 | O11: =IF(N11="","",IF(N11<($L$5-H11),"STALE","")) | P11: World Bank WDI (AG.PRD.FOOD.XD) | Q11: https://api.worldbank.org/v2/country/EGY/indicator/AG.PRD.FOOD.XD?format=json | R11: Most recent published FAO-sourced food production index value via WDI.
B12: 1.5 | C12: Post-harvest loss rate (%) | D12: C0 | E12: Context profile (not aggregated) | F12: N/A | H12: 2 | I12: 10-15% of agricultural income; up to 30% for fruit/vegetables | J12: =IF(I12="","",IF(Indicators!$H$10<>"Quantitative threshold","",IF(Indicators!$I$10="Higher",IF(N(I12)>=Indicators!$O$10,5,IF(N(I12)>=Indicators!$N$10,4,IF(N(I12)>=Indicators!$M$10,3,IF(N(I12)>=Indicators!$L$10,2,1)))),IF(N(I12)<=Indicators!$O$10,5,IF(N(I12)<=Indicators!$N$10,4,IF(N(I12)<=Indicators!$M$10,3,IF(N(I12)<=Indicators!$L$10,2,1))))))) | L12: =IF(Indicators!$D$10="C0","",IF(K12<>"",K12,IF(J12<>"",J12,""))) | M12: Medium | N12: 2020 | O12: =IF(N12="","",IF(N12<($L$5-H12),"STALE","")) -> STALE | P12: FAO/MALR, Sustainable Agricultural Development Strategy towards 2030 | Q12: https://faolex.fao.org/docs/pdf/egy141040E.pdf | R12: SADS 2030 strategy document (MALR/FAO) states pre/post-harvest losses exceed 30% in vegetables and fruit, 20% in legumes/tubers, 10% in cereals, equating to 10-15% of total agricultural income; FAO Egypt food-loss project separately cites 15-45% depending on crop.
B13: 1.6 | C13: Smallholder access to formal markets (%) | D13: C0 | E13: Context profile (not aggregated) | F13: N/A | H13: 2 | I13: ~12% (Upper Egypt) | J13: =IF(I13="","",IF(Indicators!$H$11<>"Quantitative threshold","",IF(Indicators!$I$11="Higher",IF(N(I13)>=Indicators!$O$11,5,IF(N(I13)>=Indicators!$N$11,4,IF(N(I13)>=Indicators!$M$11,3,IF(N(I13)>=Indicators!$L$11,2,1)))),IF(N(I13)<=Indicators!$O$11,5,IF(N(I13)<=Indicators!$N$11,4,IF(N(I13)<=Indicators!$M$11,3,IF(N(I13)<=Indicators!$L$11,2,1))))))) | L13: =IF(Indicators!$D$11="C0","",IF(K13<>"",K13,IF(J13<>"",J13,""))) | M13: Medium | N13: 2025 | O13: =IF(N13="","",IF(N13<($L$5-H13),"STALE","")) | P13: IFAD Executive Board Seminar Document EB-2025-OR-16 | Q13: https://webapps.ifad.org/members/eb-seminars/2025-11-25-EB-Consultations/docs/EB-2025-OR-16.pdf | R13: IFAD reports only about 12% of farmers in Upper Egypt have direct links to formal buyers; no comprehensive national figure found, so this is a regional proxy.
B14: 1.7 | C14: Agricultural credit access (% of farmers) | D14: C0 | E14: Context profile (not aggregated) | F14: N/A | H14: 2 | I14: <25% financially included; ag sector receives ~1% of institutional lending | J14: =IF(I14="","",IF(Indicators!$H$12<>"Quantitative threshold","",IF(Indicators!$I$12="Higher",IF(N(I14)>=Indicators!$O$12,5,IF(N(I14)>=Indicators!$N$12,4,IF(N(I14)>=Indicators!$M$12,3,IF(N(I14)>=Indicators!$L$12,2,1)))),IF(N(I14)<=Indicators!$O$12,5,IF(N(I14)<=Indicators!$N$12,4,IF(N(I14)<=Indicators!$M$12,3,IF(N(I14)<=Indicators!$L$12,2,1))))))) | L14: =IF(Indicators!$D$12="C0","",IF(K14<>"",K14,IF(J14<>"",J14,""))) | M14: Medium | N14: 2021 | O14: =IF(N14="","",IF(N14<($L$5-H14),"STALE","")) -> STALE | P14: World Bank / MDPI 2024 citing WB 2021 Findex | Q14: https://www.mdpi.com/1911-8074/17/11/487 | R14: Less than 25% of Egypt's rural population is financially included per bank account ownership (World Bank 2021, cited in 2024 MDPI study); older World Bank data show agriculture receiving only ~1% of total institutional lending versus 38%/26% for industry/services.
B15: 1.8 | C15: Farmers using climate-smart/sustainable practices (%) | D15: C0 | E15: Context profile (not aggregated) | F15: N/A | H15: 2 | J15: =IF(I15="","",IF(Indicators!$H$13<>"Quantitative threshold","",IF(Indicators!$I$13="Higher",IF(N(I15)>=Indicators!$O$13,5,IF(N(I15)>=Indicators!$N$13,4,IF(N(I15)>=Indicators!$M$13,3,IF(N(I15)>=Indicators!$L$13,2,1)))),IF(N(I15)<=Indicators!$O$13,5,IF(N(I15)<=Indicators!$N$13,4,IF(N(I15)<=Indicators!$M$13,3,IF(N(I15)<=Indicators!$L$13,2,1))))))) | K15: 2 | L15: =IF(Indicators!$D$13="C0","",IF(K15<>"",K15,IF(J15<>"",J15,""))) | M15: Low | N15: 2020 | O15: =IF(N15="","",IF(N15<($L$5-H15),"STALE","")) -> STALE | P15: SADS 2030 (qualitative; no adoption-rate survey found) | Q15: https://faolex.fao.org/docs/pdf/egy141040E.pdf | R15: SADS 2030 sets climate-smart and water-efficiency ambitions but does not publish a measured adoption rate among farmers; assessed level 2 (aspirational policy target, adoption not yet measured/scaled) rather than a Data Gap given the strategy explicitly frames this as a named priority.
B16: 1.9 | C16: National innovation/extension programs with digital component | D16: C4 | E16: Anchored capability rubric | F16: N/A | H16: 2 | J16: =IF(I16="","",IF(Indicators!$H$14<>"Quantitative threshold","",IF(Indicators!$I$14="Higher",IF(N(I16)>=Indicators!$O$14,5,IF(N(I16)>=Indicators!$N$14,4,IF(N(I16)>=Indicators!$M$14,3,IF(N(I16)>=Indicators!$L$14,2,1)))),IF(N(I16)<=Indicators!$O$14,5,IF(N(I16)<=Indicators!$N$14,4,IF(N(I16)<=Indicators!$M$14,3,IF(N(I16)<=Indicators!$L$14,2,1))))))) | K16: 4 | L16: =IF(Indicators!$D$14="C0","",IF(K16<>"",K16,IF(J16<>"",J16,""))) -> 4 | M16: Medium | N16: 2025 | O16: =IF(N16="","",IF(N16<($L$5-H16),"STALE","")) | P16: MALR/MCIT program review; FAO; GIZ | Q16: https://www.sis.gov.eg/Story/193871/Digital-transformation-in-agro-sector-reviewed?lang=en-us | R16: Multiple active digital-extension programs exist (Hudhud AI pest ID, El Mufeed advisory app, Morshed Zaki AI chatbot pilot with GIZ, crop-mapping/satellite project) reviewed at ministerial level in Sept 2025, indicating an established but still-maturing digital extension ecosystem — assessed at level 4 (established, multiple programs, government-led coordination) rather than 5 (fully integrated/scaled).
B17: 2.1 | C17: Rural population covered by at least 3G (%) | D17: C1 | E17: Quantitative threshold | F17: Higher | G17: YES | H17: 3 | I17: 99.8 | J17: =IF(I17="","",IF(Indicators!$H$15<>"Quantitative threshold","",IF(Indicators!$I$15="Higher",IF(N(I17)>=Indicators!$O$15,5,IF(N(I17)>=Indicators!$N$15,4,IF(N(I17)>=Indicators!$M$15,3,IF(N(I17)>=Indicators!$L$15,2,1)))),IF(N(I17)<=Indicators!$O$15,5,IF(N(I17)<=Indicators!$N$15,4,IF(N(I17)<=Indicators!$M$15,3,IF(N(I17)<=Indicators!$L$15,2,1))))))) -> 5 | L17: =IF(Indicators!$D$15="C0","",IF(K17<>"",K17,IF(J17<>"",J17,""))) -> 5 | M17: High | N17: 2024 | O17: =IF(N17="","",IF(N17<($L$5-H17),"STALE","")) | P17: ITU DataHub / ITU IDI Dataset | Q17: https://datahub.itu.int/docs/IDIDataset.xlsx | R17: CORE GATE. ITU DataHub IDI dataset population-covered-by-3G figure for Egypt is near-universal (~99.8%), consistent with ITU DDD Egypt profile showing 100% network population coverage for 3G in 2022.
B18: 2.2 | C18: Rural population covered by at least 4G (%) | D18: C1 | E18: Quantitative threshold | F18: Higher | H18: 3 | I18: 98 | J18: =IF(I18="","",IF(Indicators!$H$16<>"Quantitative threshold","",IF(Indicators!$I$16="Higher",IF(N(I18)>=Indicators!$O$16,5,IF(N(I18)>=Indicators!$N$16,4,IF(N(I18)>=Indicators!$M$16,3,IF(N(I18)>=Indicators!$L$16,2,1)))),IF(N(I18)<=Indicators!$O$16,5,IF(N(I18)<=Indicators!$N$16,4,IF(N(I18)<=Indicators!$M$16,3,IF(N(I18)<=Indicators!$L$16,2,1))))))) -> 5 | L18: =IF(Indicators!$D$16="C0","",IF(K18<>"",K18,IF(J18<>"",J18,""))) -> 5 | M18: High | N18: 2024 | O18: =IF(N18="","",IF(N18<($L$5-H18),"STALE","")) | P18: ITU DataHub / ITU IDI Dataset | Q18: https://datahub.itu.int/docs/IDIDataset.xlsx | R18: ITU IDI dataset shows ~98% population 4G coverage; ITU DDD Egypt profile (2022) reports 98% 4G network coverage nationally.
B19: 2.3 | C19: Active mobile broadband subscriptions per 100 inhabitants | D19: C1 | E19: Quantitative threshold | F19: Higher | H19: 3 | I19: 75 | J19: =IF(I19="","",IF(Indicators!$H$17<>"Quantitative threshold","",IF(Indicators!$I$17="Higher",IF(N(I19)>=Indicators!$O$17,5,IF(N(I19)>=Indicators!$N$17,4,IF(N(I19)>=Indicators!$M$17,3,IF(N(I19)>=Indicators!$L$17,2,1)))),IF(N(I19)<=Indicators!$O$17,5,IF(N(I19)<=Indicators!$N$17,4,IF(N(I19)<=Indicators!$M$17,3,IF(N(I19)<=Indicators!$L$17,2,1))))))) -> 4 | L19: =IF(Indicators!$D$17="C0","",IF(K19<>"",K19,IF(J19<>"",J19,""))) -> 4 | M19: High | N19: 2024 | O19: =IF(N19="","",IF(N19<($L$5-H19),"STALE","")) | P19: ITU DataHub / ITU IDI Dataset | Q19: https://datahub.itu.int/docs/IDIDataset.xlsx | R19: ITU IDI dataset active mobile-broadband subscriptions per 100 inhabitants for Egypt.
B20: 2.4 | C20: Individuals using the Internet (% of population) | D20: C1 | E20: Quantitative threshold | F20: Higher | H20: 3 | I20: 74.65 | J20: =IF(I20="","",IF(Indicators!$H$18<>"Quantitative threshold","",IF(Indicators!$I$18="Higher",IF(N(I20)>=Indicators!$O$18,5,IF(N(I20)>=Indicators!$N$18,4,IF(N(I20)>=Indicators!$M$18,3,IF(N(I20)>=Indicators!$L$18,2,1)))),IF(N(I20)<=Indicators!$O$18,5,IF(N(I20)<=Indicators!$N$18,4,IF(N(I20)<=Indicators!$M$18,3,IF(N(I20)<=Indicators!$L$18,2,1))))))) -> 4 | L20: =IF(Indicators!$D$18="C0","",IF(K20<>"",K20,IF(J20<>"",J20,""))) -> 4 | M20: High | N20: 2024 | O20: =IF(N20="","",IF(N20<($L$5-H20),"STALE","")) | P20: World Bank WDI (IT.NET.USER.ZS), ITU source | Q20: https://api.worldbank.org/v2/country/EGY/indicator/IT.NET.USER.ZS?format=json | R20: WDI figure (ITU-sourced) for internet users. Note DataReportal's Digital 2025 Egypt report gives a higher figure (81.9%, Jan 2025) using a different survey methodology — both cited for context.
B21: 2.5 | C21: Mobile broadband basket price (% GNI per capita) | D21: C1 | E21: Quantitative threshold | F21: Lower | G21: YES | H21: 3 | I21: 1.2 | J21: =IF(I21="","",IF(Indicators!$H$19<>"Quantitative threshold","",IF(Indicators!$I$19="Higher",IF(N(I21)>=Indicators!$O$19,5,IF(N(I21)>=Indicators!$N$19,4,IF(N(I21)>=Indicators!$M$19,3,IF(N(I21)>=Indicators!$L$19,2,1)))),IF(N(I21)<=Indicators!$O$19,5,IF(N(I21)<=Indicators!$N$19,4,IF(N(I21)<=Indicators!$M$19,3,IF(N(I21)<=Indicators!$L$19,2,1))))))) -> 4 | L21: =IF(Indicators!$D$19="C0","",IF(K21<>"",K21,IF(J21<>"",J21,""))) -> 4 | M21: High | N21: 2024 | O21: =IF(N21="","",IF(N21<($L$5-H21),"STALE","")) | P21: ITU DataHub / ENCC Egypt | Q21: https://encc-eg.org/en/pressroom/press.aspx?id=514 | R21: CORE GATE. ITU IDI mobile data+voice basket price for Egypt is in the 1.1-1.4% of GNI per capita range, well under the UN Broadband Commission 2% affordability target.
B22: 2.6 | C22: Adults with mobile phone (% age 15+) | D22: C1 | E22: Quantitative threshold | F22: Higher | H22: 3 | I22: 97.13 | J22: =IF(I22="","",IF(Indicators!$H$20<>"Quantitative threshold","",IF(Indicators!$I$20="Higher",IF(N(I22)>=Indicators!$O$20,5,IF(N(I22)>=Indicators!$N$20,4,IF(N(I22)>=Indicators!$M$20,3,IF(N(I22)>=Indicators!$L$20,2,1)))),IF(N(I22)<=Indicators!$O$20,5,IF(N(I22)<=Indicators!$N$20,4,IF(N(I22)<=Indicators!$M$20,3,IF(N(I22)<=Indicators!$L$20,2,1))))))) -> 5 | L22: =IF(Indicators!$D$20="C0","",IF(K22<>"",K22,IF(J22<>"",J22,""))) -> 5 | M22: Medium | N22: 2024 | O22: =IF(N22="","",IF(N22<($L$5-H22),"STALE","")) | P22: World Bank WDI (IT.CEL.SETS.P2, mobile cellular subscriptions per 100) | Q22: https://api.worldbank.org/v2/country/EGY/indicator/IT.CEL.SETS.P2?format=json | R22: Using mobile-cellular-subscriptions-per-100 (97.1) as a proxy for adult mobile phone ownership since a direct 15+ ownership rate was not located; MCIT Q2 2024 bulletin corroborates penetration of ~101.9% (subscriptions, not unique users).
B23: 2.7 | C23: Smartphone ownership among rural/agricultural population (%) | D23: C1 | E23: Quantitative threshold | F23: Higher | H23: 2 | I23: 13.9 | J23: =IF(I23="","",IF(Indicators!$H$21<>"Quantitative threshold","",IF(Indicators!$I$21="Higher",IF(N(I23)>=Indicators!$O$21,5,IF(N(I23)>=Indicators!$N$21,4,IF(N(I23)>=Indicators!$M$21,3,IF(N(I23)>=Indicators!$L$21,2,1)))),IF(N(I23)<=Indicators!$O$21,5,IF(N(I23)<=Indicators!$N$21,4,IF(N(I23)<=Indicators!$M$21,3,IF(N(I23)<=Indicators!$L$21,2,1))))))) -> 1 | L23: =IF(Indicators!$D$21="C0","",IF(K23<>"",K23,IF(J23<>"",J23,""))) -> 1 | M23: Low | N23: 2015 | O23: =IF(N23="","",IF(N23<($L$5-H23),"STALE","")) -> STALE | P23: CAPMAS 2015 household survey (via Ahram Online) | Q23: https://english.ahram.org.eg/NewsContent/3/12/236203/-.aspx | R23: Only figure located is dated (CAPMAS 2015): 13.9% smartphone ownership in rural households vs 31.7% urban; exceeds MaxAge, likely understates 2025-26 penetration given intervening smartphone price declines — flagged Low/Estimated confidence pending an updated survey.
B24: 2.8 | C24: Average mobile data cost in rural areas (USD per GB) | D24: C1 | E24: Quantitative threshold | F24: Lower | H24: 2 | J24: =IF(I24="","",IF(Indicators!$H$22<>"Quantitative threshold","",IF(Indicators!$I$22="Higher",IF(N(I24)>=Indicators!$O$22,5,IF(N(I24)>=Indicators!$N$22,4,IF(N(I24)>=Indicators!$M$22,3,IF(N(I24)>=Indicators!$L$22,2,1)))),IF(N(I24)<=Indicators!$O$22,5,IF(N(I24)<=Indicators!$N$22,4,IF(N(I24)<=Indicators!$M$22,3,IF(N(I24)<=Indicators!$L$22,2,1))))))) | K24: 3 | L24: =IF(Indicators!$D$22="C0","",IF(K24<>"",K24,IF(J24<>"",J24,""))) -> 3 | M24: Low | N24: 2024 | O24: =IF(N24="","",IF(N24<($L$5-H24),"STALE","")) | P24: Proxy: ITU mobile data+voice basket (~1.1-1.4% GNI p.c. national average) | Q24: https://encc-eg.org/en/pressroom/press.aspx?id=514 | R24: No rural-specific mobile data cost breakdown was found; the national mobile data+voice basket price (1.1-1.4% of GNI per capita) is used as an affordability proxy, well within global affordability benchmarks, so assessed level 3 pending a rural-specific figure.
B25: 2.9 | C25: Electricity access in rural areas (%) | D25: C1 | E25: Quantitative threshold | F25: Higher | G25: YES | H25: 2 | I25: 100 | J25: =IF(I25="","",IF(Indicators!$H$23<>"Quantitative threshold","",IF(Indicators!$I$23="Higher",IF(N(I25)>=Indicators!$O$23,5,IF(N(I25)>=Indicators!$N$23,4,IF(N(I25)>=Indicators!$M$23,3,IF(N(I25)>=Indicators!$L$23,2,1)))),IF(N(I25)<=Indicators!$O$23,5,IF(N(I25)<=Indicators!$N$23,4,IF(N(I25)<=Indicators!$M$23,3,IF(N(I25)<=Indicators!$L$23,2,1))))))) -> 5 | L25: =IF(Indicators!$D$23="C0","",IF(K25<>"",K25,IF(J25<>"",J25,""))) -> 5 | M25: High | N25: 2024 | O25: =IF(N25="","",IF(N25<($L$5-H25),"STALE","")) | P25: World Bank WDI (EG.ELC.ACCS.RU.ZS) | Q25: https://api.worldbank.org/v2/country/EGY/indicator/EG.ELC.ACCS.RU.ZS?format=json | R25: CORE GATE. Egypt has achieved universal (100%) rural electricity access per WDI.
B26: 2.10 | C26: Average download speed in agricultural areas (Mbps) | D26: C1 | E26: Quantitative threshold | F26: Higher | H26: 2 | I26: 24.17 | J26: =IF(I26="","",IF(Indicators!$H$24<>"Quantitative threshold","",IF(Indicators!$I$24="Higher",IF(N(I26)>=Indicators!$O$24,5,IF(N(I26)>=Indicators!$N$24,4,IF(N(I26)>=Indicators!$M$24,3,IF(N(I26)>=Indicators!$L$24,2,1)))),IF(N(I26)<=Indicators!$O$24,5,IF(N(I26)<=Indicators!$N$24,4,IF(N(I26)<=Indicators!$M$24,3,IF(N(I26)<=Indicators!$L$24,2,1))))))) -> 4 | L26: =IF(Indicators!$D$24="C0","",IF(K26<>"",K26,IF(J26<>"",J26,""))) -> 4 | M26: Low | N26: 2025 | O26: =IF(N26="","",IF(N26<($L$5-H26),"STALE","")) | P26: Ookla via DataReportal Digital 2025 Egypt (national median, proxy) | Q26: https://datareportal.com/reports/digital-2025-egypt | R26: No agriculture-area-specific broadband speed data was found; using the national median mobile download speed (24.17 Mbps, up from 22.11 Mbps in 2024) as a proxy since rural/agricultural-zone-specific measurement is unavailable.
B27: 2.11 | C27: Device financing/subsidy schemes for farmers | D27: C1 | E27: Anchored capability rubric | F27: N/A | H27: 2 | J27: =IF(I27="","",IF(Indicators!$H$25<>"Quantitative threshold","",IF(Indicators!$I$25="Higher",IF(N(I27)>=Indicators!$O$25,5,IF(N(I27)>=Indicators!$N$25,4,IF(N(I27)>=Indicators!$M$25,3,IF(N(I27)>=Indicators!$L$25,2,1)))),IF(N(I27)<=Indicators!$O$25,5,IF(N(I27)<=Indicators!$N$25,4,IF(N(I27)<=Indicators!$M$25,3,IF(N(I27)<=Indicators!$L$25,2,1))))))) | K27: 2 | L27: =IF(Indicators!$D$25="C0","",IF(K27<>"",K27,IF(J27<>"",J27,""))) -> 2 | M27: Low | N27: 2025 | O27: =IF(N27="","",IF(N27<($L$5-H27),"STALE","")) | P27: Sector review (no dedicated scheme identified) | R27: No dedicated national device-financing/subsidy scheme specifically for farmers was identified; general consumer device financing exists in the broader Egyptian market but not targeted at farmers — assessed at a low maturity level (2) as an emerging/ad hoc capability.
B28: 3.1 | C28: UN E-Government Development Index (EGDI) | D28: C2 | E28: Quantitative threshold | F28: Higher | H28: 3 | I28: 0.6699 | J28: =IF(I28="","",IF(Indicators!$H$26<>"Quantitative threshold","",IF(Indicators!$I$26="Higher",IF(N(I28)>=Indicators!$O$26,5,IF(N(I28)>=Indicators!$N$26,4,IF(N(I28)>=Indicators!$M$26,3,IF(N(I28)>=Indicators!$L$26,2,1)))),IF(N(I28)<=Indicators!$O$26,5,IF(N(I28)<=Indicators!$N$26,4,IF(N(I28)<=Indicators!$M$26,3,IF(N(I28)<=Indicators!$L$26,2,1))))))) -> 4 | L28: =IF(Indicators!$D$26="C0","",IF(K28<>"",K28,IF(J28<>"",J28,""))) -> 4 | M28: High | N28: 2024 | O28: =IF(N28="","",IF(N28<($L$5-H28),"STALE","")) | P28: UN E-Government Survey 2024 | Q28: https://desapublications.un.org/sites/default/files/publications/2024-10/Chapter%203%20%20E-Government%20Survey%202024.pdf | R28: Egypt EGDI rose to 0.6699 (rank 95/193, rating H3) in the 2024 UN E-Government Survey, up from 0.5895 (rank 103) in 2022.
B29: 3.2 | C29: Open Data Inventory (ODIN) score | D29: C2 | E29: Quantitative threshold | F29: Higher | H29: 3 | J29: =IF(I29="","",IF(Indicators!$H$27<>"Quantitative threshold","",IF(Indicators!$I$27="Higher",IF(N(I29)>=Indicators!$O$27,5,IF(N(I29)>=Indicators!$N$27,4,IF(N(I29)>=Indicators!$M$27,3,IF(N(I29)>=Indicators!$L$27,2,1)))),IF(N(I29)<=Indicators!$O$27,5,IF(N(I29)<=Indicators!$N$27,4,IF(N(I29)<=Indicators!$M$27,3,IF(N(I29)<=Indicators!$L$27,2,1))))))) | K29: 2 | L29: =IF(Indicators!$D$27="C0","",IF(K29<>"",K29,IF(J29<>"",J29,""))) -> 2 | M29: Low | N29: 2022 | O29: =IF(N29="","",IF(N29<($L$5-H29),"STALE","")) | P29: Open Data Watch ODIN (score not numerically confirmed; qualitative placement only) | Q29: https://odin.opendatawatch.com/ | R29: Direct retrieval of Egypt's numeric ODIN score/rank from Open Data Watch's country-profile and rankings pages did not return extractable data in this session. Egypt does not have a strong open-data reputation in adjacent benchmarks (no dedicated national ag open-data portal per indicator 3.5; general EGDI Online Service Index of 0.70 suggests moderate but incomplete e-government data openness) — assessed a cautious level 2 pending direct confirmation of the official ODIN score.
B30: 3.3 | C30: National farmer registry/database | D30: C2 | E30: Anchored capability rubric | F30: N/A | G30: YES | H30: 2 | J30: =IF(I30="","",IF(Indicators!$H$28<>"Quantitative threshold","",IF(Indicators!$I$28="Higher",IF(N(I30)>=Indicators!$O$28,5,IF(N(I30)>=Indicators!$N$28,4,IF(N(I30)>=Indicators!$M$28,3,IF(N(I30)>=Indicators!$L$28,2,1)))),IF(N(I30)<=Indicators!$O$28,5,IF(N(I30)<=Indicators!$N$28,4,IF(N(I30)<=Indicators!$M$28,3,IF(N(I30)<=Indicators!$L$28,2,1))))))) | K30: 4 | L30: =IF(Indicators!$D$28="C0","",IF(K30<>"",K30,IF(J30<>"",J30,""))) -> 4 | M30: Medium | N30: 2025 | O30: =IF(N30="","",IF(N30<($L$5-H30),"STALE","")) | P30: MALR Farmer Card / Meeza Farmer Card system | Q30: https://oxfordbusinessgroup.com/reports/egypt/2022-report/economy/tools-of-the-trade-digitalisation-is-key-to-efforts-to-bolster-food-and-water-security | R30: CORE GATE. Egypt operates a national 'Farmer Card' smart-card registry (since 2016) recording landholding, quota, and subsidy data, digitally linked since 2020 to the Meeza payment system and Agricultural Bank of Egypt for subsidized lending — an operating, integrated registry, assessed level 4 (established and linked to financial services) short of level 5 (fully interoperable across all ag programs).
B31: 3.4 | C31: Digital land/plot registration system | D31: C2 | E31: Anchored capability rubric | F31: N/A | H31: 2 | J31: =IF(I31="","",IF(Indicators!$H$29<>"Quantitative threshold","",IF(Indicators!$I$29="Higher",IF(N(I31)>=Indicators!$O$29,5,IF(N(I31)>=Indicators!$N$29,4,IF(N(I31)>=Indicators!$M$29,3,IF(N(I31)>=Indicators!$L$29,2,1)))),IF(N(I31)<=Indicators!$O$29,5,IF(N(I31)<=Indicators!$N$29,4,IF(N(I31)<=Indicators!$M$29,3,IF(N(I31)<=Indicators!$L$29,2,1))))))) | K31: 3 | L31: =IF(Indicators!$D$29="C0","",IF(K31<>"",K31,IF(J31<>"",J31,""))) -> 3 | M31: Medium | N31: 2026 | O31: =IF(N31="","",IF(N31<($L$5-H31),"STALE","")) | P31: Ministry of Justice / ESA cadastre modernization; Ahram Online | Q31: https://english.ahram.org.eg/News/560931.aspx | R31: Egypt has a long-running but incomplete land registration digitization effort (Nationwide Title Cadastre System since ~2005); a new digital platform for informal land legalization (Law 168/2025) launched May 2026 (nplr.estrdad.gov.eg), indicating continued modernization but not yet comprehensive national coverage — assessed level 3 (partial/piloting).
B32: 3.5 | C32: National agricultural data portal / open data | D32: C2 | E32: Anchored capability rubric | F32: N/A | H32: 2 | J32: =IF(I32="","",IF(Indicators!$H$30<>"Quantitative threshold","",IF(Indicators!$I$30="Higher",IF(N(I32)>=Indicators!$O$30,5,IF(N(I32)>=Indicators!$N$30,4,IF(N(I32)>=Indicators!$M$30,3,IF(N(I32)>=Indicators!$L$30,2,1)))),IF(N(I32)<=Indicators!$O$30,5,IF(N(I32)<=Indicators!$N$30,4,IF(N(I32)<=Indicators!$M$30,3,IF(N(I32)<=Indicators!$L$30,2,1))))))) | K32: 2 | L32: =IF(Indicators!$D$30="C0","",IF(K32<>"",K32,IF(J32<>"",J32,""))) -> 2 | M32: Low | N32: 2025 | O32: =IF(N32="","",IF(N32<($L$5-H32),"STALE","")) | P32: Sector review | R32: No single comprehensive national agricultural open-data portal was identified; MALR/MCIT projects (Digital Egypt integration, crop-mapping) suggest data exists internally but is not clearly published as an open portal — assessed level 2 (early-stage/fragmented).
B33: 3.6 | C33: Weather/climate data infrastructure for agriculture | D33: C2 | E33: Anchored capability rubric | F33: N/A | H33: 2 | J33: =IF(I33="","",IF(Indicators!$H$31<>"Quantitative threshold","",IF(Indicators!$I$31="Higher",IF(N(I33)>=Indicators!$O$31,5,IF(N(I33)>=Indicators!$N$31,4,IF(N(I33)>=Indicators!$M$31,3,IF(N(I33)>=Indicators!$L$31,2,1)))),IF(N(I33)<=Indicators!$O$31,5,IF(N(I33)<=Indicators!$N$31,4,IF(N(I33)<=Indicators!$M$31,3,IF(N(I33)<=Indicators!$L$31,2,1))))))) | K33: 3 | L33: =IF(Indicators!$D$31="C0","",IF(K33<>"",K33,IF(J33<>"",J33,""))) -> 3 | M33: Medium | N33: 2025 | O33: =IF(N33="","",IF(N33<($L$5-H33),"STALE","")) | P33: DAIRS climate early-warning system (per CGIAR/ICARDA review) | Q33: https://cgspace.cgiar.org/server/api/core/bitstreams/d4a33acc-564a-4e4c-a413-81ba3ebd4d90/content | R33: Government-led DAIRS climate early-warning system is under development/limited rollout per ICARDA 2025 review; functioning but not yet at full national scale — assessed level 3.
B34: 3.7 | C34: Satellite/earth observation data integration capability | D34: C2 | E34: Anchored capability rubric | F34: N/A | H34: 2 | J34: =IF(I34="","",IF(Indicators!$H$32<>"Quantitative threshold","",IF(Indicators!$I$32="Higher",IF(N(I34)>=Indicators!$O$32,5,IF(N(I34)>=Indicators!$N$32,4,IF(N(I34)>=Indicators!$M$32,3,IF(N(I34)>=Indicators!$L$32,2,1)))),IF(N(I34)<=Indicators!$O$32,5,IF(N(I34)<=Indicators!$N$32,4,IF(N(I34)<=Indicators!$M$32,3,IF(N(I34)<=Indicators!$L$32,2,1))))))) | K34: 4 | L34: =IF(Indicators!$D$32="C0","",IF(K34<>"",K34,IF(J34<>"",J34,""))) -> 4 | M34: Medium | N34: 2025 | O34: =IF(N34="","",IF(N34<($L$5-H34),"STALE","")) | P34: SIS.gov.eg MALR/MCIT crop-mapping project review | Q34: https://www.sis.gov.eg/Story/193871/Digital-transformation-in-agro-sector-reviewed?lang=en-us | R34: Egypt has an active MALR-MCIT project using AI and satellite imagery to map agricultural land, forecast crop yields, and monitor pests (reviewed September 2025) — an operating capability, assessed level 4.
B35: 3.8 | C35: National soil map/database (digital) | D35: C2 | E35: Anchored capability rubric | F35: N/A | H35: 2 | J35: =IF(I35="","",IF(Indicators!$H$33<>"Quantitative threshold","",IF(Indicators!$I$33="Higher",IF(N(I35)>=Indicators!$O$33,5,IF(N(I35)>=Indicators!$N$33,4,IF(N(I35)>=Indicators!$M$33,3,IF(N(I35)>=Indicators!$L$33,2,1)))),IF(N(I35)<=Indicators!$O$33,5,IF(N(I35)<=Indicators!$N$33,4,IF(N(I35)<=Indicators!$M$33,3,IF(N(I35)<=Indicators!$L$33,2,1))))))) | K35: 2 | L35: =IF(Indicators!$D$33="C0","",IF(K35<>"",K35,IF(J35<>"",J35,""))) -> 2 | M35: Low | N35: 2025 | O35: =IF(N35="","",IF(N35<($L$5-H35),"STALE","")) | P35: Sector review | R35: No verified evidence of a comprehensive, publicly accessible digital national soil map/database for Egypt was located in this search; historical soil surveys exist but digitization status is unclear — assessed level 2 pending further evidence.
B36: 3.9 | C36: Digital advisory platforms reaching >10,000 users | D36: C2 | E36: Quantitative threshold | F36: Higher | H36: 2 | I36: 100,000+ users (Mahsoly, AlMorshed Poultry); 10,000+ (several other advisory platforms) | J36: =IF(I36="","",IF(Indicators!$H$34<>"Quantitative threshold","",IF(Indicators!$I$34="Higher",IF(N(I36)>=Indicators!$O$34,5,IF(N(I36)>=Indicators!$N$34,4,IF(N(I36)>=Indicators!$M$34,3,IF(N(I36)>=Indicators!$L$34,2,1)))),IF(N(I36)<=Indicators!$O$34,5,IF(N(I36)<=Indicators!$N$34,4,IF(N(I36)<=Indicators!$M$34,3,IF(N(I36)<=Indicators!$L$34,2,1))))))) -> 1 | K36: 4 | L36: =IF(Indicators!$D$34="C0","",IF(K36<>"",K36,IF(J36<>"",J36,""))) -> 4 | M36: Medium | N36: 2025 | O36: =IF(N36="","",IF(N36<($L$5-H36),"STALE","")) | P36: CGIAR/ICARDA digital agriculture review | Q36: https://cgspace.cgiar.org/server/api/core/bitstreams/9f8108a1-d7e7-54a1-8527-3111f8e4bfc0/content | R36: ICARDA 2025 review reports Mahsoly and AlMorshed Poultry each reaching 100,000+ users, with several other advisory platforms (El-Mufeed, Mazra3ty, Fila7a) reaching 10,000+ — clear threshold pass, assessed level 4.
B37: 3.10 | C37: Digital agricultural market/e-commerce platforms (>5,000 active users) | D37: C2 | E37: Anchored capability rubric | F37: N/A | H37: 2 | J37: =IF(I37="","",IF(Indicators!$H$35<>"Quantitative threshold","",IF(Indicators!$I$35="Higher",IF(N(I37)>=Indicators!$O$35,5,IF(N(I37)>=Indicators!$N$35,4,IF(N(I37)>=Indicators!$M$35,3,IF(N(I37)>=Indicators!$L$35,2,1)))),IF(N(I37)<=Indicators!$O$35,5,IF(N(I37)<=Indicators!$N$35,4,IF(N(I37)<=Indicators!$M$35,3,IF(N(I37)<=Indicators!$L$35,2,1))))))) | K37: 3 | L37: =IF(Indicators!$D$35="C0","",IF(K37<>"",K37,IF(J37<>"",J37,""))) -> 3 | M37: Medium | N37: 2025 | O37: =IF(N37="","",IF(N37<($L$5-H37),"STALE","")) | P37: Sector review (Mozare3, AgriCash, Mahsoly) | Q37: https://medium.com/@abdelrhmansoliman96/egypts-foodtech-market-map-2024-a-comprehensive-analysis-of-the-digital-food-ecosystem-cbcd6d81814f | R37: Mozare3 reports financing ~6,300 smallholder farmers (below the 5,000-active-user threshold but close), and platforms like Mahsoly report 100,000+ users for price-monitoring rather than transactional e-commerce; assessed level 3 (emerging, multiple platforms, uneven scale).
B38: 3.11 | C38: Interoperability standards for agricultural data | D38: C2 | E38: Anchored capability rubric | F38: N/A | G38: YES | H38: 2 | J38: =IF(I38="","",IF(Indicators!$H$36<>"Quantitative threshold","",IF(Indicators!$I$36="Higher",IF(N(I38)>=Indicators!$O$36,5,IF(N(I38)>=Indicators!$N$36,4,IF(N(I38)>=Indicators!$M$36,3,IF(N(I38)>=Indicators!$L$36,2,1)))),IF(N(I38)<=Indicators!$O$36,5,IF(N(I38)<=Indicators!$N$36,4,IF(N(I38)<=Indicators!$M$36,3,IF(N(I38)<=Indicators!$L$36,2,1))))))) | K38: 2 | L38: =IF(Indicators!$D$36="C0","",IF(K38<>"",K38,IF(J38<>"",J38,""))) -> 2 | M38: Low | N38: 2025 | O38: =IF(N38="","",IF(N38<($L$5-H38),"STALE","")) | P38: Sector review | R38: No dedicated agricultural-data interoperability standard was identified; broader Digital Egypt platform integration efforts exist across MALR/MCIT/ABE systems (Farmer Card, Meeza, Digital Egypt) but no documented common data standard for agriculture specifically — CORE GATE, assessed level 2 (ad hoc, bilateral integrations only).
B39: 3.12 | C39: AI-ready agricultural datasets | D39: C2 | E39: Anchored capability rubric | F39: N/A | H39: 2 | J39: =IF(I39="","",IF(Indicators!$H$37<>"Quantitative threshold","",IF(Indicators!$I$37="Higher",IF(N(I39)>=Indicators!$O$37,5,IF(N(I39)>=Indicators!$N$37,4,IF(N(I39)>=Indicators!$M$37,3,IF(N(I39)>=Indicators!$L$37,2,1)))),IF(N(I39)<=Indicators!$O$37,5,IF(N(I39)<=Indicators!$N$37,4,IF(N(I39)<=Indicators!$M$37,3,IF(N(I39)<=Indicators!$L$37,2,1))))))) | K39: 2 | L39: =IF(Indicators!$D$37="C0","",IF(K39<>"",K39,IF(J39<>"",J39,""))) -> 2 | M39: Low | N39: 2025 | O39: =IF(N39="","",IF(N39<($L$5-H39),"STALE","")) | P39: Sector review (satellite/crop-mapping project as precursor) | Q39: https://www.sis.gov.eg/Story/193871/Digital-transformation-in-agro-sector-reviewed?lang=en-us | R39: The MALR-MCIT satellite/AI crop-mapping project implies emerging structured datasets suitable for AI use, but no evidence of a curated, published AI-ready agricultural dataset was found — assessed level 2.
B40: 3.13 | C40: Machine-readable open agricultural data (share of national ag statistics as open APIs) | D40: C2 | E40: Quantitative threshold | F40: Higher | H40: 2 | J40: =IF(I40="","",IF(Indicators!$H$38<>"Quantitative threshold","",IF(Indicators!$I$38="Higher",IF(N(I40)>=Indicators!$O$38,5,IF(N(I40)>=Indicators!$N$38,4,IF(N(I40)>=Indicators!$M$38,3,IF(N(I40)>=Indicators!$L$38,2,1)))),IF(N(I40)<=Indicators!$O$38,5,IF(N(I40)<=Indicators!$N$38,4,IF(N(I40)<=Indicators!$M$38,3,IF(N(I40)<=Indicators!$L$38,2,1))))))) | K40: 1 | L40: =IF(Indicators!$D$38="C0","",IF(K40<>"",K40,IF(J40<>"",J40,""))) -> 1 | M40: Low | N40: 2025 | O40: =IF(N40="","",IF(N40<($L$5-H40),"STALE","")) | P40: Sector review (no evidence of open agricultural-statistics APIs) | R40: New quantitative indicator (thresholds L2=20, L3=40, L4=60, L5=80). No evidence was found of Egypt publishing national agricultural statistics via open, machine-readable APIs; MALR/CAPMAS agricultural census and statistical data appear to be published in conventional report/PDF form rather than API-accessible formats — assessed level 1 (below L2 threshold; no confirmed open-API provision), consistent with the broader Open Data Inventory data gap (indicator 3.2).
B41: 4.1 | C41: Data protection/privacy law | D41: C3 | E41: Anchored capability rubric | F41: N/A | G41: YES | H41: 3 | J41: =IF(I41="","",IF(Indicators!$H$39<>"Quantitative threshold","",IF(Indicators!$I$39="Higher",IF(N(I41)>=Indicators!$O$39,5,IF(N(I41)>=Indicators!$N$39,4,IF(N(I41)>=Indicators!$M$39,3,IF(N(I41)>=Indicators!$L$39,2,1)))),IF(N(I41)<=Indicators!$O$39,5,IF(N(I41)<=Indicators!$N$39,4,IF(N(I41)<=Indicators!$M$39,3,IF(N(I41)<=Indicators!$L$39,2,1))))))) | K41: 4 | L41: =IF(Indicators!$D$39="C0","",IF(K41<>"",K41,IF(J41<>"",J41,""))) -> 4 | M41: High | N41: 2020 | O41: =IF(N41="","",IF(N41<($L$5-H41),"STALE","")) -> STALE | P41: Personal Data Protection Law No. 151/2020 | Q41: https://www.acc.com/sites/default/files/program-materials/upload/Data%20Protection%20Law%20-%20Egypt%20-%20EN%20-%20MBH.PDF | R41: CORE GATE. Egypt's PDPL (Law 151/2020) is in force, covering electronic processing of personal data with carve-outs for national security/judicial/media; comprehensive general law but implementing regulations and enforcement track record still maturing — assessed level 4.
B42: 4.2 | C42: Cybersecurity legal framework (ITU GCI) | D42: C3 | E42: Quantitative threshold | F42: Higher | G42: YES | H42: 3 | I42: 100 | J42: =IF(I42="","",IF(Indicators!$H$40<>"Quantitative threshold","",IF(Indicators!$I$40="Higher",IF(N(I42)>=Indicators!$O$40,5,IF(N(I42)>=Indicators!$N$40,4,IF(N(I42)>=Indicators!$M$40,3,IF(N(I42)>=Indicators!$L$40,2,1)))),IF(N(I42)<=Indicators!$O$40,5,IF(N(I42)<=Indicators!$N$40,4,IF(N(I42)<=Indicators!$M$40,3,IF(N(I42)<=Indicators!$L$40,2,1))))))) -> 5 | L42: =IF(Indicators!$D$40="C0","",IF(K42<>"",K42,IF(J42<>"",J42,""))) -> 5 | M42: High | N42: 2024 | O42: =IF(N42="","",IF(N42<($L$5-H42),"STALE","")) | P42: ITU Global Cybersecurity Index 2024 | Q42: https://www.itu.int/epublications/publication/global-cybersecurity-index-2024 | R42: CORE GATE. Egypt scored a perfect 100/100 in the ITU GCI 2024, Tier 1 'Role-Modelling' status, with 20/20 across all five pillars including the legal-measures pillar; up from 95.48 in the 2020 edition.
B43: 4.3 | C43: Government AI Readiness Index | D43: C3 | E43: Quantitative threshold | F43: Higher | H43: 3 | I43: 57.5 | J43: =IF(I43="","",IF(Indicators!$H$41<>"Quantitative threshold","",IF(Indicators!$I$41="Higher",IF(N(I43)>=Indicators!$O$41,5,IF(N(I43)>=Indicators!$N$41,4,IF(N(I43)>=Indicators!$M$41,3,IF(N(I43)>=Indicators!$L$41,2,1)))),IF(N(I43)<=Indicators!$O$41,5,IF(N(I43)<=Indicators!$N$41,4,IF(N(I43)<=Indicators!$M$41,3,IF(N(I43)<=Indicators!$L$41,2,1))))))) -> 3 | L43: =IF(Indicators!$D$41="C0","",IF(K43<>"",K43,IF(J43<>"",J43,""))) -> 3 | M43: High | N43: 2025 | O43: =IF(N43="","",IF(N43<($L$5-H43),"STALE","")) | P43: Oxford Insights Government AI Readiness Index 2025 | Q43: https://english.ahram.org.eg/NewsContent/3/1239/560268/Business/Tech/Egypt-tops-Africa-in-AI-readiness,-ranks-st-global.aspx | R43: Egypt scored 57.5 and ranked 51st globally (1st in Africa, 4th in MENA) in the 2025 Oxford Insights Government AI Readiness Index, up 14 places from 65th (score 55.63) in the 2024 edition.
B44: 4.4 | C44: National digital agriculture strategy | D44: C3 | E44: Anchored capability rubric | F44: N/A | H44: 2 | J44: =IF(I44="","",IF(Indicators!$H$42<>"Quantitative threshold","",IF(Indicators!$I$42="Higher",IF(N(I44)>=Indicators!$O$42,5,IF(N(I44)>=Indicators!$N$42,4,IF(N(I44)>=Indicators!$M$42,3,IF(N(I44)>=Indicators!$L$42,2,1)))),IF(N(I44)<=Indicators!$O$42,5,IF(N(I44)<=Indicators!$N$42,4,IF(N(I44)<=Indicators!$M$42,3,IF(N(I44)<=Indicators!$L$42,2,1))))))) | K44: 3 | L44: =IF(Indicators!$D$42="C0","",IF(K44<>"",K44,IF(J44<>"",J44,""))) -> 3 | M44: Medium | N44: 2020 | O44: =IF(N44="","",IF(N44<($L$5-H44),"STALE","")) -> STALE | P44: Sustainable Agricultural Development Strategy towards 2030 (SADS 2030) | Q44: https://faolex.fao.org/docs/pdf/egy141040E.pdf | R44: SADS 2030 (originally 2009, updated executive summary Dec 2020, with MALR-FAO protocol for further update) addresses digital agriculture themes within a broader agricultural strategy, but there is no evidence of a freestanding, dedicated 'digital agriculture strategy' document — assessed level 3 (embedded within broader sector strategy).
B45: 4.5 | C45: Agricultural data governance framework | D45: C3 | E45: Anchored capability rubric | F45: N/A | G45: YES | H45: 2 | J45: =IF(I45="","",IF(Indicators!$H$43<>"Quantitative threshold","",IF(Indicators!$I$43="Higher",IF(N(I45)>=Indicators!$O$43,5,IF(N(I45)>=Indicators!$N$43,4,IF(N(I45)>=Indicators!$M$43,3,IF(N(I45)>=Indicators!$L$43,2,1)))),IF(N(I45)<=Indicators!$O$43,5,IF(N(I45)<=Indicators!$N$43,4,IF(N(I45)<=Indicators!$M$43,3,IF(N(I45)<=Indicators!$L$43,2,1))))))) | K45: 2 | L45: =IF(Indicators!$D$43="C0","",IF(K45<>"",K45,IF(J45<>"",J45,""))) -> 2 | M45: Low | N45: 2025 | O45: =IF(N45="","",IF(N45<($L$5-H45),"STALE","")) | P45: Sector review | R45: CORE GATE. No dedicated agricultural data governance framework was identified beyond the general PDPL (Law 151/2020); MALR's institutional data practices are not documented in detail — assessed level 2.
B46: 4.6 | C46: National AI strategy with agriculture component | D46: C3 | E46: Anchored capability rubric | F46: N/A | H46: 2 | J46: =IF(I46="","",IF(Indicators!$H$44<>"Quantitative threshold","",IF(Indicators!$I$44="Higher",IF(N(I46)>=Indicators!$O$44,5,IF(N(I46)>=Indicators!$N$44,4,IF(N(I46)>=Indicators!$M$44,3,IF(N(I46)>=Indicators!$L$44,2,1)))),IF(N(I46)<=Indicators!$O$44,5,IF(N(I46)<=Indicators!$N$44,4,IF(N(I46)<=Indicators!$M$44,3,IF(N(I46)<=Indicators!$L$44,2,1))))))) | K46: 4 | L46: =IF(Indicators!$D$44="C0","",IF(K46<>"",K46,IF(J46<>"",J46,""))) -> 4 | M46: High | N46: 2025 | O46: =IF(N46="","",IF(N46<($L$5-H46),"STALE","")) | P46: Egypt National AI Strategy, 2nd edition (2025-2030) | Q46: https://mcit.gov.eg/Upcont/Documents/Publications_572021000_Egypt_Nation_%20Artificial_Intelligence_Strategy_05072021.pdf | R46: Egypt's National AI Strategy (1st edition 2021, 2nd edition 2025-2030) explicitly names agriculture as a Phase 1 priority sector, overseen by the National Council for AI (established 2019, chaired by the MCIT Minister) — assessed level 4 (explicit sectoral priority with institutional backing, not yet fully implemented/measured).
B47: 4.7 | C47: Digital ID system coverage (% of population) | D47: C3 | E47: Quantitative threshold | F47: Higher | H47: 2 | I47: 97.2 | J47: =IF(I47="","",IF(Indicators!$H$45<>"Quantitative threshold","",IF(Indicators!$I$45="Higher",IF(N(I47)>=Indicators!$O$45,5,IF(N(I47)>=Indicators!$N$45,4,IF(N(I47)>=Indicators!$M$45,3,IF(N(I47)>=Indicators!$L$45,2,1)))),IF(N(I47)<=Indicators!$O$45,5,IF(N(I47)<=Indicators!$N$45,4,IF(N(I47)<=Indicators!$M$45,3,IF(N(I47)<=Indicators!$L$45,2,1))))))) -> 5 | L47: =IF(Indicators!$D$45="C0","",IF(K47<>"",K47,IF(J47<>"",J47,""))) -> 5 | M47: High | N47: 2021 | O47: =IF(N47="","",IF(N47<($L$5-H47),"STALE","")) -> STALE | P47: World Bank ID4D Global Dataset | Q47: https://documents1.worldbank.org/curated/en/099705012232226786/pdf/P176341032c1ef0b20adf10abad304425ef.pdf | R47: World Bank ID4D dataset reports 97.2% adult (16+) ownership of Egypt's National ID Card (بطاقة الرقم القومي), among the highest coverage rates globally; mandatory registration law dates to 1949. Note: a 2025 Ahram Online report cites ~4 million women nationally still lacking cards.
B48: 4.8 | C48: Data sovereignty provisions for agricultural data | D48: C3 | E48: Anchored capability rubric | F48: N/A | H48: 2 | J48: =IF(I48="","",IF(Indicators!$H$46<>"Quantitative threshold","",IF(Indicators!$I$46="Higher",IF(N(I48)>=Indicators!$O$46,5,IF(N(I48)>=Indicators!$N$46,4,IF(N(I48)>=Indicators!$M$46,3,IF(N(I48)>=Indicators!$L$46,2,1)))),IF(N(I48)<=Indicators!$O$46,5,IF(N(I48)<=Indicators!$N$46,4,IF(N(I48)<=Indicators!$M$46,3,IF(N(I48)<=Indicators!$L$46,2,1))))))) | K48: 2 | L48: =IF(Indicators!$D$46="C0","",IF(K48<>"",K48,IF(J48<>"",J48,""))) -> 2 | M48: Low | N48: 2020 | O48: =IF(N48="","",IF(N48<($L$5-H48),"STALE","")) -> STALE | P48: Personal Data Protection Law 151/2020 (general, not ag-specific) | Q48: https://www.acc.com/sites/default/files/program-materials/upload/Data%20Protection%20Law%20-%20Egypt%20-%20EN%20-%20MBH.PDF | R48: PDPL 151/2020 includes general cross-border data transfer restrictions but no agriculture-specific data sovereignty provisions were identified — assessed level 2.
B49: 4.9 | C49: Inter-ministerial coordination mechanism for digital agriculture | D49: C3 | E49: Anchored capability rubric | F49: N/A | G49: YES | H49: 2 | J49: =IF(I49="","",IF(Indicators!$H$47<>"Quantitative threshold","",IF(Indicators!$I$47="Higher",IF(N(I49)>=Indicators!$O$47,5,IF(N(I49)>=Indicators!$N$47,4,IF(N(I49)>=Indicators!$M$47,3,IF(N(I49)>=Indicators!$L$47,2,1)))),IF(N(I49)<=Indicators!$O$47,5,IF(N(I49)<=Indicators!$N$47,4,IF(N(I49)<=Indicators!$M$47,3,IF(N(I49)<=Indicators!$L$47,2,1))))))) | K49: 4 | L49: =IF(Indicators!$D$47="C0","",IF(K49<>"",K49,IF(J49<>"",J49,""))) -> 4 | M49: Medium | N49: 2025 | O49: =IF(N49="","",IF(N49<($L$5-H49),"STALE","")) | P49: MALR-MCIT joint project reviews (SIS.gov.eg, Zawya) | Q49: https://www.sis.gov.eg/Story/193871/Digital-transformation-in-agro-sector-reviewed?lang=en-us | R49: CORE GATE. Regular joint MALR-MCIT reviews of digital transformation projects in the agricultural sector are documented (e.g., Sept 2025 SIS report, 2021 Zawya report) covering Farmer Card automation, Hudhud, and satellite crop-mapping — an active, recurring coordination mechanism, assessed level 4.
B50: 4.10 | C50: Competition/antitrust framework for digital agricultural markets | D50: C3 | E50: Anchored capability rubric | F50: N/A | H50: 2 | J50: =IF(I50="","",IF(Indicators!$H$48<>"Quantitative threshold","",IF(Indicators!$I$48="Higher",IF(N(I50)>=Indicators!$O$48,5,IF(N(I50)>=Indicators!$N$48,4,IF(N(I50)>=Indicators!$M$48,3,IF(N(I50)>=Indicators!$L$48,2,1)))),IF(N(I50)<=Indicators!$O$48,5,IF(N(I50)<=Indicators!$N$48,4,IF(N(I50)<=Indicators!$M$48,3,IF(N(I50)<=Indicators!$L$48,2,1))))))) | K50: 2 | L50: =IF(Indicators!$D$48="C0","",IF(K50<>"",K50,IF(J50<>"",J50,""))) -> 2 | M50: Low | N50: 2025 | O50: =IF(N50="","",IF(N50<($L$5-H50),"STALE","")) | P50: Sector review (general competition law, not ag-digital specific) | R50: Egypt has a general Competition Law/Egyptian Competition Authority, but no agriculture-digital-market-specific competition framework was identified — assessed level 2.
B51: 4.11 | C51: Public procurement rules enabling digital agriculture innovation | D51: C3 | E51: Anchored capability rubric | F51: N/A | H51: 2 | J51: =IF(I51="","",IF(Indicators!$H$49<>"Quantitative threshold","",IF(Indicators!$I$49="Higher",IF(N(I51)>=Indicators!$O$49,5,IF(N(I51)>=Indicators!$N$49,4,IF(N(I51)>=Indicators!$M$49,3,IF(N(I51)>=Indicators!$L$49,2,1)))),IF(N(I51)<=Indicators!$O$49,5,IF(N(I51)<=Indicators!$N$49,4,IF(N(I51)<=Indicators!$M$49,3,IF(N(I51)<=Indicators!$L$49,2,1))))))) | K51: 2 | L51: =IF(Indicators!$D$49="C0","",IF(K51<>"",K51,IF(J51<>"",J51,""))) -> 2 | M51: Low | N51: 2025 | O51: =IF(N51="","",IF(N51<($L$5-H51),"STALE","")) | P51: Sector review | R51: No evidence found of procurement rules specifically tailored to enable digital agriculture innovation (e.g., innovation partnerships, agile procurement for agtech); general public procurement law applies — assessed level 2.
B52: 4.12 | C52: Spectrum allocation for rural/agricultural IoT | D52: C3 | E52: Anchored capability rubric | F52: N/A | H52: 2 | J52: =IF(I52="","",IF(Indicators!$H$50<>"Quantitative threshold","",IF(Indicators!$I$50="Higher",IF(N(I52)>=Indicators!$O$50,5,IF(N(I52)>=Indicators!$N$50,4,IF(N(I52)>=Indicators!$M$50,3,IF(N(I52)>=Indicators!$L$50,2,1)))),IF(N(I52)<=Indicators!$O$50,5,IF(N(I52)<=Indicators!$N$50,4,IF(N(I52)<=Indicators!$M$50,3,IF(N(I52)<=Indicators!$L$50,2,1))))))) | K52: 2 | L52: =IF(Indicators!$D$50="C0","",IF(K52<>"",K52,IF(J52<>"",J52,""))) -> 2 | M52: Low | N52: 2025 | O52: =IF(N52="","",IF(N52<($L$5-H52),"STALE","")) | P52: Sector review (NTRA general spectrum policy) | Q52: https://www.tra.gov.eg/en/ | R52: No evidence of spectrum specifically allocated for rural/agricultural IoT use cases; Egypt's telecom regulator (NTRA) manages general spectrum allocation but ag-IoT-specific bands were not identified — assessed level 2.
B53: 4.13 | C53: Responsible AI principles/guidelines for agriculture | D53: C3 | E53: Anchored capability rubric | F53: N/A | H53: 2 | J53: =IF(I53="","",IF(Indicators!$H$51<>"Quantitative threshold","",IF(Indicators!$I$51="Higher",IF(N(I53)>=Indicators!$O$51,5,IF(N(I53)>=Indicators!$N$51,4,IF(N(I53)>=Indicators!$M$51,3,IF(N(I53)>=Indicators!$L$51,2,1)))),IF(N(I53)<=Indicators!$O$51,5,IF(N(I53)<=Indicators!$N$51,4,IF(N(I53)<=Indicators!$M$51,3,IF(N(I53)<=Indicators!$L$51,2,1))))))) | K53: 3 | L53: =IF(Indicators!$D$51="C0","",IF(K53<>"",K53,IF(J53<>"",J53,""))) -> 3 | M53: Medium | N53: 2025 | O53: =IF(N53="","",IF(N53<($L$5-H53),"STALE","")) | P53: Egypt National AI Strategy (2nd edition) - general responsible AI provisions | Q53: https://v45.diplomacy.edu/resource/egypts-national-ai-strategy-second-edition-2025-2030 | R53: Egypt's National AI Strategy 2nd edition includes general responsible-AI/governance provisions but no agriculture-sector-specific responsible AI guidelines were identified — assessed level 3 (general framework exists, not sector-tailored).
B54: 5.1 | C54: Mean years of schooling (adults 25+) | D54: C4 | E54: Quantitative threshold | F54: Higher | H54: 3 | I54: 7.5 | J54: =IF(I54="","",IF(Indicators!$H$52<>"Quantitative threshold","",IF(Indicators!$I$52="Higher",IF(N(I54)>=Indicators!$O$52,5,IF(N(I54)>=Indicators!$N$52,4,IF(N(I54)>=Indicators!$M$52,3,IF(N(I54)>=Indicators!$L$52,2,1)))),IF(N(I54)<=Indicators!$O$52,5,IF(N(I54)<=Indicators!$N$52,4,IF(N(I54)<=Indicators!$M$52,3,IF(N(I54)<=Indicators!$L$52,2,1))))))) -> 3 | L54: =IF(Indicators!$D$52="C0","",IF(K54<>"",K54,IF(J54<>"",J54,""))) -> 3 | M54: Medium | N54: 2023 | O54: =IF(N54="","",IF(N54<($L$5-H54),"STALE","")) | P54: UNDP Human Development Report 2025 (Egypt country insights) | Q54: https://hdr.undp.org/data-center/country-insights | R54: Estimate drawn from UNDP HDR country insights components underlying Egypt's HDI (0.754); precise mean-years-of-schooling figure should be verified directly against the HDR statistical annex if higher precision is required.
B55: 5.2 | C55: Adult literacy rate (% age 15+) | D55: C4 | E55: Quantitative threshold | F55: Higher | H55: 3 | I55: 79.45 | J55: =IF(I55="","",IF(Indicators!$H$53<>"Quantitative threshold","",IF(Indicators!$I$53="Higher",IF(N(I55)>=Indicators!$O$53,5,IF(N(I55)>=Indicators!$N$53,4,IF(N(I55)>=Indicators!$M$53,3,IF(N(I55)>=Indicators!$L$53,2,1)))),IF(N(I55)<=Indicators!$O$53,5,IF(N(I55)<=Indicators!$N$53,4,IF(N(I55)<=Indicators!$M$53,3,IF(N(I55)<=Indicators!$L$53,2,1))))))) -> 3 | L55: =IF(Indicators!$D$53="C0","",IF(K55<>"",K55,IF(J55<>"",J55,""))) -> 3 | M55: High | N55: 2022 | O55: =IF(N55="","",IF(N55<($L$5-H55),"STALE","")) | P55: World Bank WDI (SE.ADT.LITR.ZS) | Q55: https://api.worldbank.org/v2/country/EGY/indicator/SE.ADT.LITR.ZS?format=json | R55: Most recent WDI adult literacy rate for Egypt.
B56: 5.3 | C56: Tertiary enrollment in STEM fields (% gross) | D56: C4 | E56: Quantitative threshold | F56: Higher | H56: 3 | I56: 38.04 | J56: =IF(I56="","",IF(Indicators!$H$54<>"Quantitative threshold","",IF(Indicators!$I$54="Higher",IF(N(I56)>=Indicators!$O$54,5,IF(N(I56)>=Indicators!$N$54,4,IF(N(I56)>=Indicators!$M$54,3,IF(N(I56)>=Indicators!$L$54,2,1)))),IF(N(I56)<=Indicators!$O$54,5,IF(N(I56)<=Indicators!$N$54,4,IF(N(I56)<=Indicators!$M$54,3,IF(N(I56)<=Indicators!$L$54,2,1))))))) -> 4 | L56: =IF(Indicators!$D$54="C0","",IF(K56<>"",K56,IF(J56<>"",J56,""))) -> 4 | M56: Low | N56: 2023 | O56: =IF(N56="","",IF(N56<($L$5-H56),"STALE","")) | P56: World Bank WDI (SE.TER.ENRR, overall tertiary enrollment) | Q56: https://api.worldbank.org/v2/country/EGY/indicator/SE.TER.ENRR?format=json | R56: WDI provides overall gross tertiary enrollment (38.04%), not STEM-specific; no disaggregated STEM tertiary enrollment figure for Egypt was located, so this is a proxy — confidence downgraded to Low for the STEM-specific claim.
B57: 5.4 | C57: Digital literacy among farmers (%) | D57: C4 | E57: Quantitative threshold | F57: Higher | H57: 2 | I57: ~46-48% face awareness/literacy barriers (i.e., roughly half of farmers report low digital literacy as a key adoption barrier) | J57: =IF(I57="","",IF(Indicators!$H$55<>"Quantitative threshold","",IF(Indicators!$I$55="Higher",IF(N(I57)>=Indicators!$O$55,5,IF(N(I57)>=Indicators!$N$55,4,IF(N(I57)>=Indicators!$M$55,3,IF(N(I57)>=Indicators!$L$55,2,1)))),IF(N(I57)<=Indicators!$O$55,5,IF(N(I57)<=Indicators!$N$55,4,IF(N(I57)<=Indicators!$M$55,3,IF(N(I57)<=Indicators!$L$55,2,1))))))) -> 1 | L57: =IF(Indicators!$D$55="C0","",IF(K57<>"",K57,IF(J57<>"",J57,""))) -> 1 | M57: Medium | N57: 2024 | O57: =IF(N57="","",IF(N57<($L$5-H57),"STALE","")) | P57: CGIAR digital literacy training study (IFPRI, Minya/Beni Suef) | Q57: https://cgspace.cgiar.org/server/api/core/bitstreams/81b8d4be-61c7-470a-9b12-52a0c51d2d4c/content | R57: CGIAR/IFPRI baseline survey of Egyptian smallholders found 52% cited general digital literacy as a key adoption challenge and 54% cited lack of awareness of digital applications; a related Journal of Ecohumanism Beni Suef survey found 53.9% of farmers unfamiliar with ICT/IoT tools — consistent picture of substantial digital literacy gaps, not a single official national rate.
B58: 5.5 | C58: Extension workers trained in digital tools (%) | D58: C4 | E58: Quantitative threshold | F58: Higher | G58: YES | H58: 2 | J58: =IF(I58="","",IF(Indicators!$H$56<>"Quantitative threshold","",IF(Indicators!$I$56="Higher",IF(N(I58)>=Indicators!$O$56,5,IF(N(I58)>=Indicators!$N$56,4,IF(N(I58)>=Indicators!$M$56,3,IF(N(I58)>=Indicators!$L$56,2,1)))),IF(N(I58)<=Indicators!$O$56,5,IF(N(I58)<=Indicators!$N$56,4,IF(N(I58)<=Indicators!$M$56,3,IF(N(I58)<=Indicators!$L$56,2,1))))))) | K58: 3 | L58: =IF(Indicators!$D$56="C0","",IF(K58<>"",K58,IF(J58<>"",J58,""))) -> 3 | M58: Medium | N58: 2025 | O58: =IF(N58="","",IF(N58<($L$5-H58),"STALE","")) | P58: GFRAS Egypt country profile; GIZ Morshed Zaki pilot | Q58: https://www.g-fras.org/en/world-wide-extension-study/africa/northern-africa/egypt.html | R58: CORE GATE. Egypt has ~7,421 public extension staff nationally (GFRAS); digital-tool training is occurring through specific donor-backed pilots (e.g., GIZ's 'Morshed Zaki' AI chatbot prototype, 2025-2026) but no evidence of comprehensive, system-wide digital training coverage across all extension workers — assessed level 3 (partial/pilot-stage).
B59: 5.6 | C59: Farmer-to-digital-extension-worker ratio | D59: C4 | E59: Anchored capability rubric | F59: N/A | H59: 2 | I59: ~1 extension worker per 200 families / 500 feddans (general ratio; digital-specific ratio far higher/unquantified) | J59: =IF(I59="","",IF(Indicators!$H$57<>"Quantitative threshold","",IF(Indicators!$I$57="Higher",IF(N(I59)>=Indicators!$O$57,5,IF(N(I59)>=Indicators!$N$57,4,IF(N(I59)>=Indicators!$M$57,3,IF(N(I59)>=Indicators!$L$57,2,1)))),IF(N(I59)<=Indicators!$O$57,5,IF(N(I59)<=Indicators!$N$57,4,IF(N(I59)<=Indicators!$M$57,3,IF(N(I59)<=Indicators!$L$57,2,1))))))) | L59: =IF(Indicators!$D$57="C0","",IF(K59<>"",K59,IF(J59<>"",J59,""))) | M59: Low | N59: 2012 | O59: =IF(N59="","",IF(N59<($L$5-H59),"STALE","")) -> STALE | P59: GFRAS Egypt country profile; CIHEAM 2012 | Q59: https://www.g-fras.org/en/world-wide-extension-study/africa/northern-africa/egypt.html | R59: GFRAS/CIHEAM data show a standard extension design ratio of one worker per ~200 families or 500 feddans (200 ha), with a total national extension workforce of only ~6,604-7,421 against ~4 million agricultural holdings (2020 census) — implying a much higher effective ratio in practice (~540:1) and an even sparser ratio for workers specifically trained in digital tools, which was not separately quantified.
B60: 5.7 | C60: Dedicated digital/AI units in Ministry of Agriculture | D60: C4 | E60: Anchored capability rubric | F60: N/A | G60: YES | H60: 2 | J60: =IF(I60="","",IF(Indicators!$H$58<>"Quantitative threshold","",IF(Indicators!$I$58="Higher",IF(N(I60)>=Indicators!$O$58,5,IF(N(I60)>=Indicators!$N$58,4,IF(N(I60)>=Indicators!$M$58,3,IF(N(I60)>=Indicators!$L$58,2,1)))),IF(N(I60)<=Indicators!$O$58,5,IF(N(I60)<=Indicators!$N$58,4,IF(N(I60)<=Indicators!$M$58,3,IF(N(I60)<=Indicators!$L$58,2,1))))))) | K60: 4 | L60: =IF(Indicators!$D$58="C0","",IF(K60<>"",K60,IF(J60<>"",J60,""))) -> 4 | M60: Medium | N60: 2021 | O60: =IF(N60="","",IF(N60<($L$5-H60),"STALE","")) -> STALE | P60: Zawya 2021 / SIS.gov.eg 2025 - MALR Digital Transformation Unit | Q60: https://www.zawya.com/en/business/egyptian-government-reviews-digital-transformation-projects-in-agricultural-sector-sed7vbfx | R60: CORE GATE. MALR has an established Digital Transformation Unit (referenced in 2021 reporting, still active per Sept 2025 SIS review) coordinating joint projects with MCIT — assessed level 4 (dedicated unit with sustained, multi-year activity).
B61: 5.8 | C61: University programs in agtech/digital agriculture | D61: C4 | E61: Anchored capability rubric | F61: N/A | H61: 2 | J61: =IF(I61="","",IF(Indicators!$H$59<>"Quantitative threshold","",IF(Indicators!$I$59="Higher",IF(N(I61)>=Indicators!$O$59,5,IF(N(I61)>=Indicators!$N$59,4,IF(N(I61)>=Indicators!$M$59,3,IF(N(I61)>=Indicators!$L$59,2,1)))),IF(N(I61)<=Indicators!$O$59,5,IF(N(I61)<=Indicators!$N$59,4,IF(N(I61)<=Indicators!$M$59,3,IF(N(I61)<=Indicators!$L$59,2,1))))))) | K61: 2 | L61: =IF(Indicators!$D$59="C0","",IF(K61<>"",K61,IF(J61<>"",J61,""))) -> 2 | M61: Low | N61: 2025 | O61: =IF(N61="","",IF(N61<($L$5-H61),"STALE","")) | P61: Sector review | R61: No dedicated university degree/certificate program specifically in agtech/digital agriculture was identified for Egypt in this search; general agricultural faculties exist at Cairo University, Ain Shams, and others, but digital-agriculture-specific curricula were not confirmed — assessed level 2.
B62: 5.9 | C62: Data science/AI training programs for agriculture | D62: C4 | E62: Anchored capability rubric | F62: N/A | H62: 2 | J62: =IF(I62="","",IF(Indicators!$H$60<>"Quantitative threshold","",IF(Indicators!$I$60="Higher",IF(N(I62)>=Indicators!$O$60,5,IF(N(I62)>=Indicators!$N$60,4,IF(N(I62)>=Indicators!$M$60,3,IF(N(I62)>=Indicators!$L$60,2,1)))),IF(N(I62)<=Indicators!$O$60,5,IF(N(I62)<=Indicators!$N$60,4,IF(N(I62)<=Indicators!$M$60,3,IF(N(I62)<=Indicators!$L$60,2,1))))))) | K62: 2 | L62: =IF(Indicators!$D$60="C0","",IF(K62<>"",K62,IF(J62<>"",J62,""))) -> 2 | M62: Low | N62: 2025 | O62: =IF(N62="","",IF(N62<($L$5-H62),"STALE","")) | P62: Sector review (general AI training exists, not ag-specific) | R62: Egypt has broad national AI capacity-building efforts (National AI Strategy, ITIDA/TIEC training programs) but no agriculture-sector-specific data science/AI training program was identified — assessed level 2.
B63: 5.10 | C63: Digital skills training reach (% of farmer population per year) | D63: C4 | E63: Quantitative threshold | F63: Higher | H63: 2 | I63: ~3,332-4,000 farmers per program cycle (GIZ AIP/CGIAR pilots in Minya and Beni Suef) — a small fraction of Egypt's ~4 million agricultural holdings | J63: =IF(I63="","",IF(Indicators!$H$61<>"Quantitative threshold","",IF(Indicators!$I$61="Higher",IF(N(I63)>=Indicators!$O$61,5,IF(N(I63)>=Indicators!$N$61,4,IF(N(I63)>=Indicators!$M$61,3,IF(N(I63)>=Indicators!$L$61,2,1)))),IF(N(I63)<=Indicators!$O$61,5,IF(N(I63)<=Indicators!$N$61,4,IF(N(I63)<=Indicators!$M$61,3,IF(N(I63)<=Indicators!$L$61,2,1))))))) -> 1 | L63: =IF(Indicators!$D$61="C0","",IF(K63<>"",K63,IF(J63<>"",J63,""))) -> 1 | M63: Low | N63: 2024 | O63: =IF(N63="","",IF(N63<($L$5-H63),"STALE","")) | P63: GIZ Agricultural Innovation Project / CGIAR-IFPRI digital literacy study | Q63: https://www.linkedin.com/posts/gizegypt_utilizing-communication-for-agricultural-activity-7211322361466208256-hpFX | R63: GIZ's Agricultural Innovation Project (AIP) trained ~30 local trainers and reached a baseline sample of ~3,332-4,000 farmers across Minya and Beni Suef governorates (2023-2024); this is a donor-funded pilot reach, not a national percentage — implies well under 1% of Egypt's ~4 million agricultural holdings are reached annually through documented programs.
B64: 5.11 | C64: Institutional digital maturity of key agricultural agencies | D64: C4 | E64: Anchored capability rubric | F64: N/A | H64: 2 | J64: =IF(I64="","",IF(Indicators!$H$62<>"Quantitative threshold","",IF(Indicators!$I$62="Higher",IF(N(I64)>=Indicators!$O$62,5,IF(N(I64)>=Indicators!$N$62,4,IF(N(I64)>=Indicators!$M$62,3,IF(N(I64)>=Indicators!$L$62,2,1)))),IF(N(I64)<=Indicators!$O$62,5,IF(N(I64)<=Indicators!$N$62,4,IF(N(I64)<=Indicators!$M$62,3,IF(N(I64)<=Indicators!$L$62,2,1))))))) | K64: 3 | L64: =IF(Indicators!$D$62="C0","",IF(K64<>"",K64,IF(J64<>"",J64,""))) -> 3 | M64: Medium | N64: 2025 | O64: =IF(N64="","",IF(N64<($L$5-H64),"STALE","")) | P64: Composite assessment from MALR/MCIT project reviews | Q64: https://www.sis.gov.eg/Story/193871/Digital-transformation-in-agro-sector-reviewed?lang=en-us | R64: Based on evidence of an active Digital Transformation Unit, Farmer Card/Meeza integration, satellite crop-mapping, and recurring MALR-MCIT coordination, MALR shows moderate-to-good institutional digital maturity but not yet fully integrated/data-driven operations across all agencies — assessed level 3.
B65: 5.12 | C65: Gender balance in digital agriculture workforce | D65: C4 | E65: Quantitative threshold | F65: Higher | H65: 2 | I65: 3.9 | J65: =IF(I65="","",IF(Indicators!$H$63<>"Quantitative threshold","",IF(Indicators!$I$63="Higher",IF(N(I65)>=Indicators!$O$63,5,IF(N(I65)>=Indicators!$N$63,4,IF(N(I65)>=Indicators!$M$63,3,IF(N(I65)>=Indicators!$L$63,2,1)))),IF(N(I65)<=Indicators!$O$63,5,IF(N(I65)<=Indicators!$N$63,4,IF(N(I65)<=Indicators!$M$63,3,IF(N(I65)<=Indicators!$L$63,2,1))))))) -> 1 | L65: =IF(Indicators!$D$63="C0","",IF(K65<>"",K65,IF(J65<>"",J65,""))) -> 1 | M65: Medium | N65: 2018 | O65: =IF(N65="","",IF(N65<($L$5-H65),"STALE","")) -> STALE | P65: JICA Gender Profile Egypt 2018 / CAWTAR Gender Assessment | Q65: https://www.jica.go.jp/activities/issues/gender/reports/__icsFiles/afieldfile/2025/01/20/Egypt_English2018.pdf | R65: Female agricultural extension officers make up only ~3.9% of total extension staff per JICA (2018, citing 2011 administrative data) and CAWTAR gender assessment (<4%); used here as the best available proxy for gender balance in the (extension-heavy) digital agriculture workforce given the absence of a digital-agriculture-specific gender breakdown. Older CIHEAM 2012 data show a higher ~18.9% female share, indicating some inconsistency across sources/years.
B66: 5.13 | C66: Gender parity in extension services (% female extension officers) | D66: C4 | E66: Quantitative threshold | F66: Higher | H66: 3 | I66: 3.9 | J66: =IF(I66="","",IF(Indicators!$H$64<>"Quantitative threshold","",IF(Indicators!$I$64="Higher",IF(N(I66)>=Indicators!$O$64,5,IF(N(I66)>=Indicators!$N$64,4,IF(N(I66)>=Indicators!$M$64,3,IF(N(I66)>=Indicators!$L$64,2,1)))),IF(N(I66)<=Indicators!$O$64,5,IF(N(I66)<=Indicators!$N$64,4,IF(N(I66)<=Indicators!$M$64,3,IF(N(I66)<=Indicators!$L$64,2,1))))))) -> 1 | L66: =IF(Indicators!$D$64="C0","",IF(K66<>"",K66,IF(J66<>"",J66,""))) -> 1 | M66: Medium | N66: 2018 | O66: =IF(N66="","",IF(N66<($L$5-H66),"STALE","")) -> STALE | P66: JICA Gender Profile Egypt 2018 / CAWTAR Gender Assessment | Q66: https://www.jica.go.jp/activities/issues/gender/reports/__icsFiles/afieldfile/2025/01/20/Egypt_English2018.pdf | R66: New quantitative indicator (thresholds L2=10, L3=25, L4=40, L5=50). Female extension officers comprise only ~3.9% of Egypt's total extension workforce per JICA (2018, citing 2011 data) and CAWTAR's gender assessment (<4%), placing Egypt below even the L2 threshold (10%) — a binding gender-equity constraint. Note: older CIHEAM 2012 data show a higher 18.9% figure, and GFRAS aggregate figures are inconsistent across sources/years, but the most recent dedicated gender-assessment sources converge on ~3.9-4%.
B67: 6.1 | C67: Global Innovation Index (GII) score | D67: E1 | E67: Quantitative threshold | F67: Higher | H67: 3 | I67: 23.7 | J67: =IF(I67="","",IF(Indicators!$H$65<>"Quantitative threshold","",IF(Indicators!$I$65="Higher",IF(N(I67)>=Indicators!$O$65,5,IF(N(I67)>=Indicators!$N$65,4,IF(N(I67)>=Indicators!$M$65,3,IF(N(I67)>=Indicators!$L$65,2,1)))),IF(N(I67)<=Indicators!$O$65,5,IF(N(I67)<=Indicators!$N$65,4,IF(N(I67)<=Indicators!$M$65,3,IF(N(I67)<=Indicators!$L$65,2,1))))))) -> 1 | L67: =IF(Indicators!$D$65="C0","",IF(K67<>"",K67,IF(J67<>"",J67,""))) -> 1 | M67: High | N67: 2024 | O67: =IF(N67="","",IF(N67<($L$5-H67),"STALE","")) | P67: WIPO Global Innovation Index 2024 | Q67: https://www.wipo.int/edocs/gii-ranking/2024/eg.pdf | R67: Egypt scored 23.7 (down from 24.2 in 2023) and ranked 86th of 133 economies in the WIPO GII 2024; Innovation Inputs rank 95th, Innovation Outputs rank 80th.
B68: 6.2 | C68: R&D expenditure (% of GDP) | D68: E1 | E68: Quantitative threshold | F68: Higher | H68: 3 | I68: 1.018 | J68: =IF(I68="","",IF(Indicators!$H$66<>"Quantitative threshold","",IF(Indicators!$I$66="Higher",IF(N(I68)>=Indicators!$O$66,5,IF(N(I68)>=Indicators!$N$66,4,IF(N(I68)>=Indicators!$M$66,3,IF(N(I68)>=Indicators!$L$66,2,1)))),IF(N(I68)<=Indicators!$O$66,5,IF(N(I68)<=Indicators!$N$66,4,IF(N(I68)<=Indicators!$M$66,3,IF(N(I68)<=Indicators!$L$66,2,1))))))) -> 4 | L68: =IF(Indicators!$D$66="C0","",IF(K68<>"",K68,IF(J68<>"",J68,""))) -> 4 | M68: High | N68: 2024 | O68: =IF(N68="","",IF(N68<($L$5-H68),"STALE","")) | P68: World Bank WDI (GB.XPD.RSDV.GD.ZS) | Q68: https://api.worldbank.org/v2/country/EGY/indicator/GB.XPD.RSDV.GD.ZS?format=json | R68: Most recent WDI R&D expenditure figure for Egypt (1.02% of GDP).
B69: 6.3 | C69: Business Ready (B-READY) score | D69: E1 | E69: Quantitative threshold | F69: Higher | H69: 3 | J69: =IF(I69="","",IF(Indicators!$H$67<>"Quantitative threshold","",IF(Indicators!$I$67="Higher",IF(N(I69)>=Indicators!$O$67,5,IF(N(I69)>=Indicators!$N$67,4,IF(N(I69)>=Indicators!$M$67,3,IF(N(I69)>=Indicators!$L$67,2,1)))),IF(N(I69)<=Indicators!$O$67,5,IF(N(I69)<=Indicators!$N$67,4,IF(N(I69)<=Indicators!$M$67,3,IF(N(I69)<=Indicators!$L$67,2,1))))))) | K69: 3 | L69: =IF(Indicators!$D$67="C0","",IF(K69<>"",K69,IF(J69<>"",J69,""))) -> 3 | M69: Low | N69: 2024 | O69: =IF(N69="","",IF(N69<($L$5-H69),"STALE","")) | P69: World Bank B-READY (Egypt not in initial 50-economy cohort; regional MENA context used) | Q69: https://www.worldbank.org/en/businessready/data | R69: The World Bank's B-READY 2024 report initially covered only 50 economies, and no populated overall B-READY score specifically for Egypt could be confirmed from the World Bank Open Data pages fetched in this session; Egypt's predecessor 'Doing Business' ranking (now discontinued) placed it in the lower-middle range regionally — assessed a cautious level 3 pending direct confirmation of Egypt's inclusion and score in a later B-READY cohort/update.
B70: 6.4 | C70: Active agtech startups/firms | D70: E1 | E70: Anchored capability rubric | F70: N/A | H70: 2 | I70: Dozens (e.g., Mozare3, AgriCash, Mahsoly-adjacent ventures, plus F6S-listed cohort) | J70: =IF(I70="","",IF(Indicators!$H$68<>"Quantitative threshold","",IF(Indicators!$I$68="Higher",IF(N(I70)>=Indicators!$O$68,5,IF(N(I70)>=Indicators!$N$68,4,IF(N(I70)>=Indicators!$M$68,3,IF(N(I70)>=Indicators!$L$68,2,1)))),IF(N(I70)<=Indicators!$O$68,5,IF(N(I70)<=Indicators!$N$68,4,IF(N(I70)<=Indicators!$M$68,3,IF(N(I70)<=Indicators!$L$68,2,1))))))) | K70: 3 | L70: =IF(Indicators!$D$68="C0","",IF(K70<>"",K70,IF(J70<>"",J70,""))) -> 3 | M70: Medium | N70: 2026 | O70: =IF(N70="","",IF(N70<($L$5-H70),"STALE","")) | P70: F6S AgriTech Egypt directory; sector market maps | Q70: https://www.f6s.com/companies/agritech/egypt/co | R70: F6S lists a cohort of agtech companies in Egypt (12+ notable ones as of August 2026); combined with Mozare3, AgriCash, Mahsoly and others identified in market maps, indicates a growing but still-small ecosystem — assessed level 3.
B71: 6.5 | C71: Venture capital/investment in agtech (annual USD) | D71: E1 | E71: Anchored capability rubric | F71: N/A | H71: 2 | I71: ~$1.1M+ (Mozare3 pre-seed, 2021) plus subsequent seed rounds (AgriCash, 2025) | J71: =IF(I71="","",IF(Indicators!$H$69<>"Quantitative threshold","",IF(Indicators!$I$69="Higher",IF(N(I71)>=Indicators!$O$69,5,IF(N(I71)>=Indicators!$N$69,4,IF(N(I71)>=Indicators!$M$69,3,IF(N(I71)>=Indicators!$L$69,2,1)))),IF(N(I71)<=Indicators!$O$69,5,IF(N(I71)<=Indicators!$N$69,4,IF(N(I71)<=Indicators!$M$69,3,IF(N(I71)<=Indicators!$L$69,2,1))))))) | L71: =IF(Indicators!$D$69="C0","",IF(K71<>"",K71,IF(J71<>"",J71,""))) | M71: Low | N71: 2025 | O71: =IF(N71="","",IF(N71<($L$5-H71),"STALE","")) | P71: EgyptInnovate; Business Monthly Egypt | Q71: https://egyptinnovate.com/en/%D8%A3%D8%AE%D8%A8%D8%A7%D8%B1/agricash-secures-seed-funding-scale-ai-driven-agri-fintech-platform-egypt-and-beyond | R71: No aggregated annual agtech VC investment total for Egypt was found; only individual deal data points are available (Mozare3 ~$1.1M pre-seed 2021 plus later Series A; AgriCash seed round 2025, amount undisclosed) — treated as illustrative rather than a comprehensive annual total.
B72: 6.6 | C72: Agtech accelerators/incubators | D72: E1 | E72: Anchored capability rubric | F72: N/A | H72: 2 | J72: =IF(I72="","",IF(Indicators!$H$70<>"Quantitative threshold","",IF(Indicators!$I$70="Higher",IF(N(I72)>=Indicators!$O$70,5,IF(N(I72)>=Indicators!$N$70,4,IF(N(I72)>=Indicators!$M$70,3,IF(N(I72)>=Indicators!$L$70,2,1)))),IF(N(I72)<=Indicators!$O$70,5,IF(N(I72)<=Indicators!$N$70,4,IF(N(I72)<=Indicators!$M$70,3,IF(N(I72)<=Indicators!$L$70,2,1))))))) | K72: 4 | L72: =IF(Indicators!$D$70="C0","",IF(K72<>"",K72,IF(J72<>"",J72,""))) -> 4 | M72: High | N72: 2025 | O72: =IF(N72="","",IF(N72<($L$5-H72),"STALE","")) | P72: Flat6Labs (Ebtekar, Themar programs); AUC Venture Lab; Nilepreneurs | Q72: https://flat6labs.com/programs-type/programs-for-entrepreneurs/ | R72: Egypt has multiple active, named agtech-focused accelerator programs: Flat6Labs' 'Ebtekar Agri Digital Acceleration Program' (with GIZ) and 'Themar AgriTech Acceleration Program' (with SANAD), plus AUC Venture Lab and Nilepreneurs Innovation Hubs supporting agritech — assessed level 4 (multiple established programs).
B73: 6.7 | C73: Agribusiness firms using AI/ML in operations (%) | D73: E1 | E73: Quantitative threshold | F73: Higher | H73: 2 | J73: =IF(I73="","",IF(Indicators!$H$71<>"Quantitative threshold","",IF(Indicators!$I$71="Higher",IF(N(I73)>=Indicators!$O$71,5,IF(N(I73)>=Indicators!$N$71,4,IF(N(I73)>=Indicators!$M$71,3,IF(N(I73)>=Indicators!$L$71,2,1)))),IF(N(I73)<=Indicators!$O$71,5,IF(N(I73)<=Indicators!$N$71,4,IF(N(I73)<=Indicators!$M$71,3,IF(N(I73)<=Indicators!$L$71,2,1))))))) | K73: 2 | L73: =IF(Indicators!$D$71="C0","",IF(K73<>"",K73,IF(J73<>"",J73,""))) -> 2 | M73: Low | N73: 2025 | O73: =IF(N73="","",IF(N73<($L$5-H73),"STALE","")) | P73: Sector review (qualitative; no survey-based percentage located) | R73: No survey-based percentage of Egyptian agribusiness firms using AI/ML was located; qualitative evidence (AgriCash's AI-driven agri-fintech, Hudhud's AI pest ID) shows early adopters exist but this is not representative of the wider agribusiness sector — assessed level 2 (early/niche adoption).
B74: 6.8 | C74: Regulatory sandboxes for agtech/fintech | D74: E1 | E74: Anchored capability rubric | F74: N/A | H74: 2 | J74: =IF(I74="","",IF(Indicators!$H$72<>"Quantitative threshold","",IF(Indicators!$I$72="Higher",IF(N(I74)>=Indicators!$O$72,5,IF(N(I74)>=Indicators!$N$72,4,IF(N(I74)>=Indicators!$M$72,3,IF(N(I74)>=Indicators!$L$72,2,1)))),IF(N(I74)<=Indicators!$O$72,5,IF(N(I74)<=Indicators!$N$72,4,IF(N(I74)<=Indicators!$M$72,3,IF(N(I74)<=Indicators!$L$72,2,1))))))) | K74: 3 | L74: =IF(Indicators!$D$72="C0","",IF(K74<>"",K74,IF(J74<>"",J74,""))) -> 3 | M74: Medium | N74: 2023 | O74: =IF(N74="","",IF(N74<($L$5-H74),"STALE","")) | P74: Central Bank of Egypt fintech/agri-finance regulation | Q74: https://www.kenresearch.com/egypt-ai-in-mobile-agri-lending-platforms-market | R74: CBE operates a broader fintech regulatory sandbox and issued a 2023 'Financial Inclusion for Agricultural Sector Regulation' requiring licensed institutions to allocate ≥10% of loan portfolios to smallholders — supportive regulatory environment for agri-fintech, though not an agtech-specific sandbox — assessed level 3.
B75: 6.9 | C75: Public-private partnerships in digital agriculture | D75: E1 | E75: Anchored capability rubric | F75: N/A | H75: 2 | J75: =IF(I75="","",IF(Indicators!$H$73<>"Quantitative threshold","",IF(Indicators!$I$73="Higher",IF(N(I75)>=Indicators!$O$73,5,IF(N(I75)>=Indicators!$N$73,4,IF(N(I75)>=Indicators!$M$73,3,IF(N(I75)>=Indicators!$L$73,2,1)))),IF(N(I75)<=Indicators!$O$73,5,IF(N(I75)<=Indicators!$N$73,4,IF(N(I75)<=Indicators!$M$73,3,IF(N(I75)<=Indicators!$L$73,2,1))))))) | K75: 4 | L75: =IF(Indicators!$D$73="C0","",IF(K75<>"",K75,IF(J75<>"",J75,""))) -> 4 | M75: Medium | N75: 2021 | O75: =IF(N75="","",IF(N75<($L$5-H75),"STALE","")) -> STALE | P75: MALR-e-finance 'Agri Egypt' network; ABE-fintech partnerships | Q75: https://www.dailynewsegypt.com/2021/07/14/agriculture-ministry-e-finance-launch-ai-powered-agri-egypt-digital-network/ | R75: Multiple active PPPs identified: MALR + e-finance 'Agri Egypt' AI-powered digital network (2021); Agricultural Bank of Egypt links with Mozare3 and other agri-fintechs; CBE Nclude Fund disbursements to agrifood-payment fintechs — assessed level 4.
B76: 6.10 | C76: Government grants/funding for agtech innovation (annual USD) | D76: E1 | E76: Anchored capability rubric | F76: N/A | H76: 2 | J76: =IF(I76="","",IF(Indicators!$H$74<>"Quantitative threshold","",IF(Indicators!$I$74="Higher",IF(N(I76)>=Indicators!$O$74,5,IF(N(I76)>=Indicators!$N$74,4,IF(N(I76)>=Indicators!$M$74,3,IF(N(I76)>=Indicators!$L$74,2,1)))),IF(N(I76)<=Indicators!$O$74,5,IF(N(I76)<=Indicators!$N$74,4,IF(N(I76)<=Indicators!$M$74,3,IF(N(I76)<=Indicators!$L$74,2,1))))))) | K76: 2 | L76: =IF(Indicators!$D$74="C0","",IF(K76<>"",K76,IF(J76<>"",J76,""))) -> 2 | M76: Low | N76: 2025 | O76: =IF(N76="","",IF(N76<($L$5-H76),"STALE","")) | P76: Sector review (Nilepreneurs, SANAD-backed programs; no aggregated annual total found) | Q76: https://startupegypt.org.eg/blog/top-startup-accelerators-egypt | R76: No aggregated annual dollar figure for government grants/funding specifically targeting agtech innovation was located; government-backed vehicles exist (Nilepreneurs Innovation Hubs grants, SANAD Entrepreneurship Academy co-funded Flat6Labs programs) but without a disclosed dedicated agtech allocation — assessed level 2.
B77: 6.11 | C77: Digital financial services platforms for agriculture | D77: E1 | E77: Anchored capability rubric | F77: N/A | H77: 2 | J77: =IF(I77="","",IF(Indicators!$H$75<>"Quantitative threshold","",IF(Indicators!$I$75="Higher",IF(N(I77)>=Indicators!$O$75,5,IF(N(I77)>=Indicators!$N$75,4,IF(N(I77)>=Indicators!$M$75,3,IF(N(I77)>=Indicators!$L$75,2,1)))),IF(N(I77)<=Indicators!$O$75,5,IF(N(I77)<=Indicators!$N$75,4,IF(N(I77)<=Indicators!$M$75,3,IF(N(I77)<=Indicators!$L$75,2,1))))))) | K77: 4 | L77: =IF(Indicators!$D$75="C0","",IF(K77<>"",K77,IF(J77<>"",J77,""))) -> 4 | M77: High | N77: 2025 | O77: =IF(N77="","",IF(N77<($L$5-H77),"STALE","")) | P77: Mozare3, AgriCash, Meeza Farmer Card, ABE | Q77: https://businessmonthlyeg.com/from-fields-to-fintech-agritech-transforms-egypts-farming-sector/ | R77: Multiple operating digital financial-services platforms for agriculture: Mozare3 (contract farming + digital payments, ~6,300 farmers financed, 97% repayment rate), AgriCash (AI-driven BNPL agri-fintech), and the Meeza Farmer Card linked to Agricultural Bank of Egypt lending — assessed level 4.
B78: 6.12 | C78: Digital public goods adopted in agriculture | D78: E1 | E78: Anchored capability rubric | F78: N/A | H78: 2 | J78: =IF(I78="","",IF(Indicators!$H$76<>"Quantitative threshold","",IF(Indicators!$I$76="Higher",IF(N(I78)>=Indicators!$O$76,5,IF(N(I78)>=Indicators!$N$76,4,IF(N(I78)>=Indicators!$M$76,3,IF(N(I78)>=Indicators!$L$76,2,1)))),IF(N(I78)<=Indicators!$O$76,5,IF(N(I78)<=Indicators!$N$76,4,IF(N(I78)<=Indicators!$M$76,3,IF(N(I78)<=Indicators!$L$76,2,1))))))) | K78: 3 | L78: =IF(Indicators!$D$76="C0","",IF(K78<>"",K78,IF(J78<>"",J78,""))) -> 3 | M78: Medium | N78: 2025 | O78: =IF(N78="","",IF(N78<($L$5-H78),"STALE","")) | P78: El Mufeed (FAO/MALR); Hudhud | Q78: https://egypt.un.org/en/106025-fao-malr-invite-extension-agents-use-%E2%80%9Cel-mufeed%E2%80%9D-app-and-disseminate-among-targeted-groups | R78: El Mufeed (FAO/MALR digital advisory tool) and Hudhud (AI pest-ID app) function as quasi-public digital goods for farmers and extension agents, though neither is formally registered as a global 'Digital Public Good' (DPGA registry) as far as identified — assessed level 3.
B79: 6.13 | C79: SME access to digital agriculture tools/platforms (%) | D79: E1 | E79: Quantitative threshold | F79: Higher | H79: 2 | J79: =IF(I79="","",IF(Indicators!$H$77<>"Quantitative threshold","",IF(Indicators!$I$77="Higher",IF(N(I79)>=Indicators!$O$77,5,IF(N(I79)>=Indicators!$N$77,4,IF(N(I79)>=Indicators!$M$77,3,IF(N(I79)>=Indicators!$L$77,2,1)))),IF(N(I79)<=Indicators!$O$77,5,IF(N(I79)<=Indicators!$N$77,4,IF(N(I79)<=Indicators!$M$77,3,IF(N(I79)<=Indicators!$L$77,2,1))))))) | K79: 2 | L79: =IF(Indicators!$D$77="C0","",IF(K79<>"",K79,IF(J79<>"",J79,""))) -> 2 | M79: Low | N79: 2025 | O79: =IF(N79="","",IF(N79<($L$5-H79),"STALE","")) | P79: Sector review (no SME-specific percentage located) | R79: No percentage figure for SME (as distinct from smallholder/individual farmer) access to digital agriculture tools/platforms was located; assessed level 2 given the broader agtech ecosystem remains small and platform access for formal agribusiness SMEs was not specifically documented.
B80: 6.14 | C80: Agri-fintech / mobile-money rails accessible to smallholders | D80: E1 | E80: Anchored capability rubric | F80: N/A | G80: YES | H80: 2 | J80: =IF(I80="","",IF(Indicators!$H$78<>"Quantitative threshold","",IF(Indicators!$I$78="Higher",IF(N(I80)>=Indicators!$O$78,5,IF(N(I80)>=Indicators!$N$78,4,IF(N(I80)>=Indicators!$M$78,3,IF(N(I80)>=Indicators!$L$78,2,1)))),IF(N(I80)<=Indicators!$O$78,5,IF(N(I80)<=Indicators!$N$78,4,IF(N(I80)<=Indicators!$M$78,3,IF(N(I80)<=Indicators!$L$78,2,1))))))) | K80: 4 | L80: =IF(Indicators!$D$78="C0","",IF(K80<>"",K80,IF(J80<>"",J80,""))) -> 4 | M80: High | N80: 2025 | O80: =IF(N80="","",IF(N80<($L$5-H80),"STALE","")) | P80: Mozare3, AgriCash, Meeza Farmer Card, CBE 2023 regulation, GSMA Mobile Money Regulatory Index | Q80: https://www.tra.gov.eg/en/the-gsma-global-system-for-mobile-communications-association-has-released-its-annual-regulatory-index-for-mobile-money-for-2024-egypts-national-telecom-regulatory-authority-ntra-advanced/ | R80: CORE GATE (new indicator). Egypt has multiple operating agri-fintech rails: Mozare3 (contract farming + digital payments, ~6,300 smallholders financed, 97% repayment), AgriCash (AI-driven BNPL agri-fintech), the Meeza Farmer Card linked to Agricultural Bank of Egypt, and a 2023 Central Bank of Egypt regulation requiring licensed institutions to allocate ≥10% of loan portfolios to smallholder farmers. Egypt also ranks 6th globally (of 90 countries) on GSMA's 2024 Mobile Money Regulatory Index, up 39 places, with a score of 93/100 — strong and rapidly improving rails, assessed level 4 (short of level 5 given mobile money account ownership is still only 15.6% of adults).
B81: 7.1 | C81: AI-related scientific publications per million population | D81: E2 | E81: Quantitative threshold | F81: Higher | H81: 3 | I81: 1.2 | J81: =IF(I81="","",IF(Indicators!$H$79<>"Quantitative threshold","",IF(Indicators!$I$79="Higher",IF(N(I81)>=Indicators!$O$79,5,IF(N(I81)>=Indicators!$N$79,4,IF(N(I81)>=Indicators!$M$79,3,IF(N(I81)>=Indicators!$L$79,2,1)))),IF(N(I81)<=Indicators!$O$79,5,IF(N(I81)<=Indicators!$N$79,4,IF(N(I81)<=Indicators!$M$79,3,IF(N(I81)<=Indicators!$L$79,2,1))))))) -> 2 | L81: =IF(Indicators!$D$79="C0","",IF(K81<>"",K81,IF(J81<>"",J81,""))) -> 2 | M81: Medium | N81: 2023 | O81: =IF(N81="","",IF(N81<($L$5-H81),"STALE","")) | P81: OECD AI Review of Egypt (2024), reportlinker AI publication count | Q81: https://www.oecd.org/content/dam/oecd/en/publications/reports/2024/05/oecd-artificial-intelligence-review-of-egypt_3c437131/2a282726-en.pdf | R81: OECD's 2024 AI Review of Egypt confirms Egyptian AI publications have grown steadily over the past decade and that Egypt compares favorably per capita with Brazil, India, and Thailand, though it lags Israel and Qatar; a separate industry dataset (ReportLinker) estimates ~136.7 AI scientific publications in Egypt for 2023. Dividing by Egypt's ~113 million population yields an approximate rate of ~1.2 AI publications per million population (2023) — a derived estimate, not a directly published per-capita figure, so confidence is Medium.
B82: 7.2 | C82: AI systems deployed in public agricultural sector | D82: E2 | E82: Anchored capability rubric | F82: N/A | H82: 2 | J82: =IF(I82="","",IF(Indicators!$H$80<>"Quantitative threshold","",IF(Indicators!$I$80="Higher",IF(N(I82)>=Indicators!$O$80,5,IF(N(I82)>=Indicators!$N$80,4,IF(N(I82)>=Indicators!$M$80,3,IF(N(I82)>=Indicators!$L$80,2,1)))),IF(N(I82)<=Indicators!$O$80,5,IF(N(I82)<=Indicators!$N$80,4,IF(N(I82)<=Indicators!$M$80,3,IF(N(I82)<=Indicators!$L$80,2,1))))))) | K82: 4 | L82: =IF(Indicators!$D$80="C0","",IF(K82<>"",K82,IF(J82<>"",J82,""))) -> 4 | M82: Medium | N82: 2025 | O82: =IF(N82="","",IF(N82<($L$5-H82),"STALE","")) | P82: Hudhud AI pest-ID app; MALR-MCIT satellite/AI crop-mapping project | Q82: https://farmersreviewafrica.com/egypt-launches-ai-enabled-system-to-enhance-agriculture-process/ | R82: Egypt has at least two operating public-sector AI deployments in agriculture: Hudhud (AI pest/disease identification via smartphone photo, launched Dec 2021) and a satellite-imagery/AI crop-mapping and yield-forecasting project (reviewed Sept 2025) — assessed level 4.
B83: 7.3 | C83: AI-enabled advisory services (farmer reach %) | D83: E2 | E83: Quantitative threshold | F83: Higher | H83: 2 | I83: Hudhud currently accessible to a select group of program-participating farmers (not yet national scale) | J83: =IF(I83="","",IF(Indicators!$H$81<>"Quantitative threshold","",IF(Indicators!$I$81="Higher",IF(N(I83)>=Indicators!$O$81,5,IF(N(I83)>=Indicators!$N$81,4,IF(N(I83)>=Indicators!$M$81,3,IF(N(I83)>=Indicators!$L$81,2,1)))),IF(N(I83)<=Indicators!$O$81,5,IF(N(I83)<=Indicators!$N$81,4,IF(N(I83)<=Indicators!$M$81,3,IF(N(I83)<=Indicators!$L$81,2,1))))))) -> 1 | L83: =IF(Indicators!$D$81="C0","",IF(K83<>"",K83,IF(J83<>"",J83,""))) -> 1 | M83: Low | N83: 2022 | O83: =IF(N83="","",IF(N83<($L$5-H83),"STALE","")) -> STALE | P83: MENA Observatory AI report | Q83: https://menaobservatory.ai/storage/CHOmuyRvzMEC5LmRtmNQMZHpjlZbEM-metaQTJLNEQgLSBNRU5BIEFJIC0gRm9vZCBTZWN1cml0eSAtIEVneXB0IC0gVjIucGRm-.pdf | R83: MENA AI Observatory notes Hudhud remains accessible only to a select group of farmers in government programs rather than broad national reach; no percentage figure of total farmer population reached was found.
B84: 7.4 | C84: AI for crop/pest/disease detection and monitoring | D84: E2 | E84: Quantitative threshold | F84: Higher | H84: 2 | J84: =IF(I84="","",IF(Indicators!$H$82<>"Quantitative threshold","",IF(Indicators!$I$82="Higher",IF(N(I84)>=Indicators!$O$82,5,IF(N(I84)>=Indicators!$N$82,4,IF(N(I84)>=Indicators!$M$82,3,IF(N(I84)>=Indicators!$L$82,2,1)))),IF(N(I84)<=Indicators!$O$82,5,IF(N(I84)<=Indicators!$N$82,4,IF(N(I84)<=Indicators!$M$82,3,IF(N(I84)<=Indicators!$L$82,2,1))))))) | K84: 4 | L84: =IF(Indicators!$D$82="C0","",IF(K84<>"",K84,IF(J84<>"",J84,""))) -> 4 | M84: High | N84: 2025 | O84: =IF(N84="","",IF(N84<($L$5-H84),"STALE","")) | P84: Hudhud app; MALR-MCIT satellite crop project | Q84: https://www.sis.gov.eg/Story/193871/Digital-transformation-in-agro-sector-reviewed?lang=en-us | R84: Hudhud (AI-powered pest/disease identification via image recognition) and the satellite-based AI crop-mapping/pest-monitoring project are both actively operating — assessed level 4.
B85: 7.5 | C85: AI in agricultural finance (credit scoring, insurance) | D85: E2 | E85: Quantitative threshold | F85: Higher | H85: 2 | J85: =IF(I85="","",IF(Indicators!$H$83<>"Quantitative threshold","",IF(Indicators!$I$83="Higher",IF(N(I85)>=Indicators!$O$83,5,IF(N(I85)>=Indicators!$N$83,4,IF(N(I85)>=Indicators!$M$83,3,IF(N(I85)>=Indicators!$L$83,2,1)))),IF(N(I85)<=Indicators!$O$83,5,IF(N(I85)<=Indicators!$N$83,4,IF(N(I85)<=Indicators!$M$83,3,IF(N(I85)<=Indicators!$L$83,2,1))))))) | K85: 4 | L85: =IF(Indicators!$D$83="C0","",IF(K85<>"",K85,IF(J85<>"",J85,""))) -> 4 | M85: Medium | N85: 2025 | O85: =IF(N85="","",IF(N85<($L$5-H85),"STALE","")) | P85: AgriCash (AI-driven agri-fintech BNPL) | Q85: https://egyptinnovate.com/en/%D8%A3%D8%AE%D8%A8%D8%A7%D8%B1/agricash-secures-seed-funding-scale-ai-driven-agri-fintech-platform-egypt-and-beyond | R85: AgriCash explicitly markets itself as an 'AI-driven agri-fintech' platform for BNPL agricultural finance, targeting EGP 500M in transaction volume in 2025 — an active, named deployment of AI in ag-finance, assessed level 4.
B86: 7.6 | C86: AI for supply chain optimization and traceability | D86: E2 | E86: Quantitative threshold | F86: Higher | H86: 2 | J86: =IF(I86="","",IF(Indicators!$H$84<>"Quantitative threshold","",IF(Indicators!$I$84="Higher",IF(N(I86)>=Indicators!$O$84,5,IF(N(I86)>=Indicators!$N$84,4,IF(N(I86)>=Indicators!$M$84,3,IF(N(I86)>=Indicators!$L$84,2,1)))),IF(N(I86)<=Indicators!$O$84,5,IF(N(I86)<=Indicators!$N$84,4,IF(N(I86)<=Indicators!$M$84,3,IF(N(I86)<=Indicators!$L$84,2,1))))))) | K86: 2 | L86: =IF(Indicators!$D$84="C0","",IF(K86<>"",K86,IF(J86<>"",J86,""))) -> 2 | M86: Low | N86: 2025 | O86: =IF(N86="","",IF(N86<($L$5-H86),"STALE","")) | P86: Sector review | R86: No specific evidence of AI-based agricultural supply-chain optimization or traceability systems in Egypt was identified beyond general price-monitoring tools (Mahsoly, which is data-driven but not confirmed as AI/ML-based) — assessed level 2.
B87: 7.7 | C87: AI for climate forecasting and agricultural risk management | D87: E2 | E87: Quantitative threshold | F87: Higher | H87: 2 | J87: =IF(I87="","",IF(Indicators!$H$85<>"Quantitative threshold","",IF(Indicators!$I$85="Higher",IF(N(I87)>=Indicators!$O$85,5,IF(N(I87)>=Indicators!$N$85,4,IF(N(I87)>=Indicators!$M$85,3,IF(N(I87)>=Indicators!$L$85,2,1)))),IF(N(I87)<=Indicators!$O$85,5,IF(N(I87)<=Indicators!$N$85,4,IF(N(I87)<=Indicators!$M$85,3,IF(N(I87)<=Indicators!$L$85,2,1))))))) | K87: 3 | L87: =IF(Indicators!$D$85="C0","",IF(K87<>"",K87,IF(J87<>"",J87,""))) -> 3 | M87: Medium | N87: 2025 | O87: =IF(N87="","",IF(N87<($L$5-H87),"STALE","")) | P87: DAIRS climate early-warning system (ICARDA review) | Q87: https://cgspace.cgiar.org/server/api/core/bitstreams/d4a33acc-564a-4e4c-a413-81ba3ebd4d90/content | R87: DAIRS climate early-warning system is under development per ICARDA's 2025 review; unclear how much AI/ML (versus conventional forecasting) underpins it — assessed level 3.
B88: 7.8 | C88: AI talent in agriculture sector | D88: E2 | E88: Anchored capability rubric | F88: N/A | H88: 2 | J88: =IF(I88="","",IF(Indicators!$H$86<>"Quantitative threshold","",IF(Indicators!$I$86="Higher",IF(N(I88)>=Indicators!$O$86,5,IF(N(I88)>=Indicators!$N$86,4,IF(N(I88)>=Indicators!$M$86,3,IF(N(I88)>=Indicators!$L$86,2,1)))),IF(N(I88)<=Indicators!$O$86,5,IF(N(I88)<=Indicators!$N$86,4,IF(N(I88)<=Indicators!$M$86,3,IF(N(I88)<=Indicators!$L$86,2,1))))))) | K88: 2 | L88: =IF(Indicators!$D$86="C0","",IF(K88<>"",K88,IF(J88<>"",J88,""))) -> 2 | M88: Low | N88: 2025 | O88: =IF(N88="","",IF(N88<($L$5-H88),"STALE","")) | P88: Sector review (qualitative; no headcount figure located) | R88: No headcount or percentage figure for AI-specific talent employed within Egypt's agriculture sector was located; a small number of named AI-driven ventures (Hudhud, AgriCash, satellite crop-mapping project) imply nascent but very limited specialized AI talent concentration — assessed level 2.
B89: 7.9 | C89: Cybersecurity of agricultural digital systems | D89: E2 | E89: Anchored capability rubric | F89: N/A | G89: YES | H89: 2 | J89: =IF(I89="","",IF(Indicators!$H$87<>"Quantitative threshold","",IF(Indicators!$I$87="Higher",IF(N(I89)>=Indicators!$O$87,5,IF(N(I89)>=Indicators!$N$87,4,IF(N(I89)>=Indicators!$M$87,3,IF(N(I89)>=Indicators!$L$87,2,1)))),IF(N(I89)<=Indicators!$O$87,5,IF(N(I89)<=Indicators!$N$87,4,IF(N(I89)<=Indicators!$M$87,3,IF(N(I89)<=Indicators!$L$87,2,1))))))) | K89: 3 | L89: =IF(Indicators!$D$87="C0","",IF(K89<>"",K89,IF(J89<>"",J89,""))) -> 3 | M89: Medium | N89: 2024 | O89: =IF(N89="","",IF(N89<($L$5-H89),"STALE","")) | P89: Inferred from Egypt's national ITU GCI score (general, not ag-specific) | Q89: https://www.itu.int/epublications/publication/global-cybersecurity-index-2024 | R89: CORE GATE. Egypt's overall national cybersecurity posture is very strong (ITU GCI 2024: 100/100, Tier 1), but no sector-specific evidence was found confirming that agricultural digital systems (Farmer Card, Meeza, MALR platforms) have undergone dedicated cybersecurity assessment or hardening — assessed level 3 (strong national baseline, unconfirmed sector-specific application) rather than 5.
B90: 7.10 | C90: Explainability and transparency of AI systems in agriculture | D90: E2 | E90: Anchored capability rubric | F90: N/A | H90: 2 | J90: =IF(I90="","",IF(Indicators!$H$88<>"Quantitative threshold","",IF(Indicators!$I$88="Higher",IF(N(I90)>=Indicators!$O$88,5,IF(N(I90)>=Indicators!$N$88,4,IF(N(I90)>=Indicators!$M$88,3,IF(N(I90)>=Indicators!$L$88,2,1)))),IF(N(I90)<=Indicators!$O$88,5,IF(N(I90)<=Indicators!$N$88,4,IF(N(I90)<=Indicators!$M$88,3,IF(N(I90)<=Indicators!$L$88,2,1))))))) | K90: 2 | L90: =IF(Indicators!$D$88="C0","",IF(K90<>"",K90,IF(J90<>"",J90,""))) -> 2 | M90: Low | N90: 2025 | O90: =IF(N90="","",IF(N90<($L$5-H90),"STALE","")) | P90: Sector review | R90: No evidence located regarding explainability/transparency practices for any Egyptian agricultural AI system (e.g., Hudhud's model transparency) — assessed level 2 (not yet a defined practice).
B91: 7.11 | C91: Bias monitoring and mitigation in agricultural AI | D91: E2 | E91: Anchored capability rubric | F91: N/A | H91: 2 | J91: =IF(I91="","",IF(Indicators!$H$89<>"Quantitative threshold","",IF(Indicators!$I$89="Higher",IF(N(I91)>=Indicators!$O$89,5,IF(N(I91)>=Indicators!$N$89,4,IF(N(I91)>=Indicators!$M$89,3,IF(N(I91)>=Indicators!$L$89,2,1)))),IF(N(I91)<=Indicators!$O$89,5,IF(N(I91)<=Indicators!$N$89,4,IF(N(I91)<=Indicators!$M$89,3,IF(N(I91)<=Indicators!$L$89,2,1))))))) | K91: 2 | L91: =IF(Indicators!$D$89="C0","",IF(K91<>"",K91,IF(J91<>"",J91,""))) -> 2 | M91: Low | N91: 2025 | O91: =IF(N91="","",IF(N91<($L$5-H91),"STALE","")) | P91: Sector review | R91: No evidence located regarding bias monitoring/mitigation practices for Egyptian agricultural AI systems — assessed level 2.
B92: 7.12 | C92: Farmer consent and data rights in AI systems | D92: E2 | E92: Anchored capability rubric | F92: N/A | G92: YES | H92: 2 | J92: =IF(I92="","",IF(Indicators!$H$90<>"Quantitative threshold","",IF(Indicators!$I$90="Higher",IF(N(I92)>=Indicators!$O$90,5,IF(N(I92)>=Indicators!$N$90,4,IF(N(I92)>=Indicators!$M$90,3,IF(N(I92)>=Indicators!$L$90,2,1)))),IF(N(I92)<=Indicators!$O$90,5,IF(N(I92)<=Indicators!$N$90,4,IF(N(I92)<=Indicators!$M$90,3,IF(N(I92)<=Indicators!$L$90,2,1))))))) | K92: 3 | L92: =IF(Indicators!$D$90="C0","",IF(K92<>"",K92,IF(J92<>"",J92,""))) -> 3 | M92: Medium | N92: 2020 | O92: =IF(N92="","",IF(N92<($L$5-H92),"STALE","")) -> STALE | P92: PDPL Law 151/2020 (general legal basis, not AI/ag-specific) | Q92: https://www.acc.com/sites/default/files/program-materials/upload/Data%20Protection%20Law%20-%20Egypt%20-%20EN%20-%20MBH.PDF | R92: CORE GATE. PDPL 151/2020 establishes a general legal basis for consent and data-subject rights that would apply to farmer data collected by AI systems (e.g., Hudhud photo uploads), but no agriculture-specific or AI-specific consent framework was identified — assessed level 3 (general legal coverage, sector-specific implementation unconfirmed).
B93: 8.1 | C93: Prevalence of undernourishment (% of population) | D93: O1 | E93: Quantitative threshold | F93: Lower | H93: 3 | I93: 9.4 | J93: =IF(I93="","",IF(Indicators!$H$91<>"Quantitative threshold","",IF(Indicators!$I$91="Higher",IF(N(I93)>=Indicators!$O$91,5,IF(N(I93)>=Indicators!$N$91,4,IF(N(I93)>=Indicators!$M$91,3,IF(N(I93)>=Indicators!$L$91,2,1)))),IF(N(I93)<=Indicators!$O$91,5,IF(N(I93)<=Indicators!$N$91,4,IF(N(I93)<=Indicators!$M$91,3,IF(N(I93)<=Indicators!$L$91,2,1))))))) -> 3 | L93: =IF(Indicators!$D$91="C0","",IF(K93<>"",K93,IF(J93<>"",J93,""))) -> 3 | M93: High | N93: 2023 | O93: =IF(N93="","",IF(N93<($L$5-H93),"STALE","")) | P93: World Bank WDI (SN.ITK.DEFC.ZS) | Q93: https://api.worldbank.org/v2/country/EGY/indicator/SN.ITK.DEFC.ZS?format=json | R93: Most recent WDI undernourishment prevalence figure for Egypt.
B94: 8.2 | C94: Account ownership, female (% age 15+) | D94: O1 | E94: Quantitative threshold | F94: Higher | H94: 3 | I94: 40.21 | J94: =IF(I94="","",IF(Indicators!$H$92<>"Quantitative threshold","",IF(Indicators!$I$92="Higher",IF(N(I94)>=Indicators!$O$92,5,IF(N(I94)>=Indicators!$N$92,4,IF(N(I94)>=Indicators!$M$92,3,IF(N(I94)>=Indicators!$L$92,2,1)))),IF(N(I94)<=Indicators!$O$92,5,IF(N(I94)<=Indicators!$N$92,4,IF(N(I94)<=Indicators!$M$92,3,IF(N(I94)<=Indicators!$L$92,2,1))))))) -> 3 | L94: =IF(Indicators!$D$92="C0","",IF(K94<>"",K94,IF(J94<>"",J94,""))) -> 3 | M94: High | N94: 2024 | O94: =IF(N94="","",IF(N94<($L$5-H94),"STALE","")) | P94: World Bank WDI / Global Findex (FX.OWN.TOTL.FE.ZS) | Q94: https://api.worldbank.org/v2/country/EGY/indicator/FX.OWN.TOTL.FE.ZS?format=json | R94: Global Findex 2024 data via WDI.
B95: 8.3 | C95: Gender gap in account ownership (male % minus female %) | D95: O1 | E95: Quantitative threshold | F95: Lower | H95: 3 | I95: 5.74 | J95: =IF(I95="","",IF(Indicators!$H$93<>"Quantitative threshold","",IF(Indicators!$I$93="Higher",IF(N(I95)>=Indicators!$O$93,5,IF(N(I95)>=Indicators!$N$93,4,IF(N(I95)>=Indicators!$M$93,3,IF(N(I95)>=Indicators!$L$93,2,1)))),IF(N(I95)<=Indicators!$O$93,5,IF(N(I95)<=Indicators!$N$93,4,IF(N(I95)<=Indicators!$M$93,3,IF(N(I95)<=Indicators!$L$93,2,1))))))) -> 4 | L95: =IF(Indicators!$D$93="C0","",IF(K95<>"",K95,IF(J95<>"",J95,""))) -> 4 | M95: High | N95: 2024 | O95: =IF(N95="","",IF(N95<($L$5-H95),"STALE","")) | P95: World Bank WDI / Global Findex | Q95: https://api.worldbank.org/v2/country/EGY/indicator/FX.OWN.TOTL.MA.ZS?format=json | R95: Calculated as male account ownership (45.95%) minus female account ownership (40.21%) using 2024 Global Findex data via WDI.
B96: 8.4 | C96: Mobile money account (% age 15+) | D96: O1 | E96: Quantitative threshold | F96: Higher | H96: 3 | I96: 15.6 | J96: =IF(I96="","",IF(Indicators!$H$94<>"Quantitative threshold","",IF(Indicators!$I$94="Higher",IF(N(I96)>=Indicators!$O$94,5,IF(N(I96)>=Indicators!$N$94,4,IF(N(I96)>=Indicators!$M$94,3,IF(N(I96)>=Indicators!$L$94,2,1)))),IF(N(I96)<=Indicators!$O$94,5,IF(N(I96)<=Indicators!$N$94,4,IF(N(I96)<=Indicators!$M$94,3,IF(N(I96)<=Indicators!$L$94,2,1))))))) -> 2 | L96: =IF(Indicators!$D$94="C0","",IF(K96<>"",K96,IF(J96<>"",J96,""))) -> 2 | M96: Medium | N96: 2024 | O96: =IF(N96="","",IF(N96<($L$5-H96),"STALE","")) | P96: World Bank Global Findex (via FinStatGlobe compilation) | Q96: https://data.finstatglobe.com/egypt/mobile-money-account-statistics | R96: Global Findex 2024 data show mobile money account ownership rising sharply to 15.6% of adults, up from 2.9% in 2021 — a 12.7 percentage-point jump; Egypt ranks 6th globally on GSMA's 2024 Mobile Money Regulatory Index (score 93/100, up from 80 in 2023), reflecting fast-improving regulatory support.
B97: 8.5 | C97: Women who own land (% of agricultural holders) | D97: O1 | E97: Quantitative threshold | F97: Higher | H97: 3 | I97: 5.2 | J97: =IF(I97="","",IF(Indicators!$H$95<>"Quantitative threshold","",IF(Indicators!$I$95="Higher",IF(N(I97)>=Indicators!$O$95,5,IF(N(I97)>=Indicators!$N$95,4,IF(N(I97)>=Indicators!$M$95,3,IF(N(I97)>=Indicators!$L$95,2,1)))),IF(N(I97)<=Indicators!$O$95,5,IF(N(I97)<=Indicators!$N$95,4,IF(N(I97)<=Indicators!$M$95,3,IF(N(I97)<=Indicators!$L$95,2,1))))))) -> 1 | L97: =IF(Indicators!$D$95="C0","",IF(K97<>"",K97,IF(J97<>"",J97,""))) -> 1 | M97: Medium | N97: 2015 | O97: =IF(N97="","",IF(N97<($L$5-H97),"STALE","")) -> STALE | P97: FAO Gender and Land Rights Database / FAO Country Gender Assessment Egypt | Q97: https://openknowledge.fao.org/server/api/core/bitstreams/7a31c4cf-4117-45fc-84fd-b51635c2a62a/content | R97: FAO data (2015, still the most commonly cited figure as of recent FAO/GIZ reporting) show only 5.2% of Egypt's total agricultural land area is owned by women, and only ~2% of Egyptian women own land at all — one of the lowest rates in the Arab world (regional average ~7%). A 1999 agricultural census figure shows 5.2% of agricultural holders were female, consistent with the land-area figure. Data is dated (exceeds typical MaxAge) so confidence is Medium rather than High.
B98: 8.6 | C98: Gender gap in mobile phone ownership (percentage points) | D98: O1 | E98: Quantitative threshold | F98: Lower | H98: 3 | I98: -2 | J98: =IF(I98="","",IF(Indicators!$H$96<>"Quantitative threshold","",IF(Indicators!$I$96="Higher",IF(N(I98)>=Indicators!$O$96,5,IF(N(I98)>=Indicators!$N$96,4,IF(N(I98)>=Indicators!$M$96,3,IF(N(I98)>=Indicators!$L$96,2,1)))),IF(N(I98)<=Indicators!$O$96,5,IF(N(I98)<=Indicators!$N$96,4,IF(N(I98)<=Indicators!$M$96,3,IF(N(I98)<=Indicators!$L$96,2,1))))))) -> 5 | L98: =IF(Indicators!$D$96="C0","",IF(K98<>"",K98,IF(J98<>"",J98,""))) -> 5 | M98: Medium | N98: 2022 | O98: =IF(N98="","",IF(N98<($L$5-H98),"STALE","")) | P98: GSMA Mobile Gender Gap Report 2023 (2022 survey data) | Q98: https://aimg8.dlssyht.cn/u/551001/ueditor/file/276/551001/1688461001299595.pdf | R98: GSMA's Mobile Gender Gap Report 2023 (based on 2022 consumer survey data) finds Egypt is one of only two surveyed countries (with Mexico) where women's mobile phone ownership (83%) slightly exceeds men's (81%), i.e., a small negative gender gap of about -2 percentage points in ownership — Egypt's mobile internet use gender gap is a more typical +12 percentage points (65% men vs. 57% women) in the same survey.
B99: 8.7 | C99: Women using digital agricultural services (% of women farmers) | D99: O1 | E99: Quantitative threshold | F99: Higher | H99: 3 | J99: =IF(I99="","",IF(Indicators!$H$97<>"Quantitative threshold","",IF(Indicators!$I$97="Higher",IF(N(I99)>=Indicators!$O$97,5,IF(N(I99)>=Indicators!$N$97,4,IF(N(I99)>=Indicators!$M$97,3,IF(N(I99)>=Indicators!$L$97,2,1)))),IF(N(I99)<=Indicators!$O$97,5,IF(N(I99)<=Indicators!$N$97,4,IF(N(I99)<=Indicators!$M$97,3,IF(N(I99)<=Indicators!$L$97,2,1))))))) | K99: 2 | L99: =IF(Indicators!$D$97="C0","",IF(K99<>"",K99,IF(J99<>"",J99,""))) -> 2 | M99: Low | N99: 2025 | O99: =IF(N99="","",IF(N99<($L$5-H99),"STALE","")) | P99: Sector review (no specific figure located) | R99: No figure for women farmers' use of digital agricultural services specifically was located; given very low female land ownership (5.2%, indicator 8.5) and low female extension-officer representation (indicator C4.14), women's direct engagement with formal digital ag services is likely constrained — assessed level 2 as an inferred estimate.
B100: 8.8 | C100: Youth (under 35) using digital agricultural services (%) | D100: O1 | E100: Quantitative threshold | F100: Higher | H100: 3 | J100: =IF(I100="","",IF(Indicators!$H$98<>"Quantitative threshold","",IF(Indicators!$I$98="Higher",IF(N(I100)>=Indicators!$O$98,5,IF(N(I100)>=Indicators!$N$98,4,IF(N(I100)>=Indicators!$M$98,3,IF(N(I100)>=Indicators!$L$98,2,1)))),IF(N(I100)<=Indicators!$O$98,5,IF(N(I100)<=Indicators!$N$98,4,IF(N(I100)<=Indicators!$M$98,3,IF(N(I100)<=Indicators!$L$98,2,1))))))) | K100: 3 | L100: =IF(Indicators!$D$98="C0","",IF(K100<>"",K100,IF(J100<>"",J100,""))) -> 3 | M100: Low | N100: 2025 | O100: =IF(N100="","",IF(N100<($L$5-H100),"STALE","")) | P100: Sector review (no specific figure located; inferred from general youth smartphone/digital adoption trends) | R100: No age-disaggregated figure for youth use of digital agricultural services in Egypt was located; given generally higher smartphone/internet adoption among younger cohorts nationally (Digital 2025 Egypt report), youth engagement with digital ag services is plausibly above the all-farmer average — assessed level 3 as an inferred estimate, not a measured figure.
B101: 8.9 | C101: Smallholder farmers reached by digital services (% of total) | D101: O1 | E101: Quantitative threshold | F101: Higher | H101: 3 | J101: =IF(I101="","",IF(Indicators!$H$99<>"Quantitative threshold","",IF(Indicators!$I$99="Higher",IF(N(I101)>=Indicators!$O$99,5,IF(N(I101)>=Indicators!$N$99,4,IF(N(I101)>=Indicators!$M$99,3,IF(N(I101)>=Indicators!$L$99,2,1)))),IF(N(I101)<=Indicators!$O$99,5,IF(N(I101)<=Indicators!$N$99,4,IF(N(I101)<=Indicators!$M$99,3,IF(N(I101)<=Indicators!$L$99,2,1))))))) | K101: 3 | L101: =IF(Indicators!$D$99="C0","",IF(K101<>"",K101,IF(J101<>"",J101,""))) -> 3 | M101: Low | N101: 2025 | O101: =IF(N101="","",IF(N101<($L$5-H101),"STALE","")) | P101: Composite from platform user counts vs. ~4M ag holdings (2020 census) | Q101: https://cgspace.cgiar.org/server/api/core/bitstreams/9f8108a1-d7e7-54a1-8527-3111f8e4bfc0/content | R101: Individual platforms report meaningful user bases (Mahsoly and AlMorshed Poultry each 100,000+; Mozare3 ~6,300 financed farmers) against an estimated ~4 million agricultural holdings nationally (2020 Agricultural Census), implying reach still well under half of smallholders — assessed level 3 (growing but partial reach), not a precise percentage.
B102: 8.10 | C102: Affordability of digital agriculture services for poorest quintile | D102: O1 | E102: Quantitative threshold | F102: Higher | H102: 3 | J102: =IF(I102="","",IF(Indicators!$H$100<>"Quantitative threshold","",IF(Indicators!$I$100="Higher",IF(N(I102)>=Indicators!$O$100,5,IF(N(I102)>=Indicators!$N$100,4,IF(N(I102)>=Indicators!$M$100,3,IF(N(I102)>=Indicators!$L$100,2,1)))),IF(N(I102)<=Indicators!$O$100,5,IF(N(I102)<=Indicators!$N$100,4,IF(N(I102)<=Indicators!$M$100,3,IF(N(I102)<=Indicators!$L$100,2,1))))))) | K102: 2 | L102: =IF(Indicators!$D$100="C0","",IF(K102<>"",K102,IF(J102<>"",J102,""))) -> 2 | M102: Low | N102: 2025 | O102: =IF(N102="","",IF(N102<($L$5-H102),"STALE","")) | P102: Sector review (general affordability context: mobile broadband basket ~1.2% GNI, but ag-service-specific pricing unknown) | R102: General mobile connectivity is affordable relative to GNI per capita, but no evidence on the specific affordability of paid digital agriculture services (e.g., premium advisory subscriptions) for the poorest quintile of farmers was located — assessed level 2.
B103: 8.11 | C103: Services available in local languages (% of major platforms) | D103: O1 | E103: Quantitative threshold | F103: Higher | H103: 3 | I103: High — most major platforms (Hudhud, El Mufeed, Mazra3ty, Fila7a) are Arabic-language | J103: =IF(I103="","",IF(Indicators!$H$101<>"Quantitative threshold","",IF(Indicators!$I$101="Higher",IF(N(I103)>=Indicators!$O$101,5,IF(N(I103)>=Indicators!$N$101,4,IF(N(I103)>=Indicators!$M$101,3,IF(N(I103)>=Indicators!$L$101,2,1)))),IF(N(I103)<=Indicators!$O$101,5,IF(N(I103)<=Indicators!$N$101,4,IF(N(I103)<=Indicators!$M$101,3,IF(N(I103)<=Indicators!$L$101,2,1))))))) -> 1 | L103: =IF(Indicators!$D$101="C0","",IF(K103<>"",K103,IF(J103<>"",J103,""))) -> 1 | M103: Medium | N103: 2025 | O103: =IF(N103="","",IF(N103<($L$5-H103),"STALE","")) | P103: Multiple platform reviews (ICARDA, FAO, SIS.gov.eg) | Q103: https://cgspace.cgiar.org/server/api/core/bitstreams/9f8108a1-d7e7-54a1-8527-3111f8e4bfc0/content | R103: All major identified digital agriculture platforms in Egypt (Hudhud, El Mufeed, Mazra3ty, Fila7a) are delivered in Arabic, the dominant local language for farmers, though no precise percentage-of-platforms metric exists — qualitative assessment only.
...

Sheet Blank Template
B2: [Country name] — DAMM v1.4 assessment
B3: Live scoring. Edit columns I–R. Columns J, L, O are formulas.
B5: Assessment mode | E5: Assessor | H5: Mandate date | K5: Reference year | L5: 2025
B7: ID | C7: Indicator | D7: Pillar | E7: Method | F7: Dir. | G7: Core gate | H7: Max age | I7: Value | J7: Machine L (auto) | K7: Assessor L | L7: Effective L | M7: Confidence | N7: Year | O7: Stale? | P7: Source | Q7: URL | R7: Notes / dissent
B8: 1.1 | C8: Agriculture value added per worker (constant 2015 USD) | D8: C0 | E8: Context profile (not aggregated) | F8: N/A | H8: 3 | J8: =IF(I8="","",IF(Indicators!$H$6<>"Quantitative threshold","",IF(Indicators!$I$6="Higher",IF(N(I8)>=Indicators!$O$6,5,IF(N(I8)>=Indicators!$N$6,4,IF(N(I8)>=Indicators!$M$6,3,IF(N(I8)>=Indicators!$L$6,2,1)))),IF(N(I8)<=Indicators!$O$6,5,IF(N(I8)<=Indicators!$N$6,4,IF(N(I8)<=Indicators!$M$6,3,IF(N(I8)<=Indicators!$L$6,2,1))))))) | L8: =IF(Indicators!$D$6="C0","",IF(K8<>"",K8,IF(J8<>"",J8,""))) | O8: =IF(N8="","",IF(N8<($L$5-H8),"STALE",""))
B9: 1.2 | C9: Cereal yield (kg per hectare) | D9: C0 | E9: Context profile (not aggregated) | F9: N/A | H9: 3 | J9: =IF(I9="","",IF(Indicators!$H$7<>"Quantitative threshold","",IF(Indicators!$I$7="Higher",IF(N(I9)>=Indicators!$O$7,5,IF(N(I9)>=Indicators!$N$7,4,IF(N(I9)>=Indicators!$M$7,3,IF(N(I9)>=Indicators!$L$7,2,1)))),IF(N(I9)<=Indicators!$O$7,5,IF(N(I9)<=Indicators!$N$7,4,IF(N(I9)<=Indicators!$M$7,3,IF(N(I9)<=Indicators!$L$7,2,1))))))) | L9: =IF(Indicators!$D$7="C0","",IF(K9<>"",K9,IF(J9<>"",J9,""))) | O9: =IF(N9="","",IF(N9<($L$5-H9),"STALE",""))
B10: 1.3 | C10: Employment in agriculture (% of total employment) | D10: C0 | E10: Context profile (not aggregated) | F10: N/A | H10: 3 | J10: =IF(I10="","",IF(Indicators!$H$8<>"Quantitative threshold","",IF(Indicators!$I$8="Higher",IF(N(I10)>=Indicators!$O$8,5,IF(N(I10)>=Indicators!$N$8,4,IF(N(I10)>=Indicators!$M$8,3,IF(N(I10)>=Indicators!$L$8,2,1)))),IF(N(I10)<=Indicators!$O$8,5,IF(N(I10)<=Indicators!$N$8,4,IF(N(I10)<=Indicators!$M$8,3,IF(N(I10)<=Indicators!$L$8,2,1))))))) | L10: =IF(Indicators!$D$8="C0","",IF(K10<>"",K10,IF(J10<>"",J10,""))) | O10: =IF(N10="","",IF(N10<($L$5-H10),"STALE",""))
B11: 1.4 | C11: Food production index (2014-2016 = 100) | D11: C0 | E11: Context profile (not aggregated) | F11: N/A | H11: 3 | J11: =IF(I11="","",IF(Indicators!$H$9<>"Quantitative threshold","",IF(Indicators!$I$9="Higher",IF(N(I11)>=Indicators!$O$9,5,IF(N(I11)>=Indicators!$N$9,4,IF(N(I11)>=Indicators!$M$9,3,IF(N(I11)>=Indicators!$L$9,2,1)))),IF(N(I11)<=Indicators!$O$9,5,IF(N(I11)<=Indicators!$N$9,4,IF(N(I11)<=Indicators!$M$9,3,IF(N(I11)<=Indicators!$L$9,2,1))))))) | L11: =IF(Indicators!$D$9="C0","",IF(K11<>"",K11,IF(J11<>"",J11,""))) | O11: =IF(N11="","",IF(N11<($L$5-H11),"STALE",""))
B12: 1.5 | C12: Post-harvest loss rate (%) | D12: C0 | E12: Context profile (not aggregated) | F12: N/A | H12: 2 | J12: =IF(I12="","",IF(Indicators!$H$10<>"Quantitative threshold","",IF(Indicators!$I$10="Higher",IF(N(I12)>=Indicators!$O$10,5,IF(N(I12)>=Indicators!$N$10,4,IF(N(I12)>=Indicators!$M$10,3,IF(N(I12)>=Indicators!$L$10,2,1)))),IF(N(I12)<=Indicators!$O$10,5,IF(N(I12)<=Indicators!$N$10,4,IF(N(I12)<=Indicators!$M$10,3,IF(N(I12)<=Indicators!$L$10,2,1))))))) | L12: =IF(Indicators!$D$10="C0","",IF(K12<>"",K12,IF(J12<>"",J12,""))) | O12: =IF(N12="","",IF(N12<($L$5-H12),"STALE",""))
B13: 1.6 | C13: Smallholder access to formal markets (%) | D13: C0 | E13: Context profile (not aggregated) | F13: N/A | H13: 2 | J13: =IF(I13="","",IF(Indicators!$H$11<>"Quantitative threshold","",IF(Indicators!$I$11="Higher",IF(N(I13)>=Indicators!$O$11,5,IF(N(I13)>=Indicators!$N$11,4,IF(N(I13)>=Indicators!$M$11,3,IF(N(I13)>=Indicators!$L$11,2,1)))),IF(N(I13)<=Indicators!$O$11,5,IF(N(I13)<=Indicators!$N$11,4,IF(N(I13)<=Indicators!$M$11,3,IF(N(I13)<=Indicators!$L$11,2,1))))))) | L13: =IF(Indicators!$D$11="C0","",IF(K13<>"",K13,IF(J13<>"",J13,""))) | O13: =IF(N13="","",IF(N13<($L$5-H13),"STALE",""))
B14: 1.7 | C14: Agricultural credit access (% of farmers) | D14: C0 | E14: Context profile (not aggregated) | F14: N/A | H14: 2 | J14: =IF(I14="","",IF(Indicators!$H$12<>"Quantitative threshold","",IF(Indicators!$I$12="Higher",IF(N(I14)>=Indicators!$O$12,5,IF(N(I14)>=Indicators!$N$12,4,IF(N(I14)>=Indicators!$M$12,3,IF(N(I14)>=Indicators!$L$12,2,1)))),IF(N(I14)<=Indicators!$O$12,5,IF(N(I14)<=Indicators!$N$12,4,IF(N(I14)<=Indicators!$M$12,3,IF(N(I14)<=Indicators!$L$12,2,1))))))) | L14: =IF(Indicators!$D$12="C0","",IF(K14<>"",K14,IF(J14<>"",J14,""))) | O14: =IF(N14="","",IF(N14<($L$5-H14),"STALE",""))
B15: 1.8 | C15: Farmers using climate-smart/sustainable practices (%) | D15: C0 | E15: Context profile (not aggregated) | F15: N/A | H15: 2 | J15: =IF(I15="","",IF(Indicators!$H$13<>"Quantitative threshold","",IF(Indicators!$I$13="Higher",IF(N(I15)>=Indicators!$O$13,5,IF(N(I15)>=Indicators!$N$13,4,IF(N(I15)>=Indicators!$M$13,3,IF(N(I15)>=Indicators!$L$13,2,1)))),IF(N(I15)<=Indicators!$O$13,5,IF(N(I15)<=Indicators!$N$13,4,IF(N(I15)<=Indicators!$M$13,3,IF(N(I15)<=Indicators!$L$13,2,1))))))) | L15: =IF(Indicators!$D$13="C0","",IF(K15<>"",K15,IF(J15<>"",J15,""))) | O15: =IF(N15="","",IF(N15<($L$5-H15),"STALE",""))
B16: 1.9 | C16: National innovation/extension programs with digital component | D16: C4 | E16: Anchored capability rubric | F16: N/A | H16: 2 | J16: =IF(I16="","",IF(Indicators!$H$14<>"Quantitative threshold","",IF(Indicators!$I$14="Higher",IF(N(I16)>=Indicators!$O$14,5,IF(N(I16)>=Indicators!$N$14,4,IF(N(I16)>=Indicators!$M$14,3,IF(N(I16)>=Indicators!$L$14,2,1)))),IF(N(I16)<=Indicators!$O$14,5,IF(N(I16)<=Indicators!$N$14,4,IF(N(I16)<=Indicators!$M$14,3,IF(N(I16)<=Indicators!$L$14,2,1))))))) | L16: =IF(Indicators!$D$14="C0","",IF(K16<>"",K16,IF(J16<>"",J16,""))) | O16: =IF(N16="","",IF(N16<($L$5-H16),"STALE",""))
B17: 2.1 | C17: Rural population covered by at least 3G (%) | D17: C1 | E17: Quantitative threshold | F17: Higher | G17: YES | H17: 3 | J17: =IF(I17="","",IF(Indicators!$H$15<>"Quantitative threshold","",IF(Indicators!$I$15="Higher",IF(N(I17)>=Indicators!$O$15,5,IF(N(I17)>=Indicators!$N$15,4,IF(N(I17)>=Indicators!$M$15,3,IF(N(I17)>=Indicators!$L$15,2,1)))),IF(N(I17)<=Indicators!$O$15,5,IF(N(I17)<=Indicators!$N$15,4,IF(N(I17)<=Indicators!$M$15,3,IF(N(I17)<=Indicators!$L$15,2,1))))))) | L17: =IF(Indicators!$D$15="C0","",IF(K17<>"",K17,IF(J17<>"",J17,""))) | O17: =IF(N17="","",IF(N17<($L$5-H17),"STALE",""))
B18: 2.2 | C18: Rural population covered by at least 4G (%) | D18: C1 | E18: Quantitative threshold | F18: Higher | H18: 3 | J18: =IF(I18="","",IF(Indicators!$H$16<>"Quantitative threshold","",IF(Indicators!$I$16="Higher",IF(N(I18)>=Indicators!$O$16,5,IF(N(I18)>=Indicators!$N$16,4,IF(N(I18)>=Indicators!$M$16,3,IF(N(I18)>=Indicators!$L$16,2,1)))),IF(N(I18)<=Indicators!$O$16,5,IF(N(I18)<=Indicators!$N$16,4,IF(N(I18)<=Indicators!$M$16,3,IF(N(I18)<=Indicators!$L$16,2,1))))))) | L18: =IF(Indicators!$D$16="C0","",IF(K18<>"",K18,IF(J18<>"",J18,""))) | O18: =IF(N18="","",IF(N18<($L$5-H18),"STALE",""))
B19: 2.3 | C19: Active mobile broadband subscriptions per 100 inhabitants | D19: C1 | E19: Quantitative threshold | F19: Higher | H19: 3 | J19: =IF(I19="","",IF(Indicators!$H$17<>"Quantitative threshold","",IF(Indicators!$I$17="Higher",IF(N(I19)>=Indicators!$O$17,5,IF(N(I19)>=Indicators!$N$17,4,IF(N(I19)>=Indicators!$M$17,3,IF(N(I19)>=Indicators!$L$17,2,1)))),IF(N(I19)<=Indicators!$O$17,5,IF(N(I19)<=Indicators!$N$17,4,IF(N(I19)<=Indicators!$M$17,3,IF(N(I19)<=Indicators!$L$17,2,1))))))) | L19: =IF(Indicators!$D$17="C0","",IF(K19<>"",K19,IF(J19<>"",J19,""))) | O19: =IF(N19="","",IF(N19<($L$5-H19),"STALE",""))
B20: 2.4 | C20: Individuals using the Internet (% of population) | D20: C1 | E20: Quantitative threshold | F20: Higher | H20: 3 | J20: =IF(I20="","",IF(Indicators!$H$18<>"Quantitative threshold","",IF(Indicators!$I$18="Higher",IF(N(I20)>=Indicators!$O$18,5,IF(N(I20)>=Indicators!$N$18,4,IF(N(I20)>=Indicators!$M$18,3,IF(N(I20)>=Indicators!$L$18,2,1)))),IF(N(I20)<=Indicators!$O$18,5,IF(N(I20)<=Indicators!$N$18,4,IF(N(I20)<=Indicators!$M$18,3,IF(N(I20)<=Indicators!$L$18,2,1))))))) | L20: =IF(Indicators!$D$18="C0","",IF(K20<>"",K20,IF(J20<>"",J20,""))) | O20: =IF(N20="","",IF(N20<($L$5-H20),"STALE",""))
B21: 2.5 | C21: Mobile broadband basket price (% GNI per capita) | D21: C1 | E21: Quantitative threshold | F21: Lower | G21: YES | H21: 3 | J21: =IF(I21="","",IF(Indicators!$H$19<>"Quantitative threshold","",IF(Indicators!$I$19="Higher",IF(N(I21)>=Indicators!$O$19,5,IF(N(I21)>=Indicators!$N$19,4,IF(N(I21)>=Indicators!$M$19,3,IF(N(I21)>=Indicators!$L$19,2,1)))),IF(N(I21)<=Indicators!$O$19,5,IF(N(I21)<=Indicators!$N$19,4,IF(N(I21)<=Indicators!$M$19,3,IF(N(I21)<=Indicators!$L$19,2,1))))))) | L21: =IF(Indicators!$D$19="C0","",IF(K21<>"",K21,IF(J21<>"",J21,""))) | O21: =IF(N21="","",IF(N21<($L$5-H21),"STALE",""))
B22: 2.6 | C22: Adults with mobile phone (% age 15+) | D22: C1 | E22: Quantitative threshold | F22: Higher | H22: 3 | J22: =IF(I22="","",IF(Indicators!$H$20<>"Quantitative threshold","",IF(Indicators!$I$20="Higher",IF(N(I22)>=Indicators!$O$20,5,IF(N(I22)>=Indicators!$N$20,4,IF(N(I22)>=Indicators!$M$20,3,IF(N(I22)>=Indicators!$L$20,2,1)))),IF(N(I22)<=Indicators!$O$20,5,IF(N(I22)<=Indicators!$N$20,4,IF(N(I22)<=Indicators!$M$20,3,IF(N(I22)<=Indicators!$L$20,2,1))))))) | L22: =IF(Indicators!$D$20="C0","",IF(K22<>"",K22,IF(J22<>"",J22,""))) | O22: =IF(N22="","",IF(N22<($L$5-H22),"STALE",""))
B23: 2.7 | C23: Smartphone ownership among rural/agricultural population (%) | D23: C1 | E23: Quantitative threshold | F23: Higher | H23: 2 | J23: =IF(I23="","",IF(Indicators!$H$21<>"Quantitative threshold","",IF(Indicators!$I$21="Higher",IF(N(I23)>=Indicators!$O$21,5,IF(N(I23)>=Indicators!$N$21,4,IF(N(I23)>=Indicators!$M$21,3,IF(N(I23)>=Indicators!$L$21,2,1)))),IF(N(I23)<=Indicators!$O$21,5,IF(N(I23)<=Indicators!$N$21,4,IF(N(I23)<=Indicators!$M$21,3,IF(N(I23)<=Indicators!$L$21,2,1))))))) | L23: =IF(Indicators!$D$21="C0","",IF(K23<>"",K23,IF(J23<>"",J23,""))) | O23: =IF(N23="","",IF(N23<($L$5-H23),"STALE",""))
B24: 2.8 | C24: Average mobile data cost in rural areas (USD per GB) | D24: C1 | E24: Quantitative threshold | F24: Lower | H24: 2 | J24: =IF(I24="","",IF(Indicators!$H$22<>"Quantitative threshold","",IF(Indicators!$I$22="Higher",IF(N(I24)>=Indicators!$O$22,5,IF(N(I24)>=Indicators!$N$22,4,IF(N(I24)>=Indicators!$M$22,3,IF(N(I24)>=Indicators!$L$22,2,1)))),IF(N(I24)<=Indicators!$O$22,5,IF(N(I24)<=Indicators!$N$22,4,IF(N(I24)<=Indicators!$M$22,3,IF(N(I24)<=Indicators!$L$22,2,1))))))) | L24: =IF(Indicators!$D$22="C0","",IF(K24<>"",K24,IF(J24<>"",J24,""))) | O24: =IF(N24="","",IF(N24<($L$5-H24),"STALE",""))
B25: 2.9 | C25: Electricity access in rural areas (%) | D25: C1 | E25: Quantitative threshold | F25: Higher | G25: YES | H25: 2 | J25: =IF(I25="","",IF(Indicators!$H$23<>"Quantitative threshold","",IF(Indicators!$I$23="Higher",IF(N(I25)>=Indicators!$O$23,5,IF(N(I25)>=Indicators!$N$23,4,IF(N(I25)>=Indicators!$M$23,3,IF(N(I25)>=Indicators!$L$23,2,1)))),IF(N(I25)<=Indicators!$O$23,5,IF(N(I25)<=Indicators!$N$23,4,IF(N(I25)<=Indicators!$M$23,3,IF(N(I25)<=Indicators!$L$23,2,1))))))) | L25: =IF(Indicators!$D$23="C0","",IF(K25<>"",K25,IF(J25<>"",J25,""))) | O25: =IF(N25="","",IF(N25<($L$5-H25),"STALE",""))
B26: 2.10 | C26: Average download speed in agricultural areas (Mbps) | D26: C1 | E26: Quantitative threshold | F26: Higher | H26: 2 | J26: =IF(I26="","",IF(Indicators!$H$24<>"Quantitative threshold","",IF(Indicators!$I$24="Higher",IF(N(I26)>=Indicators!$O$24,5,IF(N(I26)>=Indicators!$N$24,4,IF(N(I26)>=Indicators!$M$24,3,IF(N(I26)>=Indicators!$L$24,2,1)))),IF(N(I26)<=Indicators!$O$24,5,IF(N(I26)<=Indicators!$N$24,4,IF(N(I26)<=Indicators!$M$24,3,IF(N(I26)<=Indicators!$L$24,2,1))))))) | L26: =IF(Indicators!$D$24="C0","",IF(K26<>"",K26,IF(J26<>"",J26,""))) | O26: =IF(N26="","",IF(N26<($L$5-H26),"STALE",""))
B27: 2.11 | C27: Device financing/subsidy schemes for farmers | D27: C1 | E27: Anchored capability rubric | F27: N/A | H27: 2 | J27: =IF(I27="","",IF(Indicators!$H$25<>"Quantitative threshold","",IF(Indicators!$I$25="Higher",IF(N(I27)>=Indicators!$O$25,5,IF(N(I27)>=Indicators!$N$25,4,IF(N(I27)>=Indicators!$M$25,3,IF(N(I27)>=Indicators!$L$25,2,1)))),IF(N(I27)<=Indicators!$O$25,5,IF(N(I27)<=Indicators!$N$25,4,IF(N(I27)<=Indicators!$M$25,3,IF(N(I27)<=Indicators!$L$25,2,1))))))) | L27: =IF(Indicators!$D$25="C0","",IF(K27<>"",K27,IF(J27<>"",J27,""))) | O27: =IF(N27="","",IF(N27<($L$5-H27),"STALE",""))
B28: 3.1 | C28: UN E-Government Development Index (EGDI) | D28: C2 | E28: Quantitative threshold | F28: Higher | H28: 3 | J28: =IF(I28="","",IF(Indicators!$H$26<>"Quantitative threshold","",IF(Indicators!$I$26="Higher",IF(N(I28)>=Indicators!$O$26,5,IF(N(I28)>=Indicators!$N$26,4,IF(N(I28)>=Indicators!$M$26,3,IF(N(I28)>=Indicators!$L$26,2,1)))),IF(N(I28)<=Indicators!$O$26,5,IF(N(I28)<=Indicators!$N$26,4,IF(N(I28)<=Indicators!$M$26,3,IF(N(I28)<=Indicators!$L$26,2,1))))))) | L28: =IF(Indicators!$D$26="C0","",IF(K28<>"",K28,IF(J28<>"",J28,""))) | O28: =IF(N28="","",IF(N28<($L$5-H28),"STALE",""))
B29: 3.2 | C29: Open Data Inventory (ODIN) score | D29: C2 | E29: Quantitative threshold | F29: Higher | H29: 3 | J29: =IF(I29="","",IF(Indicators!$H$27<>"Quantitative threshold","",IF(Indicators!$I$27="Higher",IF(N(I29)>=Indicators!$O$27,5,IF(N(I29)>=Indicators!$N$27,4,IF(N(I29)>=Indicators!$M$27,3,IF(N(I29)>=Indicators!$L$27,2,1)))),IF(N(I29)<=Indicators!$O$27,5,IF(N(I29)<=Indicators!$N$27,4,IF(N(I29)<=Indicators!$M$27,3,IF(N(I29)<=Indicators!$L$27,2,1))))))) | L29: =IF(Indicators!$D$27="C0","",IF(K29<>"",K29,IF(J29<>"",J29,""))) | O29: =IF(N29="","",IF(N29<($L$5-H29),"STALE",""))
B30: 3.3 | C30: National farmer registry/database | D30: C2 | E30: Anchored capability rubric | F30: N/A | G30: YES | H30: 2 | J30: =IF(I30="","",IF(Indicators!$H$28<>"Quantitative threshold","",IF(Indicators!$I$28="Higher",IF(N(I30)>=Indicators!$O$28,5,IF(N(I30)>=Indicators!$N$28,4,IF(N(I30)>=Indicators!$M$28,3,IF(N(I30)>=Indicators!$L$28,2,1)))),IF(N(I30)<=Indicators!$O$28,5,IF(N(I30)<=Indicators!$N$28,4,IF(N(I30)<=Indicators!$M$28,3,IF(N(I30)<=Indicators!$L$28,2,1))))))) | L30: =IF(Indicators!$D$28="C0","",IF(K30<>"",K30,IF(J30<>"",J30,""))) | O30: =IF(N30="","",IF(N30<($L$5-H30),"STALE",""))
B31: 3.4 | C31: Digital land/plot registration system | D31: C2 | E31: Anchored capability rubric | F31: N/A | H31: 2 | J31: =IF(I31="","",IF(Indicators!$H$29<>"Quantitative threshold","",IF(Indicators!$I$29="Higher",IF(N(I31)>=Indicators!$O$29,5,IF(N(I31)>=Indicators!$N$29,4,IF(N(I31)>=Indicators!$M$29,3,IF(N(I31)>=Indicators!$L$29,2,1)))),IF(N(I31)<=Indicators!$O$29,5,IF(N(I31)<=Indicators!$N$29,4,IF(N(I31)<=Indicators!$M$29,3,IF(N(I31)<=Indicators!$L$29,2,1))))))) | L31: =IF(Indicators!$D$29="C0","",IF(K31<>"",K31,IF(J31<>"",J31,""))) | O31: =IF(N31="","",IF(N31<($L$5-H31),"STALE",""))
B32: 3.5 | C32: National agricultural data portal / open data | D32: C2 | E32: Anchored capability rubric | F32: N/A | H32: 2 | J32: =IF(I32="","",IF(Indicators!$H$30<>"Quantitative threshold","",IF(Indicators!$I$30="Higher",IF(N(I32)>=Indicators!$O$30,5,IF(N(I32)>=Indicators!$N$30,4,IF(N(I32)>=Indicators!$M$30,3,IF(N(I32)>=Indicators!$L$30,2,1)))),IF(N(I32)<=Indicators!$O$30,5,IF(N(I32)<=Indicators!$N$30,4,IF(N(I32)<=Indicators!$M$30,3,IF(N(I32)<=Indicators!$L$30,2,1))))))) | L32: =IF(Indicators!$D$30="C0","",IF(K32<>"",K32,IF(J32<>"",J32,""))) | O32: =IF(N32="","",IF(N32<($L$5-H32),"STALE",""))
B33: 3.6 | C33: Weather/climate data infrastructure for agriculture | D33: C2 | E33: Anchored capability rubric | F33: N/A | H33: 2 | J33: =IF(I33="","",IF(Indicators!$H$31<>"Quantitative threshold","",IF(Indicators!$I$31="Higher",IF(N(I33)>=Indicators!$O$31,5,IF(N(I33)>=Indicators!$N$31,4,IF(N(I33)>=Indicators!$M$31,3,IF(N(I33)>=Indicators!$L$31,2,1)))),IF(N(I33)<=Indicators!$O$31,5,IF(N(I33)<=Indicators!$N$31,4,IF(N(I33)<=Indicators!$M$31,3,IF(N(I33)<=Indicators!$L$31,2,1))))))) | L33: =IF(Indicators!$D$31="C0","",IF(K33<>"",K33,IF(J33<>"",J33,""))) | O33: =IF(N33="","",IF(N33<($L$5-H33),"STALE",""))
B34: 3.7 | C34: Satellite/earth observation data integration capability | D34: C2 | E34: Anchored capability rubric | F34: N/A | H34: 2 | J34: =IF(I34="","",IF(Indicators!$H$32<>"Quantitative threshold","",IF(Indicators!$I$32="Higher",IF(N(I34)>=Indicators!$O$32,5,IF(N(I34)>=Indicators!$N$32,4,IF(N(I34)>=Indicators!$M$32,3,IF(N(I34)>=Indicators!$L$32,2,1)))),IF(N(I34)<=Indicators!$O$32,5,IF(N(I34)<=Indicators!$N$32,4,IF(N(I34)<=Indicators!$M$32,3,IF(N(I34)<=Indicators!$L$32,2,1))))))) | L34: =IF(Indicators!$D$32="C0","",IF(K34<>"",K34,IF(J34<>"",J34,""))) | O34: =IF(N34="","",IF(N34<($L$5-H34),"STALE",""))
B35: 3.8 | C35: National soil map/database (digital) | D35: C2 | E35: Anchored capability rubric | F35: N/A | H35: 2 | J35: =IF(I35="","",IF(Indicators!$H$33<>"Quantitative threshold","",IF(Indicators!$I$33="Higher",IF(N(I35)>=Indicators!$O$33,5,IF(N(I35)>=Indicators!$N$33,4,IF(N(I35)>=Indicators!$M$33,3,IF(N(I35)>=Indicators!$L$33,2,1)))),IF(N(I35)<=Indicators!$O$33,5,IF(N(I35)<=Indicators!$N$33,4,IF(N(I35)<=Indicators!$M$33,3,IF(N(I35)<=Indicators!$L$33,2,1))))))) | L35: =IF(Indicators!$D$33="C0","",IF(K35<>"",K35,IF(J35<>"",J35,""))) | O35: =IF(N35="","",IF(N35<($L$5-H35),"STALE",""))
B36: 3.9 | C36: Digital advisory platforms reaching >10,000 users | D36: C2 | E36: Quantitative threshold | F36: Higher | H36: 2 | J36: =IF(I36="","",IF(Indicators!$H$34<>"Quantitative threshold","",IF(Indicators!$I$34="Higher",IF(N(I36)>=Indicators!$O$34,5,IF(N(I36)>=Indicators!$N$34,4,IF(N(I36)>=Indicators!$M$34,3,IF(N(I36)>=Indicators!$L$34,2,1)))),IF(N(I36)<=Indicators!$O$34,5,IF(N(I36)<=Indicators!$N$34,4,IF(N(I36)<=Indicators!$M$34,3,IF(N(I36)<=Indicators!$L$34,2,1))))))) | L36: =IF(Indicators!$D$34="C0","",IF(K36<>"",K36,IF(J36<>"",J36,""))) | O36: =IF(N36="","",IF(N36<($L$5-H36),"STALE",""))
B37: 3.10 | C37: Digital agricultural market/e-commerce platforms (>5,000 active users) | D37: C2 | E37: Anchored capability rubric | F37: N/A | H37: 2 | J37: =IF(I37="","",IF(Indicators!$H$35<>"Quantitative threshold","",IF(Indicators!$I$35="Higher",IF(N(I37)>=Indicators!$O$35,5,IF(N(I37)>=Indicators!$N$35,4,IF(N(I37)>=Indicators!$M$35,3,IF(N(I37)>=Indicators!$L$35,2,1)))),IF(N(I37)<=Indicators!$O$35,5,IF(N(I37)<=Indicators!$N$35,4,IF(N(I37)<=Indicators!$M$35,3,IF(N(I37)<=Indicators!$L$35,2,1))))))) | L37: =IF(Indicators!$D$35="C0","",IF(K37<>"",K37,IF(J37<>"",J37,""))) | O37: =IF(N37="","",IF(N37<($L$5-H37),"STALE",""))
B38: 3.11 | C38: Interoperability standards for agricultural data | D38: C2 | E38: Anchored capability rubric | F38: N/A | G38: YES | H38: 2 | J38: =IF(I38="","",IF(Indicators!$H$36<>"Quantitative threshold","",IF(Indicators!$I$36="Higher",IF(N(I38)>=Indicators!$O$36,5,IF(N(I38)>=Indicators!$N$36,4,IF(N(I38)>=Indicators!$M$36,3,IF(N(I38)>=Indicators!$L$36,2,1)))),IF(N(I38)<=Indicators!$O$36,5,IF(N(I38)<=Indicators!$N$36,4,IF(N(I38)<=Indicators!$M$36,3,IF(N(I38)<=Indicators!$L$36,2,1))))))) | L38: =IF(Indicators!$D$36="C0","",IF(K38<>"",K38,IF(J38<>"",J38,""))) | O38: =IF(N38="","",IF(N38<($L$5-H38),"STALE",""))
B39: 3.12 | C39: AI-ready agricultural datasets | D39: C2 | E39: Anchored capability rubric | F39: N/A | H39: 2 | J39: =IF(I39="","",IF(Indicators!$H$37<>"Quantitative threshold","",IF(Indicators!$I$37="Higher",IF(N(I39)>=Indicators!$O$37,5,IF(N(I39)>=Indicators!$N$37,4,IF(N(I39)>=Indicators!$M$37,3,IF(N(I39)>=Indicators!$L$37,2,1)))),IF(N(I39)<=Indicators!$O$37,5,IF(N(I39)<=Indicators!$N$37,4,IF(N(I39)<=Indicators!$M$37,3,IF(N(I39)<=Indicators!$L$37,2,1))))))) | L39: =IF(Indicators!$D$37="C0","",IF(K39<>"",K39,IF(J39<>"",J39,""))) | O39: =IF(N39="","",IF(N39<($L$5-H39),"STALE",""))
B40: 3.13 | C40: Machine-readable open agricultural data (share of national ag statistics as open APIs) | D40: C2 | E40: Quantitative threshold | F40: Higher | H40: 2 | J40: =IF(I40="","",IF(Indicators!$H$38<>"Quantitative threshold","",IF(Indicators!$I$38="Higher",IF(N(I40)>=Indicators!$O$38,5,IF(N(I40)>=Indicators!$N$38,4,IF(N(I40)>=Indicators!$M$38,3,IF(N(I40)>=Indicators!$L$38,2,1)))),IF(N(I40)<=Indicators!$O$38,5,IF(N(I40)<=Indicators!$N$38,4,IF(N(I40)<=Indicators!$M$38,3,IF(N(I40)<=Indicators!$L$38,2,1))))))) | L40: =IF(Indicators!$D$38="C0","",IF(K40<>"",K40,IF(J40<>"",J40,""))) | O40: =IF(N40="","",IF(N40<($L$5-H40),"STALE",""))
B41: 4.1 | C41: Data protection/privacy law | D41: C3 | E41: Anchored capability rubric | F41: N/A | G41: YES | H41: 3 | J41: =IF(I41="","",IF(Indicators!$H$39<>"Quantitative threshold","",IF(Indicators!$I$39="Higher",IF(N(I41)>=Indicators!$O$39,5,IF(N(I41)>=Indicators!$N$39,4,IF(N(I41)>=Indicators!$M$39,3,IF(N(I41)>=Indicators!$L$39,2,1)))),IF(N(I41)<=Indicators!$O$39,5,IF(N(I41)<=Indicators!$N$39,4,IF(N(I41)<=Indicators!$M$39,3,IF(N(I41)<=Indicators!$L$39,2,1))))))) | L41: =IF(Indicators!$D$39="C0","",IF(K41<>"",K41,IF(J41<>"",J41,""))) | O41: =IF(N41="","",IF(N41<($L$5-H41),"STALE",""))
B42: 4.2 | C42: Cybersecurity legal framework (ITU GCI) | D42: C3 | E42: Quantitative threshold | F42: Higher | G42: YES | H42: 3 | J42: =IF(I42="","",IF(Indicators!$H$40<>"Quantitative threshold","",IF(Indicators!$I$40="Higher",IF(N(I42)>=Indicators!$O$40,5,IF(N(I42)>=Indicators!$N$40,4,IF(N(I42)>=Indicators!$M$40,3,IF(N(I42)>=Indicators!$L$40,2,1)))),IF(N(I42)<=Indicators!$O$40,5,IF(N(I42)<=Indicators!$N$40,4,IF(N(I42)<=Indicators!$M$40,3,IF(N(I42)<=Indicators!$L$40,2,1))))))) | L42: =IF(Indicators!$D$40="C0","",IF(K42<>"",K42,IF(J42<>"",J42,""))) | O42: =IF(N42="","",IF(N42<($L$5-H42),"STALE",""))
B43: 4.3 | C43: Government AI Readiness Index | D43: C3 | E43: Quantitative threshold | F43: Higher | H43: 3 | J43: =IF(I43="","",IF(Indicators!$H$41<>"Quantitative threshold","",IF(Indicators!$I$41="Higher",IF(N(I43)>=Indicators!$O$41,5,IF(N(I43)>=Indicators!$N$41,4,IF(N(I43)>=Indicators!$M$41,3,IF(N(I43)>=Indicators!$L$41,2,1)))),IF(N(I43)<=Indicators!$O$41,5,IF(N(I43)<=Indicators!$N$41,4,IF(N(I43)<=Indicators!$M$41,3,IF(N(I43)<=Indicators!$L$41,2,1))))))) | L43: =IF(Indicators!$D$41="C0","",IF(K43<>"",K43,IF(J43<>"",J43,""))) | O43: =IF(N43="","",IF(N43<($L$5-H43),"STALE",""))
B44: 4.4 | C44: National digital agriculture strategy | D44: C3 | E44: Anchored capability rubric | F44: N/A | H44: 2 | J44: =IF(I44="","",IF(Indicators!$H$42<>"Quantitative threshold","",IF(Indicators!$I$42="Higher",IF(N(I44)>=Indicators!$O$42,5,IF(N(I44)>=Indicators!$N$42,4,IF(N(I44)>=Indicators!$M$42,3,IF(N(I44)>=Indicators!$L$42,2,1)))),IF(N(I44)<=Indicators!$O$42,5,IF(N(I44)<=Indicators!$N$42,4,IF(N(I44)<=Indicators!$M$42,3,IF(N(I44)<=Indicators!$L$42,2,1))))))) | L44: =IF(Indicators!$D$42="C0","",IF(K44<>"",K44,IF(J44<>"",J44,""))) | O44: =IF(N44="","",IF(N44<($L$5-H44),"STALE",""))
B45: 4.5 | C45: Agricultural data governance framework | D45: C3 | E45: Anchored capability rubric | F45: N/A | G45: YES | H45: 2 | J45: =IF(I45="","",IF(Indicators!$H$43<>"Quantitative threshold","",IF(Indicators!$I$43="Higher",IF(N(I45)>=Indicators!$O$43,5,IF(N(I45)>=Indicators!$N$43,4,IF(N(I45)>=Indicators!$M$43,3,IF(N(I45)>=Indicators!$L$43,2,1)))),IF(N(I45)<=Indicators!$O$43,5,IF(N(I45)<=Indicators!$N$43,4,IF(N(I45)<=Indicators!$M$43,3,IF(N(I45)<=Indicators!$L$43,2,1))))))) | L45: =IF(Indicators!$D$43="C0","",IF(K45<>"",K45,IF(J45<>"",J45,""))) | O45: =IF(N45="","",IF(N45<($L$5-H45),"STALE",""))
B46: 4.6 | C46: National AI strategy with agriculture component | D46: C3 | E46: Anchored capability rubric | F46: N/A | H46: 2 | J46: =IF(I46="","",IF(Indicators!$H$44<>"Quantitative threshold","",IF(Indicators!$I$44="Higher",IF(N(I46)>=Indicators!$O$44,5,IF(N(I46)>=Indicators!$N$44,4,IF(N(I46)>=Indicators!$M$44,3,IF(N(I46)>=Indicators!$L$44,2,1)))),IF(N(I46)<=Indicators!$O$44,5,IF(N(I46)<=Indicators!$N$44,4,IF(N(I46)<=Indicators!$M$44,3,IF(N(I46)<=Indicators!$L$44,2,1))))))) | L46: =IF(Indicators!$D$44="C0","",IF(K46<>"",K46,IF(J46<>"",J46,""))) | O46: =IF(N46="","",IF(N46<($L$5-H46),"STALE",""))
B47: 4.7 | C47: Digital ID system coverage (% of population) | D47: C3 | E47: Quantitative threshold | F47: Higher | H47: 2 | J47: =IF(I47="","",IF(Indicators!$H$45<>"Quantitative threshold","",IF(Indicators!$I$45="Higher",IF(N(I47)>=Indicators!$O$45,5,IF(N(I47)>=Indicators!$N$45,4,IF(N(I47)>=Indicators!$M$45,3,IF(N(I47)>=Indicators!$L$45,2,1)))),IF(N(I47)<=Indicators!$O$45,5,IF(N(I47)<=Indicators!$N$45,4,IF(N(I47)<=Indicators!$M$45,3,IF(N(I47)<=Indicators!$L$45,2,1))))))) | L47: =IF(Indicators!$D$45="C0","",IF(K47<>"",K47,IF(J47<>"",J47,""))) | O47: =IF(N47="","",IF(N47<($L$5-H47),"STALE",""))
B48: 4.8 | C48: Data sovereignty provisions for agricultural data | D48: C3 | E48: Anchored capability rubric | F48: N/A | H48: 2 | J48: =IF(I48="","",IF(Indicators!$H$46<>"Quantitative threshold","",IF(Indicators!$I$46="Higher",IF(N(I48)>=Indicators!$O$46,5,IF(N(I48)>=Indicators!$N$46,4,IF(N(I48)>=Indicators!$M$46,3,IF(N(I48)>=Indicators!$L$46,2,1)))),IF(N(I48)<=Indicators!$O$46,5,IF(N(I48)<=Indicators!$N$46,4,IF(N(I48)<=Indicators!$M$46,3,IF(N(I48)<=Indicators!$L$46,2,1))))))) | L48: =IF(Indicators!$D$46="C0","",IF(K48<>"",K48,IF(J48<>"",J48,""))) | O48: =IF(N48="","",IF(N48<($L$5-H48),"STALE",""))
B49: 4.9 | C49: Inter-ministerial coordination mechanism for digital agriculture | D49: C3 | E49: Anchored capability rubric | F49: N/A | G49: YES | H49: 2 | J49: =IF(I49="","",IF(Indicators!$H$47<>"Quantitative threshold","",IF(Indicators!$I$47="Higher",IF(N(I49)>=Indicators!$O$47,5,IF(N(I49)>=Indicators!$N$47,4,IF(N(I49)>=Indicators!$M$47,3,IF(N(I49)>=Indicators!$L$47,2,1)))),IF(N(I49)<=Indicators!$O$47,5,IF(N(I49)<=Indicators!$N$47,4,IF(N(I49)<=Indicators!$M$47,3,IF(N(I49)<=Indicators!$L$47,2,1))))))) | L49: =IF(Indicators!$D$47="C0","",IF(K49<>"",K49,IF(J49<>"",J49,""))) | O49: =IF(N49="","",IF(N49<($L$5-H49),"STALE",""))
B50: 4.10 | C50: Competition/antitrust framework for digital agricultural markets | D50: C3 | E50: Anchored capability rubric | F50: N/A | H50: 2 | J50: =IF(I50="","",IF(Indicators!$H$48<>"Quantitative threshold","",IF(Indicators!$I$48="Higher",IF(N(I50)>=Indicators!$O$48,5,IF(N(I50)>=Indicators!$N$48,4,IF(N(I50)>=Indicators!$M$48,3,IF(N(I50)>=Indicators!$L$48,2,1)))),IF(N(I50)<=Indicators!$O$48,5,IF(N(I50)<=Indicators!$N$48,4,IF(N(I50)<=Indicators!$M$48,3,IF(N(I50)<=Indicators!$L$48,2,1))))))) | L50: =IF(Indicators!$D$48="C0","",IF(K50<>"",K50,IF(J50<>"",J50,""))) | O50: =IF(N50="","",IF(N50<($L$5-H50),"STALE",""))
B51: 4.11 | C51: Public procurement rules enabling digital agriculture innovation | D51: C3 | E51: Anchored capability rubric | F51: N/A | H51: 2 | J51: =IF(I51="","",IF(Indicators!$H$49<>"Quantitative threshold","",IF(Indicators!$I$49="Higher",IF(N(I51)>=Indicators!$O$49,5,IF(N(I51)>=Indicators!$N$49,4,IF(N(I51)>=Indicators!$M$49,3,IF(N(I51)>=Indicators!$L$49,2,1)))),IF(N(I51)<=Indicators!$O$49,5,IF(N(I51)<=Indicators!$N$49,4,IF(N(I51)<=Indicators!$M$49,3,IF(N(I51)<=Indicators!$L$49,2,1))))))) | L51: =IF(Indicators!$D$49="C0","",IF(K51<>"",K51,IF(J51<>"",J51,""))) | O51: =IF(N51="","",IF(N51<($L$5-H51),"STALE",""))
B52: 4.12 | C52: Spectrum allocation for rural/agricultural IoT | D52: C3 | E52: Anchored capability rubric | F52: N/A | H52: 2 | J52: =IF(I52="","",IF(Indicators!$H$50<>"Quantitative threshold","",IF(Indicators!$I$50="Higher",IF(N(I52)>=Indicators!$O$50,5,IF(N(I52)>=Indicators!$N$50,4,IF(N(I52)>=Indicators!$M$50,3,IF(N(I52)>=Indicators!$L$50,2,1)))),IF(N(I52)<=Indicators!$O$50,5,IF(N(I52)<=Indicators!$N$50,4,IF(N(I52)<=Indicators!$M$50,3,IF(N(I52)<=Indicators!$L$50,2,1))))))) | L52: =IF(Indicators!$D$50="C0","",IF(K52<>"",K52,IF(J52<>"",J52,""))) | O52: =IF(N52="","",IF(N52<($L$5-H52),"STALE",""))
B53: 4.13 | C53: Responsible AI principles/guidelines for agriculture | D53: C3 | E53: Anchored capability rubric | F53: N/A | H53: 2 | J53: =IF(I53="","",IF(Indicators!$H$51<>"Quantitative threshold","",IF(Indicators!$I$51="Higher",IF(N(I53)>=Indicators!$O$51,5,IF(N(I53)>=Indicators!$N$51,4,IF(N(I53)>=Indicators!$M$51,3,IF(N(I53)>=Indicators!$L$51,2,1)))),IF(N(I53)<=Indicators!$O$51,5,IF(N(I53)<=Indicators!$N$51,4,IF(N(I53)<=Indicators!$M$51,3,IF(N(I53)<=Indicators!$L$51,2,1))))))) | L53: =IF(Indicators!$D$51="C0","",IF(K53<>"",K53,IF(J53<>"",J53,""))) | O53: =IF(N53="","",IF(N53<($L$5-H53),"STALE",""))
B54: 5.1 | C54: Mean years of schooling (adults 25+) | D54: C4 | E54: Quantitative threshold | F54: Higher | H54: 3 | J54: =IF(I54="","",IF(Indicators!$H$52<>"Quantitative threshold","",IF(Indicators!$I$52="Higher",IF(N(I54)>=Indicators!$O$52,5,IF(N(I54)>=Indicators!$N$52,4,IF(N(I54)>=Indicators!$M$52,3,IF(N(I54)>=Indicators!$L$52,2,1)))),IF(N(I54)<=Indicators!$O$52,5,IF(N(I54)<=Indicators!$N$52,4,IF(N(I54)<=Indicators!$M$52,3,IF(N(I54)<=Indicators!$L$52,2,1))))))) | L54: =IF(Indicators!$D$52="C0","",IF(K54<>"",K54,IF(J54<>"",J54,""))) | O54: =IF(N54="","",IF(N54<($L$5-H54),"STALE",""))
B55: 5.2 | C55: Adult literacy rate (% age 15+) | D55: C4 | E55: Quantitative threshold | F55: Higher | H55: 3 | J55: =IF(I55="","",IF(Indicators!$H$53<>"Quantitative threshold","",IF(Indicators!$I$53="Higher",IF(N(I55)>=Indicators!$O$53,5,IF(N(I55)>=Indicators!$N$53,4,IF(N(I55)>=Indicators!$M$53,3,IF(N(I55)>=Indicators!$L$53,2,1)))),IF(N(I55)<=Indicators!$O$53,5,IF(N(I55)<=Indicators!$N$53,4,IF(N(I55)<=Indicators!$M$53,3,IF(N(I55)<=Indicators!$L$53,2,1))))))) | L55: =IF(Indicators!$D$53="C0","",IF(K55<>"",K55,IF(J55<>"",J55,""))) | O55: =IF(N55="","",IF(N55<($L$5-H55),"STALE",""))
B56: 5.3 | C56: Tertiary enrollment in STEM fields (% gross) | D56: C4 | E56: Quantitative threshold | F56: Higher | H56: 3 | J56: =IF(I56="","",IF(Indicators!$H$54<>"Quantitative threshold","",IF(Indicators!$I$54="Higher",IF(N(I56)>=Indicators!$O$54,5,IF(N(I56)>=Indicators!$N$54,4,IF(N(I56)>=Indicators!$M$54,3,IF(N(I56)>=Indicators!$L$54,2,1)))),IF(N(I56)<=Indicators!$O$54,5,IF(N(I56)<=Indicators!$N$54,4,IF(N(I56)<=Indicators!$M$54,3,IF(N(I56)<=Indicators!$L$54,2,1))))))) | L56: =IF(Indicators!$D$54="C0","",IF(K56<>"",K56,IF(J56<>"",J56,""))) | O56: =IF(N56="","",IF(N56<($L$5-H56),"STALE",""))
B57: 5.4 | C57: Digital literacy among farmers (%) | D57: C4 | E57: Quantitative threshold | F57: Higher | H57: 2 | J57: =IF(I57="","",IF(Indicators!$H$55<>"Quantitative threshold","",IF(Indicators!$I$55="Higher",IF(N(I57)>=Indicators!$O$55,5,IF(N(I57)>=Indicators!$N$55,4,IF(N(I57)>=Indicators!$M$55,3,IF(N(I57)>=Indicators!$L$55,2,1)))),IF(N(I57)<=Indicators!$O$55,5,IF(N(I57)<=Indicators!$N$55,4,IF(N(I57)<=Indicators!$M$55,3,IF(N(I57)<=Indicators!$L$55,2,1))))))) | L57: =IF(Indicators!$D$55="C0","",IF(K57<>"",K57,IF(J57<>"",J57,""))) | O57: =IF(N57="","",IF(N57<($L$5-H57),"STALE",""))
B58: 5.5 | C58: Extension workers trained in digital tools (%) | D58: C4 | E58: Quantitative threshold | F58: Higher | G58: YES | H58: 2 | J58: =IF(I58="","",IF(Indicators!$H$56<>"Quantitative threshold","",IF(Indicators!$I$56="Higher",IF(N(I58)>=Indicators!$O$56,5,IF(N(I58)>=Indicators!$N$56,4,IF(N(I58)>=Indicators!$M$56,3,IF(N(I58)>=Indicators!$L$56,2,1)))),IF(N(I58)<=Indicators!$O$56,5,IF(N(I58)<=Indicators!$N$56,4,IF(N(I58)<=Indicators!$M$56,3,IF(N(I58)<=Indicators!$L$56,2,1))))))) | L58: =IF(Indicators!$D$56="C0","",IF(K58<>"",K58,IF(J58<>"",J58,""))) | O58: =IF(N58="","",IF(N58<($L$5-H58),"STALE",""))
B59: 5.6 | C59: Farmer-to-digital-extension-worker ratio | D59: C4 | E59: Anchored capability rubric | F59: N/A | H59: 2 | J59: =IF(I59="","",IF(Indicators!$H$57<>"Quantitative threshold","",IF(Indicators!$I$57="Higher",IF(N(I59)>=Indicators!$O$57,5,IF(N(I59)>=Indicators!$N$57,4,IF(N(I59)>=Indicators!$M$57,3,IF(N(I59)>=Indicators!$L$57,2,1)))),IF(N(I59)<=Indicators!$O$57,5,IF(N(I59)<=Indicators!$N$57,4,IF(N(I59)<=Indicators!$M$57,3,IF(N(I59)<=Indicators!$L$57,2,1))))))) | L59: =IF(Indicators!$D$57="C0","",IF(K59<>"",K59,IF(J59<>"",J59,""))) | O59: =IF(N59="","",IF(N59<($L$5-H59),"STALE",""))
B60: 5.7 | C60: Dedicated digital/AI units in Ministry of Agriculture | D60: C4 | E60: Anchored capability rubric | F60: N/A | G60: YES | H60: 2 | J60: =IF(I60="","",IF(Indicators!$H$58<>"Quantitative threshold","",IF(Indicators!$I$58="Higher",IF(N(I60)>=Indicators!$O$58,5,IF(N(I60)>=Indicators!$N$58,4,IF(N(I60)>=Indicators!$M$58,3,IF(N(I60)>=Indicators!$L$58,2,1)))),IF(N(I60)<=Indicators!$O$58,5,IF(N(I60)<=Indicators!$N$58,4,IF(N(I60)<=Indicators!$M$58,3,IF(N(I60)<=Indicators!$L$58,2,1))))))) | L60: =IF(Indicators!$D$58="C0","",IF(K60<>"",K60,IF(J60<>"",J60,""))) | O60: =IF(N60="","",IF(N60<($L$5-H60),"STALE",""))
B61: 5.8 | C61: University programs in agtech/digital agriculture | D61: C4 | E61: Anchored capability rubric | F61: N/A | H61: 2 | J61: =IF(I61="","",IF(Indicators!$H$59<>"Quantitative threshold","",IF(Indicators!$I$59="Higher",IF(N(I61)>=Indicators!$O$59,5,IF(N(I61)>=Indicators!$N$59,4,IF(N(I61)>=Indicators!$M$59,3,IF(N(I61)>=Indicators!$L$59,2,1)))),IF(N(I61)<=Indicators!$O$59,5,IF(N(I61)<=Indicators!$N$59,4,IF(N(I61)<=Indicators!$M$59,3,IF(N(I61)<=Indicators!$L$59,2,1))))))) | L61: =IF(Indicators!$D$59="C0","",IF(K61<>"",K61,IF(J61<>"",J61,""))) | O61: =IF(N61="","",IF(N61<($L$5-H61),"STALE",""))
B62: 5.9 | C62: Data science/AI training programs for agriculture | D62: C4 | E62: Anchored capability rubric | F62: N/A | H62: 2 | J62: =IF(I62="","",IF(Indicators!$H$60<>"Quantitative threshold","",IF(Indicators!$I$60="Higher",IF(N(I62)>=Indicators!$O$60,5,IF(N(I62)>=Indicators!$N$60,4,IF(N(I62)>=Indicators!$M$60,3,IF(N(I62)>=Indicators!$L$60,2,1)))),IF(N(I62)<=Indicators!$O$60,5,IF(N(I62)<=Indicators!$N$60,4,IF(N(I62)<=Indicators!$M$60,3,IF(N(I62)<=Indicators!$L$60,2,1))))))) | L62: =IF(Indicators!$D$60="C0","",IF(K62<>"",K62,IF(J62<>"",J62,""))) | O62: =IF(N62="","",IF(N62<($L$5-H62),"STALE",""))
B63: 5.10 | C63: Digital skills training reach (% of farmer population per year) | D63: C4 | E63: Quantitative threshold | F63: Higher | H63: 2 | J63: =IF(I63="","",IF(Indicators!$H$61<>"Quantitative threshold","",IF(Indicators!$I$61="Higher",IF(N(I63)>=Indicators!$O$61,5,IF(N(I63)>=Indicators!$N$61,4,IF(N(I63)>=Indicators!$M$61,3,IF(N(I63)>=Indicators!$L$61,2,1)))),IF(N(I63)<=Indicators!$O$61,5,IF(N(I63)<=Indicators!$N$61,4,IF(N(I63)<=Indicators!$M$61,3,IF(N(I63)<=Indicators!$L$61,2,1))))))) | L63: =IF(Indicators!$D$61="C0","",IF(K63<>"",K63,IF(J63<>"",J63,""))) | O63: =IF(N63="","",IF(N63<($L$5-H63),"STALE",""))
B64: 5.11 | C64: Institutional digital maturity of key agricultural agencies | D64: C4 | E64: Anchored capability rubric | F64: N/A | H64: 2 | J64: =IF(I64="","",IF(Indicators!$H$62<>"Quantitative threshold","",IF(Indicators!$I$62="Higher",IF(N(I64)>=Indicators!$O$62,5,IF(N(I64)>=Indicators!$N$62,4,IF(N(I64)>=Indicators!$M$62,3,IF(N(I64)>=Indicators!$L$62,2,1)))),IF(N(I64)<=Indicators!$O$62,5,IF(N(I64)<=Indicators!$N$62,4,IF(N(I64)<=Indicators!$M$62,3,IF(N(I64)<=Indicators!$L$62,2,1))))))) | L64: =IF(Indicators!$D$62="C0","",IF(K64<>"",K64,IF(J64<>"",J64,""))) | O64: =IF(N64="","",IF(N64<($L$5-H64),"STALE",""))
B65: 5.12 | C65: Gender balance in digital agriculture workforce | D65: C4 | E65: Quantitative threshold | F65: Higher | H65: 2 | J65: =IF(I65="","",IF(Indicators!$H$63<>"Quantitative threshold","",IF(Indicators!$I$63="Higher",IF(N(I65)>=Indicators!$O$63,5,IF(N(I65)>=Indicators!$N$63,4,IF(N(I65)>=Indicators!$M$63,3,IF(N(I65)>=Indicators!$L$63,2,1)))),IF(N(I65)<=Indicators!$O$63,5,IF(N(I65)<=Indicators!$N$63,4,IF(N(I65)<=Indicators!$M$63,3,IF(N(I65)<=Indicators!$L$63,2,1))))))) | L65: =IF(Indicators!$D$63="C0","",IF(K65<>"",K65,IF(J65<>"",J65,""))) | O65: =IF(N65="","",IF(N65<($L$5-H65),"STALE",""))
B66: 5.13 | C66: Gender parity in extension services (% female extension officers) | D66: C4 | E66: Quantitative threshold | F66: Higher | H66: 3 | J66: =IF(I66="","",IF(Indicators!$H$64<>"Quantitative threshold","",IF(Indicators!$I$64="Higher",IF(N(I66)>=Indicators!$O$64,5,IF(N(I66)>=Indicators!$N$64,4,IF(N(I66)>=Indicators!$M$64,3,IF(N(I66)>=Indicators!$L$64,2,1)))),IF(N(I66)<=Indicators!$O$64,5,IF(N(I66)<=Indicators!$N$64,4,IF(N(I66)<=Indicators!$M$64,3,IF(N(I66)<=Indicators!$L$64,2,1))))))) | L66: =IF(Indicators!$D$64="C0","",IF(K66<>"",K66,IF(J66<>"",J66,""))) | O66: =IF(N66="","",IF(N66<($L$5-H66),"STALE",""))
B67: 6.1 | C67: Global Innovation Index (GII) score | D67: E1 | E67: Quantitative threshold | F67: Higher | H67: 3 | J67: =IF(I67="","",IF(Indicators!$H$65<>"Quantitative threshold","",IF(Indicators!$I$65="Higher",IF(N(I67)>=Indicators!$O$65,5,IF(N(I67)>=Indicators!$N$65,4,IF(N(I67)>=Indicators!$M$65,3,IF(N(I67)>=Indicators!$L$65,2,1)))),IF(N(I67)<=Indicators!$O$65,5,IF(N(I67)<=Indicators!$N$65,4,IF(N(I67)<=Indicators!$M$65,3,IF(N(I67)<=Indicators!$L$65,2,1))))))) | L67: =IF(Indicators!$D$65="C0","",IF(K67<>"",K67,IF(J67<>"",J67,""))) | O67: =IF(N67="","",IF(N67<($L$5-H67),"STALE",""))
B68: 6.2 | C68: R&D expenditure (% of GDP) | D68: E1 | E68: Quantitative threshold | F68: Higher | H68: 3 | J68: =IF(I68="","",IF(Indicators!$H$66<>"Quantitative threshold","",IF(Indicators!$I$66="Higher",IF(N(I68)>=Indicators!$O$66,5,IF(N(I68)>=Indicators!$N$66,4,IF(N(I68)>=Indicators!$M$66,3,IF(N(I68)>=Indicators!$L$66,2,1)))),IF(N(I68)<=Indicators!$O$66,5,IF(N(I68)<=Indicators!$N$66,4,IF(N(I68)<=Indicators!$M$66,3,IF(N(I68)<=Indicators!$L$66,2,1))))))) | L68: =IF(Indicators!$D$66="C0","",IF(K68<>"",K68,IF(J68<>"",J68,""))) | O68: =IF(N68="","",IF(N68<($L$5-H68),"STALE",""))
B69: 6.3 | C69: Business Ready (B-READY) score | D69: E1 | E69: Quantitative threshold | F69: Higher | H69: 3 | J69: =IF(I69="","",IF(Indicators!$H$67<>"Quantitative threshold","",IF(Indicators!$I$67="Higher",IF(N(I69)>=Indicators!$O$67,5,IF(N(I69)>=Indicators!$N$67,4,IF(N(I69)>=Indicators!$M$67,3,IF(N(I69)>=Indicators!$L$67,2,1)))),IF(N(I69)<=Indicators!$O$67,5,IF(N(I69)<=Indicators!$N$67,4,IF(N(I69)<=Indicators!$M$67,3,IF(N(I69)<=Indicators!$L$67,2,1))))))) | L69: =IF(Indicators!$D$67="C0","",IF(K69<>"",K69,IF(J69<>"",J69,""))) | O69: =IF(N69="","",IF(N69<($L$5-H69),"STALE",""))
B70: 6.4 | C70: Active agtech startups/firms | D70: E1 | E70: Anchored capability rubric | F70: N/A | H70: 2 | J70: =IF(I70="","",IF(Indicators!$H$68<>"Quantitative threshold","",IF(Indicators!$I$68="Higher",IF(N(I70)>=Indicators!$O$68,5,IF(N(I70)>=Indicators!$N$68,4,IF(N(I70)>=Indicators!$M$68,3,IF(N(I70)>=Indicators!$L$68,2,1)))),IF(N(I70)<=Indicators!$O$68,5,IF(N(I70)<=Indicators!$N$68,4,IF(N(I70)<=Indicators!$M$68,3,IF(N(I70)<=Indicators!$L$68,2,1))))))) | L70: =IF(Indicators!$D$68="C0","",IF(K70<>"",K70,IF(J70<>"",J70,""))) | O70: =IF(N70="","",IF(N70<($L$5-H70),"STALE",""))
B71: 6.5 | C71: Venture capital/investment in agtech (annual USD) | D71: E1 | E71: Anchored capability rubric | F71: N/A | H71: 2 | J71: =IF(I71="","",IF(Indicators!$H$69<>"Quantitative threshold","",IF(Indicators!$I$69="Higher",IF(N(I71)>=Indicators!$O$69,5,IF(N(I71)>=Indicators!$N$69,4,IF(N(I71)>=Indicators!$M$69,3,IF(N(I71)>=Indicators!$L$69,2,1)))),IF(N(I71)<=Indicators!$O$69,5,IF(N(I71)<=Indicators!$N$69,4,IF(N(I71)<=Indicators!$M$69,3,IF(N(I71)<=Indicators!$L$69,2,1))))))) | L71: =IF(Indicators!$D$69="C0","",IF(K71<>"",K71,IF(J71<>"",J71,""))) | O71: =IF(N71="","",IF(N71<($L$5-H71),"STALE",""))
B72: 6.6 | C72: Agtech accelerators/incubators | D72: E1 | E72: Anchored capability rubric | F72: N/A | H72: 2 | J72: =IF(I72="","",IF(Indicators!$H$70<>"Quantitative threshold","",IF(Indicators!$I$70="Higher",IF(N(I72)>=Indicators!$O$70,5,IF(N(I72)>=Indicators!$N$70,4,IF(N(I72)>=Indicators!$M$70,3,IF(N(I72)>=Indicators!$L$70,2,1)))),IF(N(I72)<=Indicators!$O$70,5,IF(N(I72)<=Indicators!$N$70,4,IF(N(I72)<=Indicators!$M$70,3,IF(N(I72)<=Indicators!$L$70,2,1))))))) | L72: =IF(Indicators!$D$70="C0","",IF(K72<>"",K72,IF(J72<>"",J72,""))) | O72: =IF(N72="","",IF(N72<($L$5-H72),"STALE",""))
B73: 6.7 | C73: Agribusiness firms using AI/ML in operations (%) | D73: E1 | E73: Quantitative threshold | F73: Higher | H73: 2 | J73: =IF(I73="","",IF(Indicators!$H$71<>"Quantitative threshold","",IF(Indicators!$I$71="Higher",IF(N(I73)>=Indicators!$O$71,5,IF(N(I73)>=Indicators!$N$71,4,IF(N(I73)>=Indicators!$M$71,3,IF(N(I73)>=Indicators!$L$71,2,1)))),IF(N(I73)<=Indicators!$O$71,5,IF(N(I73)<=Indicators!$N$71,4,IF(N(I73)<=Indicators!$M$71,3,IF(N(I73)<=Indicators!$L$71,2,1))))))) | L73: =IF(Indicators!$D$71="C0","",IF(K73<>"",K73,IF(J73<>"",J73,""))) | O73: =IF(N73="","",IF(N73<($L$5-H73),"STALE",""))
B74: 6.8 | C74: Regulatory sandboxes for agtech/fintech | D74: E1 | E74: Anchored capability rubric | F74: N/A | H74: 2 | J74: =IF(I74="","",IF(Indicators!$H$72<>"Quantitative threshold","",IF(Indicators!$I$72="Higher",IF(N(I74)>=Indicators!$O$72,5,IF(N(I74)>=Indicators!$N$72,4,IF(N(I74)>=Indicators!$M$72,3,IF(N(I74)>=Indicators!$L$72,2,1)))),IF(N(I74)<=Indicators!$O$72,5,IF(N(I74)<=Indicators!$N$72,4,IF(N(I74)<=Indicators!$M$72,3,IF(N(I74)<=Indicators!$L$72,2,1))))))) | L74: =IF(Indicators!$D$72="C0","",IF(K74<>"",K74,IF(J74<>"",J74,""))) | O74: =IF(N74="","",IF(N74<($L$5-H74),"STALE",""))
B75: 6.9 | C75: Public-private partnerships in digital agriculture | D75: E1 | E75: Anchored capability rubric | F75: N/A | H75: 2 | J75: =IF(I75="","",IF(Indicators!$H$73<>"Quantitative threshold","",IF(Indicators!$I$73="Higher",IF(N(I75)>=Indicators!$O$73,5,IF(N(I75)>=Indicators!$N$73,4,IF(N(I75)>=Indicators!$M$73,3,IF(N(I75)>=Indicators!$L$73,2,1)))),IF(N(I75)<=Indicators!$O$73,5,IF(N(I75)<=Indicators!$N$73,4,IF(N(I75)<=Indicators!$M$73,3,IF(N(I75)<=Indicators!$L$73,2,1))))))) | L75: =IF(Indicators!$D$73="C0","",IF(K75<>"",K75,IF(J75<>"",J75,""))) | O75: =IF(N75="","",IF(N75<($L$5-H75),"STALE",""))
B76: 6.10 | C76: Government grants/funding for agtech innovation (annual USD) | D76: E1 | E76: Anchored capability rubric | F76: N/A | H76: 2 | J76: =IF(I76="","",IF(Indicators!$H$74<>"Quantitative threshold","",IF(Indicators!$I$74="Higher",IF(N(I76)>=Indicators!$O$74,5,IF(N(I76)>=Indicators!$N$74,4,IF(N(I76)>=Indicators!$M$74,3,IF(N(I76)>=Indicators!$L$74,2,1)))),IF(N(I76)<=Indicators!$O$74,5,IF(N(I76)<=Indicators!$N$74,4,IF(N(I76)<=Indicators!$M$74,3,IF(N(I76)<=Indicators!$L$74,2,1))))))) | L76: =IF(Indicators!$D$74="C0","",IF(K76<>"",K76,IF(J76<>"",J76,""))) | O76: =IF(N76="","",IF(N76<($L$5-H76),"STALE",""))
B77: 6.11 | C77: Digital financial services platforms for agriculture | D77: E1 | E77: Anchored capability rubric | F77: N/A | H77: 2 | J77: =IF(I77="","",IF(Indicators!$H$75<>"Quantitative threshold","",IF(Indicators!$I$75="Higher",IF(N(I77)>=Indicators!$O$75,5,IF(N(I77)>=Indicators!$N$75,4,IF(N(I77)>=Indicators!$M$75,3,IF(N(I77)>=Indicators!$L$75,2,1)))),IF(N(I77)<=Indicators!$O$75,5,IF(N(I77)<=Indicators!$N$75,4,IF(N(I77)<=Indicators!$M$75,3,IF(N(I77)<=Indicators!$L$75,2,1))))))) | L77: =IF(Indicators!$D$75="C0","",IF(K77<>"",K77,IF(J77<>"",J77,""))) | O77: =IF(N77="","",IF(N77<($L$5-H77),"STALE",""))
B78: 6.12 | C78: Digital public goods adopted in agriculture | D78: E1 | E78: Anchored capability rubric | F78: N/A | H78: 2 | J78: =IF(I78="","",IF(Indicators!$H$76<>"Quantitative threshold","",IF(Indicators!$I$76="Higher",IF(N(I78)>=Indicators!$O$76,5,IF(N(I78)>=Indicators!$N$76,4,IF(N(I78)>=Indicators!$M$76,3,IF(N(I78)>=Indicators!$L$76,2,1)))),IF(N(I78)<=Indicators!$O$76,5,IF(N(I78)<=Indicators!$N$76,4,IF(N(I78)<=Indicators!$M$76,3,IF(N(I78)<=Indicators!$L$76,2,1))))))) | L78: =IF(Indicators!$D$76="C0","",IF(K78<>"",K78,IF(J78<>"",J78,""))) | O78: =IF(N78="","",IF(N78<($L$5-H78),"STALE",""))
B79: 6.13 | C79: SME access to digital agriculture tools/platforms (%) | D79: E1 | E79: Quantitative threshold | F79: Higher | H79: 2 | J79: =IF(I79="","",IF(Indicators!$H$77<>"Quantitative threshold","",IF(Indicators!$I$77="Higher",IF(N(I79)>=Indicators!$O$77,5,IF(N(I79)>=Indicators!$N$77,4,IF(N(I79)>=Indicators!$M$77,3,IF(N(I79)>=Indicators!$L$77,2,1)))),IF(N(I79)<=Indicators!$O$77,5,IF(N(I79)<=Indicators!$N$77,4,IF(N(I79)<=Indicators!$M$77,3,IF(N(I79)<=Indicators!$L$77,2,1))))))) | L79: =IF(Indicators!$D$77="C0","",IF(K79<>"",K79,IF(J79<>"",J79,""))) | O79: =IF(N79="","",IF(N79<($L$5-H79),"STALE",""))
B80: 6.14 | C80: Agri-fintech / mobile-money rails accessible to smallholders | D80: E1 | E80: Anchored capability rubric | F80: N/A | G80: YES | H80: 2 | J80: =IF(I80="","",IF(Indicators!$H$78<>"Quantitative threshold","",IF(Indicators!$I$78="Higher",IF(N(I80)>=Indicators!$O$78,5,IF(N(I80)>=Indicators!$N$78,4,IF(N(I80)>=Indicators!$M$78,3,IF(N(I80)>=Indicators!$L$78,2,1)))),IF(N(I80)<=Indicators!$O$78,5,IF(N(I80)<=Indicators!$N$78,4,IF(N(I80)<=Indicators!$M$78,3,IF(N(I80)<=Indicators!$L$78,2,1))))))) | L80: =IF(Indicators!$D$78="C0","",IF(K80<>"",K80,IF(J80<>"",J80,""))) | O80: =IF(N80="","",IF(N80<($L$5-H80),"STALE",""))
B81: 7.1 | C81: AI-related scientific publications per million population | D81: E2 | E81: Quantitative threshold | F81: Higher | H81: 3 | J81: =IF(I81="","",IF(Indicators!$H$79<>"Quantitative threshold","",IF(Indicators!$I$79="Higher",IF(N(I81)>=Indicators!$O$79,5,IF(N(I81)>=Indicators!$N$79,4,IF(N(I81)>=Indicators!$M$79,3,IF(N(I81)>=Indicators!$L$79,2,1)))),IF(N(I81)<=Indicators!$O$79,5,IF(N(I81)<=Indicators!$N$79,4,IF(N(I81)<=Indicators!$M$79,3,IF(N(I81)<=Indicators!$L$79,2,1))))))) | L81: =IF(Indicators!$D$79="C0","",IF(K81<>"",K81,IF(J81<>"",J81,""))) | O81: =IF(N81="","",IF(N81<($L$5-H81),"STALE",""))
B82: 7.2 | C82: AI systems deployed in public agricultural sector | D82: E2 | E82: Anchored capability rubric | F82: N/A | H82: 2 | J82: =IF(I82="","",IF(Indicators!$H$80<>"Quantitative threshold","",IF(Indicators!$I$80="Higher",IF(N(I82)>=Indicators!$O$80,5,IF(N(I82)>=Indicators!$N$80,4,IF(N(I82)>=Indicators!$M$80,3,IF(N(I82)>=Indicators!$L$80,2,1)))),IF(N(I82)<=Indicators!$O$80,5,IF(N(I82)<=Indicators!$N$80,4,IF(N(I82)<=Indicators!$M$80,3,IF(N(I82)<=Indicators!$L$80,2,1))))))) | L82: =IF(Indicators!$D$80="C0","",IF(K82<>"",K82,IF(J82<>"",J82,""))) | O82: =IF(N82="","",IF(N82<($L$5-H82),"STALE",""))
B83: 7.3 | C83: AI-enabled advisory services (farmer reach %) | D83: E2 | E83: Quantitative threshold | F83: Higher | H83: 2 | J83: =IF(I83="","",IF(Indicators!$H$81<>"Quantitative threshold","",IF(Indicators!$I$81="Higher",IF(N(I83)>=Indicators!$O$81,5,IF(N(I83)>=Indicators!$N$81,4,IF(N(I83)>=Indicators!$M$81,3,IF(N(I83)>=Indicators!$L$81,2,1)))),IF(N(I83)<=Indicators!$O$81,5,IF(N(I83)<=Indicators!$N$81,4,IF(N(I83)<=Indicators!$M$81,3,IF(N(I83)<=Indicators!$L$81,2,1))))))) | L83: =IF(Indicators!$D$81="C0","",IF(K83<>"",K83,IF(J83<>"",J83,""))) | O83: =IF(N83="","",IF(N83<($L$5-H83),"STALE",""))
B84: 7.4 | C84: AI for crop/pest/disease detection and monitoring | D84: E2 | E84: Quantitative threshold | F84: Higher | H84: 2 | J84: =IF(I84="","",IF(Indicators!$H$82<>"Quantitative threshold","",IF(Indicators!$I$82="Higher",IF(N(I84)>=Indicators!$O$82,5,IF(N(I84)>=Indicators!$N$82,4,IF(N(I84)>=Indicators!$M$82,3,IF(N(I84)>=Indicators!$L$82,2,1)))),IF(N(I84)<=Indicators!$O$82,5,IF(N(I84)<=Indicators!$N$82,4,IF(N(I84)<=Indicators!$M$82,3,IF(N(I84)<=Indicators!$L$82,2,1))))))) | L84: =IF(Indicators!$D$82="C0","",IF(K84<>"",K84,IF(J84<>"",J84,""))) | O84: =IF(N84="","",IF(N84<($L$5-H84),"STALE",""))
B85: 7.5 | C85: AI in agricultural finance (credit scoring, insurance) | D85: E2 | E85: Quantitative threshold | F85: Higher | H85: 2 | J85: =IF(I85="","",IF(Indicators!$H$83<>"Quantitative threshold","",IF(Indicators!$I$83="Higher",IF(N(I85)>=Indicators!$O$83,5,IF(N(I85)>=Indicators!$N$83,4,IF(N(I85)>=Indicators!$M$83,3,IF(N(I85)>=Indicators!$L$83,2,1)))),IF(N(I85)<=Indicators!$O$83,5,IF(N(I85)<=Indicators!$N$83,4,IF(N(I85)<=Indicators!$M$83,3,IF(N(I85)<=Indicators!$L$83,2,1))))))) | L85: =IF(Indicators!$D$83="C0","",IF(K85<>"",K85,IF(J85<>"",J85,""))) | O85: =IF(N85="","",IF(N85<($L$5-H85),"STALE",""))
B86: 7.6 | C86: AI for supply chain optimization and traceability | D86: E2 | E86: Quantitative threshold | F86: Higher | H86: 2 | J86: =IF(I86="","",IF(Indicators!$H$84<>"Quantitative threshold","",IF(Indicators!$I$84="Higher",IF(N(I86)>=Indicators!$O$84,5,IF(N(I86)>=Indicators!$N$84,4,IF(N(I86)>=Indicators!$M$84,3,IF(N(I86)>=Indicators!$L$84,2,1)))),IF(N(I86)<=Indicators!$O$84,5,IF(N(I86)<=Indicators!$N$84,4,IF(N(I86)<=Indicators!$M$84,3,IF(N(I86)<=Indicators!$L$84,2,1))))))) | L86: =IF(Indicators!$D$84="C0","",IF(K86<>"",K86,IF(J86<>"",J86,""))) | O86: =IF(N86="","",IF(N86<($L$5-H86),"STALE",""))
B87: 7.7 | C87: AI for climate forecasting and agricultural risk management | D87: E2 | E87: Quantitative threshold | F87: Higher | H87: 2 | J87: =IF(I87="","",IF(Indicators!$H$85<>"Quantitative threshold","",IF(Indicators!$I$85="Higher",IF(N(I87)>=Indicators!$O$85,5,IF(N(I87)>=Indicators!$N$85,4,IF(N(I87)>=Indicators!$M$85,3,IF(N(I87)>=Indicators!$L$85,2,1)))),IF(N(I87)<=Indicators!$O$85,5,IF(N(I87)<=Indicators!$N$85,4,IF(N(I87)<=Indicators!$M$85,3,IF(N(I87)<=Indicators!$L$85,2,1))))))) | L87: =IF(Indicators!$D$85="C0","",IF(K87<>"",K87,IF(J87<>"",J87,""))) | O87: =IF(N87="","",IF(N87<($L$5-H87),"STALE",""))
B88: 7.8 | C88: AI talent in agriculture sector | D88: E2 | E88: Anchored capability rubric | F88: N/A | H88: 2 | J88: =IF(I88="","",IF(Indicators!$H$86<>"Quantitative threshold","",IF(Indicators!$I$86="Higher",IF(N(I88)>=Indicators!$O$86,5,IF(N(I88)>=Indicators!$N$86,4,IF(N(I88)>=Indicators!$M$86,3,IF(N(I88)>=Indicators!$L$86,2,1)))),IF(N(I88)<=Indicators!$O$86,5,IF(N(I88)<=Indicators!$N$86,4,IF(N(I88)<=Indicators!$M$86,3,IF(N(I88)<=Indicators!$L$86,2,1))))))) | L88: =IF(Indicators!$D$86="C0","",IF(K88<>"",K88,IF(J88<>"",J88,""))) | O88: =IF(N88="","",IF(N88<($L$5-H88),"STALE",""))
B89: 7.9 | C89: Cybersecurity of agricultural digital systems | D89: E2 | E89: Anchored capability rubric | F89: N/A | G89: YES | H89: 2 | J89: =IF(I89="","",IF(Indicators!$H$87<>"Quantitative threshold","",IF(Indicators!$I$87="Higher",IF(N(I89)>=Indicators!$O$87,5,IF(N(I89)>=Indicators!$N$87,4,IF(N(I89)>=Indicators!$M$87,3,IF(N(I89)>=Indicators!$L$87,2,1)))),IF(N(I89)<=Indicators!$O$87,5,IF(N(I89)<=Indicators!$N$87,4,IF(N(I89)<=Indicators!$M$87,3,IF(N(I89)<=Indicators!$L$87,2,1))))))) | L89: =IF(Indicators!$D$87="C0","",IF(K89<>"",K89,IF(J89<>"",J89,""))) | O89: =IF(N89="","",IF(N89<($L$5-H89),"STALE",""))
B90: 7.10 | C90: Explainability and transparency of AI systems in agriculture | D90: E2 | E90: Anchored capability rubric | F90: N/A | H90: 2 | J90: =IF(I90="","",IF(Indicators!$H$88<>"Quantitative threshold","",IF(Indicators!$I$88="Higher",IF(N(I90)>=Indicators!$O$88,5,IF(N(I90)>=Indicators!$N$88,4,IF(N(I90)>=Indicators!$M$88,3,IF(N(I90)>=Indicators!$L$88,2,1)))),IF(N(I90)<=Indicators!$O$88,5,IF(N(I90)<=Indicators!$N$88,4,IF(N(I90)<=Indicators!$M$88,3,IF(N(I90)<=Indicators!$L$88,2,1))))))) | L90: =IF(Indicators!$D$88="C0","",IF(K90<>"",K90,IF(J90<>"",J90,""))) | O90: =IF(N90="","",IF(N90<($L$5-H90),"STALE",""))
B91: 7.11 | C91: Bias monitoring and mitigation in agricultural AI | D91: E2 | E91: Anchored capability rubric | F91: N/A | H91: 2 | J91: =IF(I91="","",IF(Indicators!$H$89<>"Quantitative threshold","",IF(Indicators!$I$89="Higher",IF(N(I91)>=Indicators!$O$89,5,IF(N(I91)>=Indicators!$N$89,4,IF(N(I91)>=Indicators!$M$89,3,IF(N(I91)>=Indicators!$L$89,2,1)))),IF(N(I91)<=Indicators!$O$89,5,IF(N(I91)<=Indicators!$N$89,4,IF(N(I91)<=Indicators!$M$89,3,IF(N(I91)<=Indicators!$L$89,2,1))))))) | L91: =IF(Indicators!$D$89="C0","",IF(K91<>"",K91,IF(J91<>"",J91,""))) | O91: =IF(N91="","",IF(N91<($L$5-H91),"STALE",""))
B92: 7.12 | C92: Farmer consent and data rights in AI systems | D92: E2 | E92: Anchored capability rubric | F92: N/A | G92: YES | H92: 2 | J92: =IF(I92="","",IF(Indicators!$H$90<>"Quantitative threshold","",IF(Indicators!$I$90="Higher",IF(N(I92)>=Indicators!$O$90,5,IF(N(I92)>=Indicators!$N$90,4,IF(N(I92)>=Indicators!$M$90,3,IF(N(I92)>=Indicators!$L$90,2,1)))),IF(N(I92)<=Indicators!$O$90,5,IF(N(I92)<=Indicators!$N$90,4,IF(N(I92)<=Indicators!$M$90,3,IF(N(I92)<=Indicators!$L$90,2,1))))))) | L92: =IF(Indicators!$D$90="C0","",IF(K92<>"",K92,IF(J92<>"",J92,""))) | O92: =IF(N92="","",IF(N92<($L$5-H92),"STALE",""))
B93: 8.1 | C93: Prevalence of undernourishment (% of population) | D93: O1 | E93: Quantitative threshold | F93: Lower | H93: 3 | J93: =IF(I93="","",IF(Indicators!$H$91<>"Quantitative threshold","",IF(Indicators!$I$91="Higher",IF(N(I93)>=Indicators!$O$91,5,IF(N(I93)>=Indicators!$N$91,4,IF(N(I93)>=Indicators!$M$91,3,IF(N(I93)>=Indicators!$L$91,2,1)))),IF(N(I93)<=Indicators!$O$91,5,IF(N(I93)<=Indicators!$N$91,4,IF(N(I93)<=Indicators!$M$91,3,IF(N(I93)<=Indicators!$L$91,2,1))))))) | L93: =IF(Indicators!$D$91="C0","",IF(K93<>"",K93,IF(J93<>"",J93,""))) | O93: =IF(N93="","",IF(N93<($L$5-H93),"STALE",""))
B94: 8.2 | C94: Account ownership, female (% age 15+) | D94: O1 | E94: Quantitative threshold | F94: Higher | H94: 3 | J94: =IF(I94="","",IF(Indicators!$H$92<>"Quantitative threshold","",IF(Indicators!$I$92="Higher",IF(N(I94)>=Indicators!$O$92,5,IF(N(I94)>=Indicators!$N$92,4,IF(N(I94)>=Indicators!$M$92,3,IF(N(I94)>=Indicators!$L$92,2,1)))),IF(N(I94)<=Indicators!$O$92,5,IF(N(I94)<=Indicators!$N$92,4,IF(N(I94)<=Indicators!$M$92,3,IF(N(I94)<=Indicators!$L$92,2,1))))))) | L94: =IF(Indicators!$D$92="C0","",IF(K94<>"",K94,IF(J94<>"",J94,""))) | O94: =IF(N94="","",IF(N94<($L$5-H94),"STALE",""))
B95: 8.3 | C95: Gender gap in account ownership (male % minus female %) | D95: O1 | E95: Quantitative threshold | F95: Lower | H95: 3 | J95: =IF(I95="","",IF(Indicators!$H$93<>"Quantitative threshold","",IF(Indicators!$I$93="Higher",IF(N(I95)>=Indicators!$O$93,5,IF(N(I95)>=Indicators!$N$93,4,IF(N(I95)>=Indicators!$M$93,3,IF(N(I95)>=Indicators!$L$93,2,1)))),IF(N(I95)<=Indicators!$O$93,5,IF(N(I95)<=Indicators!$N$93,4,IF(N(I95)<=Indicators!$M$93,3,IF(N(I95)<=Indicators!$L$93,2,1))))))) | L95: =IF(Indicators!$D$93="C0","",IF(K95<>"",K95,IF(J95<>"",J95,""))) | O95: =IF(N95="","",IF(N95<($L$5-H95),"STALE",""))
B96: 8.4 | C96: Mobile money account (% age 15+) | D96: O1 | E96: Quantitative threshold | F96: Higher | H96: 3 | J96: =IF(I96="","",IF(Indicators!$H$94<>"Quantitative threshold","",IF(Indicators!$I$94="Higher",IF(N(I96)>=Indicators!$O$94,5,IF(N(I96)>=Indicators!$N$94,4,IF(N(I96)>=Indicators!$M$94,3,IF(N(I96)>=Indicators!$L$94,2,1)))),IF(N(I96)<=Indicators!$O$94,5,IF(N(I96)<=Indicators!$N$94,4,IF(N(I96)<=Indicators!$M$94,3,IF(N(I96)<=Indicators!$L$94,2,1))))))) | L96: =IF(Indicators!$D$94="C0","",IF(K96<>"",K96,IF(J96<>"",J96,""))) | O96: =IF(N96="","",IF(N96<($L$5-H96),"STALE",""))
B97: 8.5 | C97: Women who own land (% of agricultural holders) | D97: O1 | E97: Quantitative threshold | F97: Higher | H97: 3 | J97: =IF(I97="","",IF(Indicators!$H$95<>"Quantitative threshold","",IF(Indicators!$I$95="Higher",IF(N(I97)>=Indicators!$O$95,5,IF(N(I97)>=Indicators!$N$95,4,IF(N(I97)>=Indicators!$M$95,3,IF(N(I97)>=Indicators!$L$95,2,1)))),IF(N(I97)<=Indicators!$O$95,5,IF(N(I97)<=Indicators!$N$95,4,IF(N(I97)<=Indicators!$M$95,3,IF(N(I97)<=Indicators!$L$95,2,1))))))) | L97: =IF(Indicators!$D$95="C0","",IF(K97<>"",K97,IF(J97<>"",J97,""))) | O97: =IF(N97="","",IF(N97<($L$5-H97),"STALE",""))
B98: 8.6 | C98: Gender gap in mobile phone ownership (percentage points) | D98: O1 | E98: Quantitative threshold | F98: Lower | H98: 3 | J98: =IF(I98="","",IF(Indicators!$H$96<>"Quantitative threshold","",IF(Indicators!$I$96="Higher",IF(N(I98)>=Indicators!$O$96,5,IF(N(I98)>=Indicators!$N$96,4,IF(N(I98)>=Indicators!$M$96,3,IF(N(I98)>=Indicators!$L$96,2,1)))),IF(N(I98)<=Indicators!$O$96,5,IF(N(I98)<=Indicators!$N$96,4,IF(N(I98)<=Indicators!$M$96,3,IF(N(I98)<=Indicators!$L$96,2,1))))))) | L98: =IF(Indicators!$D$96="C0","",IF(K98<>"",K98,IF(J98<>"",J98,""))) | O98: =IF(N98="","",IF(N98<($L$5-H98),"STALE",""))
B99: 8.7 | C99: Women using digital agricultural services (% of women farmers) | D99: O1 | E99: Quantitative threshold | F99: Higher | H99: 3 | J99: =IF(I99="","",IF(Indicators!$H$97<>"Quantitative threshold","",IF(Indicators!$I$97="Higher",IF(N(I99)>=Indicators!$O$97,5,IF(N(I99)>=Indicators!$N$97,4,IF(N(I99)>=Indicators!$M$97,3,IF(N(I99)>=Indicators!$L$97,2,1)))),IF(N(I99)<=Indicators!$O$97,5,IF(N(I99)<=Indicators!$N$97,4,IF(N(I99)<=Indicators!$M$97,3,IF(N(I99)<=Indicators!$L$97,2,1))))))) | L99: =IF(Indicators!$D$97="C0","",IF(K99<>"",K99,IF(J99<>"",J99,""))) | O99: =IF(N99="","",IF(N99<($L$5-H99),"STALE",""))
B100: 8.8 | C100: Youth (under 35) using digital agricultural services (%) | D100: O1 | E100: Quantitative threshold | F100: Higher | H100: 3 | J100: =IF(I100="","",IF(Indicators!$H$98<>"Quantitative threshold","",IF(Indicators!$I$98="Higher",IF(N(I100)>=Indicators!$O$98,5,IF(N(I100)>=Indicators!$N$98,4,IF(N(I100)>=Indicators!$M$98,3,IF(N(I100)>=Indicators!$L$98,2,1)))),IF(N(I100)<=Indicators!$O$98,5,IF(N(I100)<=Indicators!$N$98,4,IF(N(I100)<=Indicators!$M$98,3,IF(N(I100)<=Indicators!$L$98,2,1))))))) | L100: =IF(Indicators!$D$98="C0","",IF(K100<>"",K100,IF(J100<>"",J100,""))) | O100: =IF(N100="","",IF(N100<($L$5-H100),"STALE",""))
B101: 8.9 | C101: Smallholder farmers reached by digital services (% of total) | D101: O1 | E101: Quantitative threshold | F101: Higher | H101: 3 | J101: =IF(I101="","",IF(Indicators!$H$99<>"Quantitative threshold","",IF(Indicators!$I$99="Higher",IF(N(I101)>=Indicators!$O$99,5,IF(N(I101)>=Indicators!$N$99,4,IF(N(I101)>=Indicators!$M$99,3,IF(N(I101)>=Indicators!$L$99,2,1)))),IF(N(I101)<=Indicators!$O$99,5,IF(N(I101)<=Indicators!$N$99,4,IF(N(I101)<=Indicators!$M$99,3,IF(N(I101)<=Indicators!$L$99,2,1))))))) | L101: =IF(Indicators!$D$99="C0","",IF(K101<>"",K101,IF(J101<>"",J101,""))) | O101: =IF(N101="","",IF(N101<($L$5-H101),"STALE",""))
B102: 8.10 | C102: Affordability of digital agriculture services for poorest quintile | D102: O1 | E102: Quantitative threshold | F102: Higher | H102: 3 | J102: =IF(I102="","",IF(Indicators!$H$100<>"Quantitative threshold","",IF(Indicators!$I$100="Higher",IF(N(I102)>=Indicators!$O$100,5,IF(N(I102)>=Indicators!$N$100,4,IF(N(I102)>=Indicators!$M$100,3,IF(N(I102)>=Indicators!$L$100,2,1)))),IF(N(I102)<=Indicators!$O$100,5,IF(N(I102)<=Indicators!$N$100,4,IF(N(I102)<=Indicators!$M$100,3,IF(N(I102)<=Indicators!$L$100,2,1))))))) | L102: =IF(Indicators!$D$100="C0","",IF(K102<>"",K102,IF(J102<>"",J102,""))) | O102: =IF(N102="","",IF(N102<($L$5-H102),"STALE",""))
B103: 8.11 | C103: Services available in local languages (% of major platforms) | D103: O1 | E103: Quantitative threshold | F103: Higher | H103: 3 | J103: =IF(I103="","",IF(Indicators!$H$101<>"Quantitative threshold","",IF(Indicators!$I$101="Higher",IF(N(I103)>=Indicators!$O$101,5,IF(N(I103)>=Indicators!$N$101,4,IF(N(I103)>=Indicators!$M$101,3,IF(N(I103)>=Indicators!$L$101,2,1)))),IF(N(I103)<=Indicators!$O$101,5,IF(N(I103)<=Indicators!$N$101,4,IF(N(I103)<=Indicators!$M$101,3,IF(N(I103)<=Indicators!$L$101,2,1))))))) | L103: =IF(Indicators!$D$101="C0","",IF(K103<>"",K103,IF(J103<>"",J103,""))) | O103: =IF(N103="","",IF(N103<($L$5-H103),"STALE",""))
...

Sheet Indicators
B2: Indicators (102)
B3: Pillar · role · method · thresholds. Read-only reference for scoring sheets.
B5: ID | C5: Indicator | D5: Pillar | E5: Pillar name | F5: Role | G5: Source | H5: Method | I5: Direction | J5: Core gate | K5: Max age (yrs) | L5: L2 | M5: L3 | N5: L4 | O5: L5 | P5: Rubric type
B6: 1.1 | C6: Agriculture value added per worker (constant 2015 USD) | D6: C0 | E6: C0: Agricultural context & need | F6: Context | G6: Global | H6: Context profile (not aggregated) | I6: N/A | K6: 3 | P6: Context only
B7: 1.2 | C7: Cereal yield (kg per hectare) | D7: C0 | E7: C0: Agricultural context & need | F7: Context | G7: Global | H7: Context profile (not aggregated) | I7: N/A | K7: 3 | P7: Context only
B8: 1.3 | C8: Employment in agriculture (% of total employment) | D8: C0 | E8: C0: Agricultural context & need | F8: Context | G8: Global | H8: Context profile (not aggregated) | I8: N/A | K8: 3 | P8: Context only
B9: 1.4 | C9: Food production index (2014-2016 = 100) | D9: C0 | E9: C0: Agricultural context & need | F9: Context | G9: Global | H9: Context profile (not aggregated) | I9: N/A | K9: 3 | P9: Context only
B10: 1.5 | C10: Post-harvest loss rate (%) | D10: C0 | E10: C0: Agricultural context & need | F10: Context | G10: Local | H10: Context profile (not aggregated) | I10: N/A | K10: 2 | P10: Context only
B11: 1.6 | C11: Smallholder access to formal markets (%) | D11: C0 | E11: C0: Agricultural context & need | F11: Context | G11: Local | H11: Context profile (not aggregated) | I11: N/A | K11: 2 | P11: Context only
B12: 1.7 | C12: Agricultural credit access (% of farmers) | D12: C0 | E12: C0: Agricultural context & need | F12: Context | G12: Local | H12: Context profile (not aggregated) | I12: N/A | K12: 2 | P12: Context only
B13: 1.8 | C13: Farmers using climate-smart/sustainable practices (%) | D13: C0 | E13: C0: Agricultural context & need | F13: Context | G13: Local | H13: Context profile (not aggregated) | I13: N/A | K13: 2 | P13: Context only
B14: 1.9 | C14: National innovation/extension programs with digital component | D14: C4 | E14: C4: Human & institutional capacity | F14: Capability | G14: Local | H14: Anchored capability rubric | I14: N/A | K14: 2 | P14: Anchored rubric
B15: 2.1 | C15: Rural population covered by at least 3G (%) | D15: C1 | E15: C1: Connectivity & affordable access | F15: Capability | G15: Global | H15: Quantitative threshold | I15: Higher | J15: YES | K15: 3 | L15: 20 | M15: 40 | N15: 60 | O15: 80 | P15: Numeric threshold
B16: 2.2 | C16: Rural population covered by at least 4G (%) | D16: C1 | E16: C1: Connectivity & affordable access | F16: Capability | G16: Global | H16: Quantitative threshold | I16: Higher | K16: 3 | L16: 20 | M16: 40 | N16: 60 | O16: 80 | P16: Numeric threshold
B17: 2.3 | C17: Active mobile broadband subscriptions per 100 inhabitants | D17: C1 | E17: C1: Connectivity & affordable access | F17: Capability | G17: Global | H17: Quantitative threshold | I17: Higher | K17: 3 | L17: 20 | M17: 40 | N17: 70 | O17: 100 | P17: Numeric threshold
B18: 2.4 | C18: Individuals using the Internet (% of population) | D18: C1 | E18: C1: Connectivity & affordable access | F18: Capability | G18: Global | H18: Quantitative threshold | I18: Higher | K18: 3 | L18: 20 | M18: 40 | N18: 60 | O18: 80 | P18: Numeric threshold
B19: 2.5 | C19: Mobile broadband basket price (% GNI per capita) | D19: C1 | E19: C1: Connectivity & affordable access | F19: Capability | G19: Global | H19: Quantitative threshold | I19: Lower | J19: YES | K19: 3 | L19: 10 | M19: 5 | N19: 2 | O19: 1 | P19: Numeric threshold
B20: 2.6 | C20: Adults with mobile phone (% age 15+) | D20: C1 | E20: C1: Connectivity & affordable access | F20: Capability | G20: Global | H20: Quantitative threshold | I20: Higher | K20: 3 | L20: 20 | M20: 40 | N20: 60 | O20: 80 | P20: Numeric threshold
B21: 2.7 | C21: Smartphone ownership among rural/agricultural population (%) | D21: C1 | E21: C1: Connectivity & affordable access | F21: Capability | G21: Local | H21: Quantitative threshold | I21: Higher | K21: 2 | L21: 20 | M21: 40 | N21: 60 | O21: 80 | P21: Numeric threshold
B22: 2.8 | C22: Average mobile data cost in rural areas (USD per GB) | D22: C1 | E22: C1: Connectivity & affordable access | F22: Capability | G22: Local | H22: Quantitative threshold | I22: Lower | K22: 2 | L22: 10 | M22: 5 | N22: 2 | O22: 1 | P22: Numeric threshold
B23: 2.9 | C23: Electricity access in rural areas (%) | D23: C1 | E23: C1: Connectivity & affordable access | F23: Capability | G23: Local | H23: Quantitative threshold | I23: Higher | J23: YES | K23: 2 | L23: 20 | M23: 40 | N23: 60 | O23: 80 | P23: Numeric threshold
B24: 2.10 | C24: Average download speed in agricultural areas (Mbps) | D24: C1 | E24: C1: Connectivity & affordable access | F24: Capability | G24: Local | H24: Quantitative threshold | I24: Higher | K24: 2 | L24: 2 | M24: 5 | N24: 10 | O24: 25 | P24: Numeric threshold
B25: 2.11 | C25: Device financing/subsidy schemes for farmers | D25: C1 | E25: C1: Connectivity & affordable access | F25: Capability | G25: Local | H25: Anchored capability rubric | I25: N/A | K25: 2 | P25: Anchored rubric
B26: 3.1 | C26: UN E-Government Development Index (EGDI) | D26: C2 | E26: C2: Data infrastructure & DPI | F26: Capability | G26: Global | H26: Quantitative threshold | I26: Higher | K26: 3 | L26: 0.2 | M26: 0.4 | N26: 0.6 | O26: 0.8 | P26: Numeric threshold
B27: 3.2 | C27: Open Data Inventory (ODIN) score | D27: C2 | E27: C2: Data infrastructure & DPI | F27: Capability | G27: Global | H27: Quantitative threshold | I27: Higher | K27: 3 | L27: 20 | M27: 40 | N27: 60 | O27: 80 | P27: Numeric threshold
B28: 3.3 | C28: National farmer registry/database | D28: C2 | E28: C2: Data infrastructure & DPI | F28: Capability | G28: Local | H28: Anchored capability rubric | I28: N/A | J28: YES | K28: 2 | P28: Anchored rubric
B29: 3.4 | C29: Digital land/plot registration system | D29: C2 | E29: C2: Data infrastructure & DPI | F29: Capability | G29: Local | H29: Anchored capability rubric | I29: N/A | K29: 2 | P29: Anchored rubric
B30: 3.5 | C30: National agricultural data portal / open data | D30: C2 | E30: C2: Data infrastructure & DPI | F30: Capability | G30: Local | H30: Anchored capability rubric | I30: N/A | K30: 2 | P30: Anchored rubric
B31: 3.6 | C31: Weather/climate data infrastructure for agriculture | D31: C2 | E31: C2: Data infrastructure & DPI | F31: Capability | G31: Local | H31: Anchored capability rubric | I31: N/A | K31: 2 | P31: Anchored rubric
B32: 3.7 | C32: Satellite/earth observation data integration capability | D32: C2 | E32: C2: Data infrastructure & DPI | F32: Capability | G32: Local | H32: Anchored capability rubric | I32: N/A | K32: 2 | P32: Anchored rubric
B33: 3.8 | C33: National soil map/database (digital) | D33: C2 | E33: C2: Data infrastructure & DPI | F33: Capability | G33: Local | H33: Anchored capability rubric | I33: N/A | K33: 2 | P33: Anchored rubric
B34: 3.9 | C34: Digital advisory platforms reaching >10,000 users | D34: C2 | E34: C2: Data infrastructure & DPI | F34: Capability | G34: Local | H34: Quantitative threshold | I34: Higher | K34: 2 | L34: 20 | M34: 40 | N34: 60 | O34: 80 | P34: Numeric threshold
B35: 3.10 | C35: Digital agricultural market/e-commerce platforms (>5,000 active users) | D35: C2 | E35: C2: Data infrastructure & DPI | F35: Capability | G35: Local | H35: Anchored capability rubric | I35: N/A | K35: 2 | P35: Anchored rubric
B36: 3.11 | C36: Interoperability standards for agricultural data | D36: C2 | E36: C2: Data infrastructure & DPI | F36: Capability | G36: Local | H36: Anchored capability rubric | I36: N/A | J36: YES | K36: 2 | P36: Anchored rubric
B37: 3.12 | C37: AI-ready agricultural datasets | D37: C2 | E37: C2: Data infrastructure & DPI | F37: Capability | G37: Local | H37: Anchored capability rubric | I37: N/A | K37: 2 | P37: Anchored rubric
B38: 3.13 | C38: Machine-readable open agricultural data (share of national ag statistics as open APIs) | D38: C2 | E38: C2: Data infrastructure & DPI | F38: Capability | G38: Local | H38: Quantitative threshold | I38: Higher | K38: 2 | L38: 20 | M38: 40 | N38: 60 | O38: 80 | P38: Numeric threshold
B39: 4.1 | C39: Data protection/privacy law | D39: C3 | E39: C3: Policy, governance & safeguards | F39: Capability | G39: Global | H39: Anchored capability rubric | I39: N/A | J39: YES | K39: 3 | P39: Anchored rubric
B40: 4.2 | C40: Cybersecurity legal framework (ITU GCI) | D40: C3 | E40: C3: Policy, governance & safeguards | F40: Capability | G40: Global | H40: Quantitative threshold | I40: Higher | J40: YES | K40: 3 | L40: 0.2 | M40: 0.4 | N40: 0.6 | O40: 0.8 | P40: Numeric threshold
B41: 4.3 | C41: Government AI Readiness Index | D41: C3 | E41: C3: Policy, governance & safeguards | F41: Capability | G41: Global | H41: Quantitative threshold | I41: Higher | K41: 3 | L41: 20 | M41: 40 | N41: 60 | O41: 80 | P41: Numeric threshold
B42: 4.4 | C42: National digital agriculture strategy | D42: C3 | E42: C3: Policy, governance & safeguards | F42: Capability | G42: Local | H42: Anchored capability rubric | I42: N/A | K42: 2 | P42: Anchored rubric
B43: 4.5 | C43: Agricultural data governance framework | D43: C3 | E43: C3: Policy, governance & safeguards | F43: Capability | G43: Local | H43: Anchored capability rubric | I43: N/A | J43: YES | K43: 2 | P43: Anchored rubric
B44: 4.6 | C44: National AI strategy with agriculture component | D44: C3 | E44: C3: Policy, governance & safeguards | F44: Capability | G44: Local | H44: Anchored capability rubric | I44: N/A | K44: 2 | P44: Anchored rubric
B45: 4.7 | C45: Digital ID system coverage (% of population) | D45: C3 | E45: C3: Policy, governance & safeguards | F45: Capability | G45: Local | H45: Quantitative threshold | I45: Higher | K45: 2 | L45: 20 | M45: 40 | N45: 60 | O45: 80 | P45: Numeric threshold
B46: 4.8 | C46: Data sovereignty provisions for agricultural data | D46: C3 | E46: C3: Policy, governance & safeguards | F46: Capability | G46: Local | H46: Anchored capability rubric | I46: N/A | K46: 2 | P46: Anchored rubric
B47: 4.9 | C47: Inter-ministerial coordination mechanism for digital agriculture | D47: C3 | E47: C3: Policy, governance & safeguards | F47: Capability | G47: Local | H47: Anchored capability rubric | I47: N/A | J47: YES | K47: 2 | P47: Anchored rubric
B48: 4.10 | C48: Competition/antitrust framework for digital agricultural markets | D48: C3 | E48: C3: Policy, governance & safeguards | F48: Capability | G48: Local | H48: Anchored capability rubric | I48: N/A | K48: 2 | P48: Anchored rubric
B49: 4.11 | C49: Public procurement rules enabling digital agriculture innovation | D49: C3 | E49: C3: Policy, governance & safeguards | F49: Capability | G49: Local | H49: Anchored capability rubric | I49: N/A | K49: 2 | P49: Anchored rubric
B50: 4.12 | C50: Spectrum allocation for rural/agricultural IoT | D50: C3 | E50: C3: Policy, governance & safeguards | F50: Capability | G50: Local | H50: Anchored capability rubric | I50: N/A | K50: 2 | P50: Anchored rubric
B51: 4.13 | C51: Responsible AI principles/guidelines for agriculture | D51: C3 | E51: C3: Policy, governance & safeguards | F51: Capability | G51: Local | H51: Anchored capability rubric | I51: N/A | K51: 2 | P51: Anchored rubric
B52: 5.1 | C52: Mean years of schooling (adults 25+) | D52: C4 | E52: C4: Human & institutional capacity | F52: Capability | G52: Global | H52: Quantitative threshold | I52: Higher | K52: 3 | L52: 4 | M52: 6 | N52: 8 | O52: 10 | P52: Numeric threshold
B53: 5.2 | C53: Adult literacy rate (% age 15+) | D53: C4 | E53: C4: Human & institutional capacity | F53: Capability | G53: Global | H53: Quantitative threshold | I53: Higher | K53: 3 | L53: 50 | M53: 65 | N53: 80 | O53: 90 | P53: Numeric threshold
B54: 5.3 | C54: Tertiary enrollment in STEM fields (% gross) | D54: C4 | E54: C4: Human & institutional capacity | F54: Capability | G54: Global | H54: Quantitative threshold | I54: Higher | K54: 3 | L54: 10 | M54: 20 | N54: 30 | O54: 40 | P54: Numeric threshold
B55: 5.4 | C55: Digital literacy among farmers (%) | D55: C4 | E55: C4: Human & institutional capacity | F55: Capability | G55: Local | H55: Quantitative threshold | I55: Higher | K55: 2 | L55: 10 | M55: 25 | N55: 50 | O55: 75 | P55: Numeric threshold
B56: 5.5 | C56: Extension workers trained in digital tools (%) | D56: C4 | E56: C4: Human & institutional capacity | F56: Capability | G56: Local | H56: Quantitative threshold | I56: Higher | J56: YES | K56: 2 | L56: 10 | M56: 25 | N56: 50 | O56: 75 | P56: Numeric threshold
B57: 5.6 | C57: Farmer-to-digital-extension-worker ratio | D57: C4 | E57: C4: Human & institutional capacity | F57: Capability | G57: Local | H57: Anchored capability rubric | I57: N/A | K57: 2 | P57: Anchored rubric
B58: 5.7 | C58: Dedicated digital/AI units in Ministry of Agriculture | D58: C4 | E58: C4: Human & institutional capacity | F58: Capability | G58: Local | H58: Anchored capability rubric | I58: N/A | J58: YES | K58: 2 | P58: Anchored rubric
B59: 5.8 | C59: University programs in agtech/digital agriculture | D59: C4 | E59: C4: Human & institutional capacity | F59: Capability | G59: Local | H59: Anchored capability rubric | I59: N/A | K59: 2 | P59: Anchored rubric
B60: 5.9 | C60: Data science/AI training programs for agriculture | D60: C4 | E60: C4: Human & institutional capacity | F60: Capability | G60: Local | H60: Anchored capability rubric | I60: N/A | K60: 2 | P60: Anchored rubric
B61: 5.10 | C61: Digital skills training reach (% of farmer population per year) | D61: C4 | E61: C4: Human & institutional capacity | F61: Capability | G61: Local | H61: Quantitative threshold | I61: Higher | K61: 2 | L61: 2 | M61: 5 | N61: 10 | O61: 20 | P61: Numeric threshold
B62: 5.11 | C62: Institutional digital maturity of key agricultural agencies | D62: C4 | E62: C4: Human & institutional capacity | F62: Capability | G62: Local | H62: Anchored capability rubric | I62: N/A | K62: 2 | P62: Anchored rubric
B63: 5.12 | C63: Gender balance in digital agriculture workforce | D63: C4 | E63: C4: Human & institutional capacity | F63: Capability | G63: Local | H63: Quantitative threshold | I63: Higher | K63: 2 | L63: 20 | M63: 35 | N63: 45 | O63: 50 | P63: Numeric threshold
B64: 5.13 | C64: Gender parity in extension services (% female extension officers) | D64: C4 | E64: C4: Human & institutional capacity | F64: Capability | G64: Local | H64: Quantitative threshold | I64: Higher | K64: 3 | L64: 10 | M64: 25 | N64: 40 | O64: 50 | P64: Numeric threshold
B65: 6.1 | C65: Global Innovation Index (GII) score | D65: E1 | E65: E1: Innovation & private sector | F65: Ecosystem | G65: Global | H65: Quantitative threshold | I65: Higher | K65: 3 | L65: 25 | M65: 35 | N65: 45 | O65: 55 | P65: Numeric threshold
B66: 6.2 | C66: R&D expenditure (% of GDP) | D66: E1 | E66: E1: Innovation & private sector | F66: Ecosystem | G66: Global | H66: Quantitative threshold | I66: Higher | K66: 3 | L66: 0.1 | M66: 0.5 | N66: 1 | O66: 2 | P66: Numeric threshold
B67: 6.3 | C67: Business Ready (B-READY) score | D67: E1 | E67: E1: Innovation & private sector | F67: Ecosystem | G67: Global | H67: Quantitative threshold | I67: Higher | K67: 3 | L67: 30 | M67: 45 | N67: 60 | O67: 75 | P67: Numeric threshold
B68: 6.4 | C68: Active agtech startups/firms | D68: E1 | E68: E1: Innovation & private sector | F68: Ecosystem | G68: Local | H68: Anchored capability rubric | I68: N/A | K68: 2 | P68: Anchored rubric
B69: 6.5 | C69: Venture capital/investment in agtech (annual USD) | D69: E1 | E69: E1: Innovation & private sector | F69: Ecosystem | G69: Local | H69: Anchored capability rubric | I69: N/A | K69: 2 | P69: Anchored rubric
B70: 6.6 | C70: Agtech accelerators/incubators | D70: E1 | E70: E1: Innovation & private sector | F70: Ecosystem | G70: Local | H70: Anchored capability rubric | I70: N/A | K70: 2 | P70: Anchored rubric
B71: 6.7 | C71: Agribusiness firms using AI/ML in operations (%) | D71: E1 | E71: E1: Innovation & private sector | F71: Ecosystem | G71: Local | H71: Quantitative threshold | I71: Higher | K71: 2 | L71: 5 | M71: 15 | N71: 30 | O71: 50 | P71: Numeric threshold
B72: 6.8 | C72: Regulatory sandboxes for agtech/fintech | D72: E1 | E72: E1: Innovation & private sector | F72: Ecosystem | G72: Local | H72: Anchored capability rubric | I72: N/A | K72: 2 | P72: Anchored rubric
B73: 6.9 | C73: Public-private partnerships in digital agriculture | D73: E1 | E73: E1: Innovation & private sector | F73: Ecosystem | G73: Local | H73: Anchored capability rubric | I73: N/A | K73: 2 | P73: Anchored rubric
B74: 6.10 | C74: Government grants/funding for agtech innovation (annual USD) | D74: E1 | E74: E1: Innovation & private sector | F74: Ecosystem | G74: Local | H74: Anchored capability rubric | I74: N/A | K74: 2 | P74: Anchored rubric
B75: 6.11 | C75: Digital financial services platforms for agriculture | D75: E1 | E75: E1: Innovation & private sector | F75: Ecosystem | G75: Local | H75: Anchored capability rubric | I75: N/A | K75: 2 | P75: Anchored rubric
B76: 6.12 | C76: Digital public goods adopted in agriculture | D76: E1 | E76: E1: Innovation & private sector | F76: Ecosystem | G76: Local | H76: Anchored capability rubric | I76: N/A | K76: 2 | P76: Anchored rubric
B77: 6.13 | C77: SME access to digital agriculture tools/platforms (%) | D77: E1 | E77: E1: Innovation & private sector | F77: Ecosystem | G77: Local | H77: Quantitative threshold | I77: Higher | K77: 2 | L77: 10 | M77: 25 | N77: 50 | O77: 75 | P77: Numeric threshold
B78: 6.14 | C78: Agri-fintech / mobile-money rails accessible to smallholders | D78: E1 | E78: E1: Innovation & private sector | F78: Ecosystem | G78: Local | H78: Anchored capability rubric | I78: N/A | J78: YES | K78: 2 | P78: Anchored rubric
B79: 7.1 | C79: AI-related scientific publications per million population | D79: E2 | E79: E2: Responsible AI & emerging tech | F79: Ecosystem | G79: Global | H79: Quantitative threshold | I79: Higher | K79: 3 | L79: 1 | M79: 5 | N79: 20 | O79: 50 | P79: Numeric threshold
B80: 7.2 | C80: AI systems deployed in public agricultural sector | D80: E2 | E80: E2: Responsible AI & emerging tech | F80: Ecosystem | G80: Local | H80: Anchored capability rubric | I80: N/A | K80: 2 | P80: Anchored rubric
B81: 7.3 | C81: AI-enabled advisory services (farmer reach %) | D81: E2 | E81: E2: Responsible AI & emerging tech | F81: Ecosystem | G81: Local | H81: Quantitative threshold | I81: Higher | K81: 2 | L81: 2 | M81: 10 | N81: 25 | O81: 50 | P81: Numeric threshold
B82: 7.4 | C82: AI for crop/pest/disease detection and monitoring | D82: E2 | E82: E2: Responsible AI & emerging tech | F82: Ecosystem | G82: Local | H82: Quantitative threshold | I82: Higher | K82: 2 | L82: 10 | M82: 25 | N82: 50 | O82: 75 | P82: Numeric threshold
B83: 7.5 | C83: AI in agricultural finance (credit scoring, insurance) | D83: E2 | E83: E2: Responsible AI & emerging tech | F83: Ecosystem | G83: Local | H83: Quantitative threshold | I83: Higher | K83: 2 | L83: 10 | M83: 25 | N83: 50 | O83: 75 | P83: Numeric threshold
B84: 7.6 | C84: AI for supply chain optimization and traceability | D84: E2 | E84: E2: Responsible AI & emerging tech | F84: Ecosystem | G84: Local | H84: Quantitative threshold | I84: Higher | K84: 2 | L84: 10 | M84: 25 | N84: 50 | O84: 75 | P84: Numeric threshold
B85: 7.7 | C85: AI for climate forecasting and agricultural risk management | D85: E2 | E85: E2: Responsible AI & emerging tech | F85: Ecosystem | G85: Local | H85: Quantitative threshold | I85: Higher | K85: 2 | L85: 10 | M85: 25 | N85: 50 | O85: 75 | P85: Numeric threshold
B86: 7.8 | C86: AI talent in agriculture sector | D86: E2 | E86: E2: Responsible AI & emerging tech | F86: Ecosystem | G86: Local | H86: Anchored capability rubric | I86: N/A | K86: 2 | P86: Anchored rubric
B87: 7.9 | C87: Cybersecurity of agricultural digital systems | D87: E2 | E87: E2: Responsible AI & emerging tech | F87: Ecosystem | G87: Local | H87: Anchored capability rubric | I87: N/A | J87: YES | K87: 2 | P87: Anchored rubric
B88: 7.10 | C88: Explainability and transparency of AI systems in agriculture | D88: E2 | E88: E2: Responsible AI & emerging tech | F88: Ecosystem | G88: Local | H88: Anchored capability rubric | I88: N/A | K88: 2 | P88: Anchored rubric
B89: 7.11 | C89: Bias monitoring and mitigation in agricultural AI | D89: E2 | E89: E2: Responsible AI & emerging tech | F89: Ecosystem | G89: Local | H89: Anchored capability rubric | I89: N/A | K89: 2 | P89: Anchored rubric
B90: 7.12 | C90: Farmer consent and data rights in AI systems | D90: E2 | E90: E2: Responsible AI & emerging tech | F90: Ecosystem | G90: Local | H90: Anchored capability rubric | I90: N/A | J90: YES | K90: 2 | P90: Anchored rubric
B91: 8.1 | C91: Prevalence of undernourishment (% of population) | D91: O1 | E91: O1: Inclusion, sustainability & outcomes | F91: Outcome | G91: Global | H91: Quantitative threshold | I91: Lower | K91: 3 | L91: 25 | M91: 15 | N91: 7.5 | O91: 2.5 | P91: Numeric threshold
B92: 8.2 | C92: Account ownership, female (% age 15+) | D92: O1 | E92: O1: Inclusion, sustainability & outcomes | F92: Outcome | G92: Global | H92: Quantitative threshold | I92: Higher | K92: 3 | L92: 20 | M92: 40 | N92: 60 | O92: 80 | P92: Numeric threshold
B93: 8.3 | C93: Gender gap in account ownership (male % minus female %) | D93: O1 | E93: O1: Inclusion, sustainability & outcomes | F93: Outcome | G93: Global | H93: Quantitative threshold | I93: Lower | K93: 3 | L93: 25 | M93: 15 | N93: 8 | O93: 3 | P93: Numeric threshold
B94: 8.4 | C94: Mobile money account (% age 15+) | D94: O1 | E94: O1: Inclusion, sustainability & outcomes | F94: Outcome | G94: Global | H94: Quantitative threshold | I94: Higher | K94: 3 | L94: 10 | M94: 25 | N94: 50 | O94: 75 | P94: Numeric threshold
B95: 8.5 | C95: Women who own land (% of agricultural holders) | D95: O1 | E95: O1: Inclusion, sustainability & outcomes | F95: Outcome | G95: Global | H95: Quantitative threshold | I95: Higher | K95: 3 | L95: 10 | M95: 25 | N95: 40 | O95: 50 | P95: Numeric threshold
B96: 8.6 | C96: Gender gap in mobile phone ownership (percentage points) | D96: O1 | E96: O1: Inclusion, sustainability & outcomes | F96: Outcome | G96: Local | H96: Quantitative threshold | I96: Lower | K96: 3 | L96: 20 | M96: 10 | N96: 5 | O96: 2 | P96: Numeric threshold
B97: 8.7 | C97: Women using digital agricultural services (% of women farmers) | D97: O1 | E97: O1: Inclusion, sustainability & outcomes | F97: Outcome | G97: Local | H97: Quantitative threshold | I97: Higher | K97: 3 | L97: 10 | M97: 25 | N97: 50 | O97: 75 | P97: Numeric threshold
B98: 8.8 | C98: Youth (under 35) using digital agricultural services (%) | D98: O1 | E98: O1: Inclusion, sustainability & outcomes | F98: Outcome | G98: Local | H98: Quantitative threshold | I98: Higher | K98: 3 | L98: 10 | M98: 25 | N98: 50 | O98: 75 | P98: Numeric threshold
B99: 8.9 | C99: Smallholder farmers reached by digital services (% of total) | D99: O1 | E99: O1: Inclusion, sustainability & outcomes | F99: Outcome | G99: Local | H99: Quantitative threshold | I99: Higher | K99: 3 | L99: 10 | M99: 25 | N99: 50 | O99: 75 | P99: Numeric threshold
