Workbook

Sheet Read Me
C2: DAMM v1.7 — Scoring Workbook
C3: Digital Agriculture Maturity Model · draft for review · August 2026
C5: This file is the blank template. Copy it once per country and rename the scoring sheet.
C7: The four steps
C8: 1 · ASSEMBLE | D8: Fill the six yellow columns on the scoring sheet: Value, Source, Source URL, Tier, Year, Assessor level. Every indicator gets a value, a source and a year — or a recorded gap. No level may exist without a recorded value.
C9: 2 · DERIVE | D9: Automatic. Evidence class, level, staleness, pillar bands, the layer profile, prerequisite status and the use-case matrix all compute by formula. Nothing here is typed.
C10: 3 · REPORT | D10: The diagnostic report renders from this workbook. It is the deliverable; this file is the instrument behind it.
C11: 4 · USE | D11: The task team leader takes the report into roadmap preparation, closes the verify list on mission, and executes the refresh list.
C13: What to type, and where
C14: Yellow cells, blue text | D14: The only cells an assessor edits: Value, Source, Source URL, Tier, Year, Assessor level (columns M–R of the scoring sheet).
C15: Everything else | D15: Model reference or derived by formula. Do not overwrite: a typed level that contradicts its value is the defect this model exists to prevent.
C16: Value | D16: A number, a citation ("NDPA 2023 in force; NDPC enforcing"), or a recorded gap beginning DATA GAP — followed by the sources actually searched.
C17: Tier | D17: T1–T5 per the Tiers sheet. Reported, never weighted. Machine-fetched rows arrive with the tier already filled by the pipeline.
C18: Assessor level | D18: 1–5, for ladder indicators only. Threshold indicators score themselves from the value.
C20: Quality control — gate sign-off
D21: Automated checks run at render time and block the report on failure. The three human gates are recorded here (QC Protocol).
C22: Gate | D22: What it certifies | E22: Name | F22: Date | G22: Note
C23: G1 | D23: Assessor has confirmed every machine-filled row: value, source, year, tier; every recorded gap accepted or re-searched.
C24: G2 | D24: A second reviewer has re-checked 100% of prerequisite rows and 100% of judged rows, plus a 15% sample of the remainder.
C25: G3 | D25: Task team leader sign-off against the four prohibitions, before anything leaves the team.
C27: The four prohibitions
D28: · No cross-country ranking.
D29: · No band used as a project development objective, disbursement-linked indicator, or disbursement condition.
D30: · No automatic financing decisions.
D31: · No public claim before human review.

Sheet Config
B1: Config — every constant with its meaning
B2: Assessment year | C2: 2026 | D2: ENTRY (yellow). Staleness is measured against this year.
B3: Staleness limit (years) | C3: 3 | D3: A reading older than this is flagged STALE. One rule for all indicators.
B4: Readiness threshold | C4: 2.6 | D4: A use-case column whose bearing indicators average below this reads Partial.
B5: Leapfrog threshold | C5: 1.5 | D5: |mean(Foundation) − mean(Transformation)| above this raises a structural flag.
B6: Band: Nascent | C6: 1.0 – <1.8 | D6: Half-open bands; a pillar band in parentheses means judged, gap and held rows outnumber the levelled measured and documented ones.
B7: Band: Emerging | C7: 1.8 – <2.6
B8: Band: Established | C8: 2.6 – <3.4
B9: Band: Advanced | C9: 3.4 – <4.2
B10: Band: Transformative | C10: 4.2 – 5.0
B11: Universal prerequisites | C11: 2.1, 2.9, 4.1 | D11: Absence blocks every use-case column. A universal prerequisite at Present (narrow) caps every column at Partial.
B12: AI-enabled services | C12: 7.12 binds AGI | D12: Ruling pending ratification: the consent-and-rights prerequisite binds the agricultural-intelligence column.

Sheet Ladder
B1: The shared ladder — scoring an indicator that is not a measurement
B2: Ask in stages: presence first, then quality, then scale. Stop at the first rung the evidence does not support.
B4: Level | C4: Condition | D4: Evidence required
B5: 1 | C5: Absent | D5: The search that established absence: sources consulted, in order.
B6: 2 | C6: Announced | D6: The announcement, draft or commitment, cited.
B7: 3 | C7: Adopted, or operating narrowly | D7: The instrument or system itself, with its adoption date or its operating footprint.
B8: 4 | C8: Operating with quality | D8: Governance, funding and institutionalisation — the evidence that it is run, not just live.
B9: 5 | C9: Operating at scale, with evidence of use | D9: Coverage or reach in the indicator's own unit, from a source that is not the operator's own claim.
B11: A scale figure reported only by the operator of the service does not carry rung 5.

Sheet Tiers
B1: Source tiers — what may carry what
B2: Tiers are reported beside the evidence class and never weighted. Search in tier order and stop when found; a dead end is recorded as a gap with its trail.
B4: Tier | C4: What it is | D4: Typical sources | E4: Admissible for
B5: T1 | C5: Official statistics & international databases | D5: FAOSTAT · AQUASTAT · World Bank WDI/ID4D/Findex · ITU · UN DESA · national statistical offices | E5: Any claim. The default for every number.
B6: T2 | C6: Peer-reviewed literature & IO flagship reports | D6: Journals · systematic reviews · World Bank / FAO / IFPRI / CGIAR flagships · evaluated impact studies | E6: Any claim. Required for impact and effectiveness claims.
B7: T3 | C7: Government legal, policy & budget artefacts | D7: Gazetted laws · adopted strategies · budgets · regulator reports · official programme pages | E7: Presence facts, policy intent, programme design — not outcomes.
B8: T4 | C8: Reputable grey literature | D8: GSMA · GIZ · USAID · AGRA · AfDB · donor evaluations · established industry analyses | E8: Context and sector narrative, flagged as T4; presence facts where T3 is silent.
B9: T5 | C9: News, vendor & market material | D9: Press · company sites · market-research releases · blogs | E9: Initiative register only, existence facts only. A T5-only citation derives the class Judged, never Documented.
C11: · Every citation is a deep link to the document, with an access date. A link that resolves only to a domain root is not a citation.
C12: · A load-bearing number needs two independent T1–T2 confirmations, or it ships flagged single-source.
C13: · Vintage beats tier at the margin for narrative; the scored row still records the official figure and its staleness honestly.

Sheet Scoring
A1: Country — DAMM v1.7 assessment
A2: Edit only the yellow columns (M–R). Everything else is model reference or derived by formula.
A4: ID | B4: Indicator | C4: Pillar | D4: Layer | E4: Use cases | F4: Prereq | G4: Meth | H4: Dir | I4: L2 | J4: L3 | K4: L4 | L4: L5 | M4: Value | N4: Source | O4: Source URL | P4: Tier | Q4: Year | R4: Assessor level | S4: Class | T4: Level | U4: Stale | V4: b_ADV | W4: b_SMF | X4: b_MKT | Y4: b_SCM | Z4: b_FIN | AA4: b_AGI | AB4: Open definition question (for ratification) | AC4: Ratification hold
A5: 1.1 | B5: Agriculture value added per worker (USD) | C5: A1 | D5: Foundation | E5: NEED | G5: T | H5: H | I5: 1000 | J5: 2500 | K5: 5000 | L5: 10000 | S5: =IF($M5="","",IF(ISNUMBER($M5),"Measured",IF(ISNUMBER(SEARCH("DATA GAP",UPPER($M5))),"Gap",IF(AND($N5<>"",$P5<>"T5"),"Documented","Judged")))) | T5: =IF($AC5<>"","",IF(OR($S5="",$S5="Gap"),"",IF($S5="Measured",1+IF($H5="H",IF($M5>=$I5,1,0)+IF($M5>=$J5,1,0)+IF($M5>=$K5,1,0)+IF($M5>=$L5,1,0),IF($M5<=$I5,1,0)+IF($M5<=$J5,1,0)+IF($M5<=$K5,1,0)+IF($M5<=$L5,1,0)),IF($R5<>"",$R5,"")))) | U5: =IF(OR($S5="",$S5="Gap",$Q5=""),"",IF($Q5<Config!$C$2-Config!$C$3,"STALE","")) | V5: =IF(OR(ISNUMBER(SEARCH("ALL",$E5)),ISNUMBER(SEARCH("ADV",$E5))),1,0) -> 0 | W5: =IF(OR(ISNUMBER(SEARCH("ALL",$E5)),ISNUMBER(SEARCH("SMF",$E5))),1,0) -> 0 | X5: =IF(OR(ISNUMBER(SEARCH("ALL",$E5)),ISNUMBER(SEARCH("MKT",$E5))),1,0) -> 0 | Y5: =IF(OR(ISNUMBER(SEARCH("ALL",$E5)),ISNUMBER(SEARCH("SCM",$E5))),1,0) -> 0 | Z5: =IF(OR(ISNUMBER(SEARCH("ALL",$E5)),ISNUMBER(SEARCH("FIN",$E5))),1,0) -> 0 | AA5: =IF(OR(ISNUMBER(SEARCH("ALL",$E5)),ISNUMBER(SEARCH("AGI",$E5))),1,0) -> 0
A6: 1.2 | B6: Cereal yield (kg/ha) | C6: A1 | D6: Foundation | E6: NEED | G6: T | H6: H | I6: 1500 | J6: 3000 | K6: 4500 | L6: 6000 | S6: =IF($M6="","",IF(ISNUMBER($M6),"Measured",IF(ISNUMBER(SEARCH("DATA GAP",UPPER($M6))),"Gap",IF(AND($N6<>"",$P6<>"T5"),"Documented","Judged")))) | T6: =IF($AC6<>"","",IF(OR($S6="",$S6="Gap"),"",IF($S6="Measured",1+IF($H6="H",IF($M6>=$I6,1,0)+IF($M6>=$J6,1,0)+IF($M6>=$K6,1,0)+IF($M6>=$L6,1,0),IF($M6<=$I6,1,0)+IF($M6<=$J6,1,0)+IF($M6<=$K6,1,0)+IF($M6<=$L6,1,0)),IF($R6<>"",$R6,"")))) | U6: =IF(OR($S6="",$S6="Gap",$Q6=""),"",IF($Q6<Config!$C$2-Config!$C$3,"STALE","")) | V6: =IF(OR(ISNUMBER(SEARCH("ALL",$E6)),ISNUMBER(SEARCH("ADV",$E6))),1,0) -> 0 | W6: =IF(OR(ISNUMBER(SEARCH("ALL",$E6)),ISNUMBER(SEARCH("SMF",$E6))),1,0) -> 0 | X6: =IF(OR(ISNUMBER(SEARCH("ALL",$E6)),ISNUMBER(SEARCH("MKT",$E6))),1,0) -> 0 | Y6: =IF(OR(ISNUMBER(SEARCH("ALL",$E6)),ISNUMBER(SEARCH("SCM",$E6))),1,0) -> 0 | Z6: =IF(OR(ISNUMBER(SEARCH("ALL",$E6)),ISNUMBER(SEARCH("FIN",$E6))),1,0) -> 0 | AA6: =IF(OR(ISNUMBER(SEARCH("ALL",$E6)),ISNUMBER(SEARCH("AGI",$E6))),1,0) -> 0
A7: 1.3 | B7: Employment in agriculture (%) | C7: A1 | D7: Foundation | E7: NEED | G7: T | H7: L | I7: 45 | J7: 30 | K7: 15 | L7: 5 | S7: =IF($M7="","",IF(ISNUMBER($M7),"Measured",IF(ISNUMBER(SEARCH("DATA GAP",UPPER($M7))),"Gap",IF(AND($N7<>"",$P7<>"T5"),"Documented","Judged")))) | T7: =IF($AC7<>"","",IF(OR($S7="",$S7="Gap"),"",IF($S7="Measured",1+IF($H7="H",IF($M7>=$I7,1,0)+IF($M7>=$J7,1,0)+IF($M7>=$K7,1,0)+IF($M7>=$L7,1,0),IF($M7<=$I7,1,0)+IF($M7<=$J7,1,0)+IF($M7<=$K7,1,0)+IF($M7<=$L7,1,0)),IF($R7<>"",$R7,"")))) | U7: =IF(OR($S7="",$S7="Gap",$Q7=""),"",IF($Q7<Config!$C$2-Config!$C$3,"STALE","")) | V7: =IF(OR(ISNUMBER(SEARCH("ALL",$E7)),ISNUMBER(SEARCH("ADV",$E7))),1,0) -> 0 | W7: =IF(OR(ISNUMBER(SEARCH("ALL",$E7)),ISNUMBER(SEARCH("SMF",$E7))),1,0) -> 0 | X7: =IF(OR(ISNUMBER(SEARCH("ALL",$E7)),ISNUMBER(SEARCH("MKT",$E7))),1,0) -> 0 | Y7: =IF(OR(ISNUMBER(SEARCH("ALL",$E7)),ISNUMBER(SEARCH("SCM",$E7))),1,0) -> 0 | Z7: =IF(OR(ISNUMBER(SEARCH("ALL",$E7)),ISNUMBER(SEARCH("FIN",$E7))),1,0) -> 0 | AA7: =IF(OR(ISNUMBER(SEARCH("ALL",$E7)),ISNUMBER(SEARCH("AGI",$E7))),1,0) -> 0
A8: 1.4 | B8: Food production index (2014-16=100) | C8: A1 | D8: Foundation | E8: NEED | G8: T | H8: H | I8: 95 | J8: 105 | K8: 115 | L8: 130 | S8: =IF($M8="","",IF(ISNUMBER($M8),"Measured",IF(ISNUMBER(SEARCH("DATA GAP",UPPER($M8))),"Gap",IF(AND($N8<>"",$P8<>"T5"),"Documented","Judged")))) | T8: =IF($AC8<>"","",IF(OR($S8="",$S8="Gap"),"",IF($S8="Measured",1+IF($H8="H",IF($M8>=$I8,1,0)+IF($M8>=$J8,1,0)+IF($M8>=$K8,1,0)+IF($M8>=$L8,1,0),IF($M8<=$I8,1,0)+IF($M8<=$J8,1,0)+IF($M8<=$K8,1,0)+IF($M8<=$L8,1,0)),IF($R8<>"",$R8,"")))) | U8: =IF(OR($S8="",$S8="Gap",$Q8=""),"",IF($Q8<Config!$C$2-Config!$C$3,"STALE","")) | V8: =IF(OR(ISNUMBER(SEARCH("ALL",$E8)),ISNUMBER(SEARCH("ADV",$E8))),1,0) -> 0 | W8: =IF(OR(ISNUMBER(SEARCH("ALL",$E8)),ISNUMBER(SEARCH("SMF",$E8))),1,0) -> 0 | X8: =IF(OR(ISNUMBER(SEARCH("ALL",$E8)),ISNUMBER(SEARCH("MKT",$E8))),1,0) -> 0 | Y8: =IF(OR(ISNUMBER(SEARCH("ALL",$E8)),ISNUMBER(SEARCH("SCM",$E8))),1,0) -> 0 | Z8: =IF(OR(ISNUMBER(SEARCH("ALL",$E8)),ISNUMBER(SEARCH("FIN",$E8))),1,0) -> 0 | AA8: =IF(OR(ISNUMBER(SEARCH("ALL",$E8)),ISNUMBER(SEARCH("AGI",$E8))),1,0) -> 0
A9: 1.5 | B9: Post-harvest loss rate (%) | C9: A1 | D9: Foundation | E9: NEED | G9: T | H9: L | I9: 30 | J9: 20 | K9: 12 | L9: 5 | S9: =IF($M9="","",IF(ISNUMBER($M9),"Measured",IF(ISNUMBER(SEARCH("DATA GAP",UPPER($M9))),"Gap",IF(AND($N9<>"",$P9<>"T5"),"Documented","Judged")))) | T9: =IF($AC9<>"","",IF(OR($S9="",$S9="Gap"),"",IF($S9="Measured",1+IF($H9="H",IF($M9>=$I9,1,0)+IF($M9>=$J9,1,0)+IF($M9>=$K9,1,0)+IF($M9>=$L9,1,0),IF($M9<=$I9,1,0)+IF($M9<=$J9,1,0)+IF($M9<=$K9,1,0)+IF($M9<=$L9,1,0)),IF($R9<>"",$R9,"")))) | U9: =IF(OR($S9="",$S9="Gap",$Q9=""),"",IF($Q9<Config!$C$2-Config!$C$3,"STALE","")) | V9: =IF(OR(ISNUMBER(SEARCH("ALL",$E9)),ISNUMBER(SEARCH("ADV",$E9))),1,0) -> 0 | W9: =IF(OR(ISNUMBER(SEARCH("ALL",$E9)),ISNUMBER(SEARCH("SMF",$E9))),1,0) -> 0 | X9: =IF(OR(ISNUMBER(SEARCH("ALL",$E9)),ISNUMBER(SEARCH("MKT",$E9))),1,0) -> 0 | Y9: =IF(OR(ISNUMBER(SEARCH("ALL",$E9)),ISNUMBER(SEARCH("SCM",$E9))),1,0) -> 0 | Z9: =IF(OR(ISNUMBER(SEARCH("ALL",$E9)),ISNUMBER(SEARCH("FIN",$E9))),1,0) -> 0 | AA9: =IF(OR(ISNUMBER(SEARCH("ALL",$E9)),ISNUMBER(SEARCH("AGI",$E9))),1,0) -> 0
A10: 1.6 | B10: Smallholder access to formal markets (%) | C10: A1 | D10: Foundation | E10: NEED,MKT | G10: T | H10: H | I10: 20 | J10: 40 | K10: 60 | L10: 80 | S10: =IF($M10="","",IF(ISNUMBER($M10),"Measured",IF(ISNUMBER(SEARCH("DATA GAP",UPPER($M10))),"Gap",IF(AND($N10<>"",$P10<>"T5"),"Documented","Judged")))) | T10: =IF($AC10<>"","",IF(OR($S10="",$S10="Gap"),"",IF($S10="Measured",1+IF($H10="H",IF($M10>=$I10,1,0)+IF($M10>=$J10,1,0)+IF($M10>=$K10,1,0)+IF($M10>=$L10,1,0),IF($M10<=$I10,1,0)+IF($M10<=$J10,1,0)+IF($M10<=$K10,1,0)+IF($M10<=$L10,1,0)),IF($R10<>"",$R10,"")))) | U10: =IF(OR($S10="",$S10="Gap",$Q10=""),"",IF($Q10<Config!$C$2-Config!$C$3,"STALE","")) | V10: =IF(OR(ISNUMBER(SEARCH("ALL",$E10)),ISNUMBER(SEARCH("ADV",$E10))),1,0) -> 0 | W10: =IF(OR(ISNUMBER(SEARCH("ALL",$E10)),ISNUMBER(SEARCH("SMF",$E10))),1,0) -> 0 | X10: =IF(OR(ISNUMBER(SEARCH("ALL",$E10)),ISNUMBER(SEARCH("MKT",$E10))),1,0) -> 1 | Y10: =IF(OR(ISNUMBER(SEARCH("ALL",$E10)),ISNUMBER(SEARCH("SCM",$E10))),1,0) -> 0 | Z10: =IF(OR(ISNUMBER(SEARCH("ALL",$E10)),ISNUMBER(SEARCH("FIN",$E10))),1,0) -> 0 | AA10: =IF(OR(ISNUMBER(SEARCH("ALL",$E10)),ISNUMBER(SEARCH("AGI",$E10))),1,0) -> 0
A11: 1.7 | B11: Agricultural credit access (% farmers) | C11: A1 | D11: Foundation | E11: NEED,FIN | G11: T | H11: H | I11: 10 | J11: 25 | K11: 40 | L11: 60 | S11: =IF($M11="","",IF(ISNUMBER($M11),"Measured",IF(ISNUMBER(SEARCH("DATA GAP",UPPER($M11))),"Gap",IF(AND($N11<>"",$P11<>"T5"),"Documented","Judged")))) | T11: =IF($AC11<>"","",IF(OR($S11="",$S11="Gap"),"",IF($S11="Measured",1+IF($H11="H",IF($M11>=$I11,1,0)+IF($M11>=$J11,1,0)+IF($M11>=$K11,1,0)+IF($M11>=$L11,1,0),IF($M11<=$I11,1,0)+IF($M11<=$J11,1,0)+IF($M11<=$K11,1,0)+IF($M11<=$L11,1,0)),IF($R11<>"",$R11,"")))) | U11: =IF(OR($S11="",$S11="Gap",$Q11=""),"",IF($Q11<Config!$C$2-Config!$C$3,"STALE","")) | V11: =IF(OR(ISNUMBER(SEARCH("ALL",$E11)),ISNUMBER(SEARCH("ADV",$E11))),1,0) -> 0 | W11: =IF(OR(ISNUMBER(SEARCH("ALL",$E11)),ISNUMBER(SEARCH("SMF",$E11))),1,0) -> 0 | X11: =IF(OR(ISNUMBER(SEARCH("ALL",$E11)),ISNUMBER(SEARCH("MKT",$E11))),1,0) -> 0 | Y11: =IF(OR(ISNUMBER(SEARCH("ALL",$E11)),ISNUMBER(SEARCH("SCM",$E11))),1,0) -> 0 | Z11: =IF(OR(ISNUMBER(SEARCH("ALL",$E11)),ISNUMBER(SEARCH("FIN",$E11))),1,0) -> 1 | AA11: =IF(OR(ISNUMBER(SEARCH("ALL",$E11)),ISNUMBER(SEARCH("AGI",$E11))),1,0) -> 0
A12: 1.8 | B12: Farmers using climate-smart practices (%) | C12: A1 | D12: Foundation | E12: NEED,ADV | G12: T | H12: H | I12: 20 | J12: 40 | K12: 60 | L12: 80 | S12: =IF($M12="","",IF(ISNUMBER($M12),"Measured",IF(ISNUMBER(SEARCH("DATA GAP",UPPER($M12))),"Gap",IF(AND($N12<>"",$P12<>"T5"),"Documented","Judged")))) | T12: =IF($AC12<>"","",IF(OR($S12="",$S12="Gap"),"",IF($S12="Measured",1+IF($H12="H",IF($M12>=$I12,1,0)+IF($M12>=$J12,1,0)+IF($M12>=$K12,1,0)+IF($M12>=$L12,1,0),IF($M12<=$I12,1,0)+IF($M12<=$J12,1,0)+IF($M12<=$K12,1,0)+IF($M12<=$L12,1,0)),IF($R12<>"",$R12,"")))) | U12: =IF(OR($S12="",$S12="Gap",$Q12=""),"",IF($Q12<Config!$C$2-Config!$C$3,"STALE","")) | V12: =IF(OR(ISNUMBER(SEARCH("ALL",$E12)),ISNUMBER(SEARCH("ADV",$E12))),1,0) -> 1 | W12: =IF(OR(ISNUMBER(SEARCH("ALL",$E12)),ISNUMBER(SEARCH("SMF",$E12))),1,0) -> 0 | X12: =IF(OR(ISNUMBER(SEARCH("ALL",$E12)),ISNUMBER(SEARCH("MKT",$E12))),1,0) -> 0 | Y12: =IF(OR(ISNUMBER(SEARCH("ALL",$E12)),ISNUMBER(SEARCH("SCM",$E12))),1,0) -> 0 | Z12: =IF(OR(ISNUMBER(SEARCH("ALL",$E12)),ISNUMBER(SEARCH("FIN",$E12))),1,0) -> 0 | AA12: =IF(OR(ISNUMBER(SEARCH("ALL",$E12)),ISNUMBER(SEARCH("AGI",$E12))),1,0) -> 0
A13: 8.1 | B13: Prevalence of undernourishment (%) | C13: A1 | D13: Foundation | E13: NEED | G13: T | H13: L | I13: 25 | J13: 15 | K13: 7.5 | L13: 2.5 | S13: =IF($M13="","",IF(ISNUMBER($M13),"Measured",IF(ISNUMBER(SEARCH("DATA GAP",UPPER($M13))),"Gap",IF(AND($N13<>"",$P13<>"T5"),"Documented","Judged")))) | T13: =IF($AC13<>"","",IF(OR($S13="",$S13="Gap"),"",IF($S13="Measured",1+IF($H13="H",IF($M13>=$I13,1,0)+IF($M13>=$J13,1,0)+IF($M13>=$K13,1,0)+IF($M13>=$L13,1,0),IF($M13<=$I13,1,0)+IF($M13<=$J13,1,0)+IF($M13<=$K13,1,0)+IF($M13<=$L13,1,0)),IF($R13<>"",$R13,"")))) | U13: =IF(OR($S13="",$S13="Gap",$Q13=""),"",IF($Q13<Config!$C$2-Config!$C$3,"STALE","")) | V13: =IF(OR(ISNUMBER(SEARCH("ALL",$E13)),ISNUMBER(SEARCH("ADV",$E13))),1,0) -> 0 | W13: =IF(OR(ISNUMBER(SEARCH("ALL",$E13)),ISNUMBER(SEARCH("SMF",$E13))),1,0) -> 0 | X13: =IF(OR(ISNUMBER(SEARCH("ALL",$E13)),ISNUMBER(SEARCH("MKT",$E13))),1,0) -> 0 | Y13: =IF(OR(ISNUMBER(SEARCH("ALL",$E13)),ISNUMBER(SEARCH("SCM",$E13))),1,0) -> 0 | Z13: =IF(OR(ISNUMBER(SEARCH("ALL",$E13)),ISNUMBER(SEARCH("FIN",$E13))),1,0) -> 0 | AA13: =IF(OR(ISNUMBER(SEARCH("ALL",$E13)),ISNUMBER(SEARCH("AGI",$E13))),1,0) -> 0
A14: 8.5 | B14: Women who own land (% holders) | C14: A1 | D14: Foundation | E14: NEED,EQ | G14: T | H14: H | I14: 10 | J14: 25 | K14: 40 | L14: 50 | S14: =IF($M14="","",IF(ISNUMBER($M14),"Measured",IF(ISNUMBER(SEARCH("DATA GAP",UPPER($M14))),"Gap",IF(AND($N14<>"",$P14<>"T5"),"Documented","Judged")))) | T14: =IF($AC14<>"","",IF(OR($S14="",$S14="Gap"),"",IF($S14="Measured",1+IF($H14="H",IF($M14>=$I14,1,0)+IF($M14>=$J14,1,0)+IF($M14>=$K14,1,0)+IF($M14>=$L14,1,0),IF($M14<=$I14,1,0)+IF($M14<=$J14,1,0)+IF($M14<=$K14,1,0)+IF($M14<=$L14,1,0)),IF($R14<>"",$R14,"")))) | U14: =IF(OR($S14="",$S14="Gap",$Q14=""),"",IF($Q14<Config!$C$2-Config!$C$3,"STALE","")) | V14: =IF(OR(ISNUMBER(SEARCH("ALL",$E14)),ISNUMBER(SEARCH("ADV",$E14))),1,0) -> 0 | W14: =IF(OR(ISNUMBER(SEARCH("ALL",$E14)),ISNUMBER(SEARCH("SMF",$E14))),1,0) -> 0 | X14: =IF(OR(ISNUMBER(SEARCH("ALL",$E14)),ISNUMBER(SEARCH("MKT",$E14))),1,0) -> 0 | Y14: =IF(OR(ISNUMBER(SEARCH("ALL",$E14)),ISNUMBER(SEARCH("SCM",$E14))),1,0) -> 0 | Z14: =IF(OR(ISNUMBER(SEARCH("ALL",$E14)),ISNUMBER(SEARCH("FIN",$E14))),1,0) -> 0 | AA14: =IF(OR(ISNUMBER(SEARCH("ALL",$E14)),ISNUMBER(SEARCH("AGI",$E14))),1,0) -> 0
A15: 2.1 | B15: Rural mobile broadband coverage (3G/4G) | C15: C1 | D15: Foundation | E15: ALL | F15: UNIVERSAL | G15: T | H15: H | I15: 20 | J15: 40 | K15: 60 | L15: 80 | S15: =IF($M15="","",IF(ISNUMBER($M15),"Measured",IF(ISNUMBER(SEARCH("DATA GAP",UPPER($M15))),"Gap",IF(AND($N15<>"",$P15<>"T5"),"Documented","Judged")))) | T15: =IF($AC15<>"","",IF(OR($S15="",$S15="Gap"),"",IF($S15="Measured",1+IF($H15="H",IF($M15>=$I15,1,0)+IF($M15>=$J15,1,0)+IF($M15>=$K15,1,0)+IF($M15>=$L15,1,0),IF($M15<=$I15,1,0)+IF($M15<=$J15,1,0)+IF($M15<=$K15,1,0)+IF($M15<=$L15,1,0)),IF($R15<>"",$R15,"")))) | U15: =IF(OR($S15="",$S15="Gap",$Q15=""),"",IF($Q15<Config!$C$2-Config!$C$3,"STALE","")) | V15: =IF(OR(ISNUMBER(SEARCH("ALL",$E15)),ISNUMBER(SEARCH("ADV",$E15))),1,0) -> 1 | W15: =IF(OR(ISNUMBER(SEARCH("ALL",$E15)),ISNUMBER(SEARCH("SMF",$E15))),1,0) -> 1 | X15: =IF(OR(ISNUMBER(SEARCH("ALL",$E15)),ISNUMBER(SEARCH("MKT",$E15))),1,0) -> 1 | Y15: =IF(OR(ISNUMBER(SEARCH("ALL",$E15)),ISNUMBER(SEARCH("SCM",$E15))),1,0) -> 1 | Z15: =IF(OR(ISNUMBER(SEARCH("ALL",$E15)),ISNUMBER(SEARCH("FIN",$E15))),1,0) -> 1 | AA15: =IF(OR(ISNUMBER(SEARCH("ALL",$E15)),ISNUMBER(SEARCH("AGI",$E15))),1,0) -> 1
A16: 2.4 | B16: Individuals using the Internet (%) | C16: C1 | D16: Foundation | E16: ALL | G16: T | H16: H | I16: 20 | J16: 40 | K16: 60 | L16: 80 | S16: =IF($M16="","",IF(ISNUMBER($M16),"Measured",IF(ISNUMBER(SEARCH("DATA GAP",UPPER($M16))),"Gap",IF(AND($N16<>"",$P16<>"T5"),"Documented","Judged")))) | T16: =IF($AC16<>"","",IF(OR($S16="",$S16="Gap"),"",IF($S16="Measured",1+IF($H16="H",IF($M16>=$I16,1,0)+IF($M16>=$J16,1,0)+IF($M16>=$K16,1,0)+IF($M16>=$L16,1,0),IF($M16<=$I16,1,0)+IF($M16<=$J16,1,0)+IF($M16<=$K16,1,0)+IF($M16<=$L16,1,0)),IF($R16<>"",$R16,"")))) | U16: =IF(OR($S16="",$S16="Gap",$Q16=""),"",IF($Q16<Config!$C$2-Config!$C$3,"STALE","")) | V16: =IF(OR(ISNUMBER(SEARCH("ALL",$E16)),ISNUMBER(SEARCH("ADV",$E16))),1,0) -> 1 | W16: =IF(OR(ISNUMBER(SEARCH("ALL",$E16)),ISNUMBER(SEARCH("SMF",$E16))),1,0) -> 1 | X16: =IF(OR(ISNUMBER(SEARCH("ALL",$E16)),ISNUMBER(SEARCH("MKT",$E16))),1,0) -> 1 | Y16: =IF(OR(ISNUMBER(SEARCH("ALL",$E16)),ISNUMBER(SEARCH("SCM",$E16))),1,0) -> 1 | Z16: =IF(OR(ISNUMBER(SEARCH("ALL",$E16)),ISNUMBER(SEARCH("FIN",$E16))),1,0) -> 1 | AA16: =IF(OR(ISNUMBER(SEARCH("ALL",$E16)),ISNUMBER(SEARCH("AGI",$E16))),1,0) -> 1
A17: 2.5 | B17: Mobile broadband price (% GNI pc) | C17: C1 | D17: Foundation | E17: ALL | G17: T | H17: L | I17: 10 | J17: 5 | K17: 2 | L17: 1 | S17: =IF($M17="","",IF(ISNUMBER($M17),"Measured",IF(ISNUMBER(SEARCH("DATA GAP",UPPER($M17))),"Gap",IF(AND($N17<>"",$P17<>"T5"),"Documented","Judged")))) | T17: =IF($AC17<>"","",IF(OR($S17="",$S17="Gap"),"",IF($S17="Measured",1+IF($H17="H",IF($M17>=$I17,1,0)+IF($M17>=$J17,1,0)+IF($M17>=$K17,1,0)+IF($M17>=$L17,1,0),IF($M17<=$I17,1,0)+IF($M17<=$J17,1,0)+IF($M17<=$K17,1,0)+IF($M17<=$L17,1,0)),IF($R17<>"",$R17,"")))) | U17: =IF(OR($S17="",$S17="Gap",$Q17=""),"",IF($Q17<Config!$C$2-Config!$C$3,"STALE","")) | V17: =IF(OR(ISNUMBER(SEARCH("ALL",$E17)),ISNUMBER(SEARCH("ADV",$E17))),1,0) -> 1 | W17: =IF(OR(ISNUMBER(SEARCH("ALL",$E17)),ISNUMBER(SEARCH("SMF",$E17))),1,0) -> 1 | X17: =IF(OR(ISNUMBER(SEARCH("ALL",$E17)),ISNUMBER(SEARCH("MKT",$E17))),1,0) -> 1 | Y17: =IF(OR(ISNUMBER(SEARCH("ALL",$E17)),ISNUMBER(SEARCH("SCM",$E17))),1,0) -> 1 | Z17: =IF(OR(ISNUMBER(SEARCH("ALL",$E17)),ISNUMBER(SEARCH("FIN",$E17))),1,0) -> 1 | AA17: =IF(OR(ISNUMBER(SEARCH("ALL",$E17)),ISNUMBER(SEARCH("AGI",$E17))),1,0) -> 1
A18: 2.7 | B18: Rural smartphone ownership (%) | C18: C1 | D18: Foundation | E18: ALL | G18: T | H18: H | I18: 20 | J18: 40 | K18: 60 | L18: 80 | S18: =IF($M18="","",IF(ISNUMBER($M18),"Measured",IF(ISNUMBER(SEARCH("DATA GAP",UPPER($M18))),"Gap",IF(AND($N18<>"",$P18<>"T5"),"Documented","Judged")))) | T18: =IF($AC18<>"","",IF(OR($S18="",$S18="Gap"),"",IF($S18="Measured",1+IF($H18="H",IF($M18>=$I18,1,0)+IF($M18>=$J18,1,0)+IF($M18>=$K18,1,0)+IF($M18>=$L18,1,0),IF($M18<=$I18,1,0)+IF($M18<=$J18,1,0)+IF($M18<=$K18,1,0)+IF($M18<=$L18,1,0)),IF($R18<>"",$R18,"")))) | U18: =IF(OR($S18="",$S18="Gap",$Q18=""),"",IF($Q18<Config!$C$2-Config!$C$3,"STALE","")) | V18: =IF(OR(ISNUMBER(SEARCH("ALL",$E18)),ISNUMBER(SEARCH("ADV",$E18))),1,0) -> 1 | W18: =IF(OR(ISNUMBER(SEARCH("ALL",$E18)),ISNUMBER(SEARCH("SMF",$E18))),1,0) -> 1 | X18: =IF(OR(ISNUMBER(SEARCH("ALL",$E18)),ISNUMBER(SEARCH("MKT",$E18))),1,0) -> 1 | Y18: =IF(OR(ISNUMBER(SEARCH("ALL",$E18)),ISNUMBER(SEARCH("SCM",$E18))),1,0) -> 1 | Z18: =IF(OR(ISNUMBER(SEARCH("ALL",$E18)),ISNUMBER(SEARCH("FIN",$E18))),1,0) -> 1 | AA18: =IF(OR(ISNUMBER(SEARCH("ALL",$E18)),ISNUMBER(SEARCH("AGI",$E18))),1,0) -> 1
A19: 2.9 | B19: Rural electricity access (%) | C19: C1 | D19: Foundation | E19: ALL | F19: UNIVERSAL | G19: T | H19: H | I19: 20 | J19: 40 | K19: 60 | L19: 80 | S19: =IF($M19="","",IF(ISNUMBER($M19),"Measured",IF(ISNUMBER(SEARCH("DATA GAP",UPPER($M19))),"Gap",IF(AND($N19<>"",$P19<>"T5"),"Documented","Judged")))) | T19: =IF($AC19<>"","",IF(OR($S19="",$S19="Gap"),"",IF($S19="Measured",1+IF($H19="H",IF($M19>=$I19,1,0)+IF($M19>=$J19,1,0)+IF($M19>=$K19,1,0)+IF($M19>=$L19,1,0),IF($M19<=$I19,1,0)+IF($M19<=$J19,1,0)+IF($M19<=$K19,1,0)+IF($M19<=$L19,1,0)),IF($R19<>"",$R19,"")))) | U19: =IF(OR($S19="",$S19="Gap",$Q19=""),"",IF($Q19<Config!$C$2-Config!$C$3,"STALE","")) | V19: =IF(OR(ISNUMBER(SEARCH("ALL",$E19)),ISNUMBER(SEARCH("ADV",$E19))),1,0) -> 1 | W19: =IF(OR(ISNUMBER(SEARCH("ALL",$E19)),ISNUMBER(SEARCH("SMF",$E19))),1,0) -> 1 | X19: =IF(OR(ISNUMBER(SEARCH("ALL",$E19)),ISNUMBER(SEARCH("MKT",$E19))),1,0) -> 1 | Y19: =IF(OR(ISNUMBER(SEARCH("ALL",$E19)),ISNUMBER(SEARCH("SCM",$E19))),1,0) -> 1 | Z19: =IF(OR(ISNUMBER(SEARCH("ALL",$E19)),ISNUMBER(SEARCH("FIN",$E19))),1,0) -> 1 | AA19: =IF(OR(ISNUMBER(SEARCH("ALL",$E19)),ISNUMBER(SEARCH("AGI",$E19))),1,0) -> 1
A20: 2.11 | B20: Device financing/subsidy schemes | C20: C1 | D20: Foundation | E20: ALL | G20: L | S20: =IF($M20="","",IF(ISNUMBER($M20),"Measured",IF(ISNUMBER(SEARCH("DATA GAP",UPPER($M20))),"Gap",IF(AND($N20<>"",$P20<>"T5"),"Documented","Judged")))) | T20: =IF($AC20<>"","",IF(OR($S20="",$S20="Gap"),"",IF($S20="Measured",1+IF($H20="H",IF($M20>=$I20,1,0)+IF($M20>=$J20,1,0)+IF($M20>=$K20,1,0)+IF($M20>=$L20,1,0),IF($M20<=$I20,1,0)+IF($M20<=$J20,1,0)+IF($M20<=$K20,1,0)+IF($M20<=$L20,1,0)),IF($R20<>"",$R20,"")))) | U20: =IF(OR($S20="",$S20="Gap",$Q20=""),"",IF($Q20<Config!$C$2-Config!$C$3,"STALE","")) | V20: =IF(OR(ISNUMBER(SEARCH("ALL",$E20)),ISNUMBER(SEARCH("ADV",$E20))),1,0) -> 1 | W20: =IF(OR(ISNUMBER(SEARCH("ALL",$E20)),ISNUMBER(SEARCH("SMF",$E20))),1,0) -> 1 | X20: =IF(OR(ISNUMBER(SEARCH("ALL",$E20)),ISNUMBER(SEARCH("MKT",$E20))),1,0) -> 1 | Y20: =IF(OR(ISNUMBER(SEARCH("ALL",$E20)),ISNUMBER(SEARCH("SCM",$E20))),1,0) -> 1 | Z20: =IF(OR(ISNUMBER(SEARCH("ALL",$E20)),ISNUMBER(SEARCH("FIN",$E20))),1,0) -> 1 | AA20: =IF(OR(ISNUMBER(SEARCH("ALL",$E20)),ISNUMBER(SEARCH("AGI",$E20))),1,0) -> 1
A21: 3.1 | B21: UN E-Government Development Index | C21: C2 | D21: Enablers | E21: AGI,ALL | G21: T | H21: H | I21: 0.2 | J21: 0.4 | K21: 0.6 | L21: 0.8 | S21: =IF($M21="","",IF(ISNUMBER($M21),"Measured",IF(ISNUMBER(SEARCH("DATA GAP",UPPER($M21))),"Gap",IF(AND($N21<>"",$P21<>"T5"),"Documented","Judged")))) | T21: =IF($AC21<>"","",IF(OR($S21="",$S21="Gap"),"",IF($S21="Measured",1+IF($H21="H",IF($M21>=$I21,1,0)+IF($M21>=$J21,1,0)+IF($M21>=$K21,1,0)+IF($M21>=$L21,1,0),IF($M21<=$I21,1,0)+IF($M21<=$J21,1,0)+IF($M21<=$K21,1,0)+IF($M21<=$L21,1,0)),IF($R21<>"",$R21,"")))) | U21: =IF(OR($S21="",$S21="Gap",$Q21=""),"",IF($Q21<Config!$C$2-Config!$C$3,"STALE","")) | V21: =IF(OR(ISNUMBER(SEARCH("ALL",$E21)),ISNUMBER(SEARCH("ADV",$E21))),1,0) -> 1 | W21: =IF(OR(ISNUMBER(SEARCH("ALL",$E21)),ISNUMBER(SEARCH("SMF",$E21))),1,0) -> 1 | X21: =IF(OR(ISNUMBER(SEARCH("ALL",$E21)),ISNUMBER(SEARCH("MKT",$E21))),1,0) -> 1 | Y21: =IF(OR(ISNUMBER(SEARCH("ALL",$E21)),ISNUMBER(SEARCH("SCM",$E21))),1,0) -> 1 | Z21: =IF(OR(ISNUMBER(SEARCH("ALL",$E21)),ISNUMBER(SEARCH("FIN",$E21))),1,0) -> 1 | AA21: =IF(OR(ISNUMBER(SEARCH("ALL",$E21)),ISNUMBER(SEARCH("AGI",$E21))),1,0) -> 1
A22: 3.3 | B22: National farmer registry | C22: C2 | D22: Enablers | E22: FIN,AGI,ADV | F22: UC:FIN,AGI | G22: L | S22: =IF($M22="","",IF(ISNUMBER($M22),"Measured",IF(ISNUMBER(SEARCH("DATA GAP",UPPER($M22))),"Gap",IF(AND($N22<>"",$P22<>"T5"),"Documented","Judged")))) | T22: =IF($AC22<>"","",IF(OR($S22="",$S22="Gap"),"",IF($S22="Measured",1+IF($H22="H",IF($M22>=$I22,1,0)+IF($M22>=$J22,1,0)+IF($M22>=$K22,1,0)+IF($M22>=$L22,1,0),IF($M22<=$I22,1,0)+IF($M22<=$J22,1,0)+IF($M22<=$K22,1,0)+IF($M22<=$L22,1,0)),IF($R22<>"",$R22,"")))) | U22: =IF(OR($S22="",$S22="Gap",$Q22=""),"",IF($Q22<Config!$C$2-Config!$C$3,"STALE","")) | V22: =IF(OR(ISNUMBER(SEARCH("ALL",$E22)),ISNUMBER(SEARCH("ADV",$E22))),1,0) -> 1 | W22: =IF(OR(ISNUMBER(SEARCH("ALL",$E22)),ISNUMBER(SEARCH("SMF",$E22))),1,0) -> 0 | X22: =IF(OR(ISNUMBER(SEARCH("ALL",$E22)),ISNUMBER(SEARCH("MKT",$E22))),1,0) -> 0 | Y22: =IF(OR(ISNUMBER(SEARCH("ALL",$E22)),ISNUMBER(SEARCH("SCM",$E22))),1,0) -> 0 | Z22: =IF(OR(ISNUMBER(SEARCH("ALL",$E22)),ISNUMBER(SEARCH("FIN",$E22))),1,0) -> 1 | AA22: =IF(OR(ISNUMBER(SEARCH("ALL",$E22)),ISNUMBER(SEARCH("AGI",$E22))),1,0) -> 1
A23: 3.4 | B23: Digital land/plot registration | C23: C2 | D23: Enablers | E23: FIN,AGI | G23: L | S23: =IF($M23="","",IF(ISNUMBER($M23),"Measured",IF(ISNUMBER(SEARCH("DATA GAP",UPPER($M23))),"Gap",IF(AND($N23<>"",$P23<>"T5"),"Documented","Judged")))) | T23: =IF($AC23<>"","",IF(OR($S23="",$S23="Gap"),"",IF($S23="Measured",1+IF($H23="H",IF($M23>=$I23,1,0)+IF($M23>=$J23,1,0)+IF($M23>=$K23,1,0)+IF($M23>=$L23,1,0),IF($M23<=$I23,1,0)+IF($M23<=$J23,1,0)+IF($M23<=$K23,1,0)+IF($M23<=$L23,1,0)),IF($R23<>"",$R23,"")))) | U23: =IF(OR($S23="",$S23="Gap",$Q23=""),"",IF($Q23<Config!$C$2-Config!$C$3,"STALE","")) | V23: =IF(OR(ISNUMBER(SEARCH("ALL",$E23)),ISNUMBER(SEARCH("ADV",$E23))),1,0) -> 0 | W23: =IF(OR(ISNUMBER(SEARCH("ALL",$E23)),ISNUMBER(SEARCH("SMF",$E23))),1,0) -> 0 | X23: =IF(OR(ISNUMBER(SEARCH("ALL",$E23)),ISNUMBER(SEARCH("MKT",$E23))),1,0) -> 0 | Y23: =IF(OR(ISNUMBER(SEARCH("ALL",$E23)),ISNUMBER(SEARCH("SCM",$E23))),1,0) -> 0 | Z23: =IF(OR(ISNUMBER(SEARCH("ALL",$E23)),ISNUMBER(SEARCH("FIN",$E23))),1,0) -> 1 | AA23: =IF(OR(ISNUMBER(SEARCH("ALL",$E23)),ISNUMBER(SEARCH("AGI",$E23))),1,0) -> 1
A24: 3.5 | B24: Open agricultural data (machine-readable, AI-ready) | C24: C2 | D24: Enablers | E24: AGI,ADV,SMF | G24: L | S24: =IF($M24="","",IF(ISNUMBER($M24),"Measured",IF(ISNUMBER(SEARCH("DATA GAP",UPPER($M24))),"Gap",IF(AND($N24<>"",$P24<>"T5"),"Documented","Judged")))) | T24: =IF($AC24<>"","",IF(OR($S24="",$S24="Gap"),"",IF($S24="Measured",1+IF($H24="H",IF($M24>=$I24,1,0)+IF($M24>=$J24,1,0)+IF($M24>=$K24,1,0)+IF($M24>=$L24,1,0),IF($M24<=$I24,1,0)+IF($M24<=$J24,1,0)+IF($M24<=$K24,1,0)+IF($M24<=$L24,1,0)),IF($R24<>"",$R24,"")))) | U24: =IF(OR($S24="",$S24="Gap",$Q24=""),"",IF($Q24<Config!$C$2-Config!$C$3,"STALE","")) | V24: =IF(OR(ISNUMBER(SEARCH("ALL",$E24)),ISNUMBER(SEARCH("ADV",$E24))),1,0) -> 1 | W24: =IF(OR(ISNUMBER(SEARCH("ALL",$E24)),ISNUMBER(SEARCH("SMF",$E24))),1,0) -> 1 | X24: =IF(OR(ISNUMBER(SEARCH("ALL",$E24)),ISNUMBER(SEARCH("MKT",$E24))),1,0) -> 0 | Y24: =IF(OR(ISNUMBER(SEARCH("ALL",$E24)),ISNUMBER(SEARCH("SCM",$E24))),1,0) -> 0 | Z24: =IF(OR(ISNUMBER(SEARCH("ALL",$E24)),ISNUMBER(SEARCH("FIN",$E24))),1,0) -> 0 | AA24: =IF(OR(ISNUMBER(SEARCH("ALL",$E24)),ISNUMBER(SEARCH("AGI",$E24))),1,0) -> 1
A25: 3.6 | B25: Weather/climate data infrastructure | C25: C2 | D25: Enablers | E25: ADV,SMF,AGI | G25: L | S25: =IF($M25="","",IF(ISNUMBER($M25),"Measured",IF(ISNUMBER(SEARCH("DATA GAP",UPPER($M25))),"Gap",IF(AND($N25<>"",$P25<>"T5"),"Documented","Judged")))) | T25: =IF($AC25<>"","",IF(OR($S25="",$S25="Gap"),"",IF($S25="Measured",1+IF($H25="H",IF($M25>=$I25,1,0)+IF($M25>=$J25,1,0)+IF($M25>=$K25,1,0)+IF($M25>=$L25,1,0),IF($M25<=$I25,1,0)+IF($M25<=$J25,1,0)+IF($M25<=$K25,1,0)+IF($M25<=$L25,1,0)),IF($R25<>"",$R25,"")))) | U25: =IF(OR($S25="",$S25="Gap",$Q25=""),"",IF($Q25<Config!$C$2-Config!$C$3,"STALE","")) | V25: =IF(OR(ISNUMBER(SEARCH("ALL",$E25)),ISNUMBER(SEARCH("ADV",$E25))),1,0) -> 1 | W25: =IF(OR(ISNUMBER(SEARCH("ALL",$E25)),ISNUMBER(SEARCH("SMF",$E25))),1,0) -> 1 | X25: =IF(OR(ISNUMBER(SEARCH("ALL",$E25)),ISNUMBER(SEARCH("MKT",$E25))),1,0) -> 0 | Y25: =IF(OR(ISNUMBER(SEARCH("ALL",$E25)),ISNUMBER(SEARCH("SCM",$E25))),1,0) -> 0 | Z25: =IF(OR(ISNUMBER(SEARCH("ALL",$E25)),ISNUMBER(SEARCH("FIN",$E25))),1,0) -> 0 | AA25: =IF(OR(ISNUMBER(SEARCH("ALL",$E25)),ISNUMBER(SEARCH("AGI",$E25))),1,0) -> 1
A26: 3.7 | B26: Satellite/EO data integration | C26: C2 | D26: Enablers | E26: AGI,SMF | G26: L | S26: =IF($M26="","",IF(ISNUMBER($M26),"Measured",IF(ISNUMBER(SEARCH("DATA GAP",UPPER($M26))),"Gap",IF(AND($N26<>"",$P26<>"T5"),"Documented","Judged")))) | T26: =IF($AC26<>"","",IF(OR($S26="",$S26="Gap"),"",IF($S26="Measured",1+IF($H26="H",IF($M26>=$I26,1,0)+IF($M26>=$J26,1,0)+IF($M26>=$K26,1,0)+IF($M26>=$L26,1,0),IF($M26<=$I26,1,0)+IF($M26<=$J26,1,0)+IF($M26<=$K26,1,0)+IF($M26<=$L26,1,0)),IF($R26<>"",$R26,"")))) | U26: =IF(OR($S26="",$S26="Gap",$Q26=""),"",IF($Q26<Config!$C$2-Config!$C$3,"STALE","")) | V26: =IF(OR(ISNUMBER(SEARCH("ALL",$E26)),ISNUMBER(SEARCH("ADV",$E26))),1,0) -> 0 | W26: =IF(OR(ISNUMBER(SEARCH("ALL",$E26)),ISNUMBER(SEARCH("SMF",$E26))),1,0) -> 1 | X26: =IF(OR(ISNUMBER(SEARCH("ALL",$E26)),ISNUMBER(SEARCH("MKT",$E26))),1,0) -> 0 | Y26: =IF(OR(ISNUMBER(SEARCH("ALL",$E26)),ISNUMBER(SEARCH("SCM",$E26))),1,0) -> 0 | Z26: =IF(OR(ISNUMBER(SEARCH("ALL",$E26)),ISNUMBER(SEARCH("FIN",$E26))),1,0) -> 0 | AA26: =IF(OR(ISNUMBER(SEARCH("ALL",$E26)),ISNUMBER(SEARCH("AGI",$E26))),1,0) -> 1
A27: 3.8 | B27: National soil map/database | C27: C2 | D27: Enablers | E27: ADV,SMF | G27: L | S27: =IF($M27="","",IF(ISNUMBER($M27),"Measured",IF(ISNUMBER(SEARCH("DATA GAP",UPPER($M27))),"Gap",IF(AND($N27<>"",$P27<>"T5"),"Documented","Judged")))) | T27: =IF($AC27<>"","",IF(OR($S27="",$S27="Gap"),"",IF($S27="Measured",1+IF($H27="H",IF($M27>=$I27,1,0)+IF($M27>=$J27,1,0)+IF($M27>=$K27,1,0)+IF($M27>=$L27,1,0),IF($M27<=$I27,1,0)+IF($M27<=$J27,1,0)+IF($M27<=$K27,1,0)+IF($M27<=$L27,1,0)),IF($R27<>"",$R27,"")))) | U27: =IF(OR($S27="",$S27="Gap",$Q27=""),"",IF($Q27<Config!$C$2-Config!$C$3,"STALE","")) | V27: =IF(OR(ISNUMBER(SEARCH("ALL",$E27)),ISNUMBER(SEARCH("ADV",$E27))),1,0) -> 1 | W27: =IF(OR(ISNUMBER(SEARCH("ALL",$E27)),ISNUMBER(SEARCH("SMF",$E27))),1,0) -> 1 | X27: =IF(OR(ISNUMBER(SEARCH("ALL",$E27)),ISNUMBER(SEARCH("MKT",$E27))),1,0) -> 0 | Y27: =IF(OR(ISNUMBER(SEARCH("ALL",$E27)),ISNUMBER(SEARCH("SCM",$E27))),1,0) -> 0 | Z27: =IF(OR(ISNUMBER(SEARCH("ALL",$E27)),ISNUMBER(SEARCH("FIN",$E27))),1,0) -> 0 | AA27: =IF(OR(ISNUMBER(SEARCH("ALL",$E27)),ISNUMBER(SEARCH("AGI",$E27))),1,0) -> 0
A28: 3.11 | B28: Agricultural data interoperability standards | C28: C2 | D28: Enablers | E28: AGI,ALL | F28: UC:AGI | G28: L | S28: =IF($M28="","",IF(ISNUMBER($M28),"Measured",IF(ISNUMBER(SEARCH("DATA GAP",UPPER($M28))),"Gap",IF(AND($N28<>"",$P28<>"T5"),"Documented","Judged")))) | T28: =IF($AC28<>"","",IF(OR($S28="",$S28="Gap"),"",IF($S28="Measured",1+IF($H28="H",IF($M28>=$I28,1,0)+IF($M28>=$J28,1,0)+IF($M28>=$K28,1,0)+IF($M28>=$L28,1,0),IF($M28<=$I28,1,0)+IF($M28<=$J28,1,0)+IF($M28<=$K28,1,0)+IF($M28<=$L28,1,0)),IF($R28<>"",$R28,"")))) | U28: =IF(OR($S28="",$S28="Gap",$Q28=""),"",IF($Q28<Config!$C$2-Config!$C$3,"STALE","")) | V28: =IF(OR(ISNUMBER(SEARCH("ALL",$E28)),ISNUMBER(SEARCH("ADV",$E28))),1,0) -> 1 | W28: =IF(OR(ISNUMBER(SEARCH("ALL",$E28)),ISNUMBER(SEARCH("SMF",$E28))),1,0) -> 1 | X28: =IF(OR(ISNUMBER(SEARCH("ALL",$E28)),ISNUMBER(SEARCH("MKT",$E28))),1,0) -> 1 | Y28: =IF(OR(ISNUMBER(SEARCH("ALL",$E28)),ISNUMBER(SEARCH("SCM",$E28))),1,0) -> 1 | Z28: =IF(OR(ISNUMBER(SEARCH("ALL",$E28)),ISNUMBER(SEARCH("FIN",$E28))),1,0) -> 1 | AA28: =IF(OR(ISNUMBER(SEARCH("ALL",$E28)),ISNUMBER(SEARCH("AGI",$E28))),1,0) -> 1
A29: 4.1 | B29: Data protection/privacy law | C29: C3 | D29: Enablers | E29: ALL | F29: UNIVERSAL | G29: L | S29: =IF($M29="","",IF(ISNUMBER($M29),"Measured",IF(ISNUMBER(SEARCH("DATA GAP",UPPER($M29))),"Gap",IF(AND($N29<>"",$P29<>"T5"),"Documented","Judged")))) | T29: =IF($AC29<>"","",IF(OR($S29="",$S29="Gap"),"",IF($S29="Measured",1+IF($H29="H",IF($M29>=$I29,1,0)+IF($M29>=$J29,1,0)+IF($M29>=$K29,1,0)+IF($M29>=$L29,1,0),IF($M29<=$I29,1,0)+IF($M29<=$J29,1,0)+IF($M29<=$K29,1,0)+IF($M29<=$L29,1,0)),IF($R29<>"",$R29,"")))) | U29: =IF(OR($S29="",$S29="Gap",$Q29=""),"",IF($Q29<Config!$C$2-Config!$C$3,"STALE","")) | V29: =IF(OR(ISNUMBER(SEARCH("ALL",$E29)),ISNUMBER(SEARCH("ADV",$E29))),1,0) -> 1 | W29: =IF(OR(ISNUMBER(SEARCH("ALL",$E29)),ISNUMBER(SEARCH("SMF",$E29))),1,0) -> 1 | X29: =IF(OR(ISNUMBER(SEARCH("ALL",$E29)),ISNUMBER(SEARCH("MKT",$E29))),1,0) -> 1 | Y29: =IF(OR(ISNUMBER(SEARCH("ALL",$E29)),ISNUMBER(SEARCH("SCM",$E29))),1,0) -> 1 | Z29: =IF(OR(ISNUMBER(SEARCH("ALL",$E29)),ISNUMBER(SEARCH("FIN",$E29))),1,0) -> 1 | AA29: =IF(OR(ISNUMBER(SEARCH("ALL",$E29)),ISNUMBER(SEARCH("AGI",$E29))),1,0) -> 1
A30: 4.2 | B30: Cybersecurity framework (ITU GCI) | C30: C3 | D30: Enablers | E30: ALL | G30: T | H30: H | I30: 0.2 | J30: 0.4 | K30: 0.6 | L30: 0.8 | S30: =IF($M30="","",IF(ISNUMBER($M30),"Measured",IF(ISNUMBER(SEARCH("DATA GAP",UPPER($M30))),"Gap",IF(AND($N30<>"",$P30<>"T5"),"Documented","Judged")))) | T30: =IF($AC30<>"","",IF(OR($S30="",$S30="Gap"),"",IF($S30="Measured",1+IF($H30="H",IF($M30>=$I30,1,0)+IF($M30>=$J30,1,0)+IF($M30>=$K30,1,0)+IF($M30>=$L30,1,0),IF($M30<=$I30,1,0)+IF($M30<=$J30,1,0)+IF($M30<=$K30,1,0)+IF($M30<=$L30,1,0)),IF($R30<>"",$R30,"")))) | U30: =IF(OR($S30="",$S30="Gap",$Q30=""),"",IF($Q30<Config!$C$2-Config!$C$3,"STALE","")) | V30: =IF(OR(ISNUMBER(SEARCH("ALL",$E30)),ISNUMBER(SEARCH("ADV",$E30))),1,0) -> 1 | W30: =IF(OR(ISNUMBER(SEARCH("ALL",$E30)),ISNUMBER(SEARCH("SMF",$E30))),1,0) -> 1 | X30: =IF(OR(ISNUMBER(SEARCH("ALL",$E30)),ISNUMBER(SEARCH("MKT",$E30))),1,0) -> 1 | Y30: =IF(OR(ISNUMBER(SEARCH("ALL",$E30)),ISNUMBER(SEARCH("SCM",$E30))),1,0) -> 1 | Z30: =IF(OR(ISNUMBER(SEARCH("ALL",$E30)),ISNUMBER(SEARCH("FIN",$E30))),1,0) -> 1 | AA30: =IF(OR(ISNUMBER(SEARCH("ALL",$E30)),ISNUMBER(SEARCH("AGI",$E30))),1,0) -> 1
A31: 4.3 | B31: Government AI Readiness Index | C31: C3 | D31: Enablers | E31: AGI,ALL | G31: T | H31: H | I31: 20 | J31: 40 | K31: 60 | L31: 80 | S31: =IF($M31="","",IF(ISNUMBER($M31),"Measured",IF(ISNUMBER(SEARCH("DATA GAP",UPPER($M31))),"Gap",IF(AND($N31<>"",$P31<>"T5"),"Documented","Judged")))) | T31: =IF($AC31<>"","",IF(OR($S31="",$S31="Gap"),"",IF($S31="Measured",1+IF($H31="H",IF($M31>=$I31,1,0)+IF($M31>=$J31,1,0)+IF($M31>=$K31,1,0)+IF($M31>=$L31,1,0),IF($M31<=$I31,1,0)+IF($M31<=$J31,1,0)+IF($M31<=$K31,1,0)+IF($M31<=$L31,1,0)),IF($R31<>"",$R31,"")))) | U31: =IF(OR($S31="",$S31="Gap",$Q31=""),"",IF($Q31<Config!$C$2-Config!$C$3,"STALE","")) | V31: =IF(OR(ISNUMBER(SEARCH("ALL",$E31)),ISNUMBER(SEARCH("ADV",$E31))),1,0) -> 1 | W31: =IF(OR(ISNUMBER(SEARCH("ALL",$E31)),ISNUMBER(SEARCH("SMF",$E31))),1,0) -> 1 | X31: =IF(OR(ISNUMBER(SEARCH("ALL",$E31)),ISNUMBER(SEARCH("MKT",$E31))),1,0) -> 1 | Y31: =IF(OR(ISNUMBER(SEARCH("ALL",$E31)),ISNUMBER(SEARCH("SCM",$E31))),1,0) -> 1 | Z31: =IF(OR(ISNUMBER(SEARCH("ALL",$E31)),ISNUMBER(SEARCH("FIN",$E31))),1,0) -> 1 | AA31: =IF(OR(ISNUMBER(SEARCH("ALL",$E31)),ISNUMBER(SEARCH("AGI",$E31))),1,0) -> 1
A32: 4.4 | B32: National digital agriculture strategy | C32: C3 | D32: Enablers | E32: ALL | G32: L | S32: =IF($M32="","",IF(ISNUMBER($M32),"Measured",IF(ISNUMBER(SEARCH("DATA GAP",UPPER($M32))),"Gap",IF(AND($N32<>"",$P32<>"T5"),"Documented","Judged")))) | T32: =IF($AC32<>"","",IF(OR($S32="",$S32="Gap"),"",IF($S32="Measured",1+IF($H32="H",IF($M32>=$I32,1,0)+IF($M32>=$J32,1,0)+IF($M32>=$K32,1,0)+IF($M32>=$L32,1,0),IF($M32<=$I32,1,0)+IF($M32<=$J32,1,0)+IF($M32<=$K32,1,0)+IF($M32<=$L32,1,0)),IF($R32<>"",$R32,"")))) | U32: =IF(OR($S32="",$S32="Gap",$Q32=""),"",IF($Q32<Config!$C$2-Config!$C$3,"STALE","")) | V32: =IF(OR(ISNUMBER(SEARCH("ALL",$E32)),ISNUMBER(SEARCH("ADV",$E32))),1,0) -> 1 | W32: =IF(OR(ISNUMBER(SEARCH("ALL",$E32)),ISNUMBER(SEARCH("SMF",$E32))),1,0) -> 1 | X32: =IF(OR(ISNUMBER(SEARCH("ALL",$E32)),ISNUMBER(SEARCH("MKT",$E32))),1,0) -> 1 | Y32: =IF(OR(ISNUMBER(SEARCH("ALL",$E32)),ISNUMBER(SEARCH("SCM",$E32))),1,0) -> 1 | Z32: =IF(OR(ISNUMBER(SEARCH("ALL",$E32)),ISNUMBER(SEARCH("FIN",$E32))),1,0) -> 1 | AA32: =IF(OR(ISNUMBER(SEARCH("ALL",$E32)),ISNUMBER(SEARCH("AGI",$E32))),1,0) -> 1
A33: 4.5 | B33: Agricultural data governance framework | C33: C3 | D33: Enablers | E33: AGI,FIN | F33: UC:AGI | G33: L | S33: =IF($M33="","",IF(ISNUMBER($M33),"Measured",IF(ISNUMBER(SEARCH("DATA GAP",UPPER($M33))),"Gap",IF(AND($N33<>"",$P33<>"T5"),"Documented","Judged")))) | T33: =IF($AC33<>"","",IF(OR($S33="",$S33="Gap"),"",IF($S33="Measured",1+IF($H33="H",IF($M33>=$I33,1,0)+IF($M33>=$J33,1,0)+IF($M33>=$K33,1,0)+IF($M33>=$L33,1,0),IF($M33<=$I33,1,0)+IF($M33<=$J33,1,0)+IF($M33<=$K33,1,0)+IF($M33<=$L33,1,0)),IF($R33<>"",$R33,"")))) | U33: =IF(OR($S33="",$S33="Gap",$Q33=""),"",IF($Q33<Config!$C$2-Config!$C$3,"STALE","")) | V33: =IF(OR(ISNUMBER(SEARCH("ALL",$E33)),ISNUMBER(SEARCH("ADV",$E33))),1,0) -> 0 | W33: =IF(OR(ISNUMBER(SEARCH("ALL",$E33)),ISNUMBER(SEARCH("SMF",$E33))),1,0) -> 0 | X33: =IF(OR(ISNUMBER(SEARCH("ALL",$E33)),ISNUMBER(SEARCH("MKT",$E33))),1,0) -> 0 | Y33: =IF(OR(ISNUMBER(SEARCH("ALL",$E33)),ISNUMBER(SEARCH("SCM",$E33))),1,0) -> 0 | Z33: =IF(OR(ISNUMBER(SEARCH("ALL",$E33)),ISNUMBER(SEARCH("FIN",$E33))),1,0) -> 1 | AA33: =IF(OR(ISNUMBER(SEARCH("ALL",$E33)),ISNUMBER(SEARCH("AGI",$E33))),1,0) -> 1
A34: 4.6 | B34: National AI strategy with agriculture component | C34: C3 | D34: Enablers | E34: AGI,ALL | G34: L | S34: =IF($M34="","",IF(ISNUMBER($M34),"Measured",IF(ISNUMBER(SEARCH("DATA GAP",UPPER($M34))),"Gap",IF(AND($N34<>"",$P34<>"T5"),"Documented","Judged")))) | T34: =IF($AC34<>"","",IF(OR($S34="",$S34="Gap"),"",IF($S34="Measured",1+IF($H34="H",IF($M34>=$I34,1,0)+IF($M34>=$J34,1,0)+IF($M34>=$K34,1,0)+IF($M34>=$L34,1,0),IF($M34<=$I34,1,0)+IF($M34<=$J34,1,0)+IF($M34<=$K34,1,0)+IF($M34<=$L34,1,0)),IF($R34<>"",$R34,"")))) | U34: =IF(OR($S34="",$S34="Gap",$Q34=""),"",IF($Q34<Config!$C$2-Config!$C$3,"STALE","")) | V34: =IF(OR(ISNUMBER(SEARCH("ALL",$E34)),ISNUMBER(SEARCH("ADV",$E34))),1,0) -> 1 | W34: =IF(OR(ISNUMBER(SEARCH("ALL",$E34)),ISNUMBER(SEARCH("SMF",$E34))),1,0) -> 1 | X34: =IF(OR(ISNUMBER(SEARCH("ALL",$E34)),ISNUMBER(SEARCH("MKT",$E34))),1,0) -> 1 | Y34: =IF(OR(ISNUMBER(SEARCH("ALL",$E34)),ISNUMBER(SEARCH("SCM",$E34))),1,0) -> 1 | Z34: =IF(OR(ISNUMBER(SEARCH("ALL",$E34)),ISNUMBER(SEARCH("FIN",$E34))),1,0) -> 1 | AA34: =IF(OR(ISNUMBER(SEARCH("ALL",$E34)),ISNUMBER(SEARCH("AGI",$E34))),1,0) -> 1
A35: 4.7 | B35: Digital ID coverage (%) | C35: C3 | D35: Enablers | E35: FIN,ALL | F35: UC:FIN | G35: T | H35: H | I35: 20 | J35: 40 | K35: 60 | L35: 80 | S35: =IF($M35="","",IF(ISNUMBER($M35),"Measured",IF(ISNUMBER(SEARCH("DATA GAP",UPPER($M35))),"Gap",IF(AND($N35<>"",$P35<>"T5"),"Documented","Judged")))) | T35: =IF($AC35<>"","",IF(OR($S35="",$S35="Gap"),"",IF($S35="Measured",1+IF($H35="H",IF($M35>=$I35,1,0)+IF($M35>=$J35,1,0)+IF($M35>=$K35,1,0)+IF($M35>=$L35,1,0),IF($M35<=$I35,1,0)+IF($M35<=$J35,1,0)+IF($M35<=$K35,1,0)+IF($M35<=$L35,1,0)),IF($R35<>"",$R35,"")))) | U35: =IF(OR($S35="",$S35="Gap",$Q35=""),"",IF($Q35<Config!$C$2-Config!$C$3,"STALE","")) | V35: =IF(OR(ISNUMBER(SEARCH("ALL",$E35)),ISNUMBER(SEARCH("ADV",$E35))),1,0) -> 1 | W35: =IF(OR(ISNUMBER(SEARCH("ALL",$E35)),ISNUMBER(SEARCH("SMF",$E35))),1,0) -> 1 | X35: =IF(OR(ISNUMBER(SEARCH("ALL",$E35)),ISNUMBER(SEARCH("MKT",$E35))),1,0) -> 1 | Y35: =IF(OR(ISNUMBER(SEARCH("ALL",$E35)),ISNUMBER(SEARCH("SCM",$E35))),1,0) -> 1 | Z35: =IF(OR(ISNUMBER(SEARCH("ALL",$E35)),ISNUMBER(SEARCH("FIN",$E35))),1,0) -> 1 | AA35: =IF(OR(ISNUMBER(SEARCH("ALL",$E35)),ISNUMBER(SEARCH("AGI",$E35))),1,0) -> 1
A36: 4.9 | B36: Inter-ministerial coordination mechanism | C36: C3 | D36: Enablers | E36: ALL | F36: DELIVERY | G36: L | S36: =IF($M36="","",IF(ISNUMBER($M36),"Measured",IF(ISNUMBER(SEARCH("DATA GAP",UPPER($M36))),"Gap",IF(AND($N36<>"",$P36<>"T5"),"Documented","Judged")))) | T36: =IF($AC36<>"","",IF(OR($S36="",$S36="Gap"),"",IF($S36="Measured",1+IF($H36="H",IF($M36>=$I36,1,0)+IF($M36>=$J36,1,0)+IF($M36>=$K36,1,0)+IF($M36>=$L36,1,0),IF($M36<=$I36,1,0)+IF($M36<=$J36,1,0)+IF($M36<=$K36,1,0)+IF($M36<=$L36,1,0)),IF($R36<>"",$R36,"")))) | U36: =IF(OR($S36="",$S36="Gap",$Q36=""),"",IF($Q36<Config!$C$2-Config!$C$3,"STALE","")) | V36: =IF(OR(ISNUMBER(SEARCH("ALL",$E36)),ISNUMBER(SEARCH("ADV",$E36))),1,0) -> 1 | W36: =IF(OR(ISNUMBER(SEARCH("ALL",$E36)),ISNUMBER(SEARCH("SMF",$E36))),1,0) -> 1 | X36: =IF(OR(ISNUMBER(SEARCH("ALL",$E36)),ISNUMBER(SEARCH("MKT",$E36))),1,0) -> 1 | Y36: =IF(OR(ISNUMBER(SEARCH("ALL",$E36)),ISNUMBER(SEARCH("SCM",$E36))),1,0) -> 1 | Z36: =IF(OR(ISNUMBER(SEARCH("ALL",$E36)),ISNUMBER(SEARCH("FIN",$E36))),1,0) -> 1 | AA36: =IF(OR(ISNUMBER(SEARCH("ALL",$E36)),ISNUMBER(SEARCH("AGI",$E36))),1,0) -> 1
A37: 5.2 | B37: Adult literacy rate (%) | C37: C4 | D37: Enablers | E37: ALL | G37: T | H37: H | I37: 50 | J37: 65 | K37: 80 | L37: 90 | S37: =IF($M37="","",IF(ISNUMBER($M37),"Measured",IF(ISNUMBER(SEARCH("DATA GAP",UPPER($M37))),"Gap",IF(AND($N37<>"",$P37<>"T5"),"Documented","Judged")))) | T37: =IF($AC37<>"","",IF(OR($S37="",$S37="Gap"),"",IF($S37="Measured",1+IF($H37="H",IF($M37>=$I37,1,0)+IF($M37>=$J37,1,0)+IF($M37>=$K37,1,0)+IF($M37>=$L37,1,0),IF($M37<=$I37,1,0)+IF($M37<=$J37,1,0)+IF($M37<=$K37,1,0)+IF($M37<=$L37,1,0)),IF($R37<>"",$R37,"")))) | U37: =IF(OR($S37="",$S37="Gap",$Q37=""),"",IF($Q37<Config!$C$2-Config!$C$3,"STALE","")) | V37: =IF(OR(ISNUMBER(SEARCH("ALL",$E37)),ISNUMBER(SEARCH("ADV",$E37))),1,0) -> 1 | W37: =IF(OR(ISNUMBER(SEARCH("ALL",$E37)),ISNUMBER(SEARCH("SMF",$E37))),1,0) -> 1 | X37: =IF(OR(ISNUMBER(SEARCH("ALL",$E37)),ISNUMBER(SEARCH("MKT",$E37))),1,0) -> 1 | Y37: =IF(OR(ISNUMBER(SEARCH("ALL",$E37)),ISNUMBER(SEARCH("SCM",$E37))),1,0) -> 1 | Z37: =IF(OR(ISNUMBER(SEARCH("ALL",$E37)),ISNUMBER(SEARCH("FIN",$E37))),1,0) -> 1 | AA37: =IF(OR(ISNUMBER(SEARCH("ALL",$E37)),ISNUMBER(SEARCH("AGI",$E37))),1,0) -> 1
A38: 5.3 | B38: Tertiary STEM enrollment (% gross) | C38: C4 | D38: Enablers | E38: ALL | G38: T | H38: H | I38: 10 | J38: 20 | K38: 30 | L38: 40 | S38: =IF($M38="","",IF(ISNUMBER($M38),"Measured",IF(ISNUMBER(SEARCH("DATA GAP",UPPER($M38))),"Gap",IF(AND($N38<>"",$P38<>"T5"),"Documented","Judged")))) | T38: =IF($AC38<>"","",IF(OR($S38="",$S38="Gap"),"",IF($S38="Measured",1+IF($H38="H",IF($M38>=$I38,1,0)+IF($M38>=$J38,1,0)+IF($M38>=$K38,1,0)+IF($M38>=$L38,1,0),IF($M38<=$I38,1,0)+IF($M38<=$J38,1,0)+IF($M38<=$K38,1,0)+IF($M38<=$L38,1,0)),IF($R38<>"",$R38,"")))) | U38: =IF(OR($S38="",$S38="Gap",$Q38=""),"",IF($Q38<Config!$C$2-Config!$C$3,"STALE","")) | V38: =IF(OR(ISNUMBER(SEARCH("ALL",$E38)),ISNUMBER(SEARCH("ADV",$E38))),1,0) -> 1 | W38: =IF(OR(ISNUMBER(SEARCH("ALL",$E38)),ISNUMBER(SEARCH("SMF",$E38))),1,0) -> 1 | X38: =IF(OR(ISNUMBER(SEARCH("ALL",$E38)),ISNUMBER(SEARCH("MKT",$E38))),1,0) -> 1 | Y38: =IF(OR(ISNUMBER(SEARCH("ALL",$E38)),ISNUMBER(SEARCH("SCM",$E38))),1,0) -> 1 | Z38: =IF(OR(ISNUMBER(SEARCH("ALL",$E38)),ISNUMBER(SEARCH("FIN",$E38))),1,0) -> 1 | AA38: =IF(OR(ISNUMBER(SEARCH("ALL",$E38)),ISNUMBER(SEARCH("AGI",$E38))),1,0) -> 1
A39: 5.4 | B39: Digital literacy among farmers (%) | C39: C4 | D39: Enablers | E39: ALL | G39: T | H39: H | I39: 10 | J39: 25 | K39: 50 | L39: 75 | S39: =IF($M39="","",IF(ISNUMBER($M39),"Measured",IF(ISNUMBER(SEARCH("DATA GAP",UPPER($M39))),"Gap",IF(AND($N39<>"",$P39<>"T5"),"Documented","Judged")))) | T39: =IF($AC39<>"","",IF(OR($S39="",$S39="Gap"),"",IF($S39="Measured",1+IF($H39="H",IF($M39>=$I39,1,0)+IF($M39>=$J39,1,0)+IF($M39>=$K39,1,0)+IF($M39>=$L39,1,0),IF($M39<=$I39,1,0)+IF($M39<=$J39,1,0)+IF($M39<=$K39,1,0)+IF($M39<=$L39,1,0)),IF($R39<>"",$R39,"")))) | U39: =IF(OR($S39="",$S39="Gap",$Q39=""),"",IF($Q39<Config!$C$2-Config!$C$3,"STALE","")) | V39: =IF(OR(ISNUMBER(SEARCH("ALL",$E39)),ISNUMBER(SEARCH("ADV",$E39))),1,0) -> 1 | W39: =IF(OR(ISNUMBER(SEARCH("ALL",$E39)),ISNUMBER(SEARCH("SMF",$E39))),1,0) -> 1 | X39: =IF(OR(ISNUMBER(SEARCH("ALL",$E39)),ISNUMBER(SEARCH("MKT",$E39))),1,0) -> 1 | Y39: =IF(OR(ISNUMBER(SEARCH("ALL",$E39)),ISNUMBER(SEARCH("SCM",$E39))),1,0) -> 1 | Z39: =IF(OR(ISNUMBER(SEARCH("ALL",$E39)),ISNUMBER(SEARCH("FIN",$E39))),1,0) -> 1 | AA39: =IF(OR(ISNUMBER(SEARCH("ALL",$E39)),ISNUMBER(SEARCH("AGI",$E39))),1,0) -> 1
A40: 5.5 | B40: Digital extension capability | C40: C4 | D40: Enablers | E40: ADV | F40: UC:ADV | G40: L | S40: =IF($M40="","",IF(ISNUMBER($M40),"Measured",IF(ISNUMBER(SEARCH("DATA GAP",UPPER($M40))),"Gap",IF(AND($N40<>"",$P40<>"T5"),"Documented","Judged")))) | T40: =IF($AC40<>"","",IF(OR($S40="",$S40="Gap"),"",IF($S40="Measured",1+IF($H40="H",IF($M40>=$I40,1,0)+IF($M40>=$J40,1,0)+IF($M40>=$K40,1,0)+IF($M40>=$L40,1,0),IF($M40<=$I40,1,0)+IF($M40<=$J40,1,0)+IF($M40<=$K40,1,0)+IF($M40<=$L40,1,0)),IF($R40<>"",$R40,"")))) | U40: =IF(OR($S40="",$S40="Gap",$Q40=""),"",IF($Q40<Config!$C$2-Config!$C$3,"STALE","")) | V40: =IF(OR(ISNUMBER(SEARCH("ALL",$E40)),ISNUMBER(SEARCH("ADV",$E40))),1,0) -> 1 | W40: =IF(OR(ISNUMBER(SEARCH("ALL",$E40)),ISNUMBER(SEARCH("SMF",$E40))),1,0) -> 0 | X40: =IF(OR(ISNUMBER(SEARCH("ALL",$E40)),ISNUMBER(SEARCH("MKT",$E40))),1,0) -> 0 | Y40: =IF(OR(ISNUMBER(SEARCH("ALL",$E40)),ISNUMBER(SEARCH("SCM",$E40))),1,0) -> 0 | Z40: =IF(OR(ISNUMBER(SEARCH("ALL",$E40)),ISNUMBER(SEARCH("FIN",$E40))),1,0) -> 0 | AA40: =IF(OR(ISNUMBER(SEARCH("ALL",$E40)),ISNUMBER(SEARCH("AGI",$E40))),1,0) -> 0
A41: 5.7 | B41: MoAg digital/AI unit | C41: C4 | D41: Enablers | E41: ALL | F41: DELIVERY | G41: L | S41: =IF($M41="","",IF(ISNUMBER($M41),"Measured",IF(ISNUMBER(SEARCH("DATA GAP",UPPER($M41))),"Gap",IF(AND($N41<>"",$P41<>"T5"),"Documented","Judged")))) | T41: =IF($AC41<>"","",IF(OR($S41="",$S41="Gap"),"",IF($S41="Measured",1+IF($H41="H",IF($M41>=$I41,1,0)+IF($M41>=$J41,1,0)+IF($M41>=$K41,1,0)+IF($M41>=$L41,1,0),IF($M41<=$I41,1,0)+IF($M41<=$J41,1,0)+IF($M41<=$K41,1,0)+IF($M41<=$L41,1,0)),IF($R41<>"",$R41,"")))) | U41: =IF(OR($S41="",$S41="Gap",$Q41=""),"",IF($Q41<Config!$C$2-Config!$C$3,"STALE","")) | V41: =IF(OR(ISNUMBER(SEARCH("ALL",$E41)),ISNUMBER(SEARCH("ADV",$E41))),1,0) -> 1 | W41: =IF(OR(ISNUMBER(SEARCH("ALL",$E41)),ISNUMBER(SEARCH("SMF",$E41))),1,0) -> 1 | X41: =IF(OR(ISNUMBER(SEARCH("ALL",$E41)),ISNUMBER(SEARCH("MKT",$E41))),1,0) -> 1 | Y41: =IF(OR(ISNUMBER(SEARCH("ALL",$E41)),ISNUMBER(SEARCH("SCM",$E41))),1,0) -> 1 | Z41: =IF(OR(ISNUMBER(SEARCH("ALL",$E41)),ISNUMBER(SEARCH("FIN",$E41))),1,0) -> 1 | AA41: =IF(OR(ISNUMBER(SEARCH("ALL",$E41)),ISNUMBER(SEARCH("AGI",$E41))),1,0) -> 1
A42: 5.8 | B42: Agtech/data-science training pipeline | C42: C4 | D42: Enablers | E42: ALL | G42: L | S42: =IF($M42="","",IF(ISNUMBER($M42),"Measured",IF(ISNUMBER(SEARCH("DATA GAP",UPPER($M42))),"Gap",IF(AND($N42<>"",$P42<>"T5"),"Documented","Judged")))) | T42: =IF($AC42<>"","",IF(OR($S42="",$S42="Gap"),"",IF($S42="Measured",1+IF($H42="H",IF($M42>=$I42,1,0)+IF($M42>=$J42,1,0)+IF($M42>=$K42,1,0)+IF($M42>=$L42,1,0),IF($M42<=$I42,1,0)+IF($M42<=$J42,1,0)+IF($M42<=$K42,1,0)+IF($M42<=$L42,1,0)),IF($R42<>"",$R42,"")))) | U42: =IF(OR($S42="",$S42="Gap",$Q42=""),"",IF($Q42<Config!$C$2-Config!$C$3,"STALE","")) | V42: =IF(OR(ISNUMBER(SEARCH("ALL",$E42)),ISNUMBER(SEARCH("ADV",$E42))),1,0) -> 1 | W42: =IF(OR(ISNUMBER(SEARCH("ALL",$E42)),ISNUMBER(SEARCH("SMF",$E42))),1,0) -> 1 | X42: =IF(OR(ISNUMBER(SEARCH("ALL",$E42)),ISNUMBER(SEARCH("MKT",$E42))),1,0) -> 1 | Y42: =IF(OR(ISNUMBER(SEARCH("ALL",$E42)),ISNUMBER(SEARCH("SCM",$E42))),1,0) -> 1 | Z42: =IF(OR(ISNUMBER(SEARCH("ALL",$E42)),ISNUMBER(SEARCH("FIN",$E42))),1,0) -> 1 | AA42: =IF(OR(ISNUMBER(SEARCH("ALL",$E42)),ISNUMBER(SEARCH("AGI",$E42))),1,0) -> 1
A43: 5.12 | B43: Gender balance in digital-ag workforce (%) | C43: C4 | D43: Enablers | E43: EQ,ADV | G43: T | H43: H | I43: 20 | J43: 35 | K43: 45 | L43: 50 | S43: =IF($M43="","",IF(ISNUMBER($M43),"Measured",IF(ISNUMBER(SEARCH("DATA GAP",UPPER($M43))),"Gap",IF(AND($N43<>"",$P43<>"T5"),"Documented","Judged")))) | T43: =IF($AC43<>"","",IF(OR($S43="",$S43="Gap"),"",IF($S43="Measured",1+IF($H43="H",IF($M43>=$I43,1,0)+IF($M43>=$J43,1,0)+IF($M43>=$K43,1,0)+IF($M43>=$L43,1,0),IF($M43<=$I43,1,0)+IF($M43<=$J43,1,0)+IF($M43<=$K43,1,0)+IF($M43<=$L43,1,0)),IF($R43<>"",$R43,"")))) | U43: =IF(OR($S43="",$S43="Gap",$Q43=""),"",IF($Q43<Config!$C$2-Config!$C$3,"STALE","")) | V43: =IF(OR(ISNUMBER(SEARCH("ALL",$E43)),ISNUMBER(SEARCH("ADV",$E43))),1,0) -> 1 | W43: =IF(OR(ISNUMBER(SEARCH("ALL",$E43)),ISNUMBER(SEARCH("SMF",$E43))),1,0) -> 0 | X43: =IF(OR(ISNUMBER(SEARCH("ALL",$E43)),ISNUMBER(SEARCH("MKT",$E43))),1,0) -> 0 | Y43: =IF(OR(ISNUMBER(SEARCH("ALL",$E43)),ISNUMBER(SEARCH("SCM",$E43))),1,0) -> 0 | Z43: =IF(OR(ISNUMBER(SEARCH("ALL",$E43)),ISNUMBER(SEARCH("FIN",$E43))),1,0) -> 0 | AA43: =IF(OR(ISNUMBER(SEARCH("ALL",$E43)),ISNUMBER(SEARCH("AGI",$E43))),1,0) -> 0
A44: 6.1 | B44: Global Innovation Index | C44: E1 | D44: Enablers | E44: ALL | G44: T | H44: H | I44: 25 | J44: 35 | K44: 45 | L44: 55 | S44: =IF($M44="","",IF(ISNUMBER($M44),"Measured",IF(ISNUMBER(SEARCH("DATA GAP",UPPER($M44))),"Gap",IF(AND($N44<>"",$P44<>"T5"),"Documented","Judged")))) | T44: =IF($AC44<>"","",IF(OR($S44="",$S44="Gap"),"",IF($S44="Measured",1+IF($H44="H",IF($M44>=$I44,1,0)+IF($M44>=$J44,1,0)+IF($M44>=$K44,1,0)+IF($M44>=$L44,1,0),IF($M44<=$I44,1,0)+IF($M44<=$J44,1,0)+IF($M44<=$K44,1,0)+IF($M44<=$L44,1,0)),IF($R44<>"",$R44,"")))) | U44: =IF(OR($S44="",$S44="Gap",$Q44=""),"",IF($Q44<Config!$C$2-Config!$C$3,"STALE","")) | V44: =IF(OR(ISNUMBER(SEARCH("ALL",$E44)),ISNUMBER(SEARCH("ADV",$E44))),1,0) -> 1 | W44: =IF(OR(ISNUMBER(SEARCH("ALL",$E44)),ISNUMBER(SEARCH("SMF",$E44))),1,0) -> 1 | X44: =IF(OR(ISNUMBER(SEARCH("ALL",$E44)),ISNUMBER(SEARCH("MKT",$E44))),1,0) -> 1 | Y44: =IF(OR(ISNUMBER(SEARCH("ALL",$E44)),ISNUMBER(SEARCH("SCM",$E44))),1,0) -> 1 | Z44: =IF(OR(ISNUMBER(SEARCH("ALL",$E44)),ISNUMBER(SEARCH("FIN",$E44))),1,0) -> 1 | AA44: =IF(OR(ISNUMBER(SEARCH("ALL",$E44)),ISNUMBER(SEARCH("AGI",$E44))),1,0) -> 1
A45: 6.3 | B45: Business Ready (B-READY) | C45: E1 | D45: Enablers | E45: ALL | G45: T | H45: H | I45: 30 | J45: 45 | K45: 60 | L45: 75 | S45: =IF($M45="","",IF(ISNUMBER($M45),"Measured",IF(ISNUMBER(SEARCH("DATA GAP",UPPER($M45))),"Gap",IF(AND($N45<>"",$P45<>"T5"),"Documented","Judged")))) | T45: =IF($AC45<>"","",IF(OR($S45="",$S45="Gap"),"",IF($S45="Measured",1+IF($H45="H",IF($M45>=$I45,1,0)+IF($M45>=$J45,1,0)+IF($M45>=$K45,1,0)+IF($M45>=$L45,1,0),IF($M45<=$I45,1,0)+IF($M45<=$J45,1,0)+IF($M45<=$K45,1,0)+IF($M45<=$L45,1,0)),IF($R45<>"",$R45,"")))) | U45: =IF(OR($S45="",$S45="Gap",$Q45=""),"",IF($Q45<Config!$C$2-Config!$C$3,"STALE","")) | V45: =IF(OR(ISNUMBER(SEARCH("ALL",$E45)),ISNUMBER(SEARCH("ADV",$E45))),1,0) -> 1 | W45: =IF(OR(ISNUMBER(SEARCH("ALL",$E45)),ISNUMBER(SEARCH("SMF",$E45))),1,0) -> 1 | X45: =IF(OR(ISNUMBER(SEARCH("ALL",$E45)),ISNUMBER(SEARCH("MKT",$E45))),1,0) -> 1 | Y45: =IF(OR(ISNUMBER(SEARCH("ALL",$E45)),ISNUMBER(SEARCH("SCM",$E45))),1,0) -> 1 | Z45: =IF(OR(ISNUMBER(SEARCH("ALL",$E45)),ISNUMBER(SEARCH("FIN",$E45))),1,0) -> 1 | AA45: =IF(OR(ISNUMBER(SEARCH("ALL",$E45)),ISNUMBER(SEARCH("AGI",$E45))),1,0) -> 1
A46: 6.4 | B46: Agtech venture ecosystem | C46: E1 | D46: Transformation | E46: ALL | G46: L | S46: =IF($M46="","",IF(ISNUMBER($M46),"Measured",IF(ISNUMBER(SEARCH("DATA GAP",UPPER($M46))),"Gap",IF(AND($N46<>"",$P46<>"T5"),"Documented","Judged")))) | T46: =IF($AC46<>"","",IF(OR($S46="",$S46="Gap"),"",IF($S46="Measured",1+IF($H46="H",IF($M46>=$I46,1,0)+IF($M46>=$J46,1,0)+IF($M46>=$K46,1,0)+IF($M46>=$L46,1,0),IF($M46<=$I46,1,0)+IF($M46<=$J46,1,0)+IF($M46<=$K46,1,0)+IF($M46<=$L46,1,0)),IF($R46<>"",$R46,"")))) | U46: =IF(OR($S46="",$S46="Gap",$Q46=""),"",IF($Q46<Config!$C$2-Config!$C$3,"STALE","")) | V46: =IF(OR(ISNUMBER(SEARCH("ALL",$E46)),ISNUMBER(SEARCH("ADV",$E46))),1,0) -> 1 | W46: =IF(OR(ISNUMBER(SEARCH("ALL",$E46)),ISNUMBER(SEARCH("SMF",$E46))),1,0) -> 1 | X46: =IF(OR(ISNUMBER(SEARCH("ALL",$E46)),ISNUMBER(SEARCH("MKT",$E46))),1,0) -> 1 | Y46: =IF(OR(ISNUMBER(SEARCH("ALL",$E46)),ISNUMBER(SEARCH("SCM",$E46))),1,0) -> 1 | Z46: =IF(OR(ISNUMBER(SEARCH("ALL",$E46)),ISNUMBER(SEARCH("FIN",$E46))),1,0) -> 1 | AA46: =IF(OR(ISNUMBER(SEARCH("ALL",$E46)),ISNUMBER(SEARCH("AGI",$E46))),1,0) -> 1
A47: 6.9 | B47: Public-private partnerships in digital ag | C47: E1 | D47: Transformation | E47: ADV,AGI,SCM | G47: L | S47: =IF($M47="","",IF(ISNUMBER($M47),"Measured",IF(ISNUMBER(SEARCH("DATA GAP",UPPER($M47))),"Gap",IF(AND($N47<>"",$P47<>"T5"),"Documented","Judged")))) | T47: =IF($AC47<>"","",IF(OR($S47="",$S47="Gap"),"",IF($S47="Measured",1+IF($H47="H",IF($M47>=$I47,1,0)+IF($M47>=$J47,1,0)+IF($M47>=$K47,1,0)+IF($M47>=$L47,1,0),IF($M47<=$I47,1,0)+IF($M47<=$J47,1,0)+IF($M47<=$K47,1,0)+IF($M47<=$L47,1,0)),IF($R47<>"",$R47,"")))) | U47: =IF(OR($S47="",$S47="Gap",$Q47=""),"",IF($Q47<Config!$C$2-Config!$C$3,"STALE","")) | V47: =IF(OR(ISNUMBER(SEARCH("ALL",$E47)),ISNUMBER(SEARCH("ADV",$E47))),1,0) -> 1 | W47: =IF(OR(ISNUMBER(SEARCH("ALL",$E47)),ISNUMBER(SEARCH("SMF",$E47))),1,0) -> 0 | X47: =IF(OR(ISNUMBER(SEARCH("ALL",$E47)),ISNUMBER(SEARCH("MKT",$E47))),1,0) -> 0 | Y47: =IF(OR(ISNUMBER(SEARCH("ALL",$E47)),ISNUMBER(SEARCH("SCM",$E47))),1,0) -> 1 | Z47: =IF(OR(ISNUMBER(SEARCH("ALL",$E47)),ISNUMBER(SEARCH("FIN",$E47))),1,0) -> 0 | AA47: =IF(OR(ISNUMBER(SEARCH("ALL",$E47)),ISNUMBER(SEARCH("AGI",$E47))),1,0) -> 1
A48: 6.12 | B48: Digital public goods adopted | C48: E1 | D48: Transformation | E48: ALL | G48: L | S48: =IF($M48="","",IF(ISNUMBER($M48),"Measured",IF(ISNUMBER(SEARCH("DATA GAP",UPPER($M48))),"Gap",IF(AND($N48<>"",$P48<>"T5"),"Documented","Judged")))) | T48: =IF($AC48<>"","",IF(OR($S48="",$S48="Gap"),"",IF($S48="Measured",1+IF($H48="H",IF($M48>=$I48,1,0)+IF($M48>=$J48,1,0)+IF($M48>=$K48,1,0)+IF($M48>=$L48,1,0),IF($M48<=$I48,1,0)+IF($M48<=$J48,1,0)+IF($M48<=$K48,1,0)+IF($M48<=$L48,1,0)),IF($R48<>"",$R48,"")))) | U48: =IF(OR($S48="",$S48="Gap",$Q48=""),"",IF($Q48<Config!$C$2-Config!$C$3,"STALE","")) | V48: =IF(OR(ISNUMBER(SEARCH("ALL",$E48)),ISNUMBER(SEARCH("ADV",$E48))),1,0) -> 1 | W48: =IF(OR(ISNUMBER(SEARCH("ALL",$E48)),ISNUMBER(SEARCH("SMF",$E48))),1,0) -> 1 | X48: =IF(OR(ISNUMBER(SEARCH("ALL",$E48)),ISNUMBER(SEARCH("MKT",$E48))),1,0) -> 1 | Y48: =IF(OR(ISNUMBER(SEARCH("ALL",$E48)),ISNUMBER(SEARCH("SCM",$E48))),1,0) -> 1 | Z48: =IF(OR(ISNUMBER(SEARCH("ALL",$E48)),ISNUMBER(SEARCH("FIN",$E48))),1,0) -> 1 | AA48: =IF(OR(ISNUMBER(SEARCH("ALL",$E48)),ISNUMBER(SEARCH("AGI",$E48))),1,0) -> 1
A49: 6.13 | B49: SME/agribusiness adoption of digital tools (%) | C49: E1 | D49: Transformation | E49: SMF,SCM,MKT | G49: T | H49: H | I49: 10 | J49: 25 | K49: 50 | L49: 75 | S49: =IF($M49="","",IF(ISNUMBER($M49),"Measured",IF(ISNUMBER(SEARCH("DATA GAP",UPPER($M49))),"Gap",IF(AND($N49<>"",$P49<>"T5"),"Documented","Judged")))) | T49: =IF($AC49<>"","",IF(OR($S49="",$S49="Gap"),"",IF($S49="Measured",1+IF($H49="H",IF($M49>=$I49,1,0)+IF($M49>=$J49,1,0)+IF($M49>=$K49,1,0)+IF($M49>=$L49,1,0),IF($M49<=$I49,1,0)+IF($M49<=$J49,1,0)+IF($M49<=$K49,1,0)+IF($M49<=$L49,1,0)),IF($R49<>"",$R49,"")))) | U49: =IF(OR($S49="",$S49="Gap",$Q49=""),"",IF($Q49<Config!$C$2-Config!$C$3,"STALE","")) | V49: =IF(OR(ISNUMBER(SEARCH("ALL",$E49)),ISNUMBER(SEARCH("ADV",$E49))),1,0) -> 0 | W49: =IF(OR(ISNUMBER(SEARCH("ALL",$E49)),ISNUMBER(SEARCH("SMF",$E49))),1,0) -> 1 | X49: =IF(OR(ISNUMBER(SEARCH("ALL",$E49)),ISNUMBER(SEARCH("MKT",$E49))),1,0) -> 1 | Y49: =IF(OR(ISNUMBER(SEARCH("ALL",$E49)),ISNUMBER(SEARCH("SCM",$E49))),1,0) -> 1 | Z49: =IF(OR(ISNUMBER(SEARCH("ALL",$E49)),ISNUMBER(SEARCH("FIN",$E49))),1,0) -> 0 | AA49: =IF(OR(ISNUMBER(SEARCH("ALL",$E49)),ISNUMBER(SEARCH("AGI",$E49))),1,0) -> 0
A50: 6.14 | B50: Agri-fintech rails for smallholders | C50: E1 | D50: Transformation | E50: FIN | F50: UC:FIN | G50: L | S50: =IF($M50="","",IF(ISNUMBER($M50),"Measured",IF(ISNUMBER(SEARCH("DATA GAP",UPPER($M50))),"Gap",IF(AND($N50<>"",$P50<>"T5"),"Documented","Judged")))) | T50: =IF($AC50<>"","",IF(OR($S50="",$S50="Gap"),"",IF($S50="Measured",1+IF($H50="H",IF($M50>=$I50,1,0)+IF($M50>=$J50,1,0)+IF($M50>=$K50,1,0)+IF($M50>=$L50,1,0),IF($M50<=$I50,1,0)+IF($M50<=$J50,1,0)+IF($M50<=$K50,1,0)+IF($M50<=$L50,1,0)),IF($R50<>"",$R50,"")))) | U50: =IF(OR($S50="",$S50="Gap",$Q50=""),"",IF($Q50<Config!$C$2-Config!$C$3,"STALE","")) | V50: =IF(OR(ISNUMBER(SEARCH("ALL",$E50)),ISNUMBER(SEARCH("ADV",$E50))),1,0) -> 0 | W50: =IF(OR(ISNUMBER(SEARCH("ALL",$E50)),ISNUMBER(SEARCH("SMF",$E50))),1,0) -> 0 | X50: =IF(OR(ISNUMBER(SEARCH("ALL",$E50)),ISNUMBER(SEARCH("MKT",$E50))),1,0) -> 0 | Y50: =IF(OR(ISNUMBER(SEARCH("ALL",$E50)),ISNUMBER(SEARCH("SCM",$E50))),1,0) -> 0 | Z50: =IF(OR(ISNUMBER(SEARCH("ALL",$E50)),ISNUMBER(SEARCH("FIN",$E50))),1,0) -> 1 | AA50: =IF(OR(ISNUMBER(SEARCH("ALL",$E50)),ISNUMBER(SEARCH("AGI",$E50))),1,0) -> 0
A51: 3.9 | B51: Digital advisory platforms at scale | C51: E1 | D51: Transformation | E51: ADV | G51: L | S51: =IF($M51="","",IF(ISNUMBER($M51),"Measured",IF(ISNUMBER(SEARCH("DATA GAP",UPPER($M51))),"Gap",IF(AND($N51<>"",$P51<>"T5"),"Documented","Judged")))) | T51: =IF($AC51<>"","",IF(OR($S51="",$S51="Gap"),"",IF($S51="Measured",1+IF($H51="H",IF($M51>=$I51,1,0)+IF($M51>=$J51,1,0)+IF($M51>=$K51,1,0)+IF($M51>=$L51,1,0),IF($M51<=$I51,1,0)+IF($M51<=$J51,1,0)+IF($M51<=$K51,1,0)+IF($M51<=$L51,1,0)),IF($R51<>"",$R51,"")))) | U51: =IF(OR($S51="",$S51="Gap",$Q51=""),"",IF($Q51<Config!$C$2-Config!$C$3,"STALE","")) | V51: =IF(OR(ISNUMBER(SEARCH("ALL",$E51)),ISNUMBER(SEARCH("ADV",$E51))),1,0) -> 1 | W51: =IF(OR(ISNUMBER(SEARCH("ALL",$E51)),ISNUMBER(SEARCH("SMF",$E51))),1,0) -> 0 | X51: =IF(OR(ISNUMBER(SEARCH("ALL",$E51)),ISNUMBER(SEARCH("MKT",$E51))),1,0) -> 0 | Y51: =IF(OR(ISNUMBER(SEARCH("ALL",$E51)),ISNUMBER(SEARCH("SCM",$E51))),1,0) -> 0 | Z51: =IF(OR(ISNUMBER(SEARCH("ALL",$E51)),ISNUMBER(SEARCH("FIN",$E51))),1,0) -> 0 | AA51: =IF(OR(ISNUMBER(SEARCH("ALL",$E51)),ISNUMBER(SEARCH("AGI",$E51))),1,0) -> 0
A52: 3.10 | B52: Agricultural e-commerce platforms | C52: E1 | D52: Transformation | E52: MKT | G52: L | S52: =IF($M52="","",IF(ISNUMBER($M52),"Measured",IF(ISNUMBER(SEARCH("DATA GAP",UPPER($M52))),"Gap",IF(AND($N52<>"",$P52<>"T5"),"Documented","Judged")))) | T52: =IF($AC52<>"","",IF(OR($S52="",$S52="Gap"),"",IF($S52="Measured",1+IF($H52="H",IF($M52>=$I52,1,0)+IF($M52>=$J52,1,0)+IF($M52>=$K52,1,0)+IF($M52>=$L52,1,0),IF($M52<=$I52,1,0)+IF($M52<=$J52,1,0)+IF($M52<=$K52,1,0)+IF($M52<=$L52,1,0)),IF($R52<>"",$R52,"")))) | U52: =IF(OR($S52="",$S52="Gap",$Q52=""),"",IF($Q52<Config!$C$2-Config!$C$3,"STALE","")) | V52: =IF(OR(ISNUMBER(SEARCH("ALL",$E52)),ISNUMBER(SEARCH("ADV",$E52))),1,0) -> 0 | W52: =IF(OR(ISNUMBER(SEARCH("ALL",$E52)),ISNUMBER(SEARCH("SMF",$E52))),1,0) -> 0 | X52: =IF(OR(ISNUMBER(SEARCH("ALL",$E52)),ISNUMBER(SEARCH("MKT",$E52))),1,0) -> 1 | Y52: =IF(OR(ISNUMBER(SEARCH("ALL",$E52)),ISNUMBER(SEARCH("SCM",$E52))),1,0) -> 0 | Z52: =IF(OR(ISNUMBER(SEARCH("ALL",$E52)),ISNUMBER(SEARCH("FIN",$E52))),1,0) -> 0 | AA52: =IF(OR(ISNUMBER(SEARCH("ALL",$E52)),ISNUMBER(SEARCH("AGI",$E52))),1,0) -> 0
A53: 7.2 | B53: AI-enabled agricultural solutions deployed | C53: E1 | D53: Transformation | E53: ADV,FIN,SCM,SMF,AGI | G53: L | S53: =IF($M53="","",IF(ISNUMBER($M53),"Measured",IF(ISNUMBER(SEARCH("DATA GAP",UPPER($M53))),"Gap",IF(AND($N53<>"",$P53<>"T5"),"Documented","Judged")))) | T53: =IF($AC53<>"","",IF(OR($S53="",$S53="Gap"),"",IF($S53="Measured",1+IF($H53="H",IF($M53>=$I53,1,0)+IF($M53>=$J53,1,0)+IF($M53>=$K53,1,0)+IF($M53>=$L53,1,0),IF($M53<=$I53,1,0)+IF($M53<=$J53,1,0)+IF($M53<=$K53,1,0)+IF($M53<=$L53,1,0)),IF($R53<>"",$R53,"")))) | U53: =IF(OR($S53="",$S53="Gap",$Q53=""),"",IF($Q53<Config!$C$2-Config!$C$3,"STALE","")) | V53: =IF(OR(ISNUMBER(SEARCH("ALL",$E53)),ISNUMBER(SEARCH("ADV",$E53))),1,0) -> 1 | W53: =IF(OR(ISNUMBER(SEARCH("ALL",$E53)),ISNUMBER(SEARCH("SMF",$E53))),1,0) -> 1 | X53: =IF(OR(ISNUMBER(SEARCH("ALL",$E53)),ISNUMBER(SEARCH("MKT",$E53))),1,0) -> 0 | Y53: =IF(OR(ISNUMBER(SEARCH("ALL",$E53)),ISNUMBER(SEARCH("SCM",$E53))),1,0) -> 1 | Z53: =IF(OR(ISNUMBER(SEARCH("ALL",$E53)),ISNUMBER(SEARCH("FIN",$E53))),1,0) -> 1 | AA53: =IF(OR(ISNUMBER(SEARCH("ALL",$E53)),ISNUMBER(SEARCH("AGI",$E53))),1,0) -> 1
A54: 7.12 | B54: Responsible-AI safeguards (consent, rights) | C54: E1 | D54: Enablers | E54: AI | F54: UC:AI | G54: L | S54: =IF($M54="","",IF(ISNUMBER($M54),"Measured",IF(ISNUMBER(SEARCH("DATA GAP",UPPER($M54))),"Gap",IF(AND($N54<>"",$P54<>"T5"),"Documented","Judged")))) | T54: =IF($AC54<>"","",IF(OR($S54="",$S54="Gap"),"",IF($S54="Measured",1+IF($H54="H",IF($M54>=$I54,1,0)+IF($M54>=$J54,1,0)+IF($M54>=$K54,1,0)+IF($M54>=$L54,1,0),IF($M54<=$I54,1,0)+IF($M54<=$J54,1,0)+IF($M54<=$K54,1,0)+IF($M54<=$L54,1,0)),IF($R54<>"",$R54,"")))) | U54: =IF(OR($S54="",$S54="Gap",$Q54=""),"",IF($Q54<Config!$C$2-Config!$C$3,"STALE","")) | V54: =IF(OR(ISNUMBER(SEARCH("ALL",$E54)),ISNUMBER(SEARCH("ADV",$E54))),1,0) -> 0 | W54: =IF(OR(ISNUMBER(SEARCH("ALL",$E54)),ISNUMBER(SEARCH("SMF",$E54))),1,0) -> 0 | X54: =IF(OR(ISNUMBER(SEARCH("ALL",$E54)),ISNUMBER(SEARCH("MKT",$E54))),1,0) -> 0 | Y54: =IF(OR(ISNUMBER(SEARCH("ALL",$E54)),ISNUMBER(SEARCH("SCM",$E54))),1,0) -> 0 | Z54: =IF(OR(ISNUMBER(SEARCH("ALL",$E54)),ISNUMBER(SEARCH("FIN",$E54))),1,0) -> 0 | AA54: =IF(OR(ISNUMBER(SEARCH("ALL",$E54)),ISNUMBER(SEARCH("AGI",$E54))),1,0) -> 0
A55: 8.2 | B55: Account ownership, female (%) | C55: O1 | D55: Outcomes | E55: FIN,EQ | G55: T | H55: H | I55: 20 | J55: 40 | K55: 60 | L55: 80 | S55: =IF($M55="","",IF(ISNUMBER($M55),"Measured",IF(ISNUMBER(SEARCH("DATA GAP",UPPER($M55))),"Gap",IF(AND($N55<>"",$P55<>"T5"),"Documented","Judged")))) | T55: =IF($AC55<>"","",IF(OR($S55="",$S55="Gap"),"",IF($S55="Measured",1+IF($H55="H",IF($M55>=$I55,1,0)+IF($M55>=$J55,1,0)+IF($M55>=$K55,1,0)+IF($M55>=$L55,1,0),IF($M55<=$I55,1,0)+IF($M55<=$J55,1,0)+IF($M55<=$K55,1,0)+IF($M55<=$L55,1,0)),IF($R55<>"",$R55,"")))) | U55: =IF(OR($S55="",$S55="Gap",$Q55=""),"",IF($Q55<Config!$C$2-Config!$C$3,"STALE","")) | V55: =IF(OR(ISNUMBER(SEARCH("ALL",$E55)),ISNUMBER(SEARCH("ADV",$E55))),1,0) -> 0 | W55: =IF(OR(ISNUMBER(SEARCH("ALL",$E55)),ISNUMBER(SEARCH("SMF",$E55))),1,0) -> 0 | X55: =IF(OR(ISNUMBER(SEARCH("ALL",$E55)),ISNUMBER(SEARCH("MKT",$E55))),1,0) -> 0 | Y55: =IF(OR(ISNUMBER(SEARCH("ALL",$E55)),ISNUMBER(SEARCH("SCM",$E55))),1,0) -> 0 | Z55: =IF(OR(ISNUMBER(SEARCH("ALL",$E55)),ISNUMBER(SEARCH("FIN",$E55))),1,0) -> 1 | AA55: =IF(OR(ISNUMBER(SEARCH("ALL",$E55)),ISNUMBER(SEARCH("AGI",$E55))),1,0) -> 0
A56: 8.4 | B56: Mobile money account (%) | C56: O1 | D56: Outcomes | E56: FIN | G56: T | H56: H | I56: 10 | J56: 25 | K56: 50 | L56: 75 | S56: =IF($M56="","",IF(ISNUMBER($M56),"Measured",IF(ISNUMBER(SEARCH("DATA GAP",UPPER($M56))),"Gap",IF(AND($N56<>"",$P56<>"T5"),"Documented","Judged")))) | T56: =IF($AC56<>"","",IF(OR($S56="",$S56="Gap"),"",IF($S56="Measured",1+IF($H56="H",IF($M56>=$I56,1,0)+IF($M56>=$J56,1,0)+IF($M56>=$K56,1,0)+IF($M56>=$L56,1,0),IF($M56<=$I56,1,0)+IF($M56<=$J56,1,0)+IF($M56<=$K56,1,0)+IF($M56<=$L56,1,0)),IF($R56<>"",$R56,"")))) | U56: =IF(OR($S56="",$S56="Gap",$Q56=""),"",IF($Q56<Config!$C$2-Config!$C$3,"STALE","")) | V56: =IF(OR(ISNUMBER(SEARCH("ALL",$E56)),ISNUMBER(SEARCH("ADV",$E56))),1,0) -> 0 | W56: =IF(OR(ISNUMBER(SEARCH("ALL",$E56)),ISNUMBER(SEARCH("SMF",$E56))),1,0) -> 0 | X56: =IF(OR(ISNUMBER(SEARCH("ALL",$E56)),ISNUMBER(SEARCH("MKT",$E56))),1,0) -> 0 | Y56: =IF(OR(ISNUMBER(SEARCH("ALL",$E56)),ISNUMBER(SEARCH("SCM",$E56))),1,0) -> 0 | Z56: =IF(OR(ISNUMBER(SEARCH("ALL",$E56)),ISNUMBER(SEARCH("FIN",$E56))),1,0) -> 1 | AA56: =IF(OR(ISNUMBER(SEARCH("ALL",$E56)),ISNUMBER(SEARCH("AGI",$E56))),1,0) -> 0
A57: 8.6 | B57: Gender gap in phone ownership (pp) | C57: O1 | D57: Outcomes | E57: EQ | G57: T | H57: L | I57: 20 | J57: 10 | K57: 5 | L57: 2 | S57: =IF($M57="","",IF(ISNUMBER($M57),"Measured",IF(ISNUMBER(SEARCH("DATA GAP",UPPER($M57))),"Gap",IF(AND($N57<>"",$P57<>"T5"),"Documented","Judged")))) | T57: =IF($AC57<>"","",IF(OR($S57="",$S57="Gap"),"",IF($S57="Measured",1+IF($H57="H",IF($M57>=$I57,1,0)+IF($M57>=$J57,1,0)+IF($M57>=$K57,1,0)+IF($M57>=$L57,1,0),IF($M57<=$I57,1,0)+IF($M57<=$J57,1,0)+IF($M57<=$K57,1,0)+IF($M57<=$L57,1,0)),IF($R57<>"",$R57,"")))) | U57: =IF(OR($S57="",$S57="Gap",$Q57=""),"",IF($Q57<Config!$C$2-Config!$C$3,"STALE","")) | V57: =IF(OR(ISNUMBER(SEARCH("ALL",$E57)),ISNUMBER(SEARCH("ADV",$E57))),1,0) -> 0 | W57: =IF(OR(ISNUMBER(SEARCH("ALL",$E57)),ISNUMBER(SEARCH("SMF",$E57))),1,0) -> 0 | X57: =IF(OR(ISNUMBER(SEARCH("ALL",$E57)),ISNUMBER(SEARCH("MKT",$E57))),1,0) -> 0 | Y57: =IF(OR(ISNUMBER(SEARCH("ALL",$E57)),ISNUMBER(SEARCH("SCM",$E57))),1,0) -> 0 | Z57: =IF(OR(ISNUMBER(SEARCH("ALL",$E57)),ISNUMBER(SEARCH("FIN",$E57))),1,0) -> 0 | AA57: =IF(OR(ISNUMBER(SEARCH("ALL",$E57)),ISNUMBER(SEARCH("AGI",$E57))),1,0) -> 0
A58: 8.9 | B58: Smallholders reached by digital services (%) | C58: O1 | D58: Outcomes | E58: ALL,EQ | G58: T | H58: H | I58: 10 | J58: 25 | K58: 50 | L58: 75 | S58: =IF($M58="","",IF(ISNUMBER($M58),"Measured",IF(ISNUMBER(SEARCH("DATA GAP",UPPER($M58))),"Gap",IF(AND($N58<>"",$P58<>"T5"),"Documented","Judged")))) | T58: =IF($AC58<>"","",IF(OR($S58="",$S58="Gap"),"",IF($S58="Measured",1+IF($H58="H",IF($M58>=$I58,1,0)+IF($M58>=$J58,1,0)+IF($M58>=$K58,1,0)+IF($M58>=$L58,1,0),IF($M58<=$I58,1,0)+IF($M58<=$J58,1,0)+IF($M58<=$K58,1,0)+IF($M58<=$L58,1,0)),IF($R58<>"",$R58,"")))) | U58: =IF(OR($S58="",$S58="Gap",$Q58=""),"",IF($Q58<Config!$C$2-Config!$C$3,"STALE","")) | V58: =IF(OR(ISNUMBER(SEARCH("ALL",$E58)),ISNUMBER(SEARCH("ADV",$E58))),1,0) -> 1 | W58: =IF(OR(ISNUMBER(SEARCH("ALL",$E58)),ISNUMBER(SEARCH("SMF",$E58))),1,0) -> 1 | X58: =IF(OR(ISNUMBER(SEARCH("ALL",$E58)),ISNUMBER(SEARCH("MKT",$E58))),1,0) -> 1 | Y58: =IF(OR(ISNUMBER(SEARCH("ALL",$E58)),ISNUMBER(SEARCH("SCM",$E58))),1,0) -> 1 | Z58: =IF(OR(ISNUMBER(SEARCH("ALL",$E58)),ISNUMBER(SEARCH("FIN",$E58))),1,0) -> 1 | AA58: =IF(OR(ISNUMBER(SEARCH("ALL",$E58)),ISNUMBER(SEARCH("AGI",$E58))),1,0) -> 1
A59: 8.11 | B59: Services in local languages (%) | C59: O1 | D59: Outcomes | E59: ADV,EQ | G59: T | H59: H | I59: 25 | J59: 50 | K59: 75 | L59: 90 | S59: =IF($M59="","",IF(ISNUMBER($M59),"Measured",IF(ISNUMBER(SEARCH("DATA GAP",UPPER($M59))),"Gap",IF(AND($N59<>"",$P59<>"T5"),"Documented","Judged")))) | T59: =IF($AC59<>"","",IF(OR($S59="",$S59="Gap"),"",IF($S59="Measured",1+IF($H59="H",IF($M59>=$I59,1,0)+IF($M59>=$J59,1,0)+IF($M59>=$K59,1,0)+IF($M59>=$L59,1,0),IF($M59<=$I59,1,0)+IF($M59<=$J59,1,0)+IF($M59<=$K59,1,0)+IF($M59<=$L59,1,0)),IF($R59<>"",$R59,"")))) | U59: =IF(OR($S59="",$S59="Gap",$Q59=""),"",IF($Q59<Config!$C$2-Config!$C$3,"STALE","")) | V59: =IF(OR(ISNUMBER(SEARCH("ALL",$E59)),ISNUMBER(SEARCH("ADV",$E59))),1,0) -> 1 | W59: =IF(OR(ISNUMBER(SEARCH("ALL",$E59)),ISNUMBER(SEARCH("SMF",$E59))),1,0) -> 0 | X59: =IF(OR(ISNUMBER(SEARCH("ALL",$E59)),ISNUMBER(SEARCH("MKT",$E59))),1,0) -> 0 | Y59: =IF(OR(ISNUMBER(SEARCH("ALL",$E59)),ISNUMBER(SEARCH("SCM",$E59))),1,0) -> 0 | Z59: =IF(OR(ISNUMBER(SEARCH("ALL",$E59)),ISNUMBER(SEARCH("FIN",$E59))),1,0) -> 0 | AA59: =IF(OR(ISNUMBER(SEARCH("ALL",$E59)),ISNUMBER(SEARCH("AGI",$E59))),1,0) -> 0
A60: 8.12 | B60: Documented impact evidence (yield/income) | C60: O1 | D60: Outcomes | E60: ALL | G60: L | S60: =IF($M60="","",IF(ISNUMBER($M60),"Measured",IF(ISNUMBER(SEARCH("DATA GAP",UPPER($M60))),"Gap",IF(AND($N60<>"",$P60<>"T5"),"Documented","Judged")))) | T60: =IF($AC60<>"","",IF(OR($S60="",$S60="Gap"),"",IF($S60="Measured",1+IF($H60="H",IF($M60>=$I60,1,0)+IF($M60>=$J60,1,0)+IF($M60>=$K60,1,0)+IF($M60>=$L60,1,0),IF($M60<=$I60,1,0)+IF($M60<=$J60,1,0)+IF($M60<=$K60,1,0)+IF($M60<=$L60,1,0)),IF($R60<>"",$R60,"")))) | U60: =IF(OR($S60="",$S60="Gap",$Q60=""),"",IF($Q60<Config!$C$2-Config!$C$3,"STALE","")) | V60: =IF(OR(ISNUMBER(SEARCH("ALL",$E60)),ISNUMBER(SEARCH("ADV",$E60))),1,0) -> 1 | W60: =IF(OR(ISNUMBER(SEARCH("ALL",$E60)),ISNUMBER(SEARCH("SMF",$E60))),1,0) -> 1 | X60: =IF(OR(ISNUMBER(SEARCH("ALL",$E60)),ISNUMBER(SEARCH("MKT",$E60))),1,0) -> 1 | Y60: =IF(OR(ISNUMBER(SEARCH("ALL",$E60)),ISNUMBER(SEARCH("SCM",$E60))),1,0) -> 1 | Z60: =IF(OR(ISNUMBER(SEARCH("ALL",$E60)),ISNUMBER(SEARCH("FIN",$E60))),1,0) -> 1 | AA60: =IF(OR(ISNUMBER(SEARCH("ALL",$E60)),ISNUMBER(SEARCH("AGI",$E60))),1,0) -> 1
A61: 8.17 | B61: Climate advisory reach (%) | C61: O1 | D61: Outcomes | E61: ADV | G61: T | H61: H | I61: 20 | J61: 40 | K61: 60 | L61: 80 | S61: =IF($M61="","",IF(ISNUMBER($M61),"Measured",IF(ISNUMBER(SEARCH("DATA GAP",UPPER($M61))),"Gap",IF(AND($N61<>"",$P61<>"T5"),"Documented","Judged")))) | T61: =IF($AC61<>"","",IF(OR($S61="",$S61="Gap"),"",IF($S61="Measured",1+IF($H61="H",IF($M61>=$I61,1,0)+IF($M61>=$J61,1,0)+IF($M61>=$K61,1,0)+IF($M61>=$L61,1,0),IF($M61<=$I61,1,0)+IF($M61<=$J61,1,0)+IF($M61<=$K61,1,0)+IF($M61<=$L61,1,0)),IF($R61<>"",$R61,"")))) | U61: =IF(OR($S61="",$S61="Gap",$Q61=""),"",IF($Q61<Config!$C$2-Config!$C$3,"STALE","")) | V61: =IF(OR(ISNUMBER(SEARCH("ALL",$E61)),ISNUMBER(SEARCH("ADV",$E61))),1,0) -> 1 | W61: =IF(OR(ISNUMBER(SEARCH("ALL",$E61)),ISNUMBER(SEARCH("SMF",$E61))),1,0) -> 0 | X61: =IF(OR(ISNUMBER(SEARCH("ALL",$E61)),ISNUMBER(SEARCH("MKT",$E61))),1,0) -> 0 | Y61: =IF(OR(ISNUMBER(SEARCH("ALL",$E61)),ISNUMBER(SEARCH("SCM",$E61))),1,0) -> 0 | Z61: =IF(OR(ISNUMBER(SEARCH("ALL",$E61)),ISNUMBER(SEARCH("FIN",$E61))),1,0) -> 0 | AA61: =IF(OR(ISNUMBER(SEARCH("ALL",$E61)),ISNUMBER(SEARCH("AGI",$E61))),1,0) -> 0
A64: Pillar profile · n = indicators in the pillar; Rated = those that produced a level, which is what the mean averages; Held = level withheld pending ratification. A band in parentheses = judged rows, recorded gaps and held rows outnumber the levelled measured and documented ones
A65: Pillar | B65: n | C65: Rated | D65: Mean | E65: Band | F65: Measured | G65: Documented | H65: Judged | I65: Gap | J65: Held | K65: Stale
A66: A1 | B66: =COUNTIF($C$5:$C$61,$A66) -> 10 | C66: =COUNTIFS($C$5:$C$61,$A66,$T$5:$T$61,">0") -> 0 | D66: =IFERROR(ROUND(AVERAGEIF($C$5:$C$61,$A66,$T$5:$T$61),2),"") | E66: =IF($D66="","Not rated",IF((COUNTIFS($C$5:$C$61,$A66,$S$5:$S$61,"Judged",$T$5:$T$61,">0")+$I66+$J66)>($C66-COUNTIFS($C$5:$C$61,$A66,$S$5:$S$61,"Judged",$T$5:$T$61,">0")),"("&IF($D66<1.8,"Nascent",IF($D66<2.6,"Emerging",IF($D66<3.4,"Established",IF($D66<4.2,"Advanced","Transformative"))))&")",IF($D66<1.8,"Nascent",IF($D66<2.6,"Emerging",IF($D66<3.4,"Established",IF($D66<4.2,"Advanced","Transformative")))))) -> Not rated | F66: =COUNTIFS($C$5:$C$61,$A66,$S$5:$S$61,"Measured") -> 0 | G66: =COUNTIFS($C$5:$C$61,$A66,$S$5:$S$61,"Documented") -> 0 | H66: =COUNTIFS($C$5:$C$61,$A66,$S$5:$S$61,"Judged") -> 0 | I66: =COUNTIFS($C$5:$C$61,$A66,$S$5:$S$61,"Gap") -> 0 | J66: =COUNTIFS($C$5:$C$61,$A66,$AC$5:$AC$61,"<>") -> 0 | K66: =COUNTIFS($C$5:$C$61,$A66,$U$5:$U$61,"STALE") -> 0
A67: C1 | B67: =COUNTIF($C$5:$C$61,$A67) -> 6 | C67: =COUNTIFS($C$5:$C$61,$A67,$T$5:$T$61,">0") -> 0 | D67: =IFERROR(ROUND(AVERAGEIF($C$5:$C$61,$A67,$T$5:$T$61),2),"") | E67: =IF($D67="","Not rated",IF((COUNTIFS($C$5:$C$61,$A67,$S$5:$S$61,"Judged",$T$5:$T$61,">0")+$I67+$J67)>($C67-COUNTIFS($C$5:$C$61,$A67,$S$5:$S$61,"Judged",$T$5:$T$61,">0")),"("&IF($D67<1.8,"Nascent",IF($D67<2.6,"Emerging",IF($D67<3.4,"Established",IF($D67<4.2,"Advanced","Transformative"))))&")",IF($D67<1.8,"Nascent",IF($D67<2.6,"Emerging",IF($D67<3.4,"Established",IF($D67<4.2,"Advanced","Transformative")))))) -> Not rated | F67: =COUNTIFS($C$5:$C$61,$A67,$S$5:$S$61,"Measured") -> 0 | G67: =COUNTIFS($C$5:$C$61,$A67,$S$5:$S$61,"Documented") -> 0 | H67: =COUNTIFS($C$5:$C$61,$A67,$S$5:$S$61,"Judged") -> 0 | I67: =COUNTIFS($C$5:$C$61,$A67,$S$5:$S$61,"Gap") -> 0 | J67: =COUNTIFS($C$5:$C$61,$A67,$AC$5:$AC$61,"<>") -> 0 | K67: =COUNTIFS($C$5:$C$61,$A67,$U$5:$U$61,"STALE") -> 0
A68: C2 | B68: =COUNTIF($C$5:$C$61,$A68) -> 8 | C68: =COUNTIFS($C$5:$C$61,$A68,$T$5:$T$61,">0") -> 0 | D68: =IFERROR(ROUND(AVERAGEIF($C$5:$C$61,$A68,$T$5:$T$61),2),"") | E68: =IF($D68="","Not rated",IF((COUNTIFS($C$5:$C$61,$A68,$S$5:$S$61,"Judged",$T$5:$T$61,">0")+$I68+$J68)>($C68-COUNTIFS($C$5:$C$61,$A68,$S$5:$S$61,"Judged",$T$5:$T$61,">0")),"("&IF($D68<1.8,"Nascent",IF($D68<2.6,"Emerging",IF($D68<3.4,"Established",IF($D68<4.2,"Advanced","Transformative"))))&")",IF($D68<1.8,"Nascent",IF($D68<2.6,"Emerging",IF($D68<3.4,"Established",IF($D68<4.2,"Advanced","Transformative")))))) -> Not rated | F68: =COUNTIFS($C$5:$C$61,$A68,$S$5:$S$61,"Measured") -> 0 | G68: =COUNTIFS($C$5:$C$61,$A68,$S$5:$S$61,"Documented") -> 0 | H68: =COUNTIFS($C$5:$C$61,$A68,$S$5:$S$61,"Judged") -> 0 | I68: =COUNTIFS($C$5:$C$61,$A68,$S$5:$S$61,"Gap") -> 0 | J68: =COUNTIFS($C$5:$C$61,$A68,$AC$5:$AC$61,"<>") -> 0 | K68: =COUNTIFS($C$5:$C$61,$A68,$U$5:$U$61,"STALE") -> 0
A69: C3 | B69: =COUNTIF($C$5:$C$61,$A69) -> 8 | C69: =COUNTIFS($C$5:$C$61,$A69,$T$5:$T$61,">0") -> 0 | D69: =IFERROR(ROUND(AVERAGEIF($C$5:$C$61,$A69,$T$5:$T$61),2),"") | E69: =IF($D69="","Not rated",IF((COUNTIFS($C$5:$C$61,$A69,$S$5:$S$61,"Judged",$T$5:$T$61,">0")+$I69+$J69)>($C69-COUNTIFS($C$5:$C$61,$A69,$S$5:$S$61,"Judged",$T$5:$T$61,">0")),"("&IF($D69<1.8,"Nascent",IF($D69<2.6,"Emerging",IF($D69<3.4,"Established",IF($D69<4.2,"Advanced","Transformative"))))&")",IF($D69<1.8,"Nascent",IF($D69<2.6,"Emerging",IF($D69<3.4,"Established",IF($D69<4.2,"Advanced","Transformative")))))) -> Not rated | F69: =COUNTIFS($C$5:$C$61,$A69,$S$5:$S$61,"Measured") -> 0 | G69: =COUNTIFS($C$5:$C$61,$A69,$S$5:$S$61,"Documented") -> 0 | H69: =COUNTIFS($C$5:$C$61,$A69,$S$5:$S$61,"Judged") -> 0 | I69: =COUNTIFS($C$5:$C$61,$A69,$S$5:$S$61,"Gap") -> 0 | J69: =COUNTIFS($C$5:$C$61,$A69,$AC$5:$AC$61,"<>") -> 0 | K69: =COUNTIFS($C$5:$C$61,$A69,$U$5:$U$61,"STALE") -> 0
A70: C4 | B70: =COUNTIF($C$5:$C$61,$A70) -> 7 | C70: =COUNTIFS($C$5:$C$61,$A70,$T$5:$T$61,">0") -> 0 | D70: =IFERROR(ROUND(AVERAGEIF($C$5:$C$61,$A70,$T$5:$T$61),2),"") | E70: =IF($D70="","Not rated",IF((COUNTIFS($C$5:$C$61,$A70,$S$5:$S$61,"Judged",$T$5:$T$61,">0")+$I70+$J70)>($C70-COUNTIFS($C$5:$C$61,$A70,$S$5:$S$61,"Judged",$T$5:$T$61,">0")),"("&IF($D70<1.8,"Nascent",IF($D70<2.6,"Emerging",IF($D70<3.4,"Established",IF($D70<4.2,"Advanced","Transformative"))))&")",IF($D70<1.8,"Nascent",IF($D70<2.6,"Emerging",IF($D70<3.4,"Established",IF($D70<4.2,"Advanced","Transformative")))))) -> Not rated | F70: =COUNTIFS($C$5:$C$61,$A70,$S$5:$S$61,"Measured") -> 0 | G70: =COUNTIFS($C$5:$C$61,$A70,$S$5:$S$61,"Documented") -> 0 | H70: =COUNTIFS($C$5:$C$61,$A70,$S$5:$S$61,"Judged") -> 0 | I70: =COUNTIFS($C$5:$C$61,$A70,$S$5:$S$61,"Gap") -> 0 | J70: =COUNTIFS($C$5:$C$61,$A70,$AC$5:$AC$61,"<>") -> 0 | K70: =COUNTIFS($C$5:$C$61,$A70,$U$5:$U$61,"STALE") -> 0
A71: E1 | B71: =COUNTIF($C$5:$C$61,$A71) -> 11 | C71: =COUNTIFS($C$5:$C$61,$A71,$T$5:$T$61,">0") -> 0 | D71: =IFERROR(ROUND(AVERAGEIF($C$5:$C$61,$A71,$T$5:$T$61),2),"") | E71: =IF($D71="","Not rated",IF((COUNTIFS($C$5:$C$61,$A71,$S$5:$S$61,"Judged",$T$5:$T$61,">0")+$I71+$J71)>($C71-COUNTIFS($C$5:$C$61,$A71,$S$5:$S$61,"Judged",$T$5:$T$61,">0")),"("&IF($D71<1.8,"Nascent",IF($D71<2.6,"Emerging",IF($D71<3.4,"Established",IF($D71<4.2,"Advanced","Transformative"))))&")",IF($D71<1.8,"Nascent",IF($D71<2.6,"Emerging",IF($D71<3.4,"Established",IF($D71<4.2,"Advanced","Transformative")))))) -> Not rated | F71: =COUNTIFS($C$5:$C$61,$A71,$S$5:$S$61,"Measured") -> 0 | G71: =COUNTIFS($C$5:$C$61,$A71,$S$5:$S$61,"Documented") -> 0 | H71: =COUNTIFS($C$5:$C$61,$A71,$S$5:$S$61,"Judged") -> 0 | I71: =COUNTIFS($C$5:$C$61,$A71,$S$5:$S$61,"Gap") -> 0 | J71: =COUNTIFS($C$5:$C$61,$A71,$AC$5:$AC$61,"<>") -> 0 | K71: =COUNTIFS($C$5:$C$61,$A71,$U$5:$U$61,"STALE") -> 0
A72: O1 | B72: =COUNTIF($C$5:$C$61,$A72) -> 7 | C72: =COUNTIFS($C$5:$C$61,$A72,$T$5:$T$61,">0") -> 0 | D72: =IFERROR(ROUND(AVERAGEIF($C$5:$C$61,$A72,$T$5:$T$61),2),"") | E72: =IF($D72="","Not rated",IF((COUNTIFS($C$5:$C$61,$A72,$S$5:$S$61,"Judged",$T$5:$T$61,">0")+$I72+$J72)>($C72-COUNTIFS($C$5:$C$61,$A72,$S$5:$S$61,"Judged",$T$5:$T$61,">0")),"("&IF($D72<1.8,"Nascent",IF($D72<2.6,"Emerging",IF($D72<3.4,"Established",IF($D72<4.2,"Advanced","Transformative"))))&")",IF($D72<1.8,"Nascent",IF($D72<2.6,"Emerging",IF($D72<3.4,"Established",IF($D72<4.2,"Advanced","Transformative")))))) -> Not rated | F72: =COUNTIFS($C$5:$C$61,$A72,$S$5:$S$61,"Measured") -> 0 | G72: =COUNTIFS($C$5:$C$61,$A72,$S$5:$S$61,"Documented") -> 0 | H72: =COUNTIFS($C$5:$C$61,$A72,$S$5:$S$61,"Judged") -> 0 | I72: =COUNTIFS($C$5:$C$61,$A72,$S$5:$S$61,"Gap") -> 0 | J72: =COUNTIFS($C$5:$C$61,$A72,$AC$5:$AC$61,"<>") -> 0 | K72: =COUNTIFS($C$5:$C$61,$A72,$U$5:$U$61,"STALE") -> 0
A75: Layer profile and structural gap
A76: Foundation | B76: =IFERROR(ROUND(AVERAGEIF($D$5:$D$61,$A76,$T$5:$T$61),2),"")
A77: Enablers | B77: =IFERROR(ROUND(AVERAGEIF($D$5:$D$61,$A77,$T$5:$T$61),2),"")
A78: Transformation | B78: =IFERROR(ROUND(AVERAGEIF($D$5:$D$61,$A78,$T$5:$T$61),2),"")
A79: Outcomes | B79: =IFERROR(ROUND(AVERAGEIF($D$5:$D$61,$A79,$T$5:$T$61),2),"")
A81: Gap (Foundation − Transformation) | B81: =IF(OR($B$76="",$B$78=""),"",ROUND($B$76-$B$78,2)) | C81: =IF($B$81="","",IF(ABS($B$81)>Config!$C$5,IF($B$81>0,"FLAG — unrealized foundations","FLAG — services ahead of their rails"),"No structural flag"))
A84: Prerequisites (presence only; Unverified = the presence could not be evidenced)
A85: ID | B85: Prerequisite | C85: Scope | D85: Status
A86: 2.1 | B86: =INDEX($B$5:$B$61,MATCH($A86,$A$5:$A$61,0)) -> Rural mobile broadband coverage (3G/4G) | C86: Universal | D86: =IF(OR(INDEX($S$5:$S$61,MATCH($A86,$A$5:$A$61,0))="Gap",INDEX($S$5:$S$61,MATCH($A86,$A$5:$A$61,0))="",INDEX($T$5:$T$61,MATCH($A86,$A$5:$A$61,0))=""),"Unverified",IF(INDEX($T$5:$T$61,MATCH($A86,$A$5:$A$61,0))>=3,"Present",IF(INDEX($T$5:$T$61,MATCH($A86,$A$5:$A$61,0))=2,"Present (narrow)","Absent"))) -> Unverified
A87: 2.9 | B87: =INDEX($B$5:$B$61,MATCH($A87,$A$5:$A$61,0)) -> Rural electricity access (%) | C87: Universal | D87: =IF(OR(INDEX($S$5:$S$61,MATCH($A87,$A$5:$A$61,0))="Gap",INDEX($S$5:$S$61,MATCH($A87,$A$5:$A$61,0))="",INDEX($T$5:$T$61,MATCH($A87,$A$5:$A$61,0))=""),"Unverified",IF(INDEX($T$5:$T$61,MATCH($A87,$A$5:$A$61,0))>=3,"Present",IF(INDEX($T$5:$T$61,MATCH($A87,$A$5:$A$61,0))=2,"Present (narrow)","Absent"))) -> Unverified
A88: 4.1 | B88: =INDEX($B$5:$B$61,MATCH($A88,$A$5:$A$61,0)) -> Data protection/privacy law | C88: Universal | D88: =IF(OR(INDEX($S$5:$S$61,MATCH($A88,$A$5:$A$61,0))="Gap",INDEX($S$5:$S$61,MATCH($A88,$A$5:$A$61,0))="",INDEX($T$5:$T$61,MATCH($A88,$A$5:$A$61,0))=""),"Unverified",IF(INDEX($T$5:$T$61,MATCH($A88,$A$5:$A$61,0))>=3,"Present",IF(INDEX($T$5:$T$61,MATCH($A88,$A$5:$A$61,0))=2,"Present (narrow)","Absent"))) -> Unverified
A89: 3.3 | B89: =INDEX($B$5:$B$61,MATCH($A89,$A$5:$A$61,0)) -> National farmer registry | C89: Use case: FIN, AGI | D89: =IF(OR(INDEX($S$5:$S$61,MATCH($A89,$A$5:$A$61,0))="Gap",INDEX($S$5:$S$61,MATCH($A89,$A$5:$A$61,0))="",INDEX($T$5:$T$61,MATCH($A89,$A$5:$A$61,0))=""),"Unverified",IF(INDEX($T$5:$T$61,MATCH($A89,$A$5:$A$61,0))>=3,"Present",IF(INDEX($T$5:$T$61,MATCH($A89,$A$5:$A$61,0))=2,"Present (narrow)","Absent"))) -> Unverified
A90: 3.11 | B90: =INDEX($B$5:$B$61,MATCH($A90,$A$5:$A$61,0)) -> Agricultural data interoperability standards | C90: Use case: AGI | D90: =IF(OR(INDEX($S$5:$S$61,MATCH($A90,$A$5:$A$61,0))="Gap",INDEX($S$5:$S$61,MATCH($A90,$A$5:$A$61,0))="",INDEX($T$5:$T$61,MATCH($A90,$A$5:$A$61,0))=""),"Unverified",IF(INDEX($T$5:$T$61,MATCH($A90,$A$5:$A$61,0))>=3,"Present",IF(INDEX($T$5:$T$61,MATCH($A90,$A$5:$A$61,0))=2,"Present (narrow)","Absent"))) -> Unverified
A91: 4.5 | B91: =INDEX($B$5:$B$61,MATCH($A91,$A$5:$A$61,0)) -> Agricultural data governance framework | C91: Use case: AGI | D91: =IF(OR(INDEX($S$5:$S$61,MATCH($A91,$A$5:$A$61,0))="Gap",INDEX($S$5:$S$61,MATCH($A91,$A$5:$A$61,0))="",INDEX($T$5:$T$61,MATCH($A91,$A$5:$A$61,0))=""),"Unverified",IF(INDEX($T$5:$T$61,MATCH($A91,$A$5:$A$61,0))>=3,"Present",IF(INDEX($T$5:$T$61,MATCH($A91,$A$5:$A$61,0))=2,"Present (narrow)","Absent"))) -> Unverified
A92: 4.7 | B92: =INDEX($B$5:$B$61,MATCH($A92,$A$5:$A$61,0)) -> Digital ID coverage (%) | C92: Use case: FIN | D92: =IF(OR(INDEX($S$5:$S$61,MATCH($A92,$A$5:$A$61,0))="Gap",INDEX($S$5:$S$61,MATCH($A92,$A$5:$A$61,0))="",INDEX($T$5:$T$61,MATCH($A92,$A$5:$A$61,0))=""),"Unverified",IF(INDEX($T$5:$T$61,MATCH($A92,$A$5:$A$61,0))>=3,"Present",IF(INDEX($T$5:$T$61,MATCH($A92,$A$5:$A$61,0))=2,"Present (narrow)","Absent"))) -> Unverified
A93: 4.9 | B93: =INDEX($B$5:$B$61,MATCH($A93,$A$5:$A$61,0)) -> Inter-ministerial coordination mechanism | C93: Delivery flag | D93: =IF(OR(INDEX($S$5:$S$61,MATCH($A93,$A$5:$A$61,0))="Gap",INDEX($S$5:$S$61,MATCH($A93,$A$5:$A$61,0))="",INDEX($T$5:$T$61,MATCH($A93,$A$5:$A$61,0))=""),"Unverified",IF(INDEX($T$5:$T$61,MATCH($A93,$A$5:$A$61,0))>=3,"Present",IF(INDEX($T$5:$T$61,MATCH($A93,$A$5:$A$61,0))=2,"Present (narrow)","Absent"))) -> Unverified
A94: 5.5 | B94: =INDEX($B$5:$B$61,MATCH($A94,$A$5:$A$61,0)) -> Digital extension capability | C94: Use case: ADV | D94: =IF(OR(INDEX($S$5:$S$61,MATCH($A94,$A$5:$A$61,0))="Gap",INDEX($S$5:$S$61,MATCH($A94,$A$5:$A$61,0))="",INDEX($T$5:$T$61,MATCH($A94,$A$5:$A$61,0))=""),"Unverified",IF(INDEX($T$5:$T$61,MATCH($A94,$A$5:$A$61,0))>=3,"Present",IF(INDEX($T$5:$T$61,MATCH($A94,$A$5:$A$61,0))=2,"Present (narrow)","Absent"))) -> Unverified
A95: 5.7 | B95: =INDEX($B$5:$B$61,MATCH($A95,$A$5:$A$61,0)) -> MoAg digital/AI unit | C95: Delivery flag | D95: =IF(OR(INDEX($S$5:$S$61,MATCH($A95,$A$5:$A$61,0))="Gap",INDEX($S$5:$S$61,MATCH($A95,$A$5:$A$61,0))="",INDEX($T$5:$T$61,MATCH($A95,$A$5:$A$61,0))=""),"Unverified",IF(INDEX($T$5:$T$61,MATCH($A95,$A$5:$A$61,0))>=3,"Present",IF(INDEX($T$5:$T$61,MATCH($A95,$A$5:$A$61,0))=2,"Present (narrow)","Absent"))) -> Unverified
A96: 6.14 | B96: =INDEX($B$5:$B$61,MATCH($A96,$A$5:$A$61,0)) -> Agri-fintech rails for smallholders | C96: Use case: FIN | D96: =IF(OR(INDEX($S$5:$S$61,MATCH($A96,$A$5:$A$61,0))="Gap",INDEX($S$5:$S$61,MATCH($A96,$A$5:$A$61,0))="",INDEX($T$5:$T$61,MATCH($A96,$A$5:$A$61,0))=""),"Unverified",IF(INDEX($T$5:$T$61,MATCH($A96,$A$5:$A$61,0))>=3,"Present",IF(INDEX($T$5:$T$61,MATCH($A96,$A$5:$A$61,0))=2,"Present (narrow)","Absent"))) -> Unverified
A97: 7.12 | B97: =INDEX($B$5:$B$61,MATCH($A97,$A$5:$A$61,0)) -> Responsible-AI safeguards (consent, rights) | C97: Use case: AI-enabled (binds AGI) | D97: =IF(OR(INDEX($S$5:$S$61,MATCH($A97,$A$5:$A$61,0))="Gap",INDEX($S$5:$S$61,MATCH($A97,$A$5:$A$61,0))="",INDEX($T$5:$T$61,MATCH($A97,$A$5:$A$61,0))=""),"Unverified",IF(INDEX($T$5:$T$61,MATCH($A97,$A$5:$A$61,0))>=3,"Present",IF(INDEX($T$5:$T$61,MATCH($A97,$A$5:$A$61,0))=2,"Present (narrow)","Absent"))) -> Unverified
A100: Use-case readiness (feeds Playbook Step 2B — Digital Readiness)
A101: Use case area | B101: Mean of bearing indicators | C101: Status | D101: Blocking / limiting factor
A102: Advisory & extension | B102: =IFERROR(ROUND(AVERAGEIF(V$5:V$61,1,$T$5:$T$61),2),"") | C102: =IF(OR($D$86="Absent",$D$87="Absent",$D$88="Absent",$D$94="Absent"),"Blocked",IF(OR($D$86="Unverified",$D$87="Unverified",$D$88="Unverified",$D$94="Unverified"),"Unverified",IF(OR(OR($D$94="Present (narrow)"),$B102<Config!$C$4,OR($D$86="Present (narrow)",$D$87="Present (narrow)",$D$88="Present (narrow)")),"Partial","Ready"))) -> Unverified | D102: =IF($C102="Ready","",IF(TRIM(IF($D$86<>"Present",$A$86&" ","")&IF($D$87<>"Present",$A$87&" ","")&IF($D$88<>"Present",$A$88&" ","")&IF($D$94<>"Present",$A$94&" ",""))<>"",TRIM(IF($D$86<>"Present",$A$86&" ","")&IF($D$87<>"Present",$A$87&" ","")&IF($D$88<>"Present",$A$88&" ","")&IF($D$94<>"Present",$A$94&" ","")),IF($B102<Config!$C$4,"thin enablers (mean below "&TEXT(Config!$C$4,"0.0")&")",""))) -> 2.1 2.9 4.1 5.5
A103: Smart farming | B103: =IFERROR(ROUND(AVERAGEIF(W$5:W$61,1,$T$5:$T$61),2),"") | C103: =IF(OR($D$86="Absent",$D$87="Absent",$D$88="Absent"),"Blocked",IF(OR($D$86="Unverified",$D$87="Unverified",$D$88="Unverified"),"Unverified",IF(OR($B103<Config!$C$4,OR($D$86="Present (narrow)",$D$87="Present (narrow)",$D$88="Present (narrow)")),"Partial","Ready"))) -> Unverified | D103: =IF($C103="Ready","",IF(TRIM(IF($D$86<>"Present",$A$86&" ","")&IF($D$87<>"Present",$A$87&" ","")&IF($D$88<>"Present",$A$88&" ",""))<>"",TRIM(IF($D$86<>"Present",$A$86&" ","")&IF($D$87<>"Present",$A$87&" ","")&IF($D$88<>"Present",$A$88&" ","")),IF($B103<Config!$C$4,"thin enablers (mean below "&TEXT(Config!$C$4,"0.0")&")",""))) -> 2.1 2.9 4.1
A104: Market linkage | B104: =IFERROR(ROUND(AVERAGEIF(X$5:X$61,1,$T$5:$T$61),2),"") | C104: =IF(OR($D$86="Absent",$D$87="Absent",$D$88="Absent"),"Blocked",IF(OR($D$86="Unverified",$D$87="Unverified",$D$88="Unverified"),"Unverified",IF(OR($B104<Config!$C$4,OR($D$86="Present (narrow)",$D$87="Present (narrow)",$D$88="Present (narrow)")),"Partial","Ready"))) -> Unverified | D104: =IF($C104="Ready","",IF(TRIM(IF($D$86<>"Present",$A$86&" ","")&IF($D$87<>"Present",$A$87&" ","")&IF($D$88<>"Present",$A$88&" ",""))<>"",TRIM(IF($D$86<>"Present",$A$86&" ","")&IF($D$87<>"Present",$A$87&" ","")&IF($D$88<>"Present",$A$88&" ","")),IF($B104<Config!$C$4,"thin enablers (mean below "&TEXT(Config!$C$4,"0.0")&")",""))) -> 2.1 2.9 4.1
A105: Supply chain | B105: =IFERROR(ROUND(AVERAGEIF(Y$5:Y$61,1,$T$5:$T$61),2),"") | C105: =IF(OR($D$86="Absent",$D$87="Absent",$D$88="Absent"),"Blocked",IF(OR($D$86="Unverified",$D$87="Unverified",$D$88="Unverified"),"Unverified",IF(OR($B105<Config!$C$4,OR($D$86="Present (narrow)",$D$87="Present (narrow)",$D$88="Present (narrow)")),"Partial","Ready"))) -> Unverified | D105: =IF($C105="Ready","",IF(TRIM(IF($D$86<>"Present",$A$86&" ","")&IF($D$87<>"Present",$A$87&" ","")&IF($D$88<>"Present",$A$88&" ",""))<>"",TRIM(IF($D$86<>"Present",$A$86&" ","")&IF($D$87<>"Present",$A$87&" ","")&IF($D$88<>"Present",$A$88&" ","")),IF($B105<Config!$C$4,"thin enablers (mean below "&TEXT(Config!$C$4,"0.0")&")",""))) -> 2.1 2.9 4.1
A106: Financial services | B106: =IFERROR(ROUND(AVERAGEIF(Z$5:Z$61,1,$T$5:$T$61),2),"") | C106: =IF(OR($D$86="Absent",$D$87="Absent",$D$88="Absent",$D$89="Absent",$D$92="Absent",$D$96="Absent"),"Blocked",IF(OR($D$86="Unverified",$D$87="Unverified",$D$88="Unverified",$D$89="Unverified",$D$92="Unverified",$D$96="Unverified"),"Unverified",IF(OR(OR($D$89="Present (narrow)",$D$92="Present (narrow)",$D$96="Present (narrow)"),$B106<Config!$C$4,OR($D$86="Present (narrow)",$D$87="Present (narrow)",$D$88="Present (narrow)")),"Partial","Ready"))) -> Unverified | D106: =IF($C106="Ready","",IF(TRIM(IF($D$86<>"Present",$A$86&" ","")&IF($D$87<>"Present",$A$87&" ","")&IF($D$88<>"Present",$A$88&" ","")&IF($D$89<>"Present",$A$89&" ","")&IF($D$92<>"Present",$A$92&" ","")&IF($D$96<>"Present",$A$96&" ",""))<>"",TRIM(IF($D$86<>"Present",$A$86&" ","")&IF($D$87<>"Present",$A$87&" ","")&IF($D$88<>"Present",$A$88&" ","")&IF($D$89<>"Present",$A$89&" ","")&IF($D$92<>"Present",$A$92&" ","")&IF($D$96<>"Present",$A$96&" ","")),IF($B106<Config!$C$4,"thin enablers (mean below "&TEXT(Config!$C$4,"0.0")&")",""))) -> 2.1 2.9 4.1 3.3 4.7 6.14
A107: Ag intelligence | B107: =IFERROR(ROUND(AVERAGEIF(AA$5:AA$61,1,$T$5:$T$61),2),"") | C107: =IF(OR($D$86="Absent",$D$87="Absent",$D$88="Absent",$D$89="Absent",$D$90="Absent",$D$91="Absent",$D$97="Absent"),"Blocked",IF(OR($D$86="Unverified",$D$87="Unverified",$D$88="Unverified",$D$89="Unverified",$D$90="Unverified",$D$91="Unverified",$D$97="Unverified"),"Unverified",IF(OR(OR($D$89="Present (narrow)",$D$90="Present (narrow)",$D$91="Present (narrow)",$D$97="Present (narrow)"),$B107<Config!$C$4,OR($D$86="Present (narrow)",$D$87="Present (narrow)",$D$88="Present (narrow)")),"Partial","Ready"))) -> Unverified | D107: =IF($C107="Ready","",IF(TRIM(IF($D$86<>"Present",$A$86&" ","")&IF($D$87<>"Present",$A$87&" ","")&IF($D$88<>"Present",$A$88&" ","")&IF($D$89<>"Present",$A$89&" ","")&IF($D$90<>"Present",$A$90&" ","")&IF($D$91<>"Present",$A$91&" ","")&IF($D$97<>"Present",$A$97&" ",""))<>"",TRIM(IF($D$86<>"Present",$A$86&" ","")&IF($D$87<>"Present",$A$87&" ","")&IF($D$88<>"Present",$A$88&" ","")&IF($D$89<>"Present",$A$89&" ","")&IF($D$90<>"Present",$A$90&" ","")&IF($D$91<>"Present",$A$91&" ","")&IF($D$97<>"Present",$A$97&" ","")),IF($B107<Config!$C$4,"thin enablers (mean below "&TEXT(Config!$C$4,"0.0")&")",""))) -> 2.1 2.9 4.1 3.3 3.11 4.5 7.12

Sheet Issues
B1: Issues log — quality control findings
B2: Every automated failure, peer-review disagreement and sign-off exception is recorded here. Fixes change entries on the scoring sheet; derived fields are never edited.
B4: # | C4: Date | D4: Class | E4: Finding | F4: Row / ID | G4: Action | H4: Resolver | I4: Status

Sheet Visuals
A1: Visuals — charts read live from the scoring sheet
A2: Read a level chart together with the evidence-mix chart: a strong bar standing on a mostly grey evidence bar is a hypothesis, not a finding.
A3: Pillar | B3: Mean | C3: Measured | D3: Documented | E3: Judged | F3: Gap
A4: A1 Agriculture & need | B4: =Scoring!$D$66 | C4: =Scoring!$F$66 -> 0 | D4: =Scoring!$G$66 -> 0 | E4: =Scoring!$H$66 -> 0 | F4: =Scoring!$I$66 -> 0
A5: C1 Connectivity & access | B5: =Scoring!$D$67 | C5: =Scoring!$F$67 -> 0 | D5: =Scoring!$G$67 -> 0 | E5: =Scoring!$H$67 -> 0 | F5: =Scoring!$I$67 -> 0
A6: C2 Data & DPI | B6: =Scoring!$D$68 | C6: =Scoring!$F$68 -> 0 | D6: =Scoring!$G$68 -> 0 | E6: =Scoring!$H$68 -> 0 | F6: =Scoring!$I$68 -> 0
A7: C3 Policy & safeguards | B7: =Scoring!$D$69 | C7: =Scoring!$F$69 -> 0 | D7: =Scoring!$G$69 -> 0 | E7: =Scoring!$H$69 -> 0 | F7: =Scoring!$I$69 -> 0
A8: C4 People & institutions | B8: =Scoring!$D$70 | C8: =Scoring!$F$70 -> 0 | D8: =Scoring!$G$70 -> 0 | E8: =Scoring!$H$70 -> 0 | F8: =Scoring!$I$70 -> 0
A9: E1 Innovation & emerging tech | B9: =Scoring!$D$71 | C9: =Scoring!$F$71 -> 0 | D9: =Scoring!$G$71 -> 0 | E9: =Scoring!$H$71 -> 0 | F9: =Scoring!$I$71 -> 0
A10: O1 Outcomes & inclusion | B10: =Scoring!$D$72 | C10: =Scoring!$F$72 -> 0 | D10: =Scoring!$G$72 -> 0 | E10: =Scoring!$H$72 -> 0 | F10: =Scoring!$I$72 -> 0
A12: Layer | B12: Mean
A13: Foundation | B13: =Scoring!$B$76
A14: Enablers | B14: =Scoring!$B$77
A15: Transformation | B15: =Scoring!$B$78
A16: Outcomes | B16: =Scoring!$B$79
A18: Level | B18: Indicators
A19: Level 1 | B19: =COUNTIF(Scoring!$T$5:$T$61,1) -> 0
A20: Level 2 | B20: =COUNTIF(Scoring!$T$5:$T$61,2) -> 0
A21: Level 3 | B21: =COUNTIF(Scoring!$T$5:$T$61,3) -> 0
A22: Level 4 | B22: =COUNTIF(Scoring!$T$5:$T$61,4) -> 0
A23: Level 5 | B23: =COUNTIF(Scoring!$T$5:$T$61,5) -> 0
A25: Year | B25: Readings
A26: 2010 | B26: =SUMPRODUCT((Scoring!$Q$5:$Q$61=2010)*(Scoring!$S$5:$S$61<>"Gap")) -> 0
A27: 2011 | B27: =SUMPRODUCT((Scoring!$Q$5:$Q$61=2011)*(Scoring!$S$5:$S$61<>"Gap")) -> 0
A28: 2012 | B28: =SUMPRODUCT((Scoring!$Q$5:$Q$61=2012)*(Scoring!$S$5:$S$61<>"Gap")) -> 0
A29: 2013 | B29: =SUMPRODUCT((Scoring!$Q$5:$Q$61=2013)*(Scoring!$S$5:$S$61<>"Gap")) -> 0
A30: 2014 | B30: =SUMPRODUCT((Scoring!$Q$5:$Q$61=2014)*(Scoring!$S$5:$S$61<>"Gap")) -> 0
A31: 2015 | B31: =SUMPRODUCT((Scoring!$Q$5:$Q$61=2015)*(Scoring!$S$5:$S$61<>"Gap")) -> 0
A32: 2016 | B32: =SUMPRODUCT((Scoring!$Q$5:$Q$61=2016)*(Scoring!$S$5:$S$61<>"Gap")) -> 0
A33: 2017 | B33: =SUMPRODUCT((Scoring!$Q$5:$Q$61=2017)*(Scoring!$S$5:$S$61<>"Gap")) -> 0
A34: 2018 | B34: =SUMPRODUCT((Scoring!$Q$5:$Q$61=2018)*(Scoring!$S$5:$S$61<>"Gap")) -> 0
A35: 2019 | B35: =SUMPRODUCT((Scoring!$Q$5:$Q$61=2019)*(Scoring!$S$5:$S$61<>"Gap")) -> 0
A36: 2020 | B36: =SUMPRODUCT((Scoring!$Q$5:$Q$61=2020)*(Scoring!$S$5:$S$61<>"Gap")) -> 0
A37: 2021 | B37: =SUMPRODUCT((Scoring!$Q$5:$Q$61=2021)*(Scoring!$S$5:$S$61<>"Gap")) -> 0
A38: 2022 | B38: =SUMPRODUCT((Scoring!$Q$5:$Q$61=2022)*(Scoring!$S$5:$S$61<>"Gap")) -> 0
A39: 2023 | B39: =SUMPRODUCT((Scoring!$Q$5:$Q$61=2023)*(Scoring!$S$5:$S$61<>"Gap")) -> 0
A40: 2024 | B40: =SUMPRODUCT((Scoring!$Q$5:$Q$61=2024)*(Scoring!$S$5:$S$61<>"Gap")) -> 0
A41: 2025 | B41: =SUMPRODUCT((Scoring!$Q$5:$Q$61=2025)*(Scoring!$S$5:$S$61<>"Gap")) -> 0
A42: 2026 | B42: =SUMPRODUCT((Scoring!$Q$5:$Q$61=2026)*(Scoring!$S$5:$S$61<>"Gap")) -> 0
A44: Note: readings more than three years old are flagged STALE on the scoring sheet.
